Workbook

Sheet 投放账户补充
A1: 投放账户ID | B1: 名称 | C1: 业务对接人 | D1: 站内/站外 | E1: 营销活动 | F1: 公司主体 | G1: 平台 | H1: 投放方式（自投/代投） | I1: 平台对合作应供应商名称 | J1: 是否存在充值赠送金 | K1: 是否存在返利 | L1: 是否通过此账户申请开票 | M1: 使用中心 | N1: 使用二级部门 | O1: 使用三级部门 | P1: 财务对接人（如有）
A2: 6336556296 | B2: 花西子Florasis | E2: 微博推广 | F2: 杭州宜格化妆品有限公司 | G2: 微博 | H2: 自投 | I2: 上海宇枫电子商务有限公司 | J2: 是 | K2: 否 | L2: 否
A3: 6965612965 | B3: 花西子美妆日记 | E3: 微博推广 | F3: 杭州宜格化妆品有限公司 | G3: 微博 | H3: 自投 | I3: 上海宇枫电子商务有限公司
A4: 55d34272f5a26377d1b784dd | B4: 花西子Florasis | D4: 站内 | E4: 小红书加热 | I4: 薯一薯二文化传媒（上海）有限公司

Sheet 投放账户（维度数据）
A1: 站内/站外 | B1: 营销活动 | C1: 公司主体 | D1: =+++++#REF! | E1: 投放平台 | F1: 投放方式 | G1: 平台对合作应供应商名称 | H1: 对应业务场景及用途 | I1: 登录网址 | J1: 账号 | K1: 编码 | M1: 是否按消耗开票 | N1: 是否为充值账户 | O1: 是否能取到充值/消耗明细 | P1: 是否存在充值赠送金 | Q1: 是否存在返利 | R1: 是否通过此账户申请开票 | S1: 使用中心 | T1: 使用二级部门 | U1: 使用三级部门 | V1: 使用四级部门 | W1: 业务对接人 | X1: 备注 | Y1: 财务对接人 | Z1: 账户权限owner | AA1: 登录方式
D2: 正常使用/闲置 | E2: 平台的称呼，如： 抖音-巨量千川 抖音-巨量纵横 快手 淘宝AD | F2: 自投/代投 | G2: 供应商全称 | N2: 是/否 | O2: 是/否 | P2: 是/否 | Q2: 是/否 | R2: 是/否 | S2: 一级中心 | Z2: 管理密码人员 | AA2: 验证码/账户密码
A3: 站内 | B3: 考拉-常规投放 | C3: 杭州匠泽电子商务有限公司 | D3: 正常使用 | E3: 考拉 | F3: 自投 | G3: 考拉海购（杭州）科技有限公司 | H3: 考拉 | I3: https://partner.kaola.com/index | J3: 18069829269 | K3: 18069829269 | N3: 否 | O3: 否 | P3: 否 | Q3: 否 | R3: 是 | S3: 品牌运营中心 | T3: 渠道运营部 | U3: 综合渠道运营部 | V3: 综合渠道推广部 | W3: =VLOOKUP(K3,'Sheet11'!$X$2:$AH$279,11,FALSE) | Y3: 贝果 | Z3: 徐庄南 | AA3: 账号密码
A4: 站外 | B4: AD信息流 | C4: 杭州宜格化妆品有限公司 | D4: 暂停投放 | E4: 抖音 | F4: 自投 | G4: 广东省广告集团股份有限公司 | H4: 得物抖音AD引流 | I4: https://business.oceanengine.com/site/promotion?#/account | J4: huaxizi_xinxliuad2@163.com | K4: huaxizi_xinxliuad2@163.com | N4: 否 | O4: 否 | P4: 是 | Q4: 是 | R4: 是 | S4: 品牌运营中心 | W4: =VLOOKUP(K4,'Sheet11'!$X$2:$AH$279,11,FALSE) | X4: 目前未投放 | Y4: 贝果 | Z4: 徐庄南 | AA4: 账号密码
A5: 站内 | B5: 小红书加热 | C5: 杭州宜格化妆品有限公司 | E5: 小红书(TFPT08) | F5: 自投 | G5: 江苏拾光宝盒信息技术有限公司(VEN01761) | J5: 拾光宝盒（花西子美妆） | K5: 117315 | P5: 是(YES) | Q5: 是(YES) | R5: 否 | S5: =VLOOKUP(B5,'Sheet9'!$B$2:$G$191,3,FALSE) | T5: =VLOOKUP(B5,'Sheet9'!$B$2:$G$191,4,FALSE) | U5: =VLOOKUP(B5,'Sheet9'!$B$2:$G$191,5,FALSE) | V5: 内容投放组 | W5: =VLOOKUP(K5,'Sheet11'!$X$2:$AH$279,11,FALSE) | Y5: 贝果 | Z5: 甘草、清和 | AA5: 账号密码
A6: 站内 | B6: 小红书加热 | C6: 杭州宜格化妆品有限公司 | E6: 小红书(TFPT08) | F6: 自投 | G6: 江苏拾光宝盒信息技术有限公司(VEN01761) | J6: 拾光宝盒（花西子Florasis4） | K6: 168640 | P6: 是(YES) | Q6: 是(YES) | R6: 否 | S6: =VLOOKUP(B6,'Sheet9'!$B$2:$G$191,3,FALSE) | T6: =VLOOKUP(B6,'Sheet9'!$B$2:$G$191,4,FALSE) | U6: =VLOOKUP(B6,'Sheet9'!$B$2:$G$191,5,FALSE) | V6: 内容投放组 | W6: =VLOOKUP(K6,'Sheet11'!$X$2:$AH$279,11,FALSE) | Y6: 贝果 | Z6: 甘草、清和 | AA6: 账号密码
A7: 站内 | B7: 小红书加热 | C7: 杭州宜格化妆品有限公司 | E7: 小红书(TFPT08) | F7: 自投 | G7: 广东省广告集团股份有限公司(VEN02800) | J7: 省广集团（花西子Florasis） | K7: 113409 | P7: 是(YES) | Q7: 是(YES) | R7: 否 | S7: =VLOOKUP(B7,'Sheet9'!$B$2:$G$191,3,FALSE) | T7: =VLOOKUP(B7,'Sheet9'!$B$2:$G$191,4,FALSE) | U7: =VLOOKUP(B7,'Sheet9'!$B$2:$G$191,5,FALSE) | V7: 内容投放组 | W7: =VLOOKUP(K7,'Sheet11'!$X$2:$AH$279,11,FALSE) | Y7: 贝果 | Z7: 甘草、清和 | AA7: 账号密码
A8: 站内 | B8: 小红书加热 | C8: 杭州宜格化妆品有限公司 | E8: 小红书(TFPT08) | F8: 自投 | G8: 广东省广告集团股份有限公司(VEN02800) | J8: 省广-美妆 | K8: huaxizi_xhongshu2@163.com | P8: 是(YES) | Q8: 是(YES) | R8: 否 | S8: =VLOOKUP(B8,'Sheet9'!$B$2:$G$191,3,FALSE) | T8: =VLOOKUP(B8,'Sheet9'!$B$2:$G$191,4,FALSE) | U8: =VLOOKUP(B8,'Sheet9'!$B$2:$G$191,5,FALSE) | V8: 内容投放组 | W8: =VLOOKUP(K8,'Sheet11'!$X$2:$AH$279,11,FALSE) | Y8: 贝果 | Z8: 甘草、清和 | AA8: 账号密码
A9: 站内 | B9: 小红书加热 | C9: 杭州宜格化妆品有限公司 | E9: 小红书(TFPT08) | F9: 自投 | G9: 广东省广告集团股份有限公司(VEN02800) | J9: 省广集团（花西子Florasis）02 | K9: 117993 | P9: 是(YES) | Q9: 是(YES) | R9: 否 | S9: =VLOOKUP(B9,'Sheet9'!$B$2:$G$191,3,FALSE) | T9: =VLOOKUP(B9,'Sheet9'!$B$2:$G$191,4,FALSE) | U9: =VLOOKUP(B9,'Sheet9'!$B$2:$G$191,5,FALSE) | V9: 内容投放组 | W9: =VLOOKUP(K9,'Sheet11'!$X$2:$AH$279,11,FALSE) | Y9: 贝果 | Z9: 甘草、清和 | AA9: 账号密码
A10: 站内 | B10: 小红书加热 | C10: 杭州宜格化妆品有限公司 | E10: 小红书(TFPT08) | F10: 自投 | G10: 广东省广告集团股份有限公司(VEN02800) | J10: 省广集团（花西子Florasis）03 | K10: 117992 | P10: 是(YES) | Q10: 是(YES) | R10: 否 | S10: =VLOOKUP(B10,'Sheet9'!$B$2:$G$191,3,FALSE) | T10: =VLOOKUP(B10,'Sheet9'!$B$2:$G$191,4,FALSE) | U10: =VLOOKUP(B10,'Sheet9'!$B$2:$G$191,5,FALSE) | V10: 内容投放组 | W10: =VLOOKUP(K10,'Sheet11'!$X$2:$AH$279,11,FALSE) | Y10: 贝果 | Z10: 甘草、清和 | AA10: 账号密码
A11: 站外 | B11: 小红书加热 | C11: 杭州宜格化妆品有限公司 | E11: 小红书(TFPT08) | F11: 自投 | G11: 江苏拾光宝盒信息技术有限公司(VEN01761) | J11: 拾光宝盒（花西子Florasis3） | K11: 119989 | R11: 否 | S11: =VLOOKUP(B11,'Sheet9'!$B$2:$G$191,3,FALSE) | T11: =VLOOKUP(B11,'Sheet9'!$B$2:$G$191,4,FALSE) | U11: =VLOOKUP(B11,'Sheet9'!$B$2:$G$191,5,FALSE) | V11: 内容投放组 | W11: =VLOOKUP(K11,'Sheet11'!$X$2:$AH$279,11,FALSE) | Y11: 贝果 | Z11: 甘草、清和 | AA11: 账号密码
A12: 站外 | B12: 小红书加热 | C12: 杭州宜格化妆品有限公司 | E12: 小红书(TFPT08) | F12: 自投 | G12: 江苏拾光宝盒信息技术有限公司(VEN01761) | J12: 拾光宝盒（花西子Florasis） | K12: 65933 | R12: 否 | S12: =VLOOKUP(B12,'Sheet9'!$B$2:$G$191,3,FALSE) | T12: =VLOOKUP(B12,'Sheet9'!$B$2:$G$191,4,FALSE) | U12: =VLOOKUP(B12,'Sheet9'!$B$2:$G$191,5,FALSE) | V12: 内容投放组 | W12: =VLOOKUP(K12,'Sheet11'!$X$2:$AH$279,11,FALSE) | Y12: 贝果 | Z12: 甘草、清和 | AA12: 账号密码
A13: 站外 | B13: 小红书加热 | C13: 杭州宜格化妆品有限公司 | E13: 小红书(TFPT08) | F13: 自投 | G13: 江苏拾光宝盒信息技术有限公司(VEN01761) | J13: 拾光宝盒（花西子Florasis2） | K13: 119990 | R13: 否 | S13: =VLOOKUP(B13,'Sheet9'!$B$2:$G$191,3,FALSE) | T13: =VLOOKUP(B13,'Sheet9'!$B$2:$G$191,4,FALSE) | U13: =VLOOKUP(B13,'Sheet9'!$B$2:$G$191,5,FALSE) | V13: 内容投放组 | W13: =VLOOKUP(K13,'Sheet11'!$X$2:$AH$279,11,FALSE) | Y13: 贝果 | Z13: 甘草、清和 | AA13: 账号密码
A14: 站外 | B14: B站起飞加热 | C14: 杭州宜格化妆品有限公司 | D14: 暂停投放 | E14: B站 | F14: 自投 | G14: 杭州羽联信息科技有限公司 | I14: https://ad.bilibili.com/#/home | J14: hongjin@yige-group.com | K14: hongjin@yige-group.com | N14: 否 | O14: 否 | P14: 是 | Q14: 是 | R14: 否 | S14: =VLOOKUP(B14,'Sheet9'!$B$2:$G$191,3,FALSE) | T14: =VLOOKUP(B14,'Sheet9'!$B$2:$G$191,4,FALSE) | U14: =VLOOKUP(B14,'Sheet9'!$B$2:$G$191,5,FALSE) | V14: 内容投放组 | W14: =VLOOKUP(K14,'Sheet11'!$X$2:$AH$279,11,FALSE) | Y14: 贝果 | Z14: 甘草、清和 | AA14: 账号密码
A15: 站外 | B15: B站起飞加热 | C15: 杭州宜格化妆品有限公司 | D15: 暂停投放 | E15: B站 | F15: 自投 | G15: 上海无堂网络科技有限公司 | I15: https://ad.bilibili.com/#/home | J15: wanwan@yige-group.com | K15: wanwan@yige-group.com | N15: 否 | O15: 否 | P15: 是 | Q15: 是 | R15: 否 | S15: =VLOOKUP(B15,'Sheet9'!$B$2:$G$191,3,FALSE) | T15: =VLOOKUP(B15,'Sheet9'!$B$2:$G$191,4,FALSE) | U15: =VLOOKUP(B15,'Sheet9'!$B$2:$G$191,5,FALSE) | V15: 内容投放组 | W15: =VLOOKUP(K15,'Sheet11'!$X$2:$AH$279,11,FALSE) | Y15: 贝果 | Z15: 甘草、清和 | AA15: 账号密码
A16: 站外 | B16: B站起飞加热 | C16: 杭州宜格化妆品有限公司 | D16: 暂停投放 | E16: B站 | F16: 自投 | G16: 上海无堂网络科技有限公司 | I16: https://ad.bilibili.com/#/home | J16: tangli@yige.us | K16: tangli@yige.us | N16: 否 | O16: 否 | P16: 是 | Q16: 是 | R16: 否 | S16: =VLOOKUP(B16,'Sheet9'!$B$2:$G$191,3,FALSE) | T16: =VLOOKUP(B16,'Sheet9'!$B$2:$G$191,4,FALSE) | U16: =VLOOKUP(B16,'Sheet9'!$B$2:$G$191,5,FALSE) | V16: 内容投放组 | W16: =VLOOKUP(K16,'Sheet11'!$X$2:$AH$279,11,FALSE) | Y16: 贝果 | Z16: 甘草、清和 | AA16: 账号密码
A17: 站外 | B17: B站起飞加热 | C17: 杭州宜格化妆品有限公司 | D17: 暂停投放 | E17: B站 | F17: 自投 | G17: 上海无堂网络科技有限公司 | I17: https://ad.bilibili.com/#/home | J17: qinghe@zhimei.us | K17: qinghe@zhimei.us | N17: 否 | O17: 否 | P17: 是 | Q17: 是 | R17: 否 | S17: =VLOOKUP(B17,'Sheet9'!$B$2:$G$191,3,FALSE) | T17: =VLOOKUP(B17,'Sheet9'!$B$2:$G$191,4,FALSE) | U17: =VLOOKUP(B17,'Sheet9'!$B$2:$G$191,5,FALSE) | V17: 内容投放组 | W17: =VLOOKUP(K17,'Sheet11'!$X$2:$AH$279,11,FALSE) | Y17: 贝果 | Z17: 甘草、清和 | AA17: 账号密码
A18: 站外 | B18: B站起飞加热 | C18: 杭州宜格化妆品有限公司 | D18: 暂停投放 | E18: B站 | F18: 自投 | G18: 上海无堂网络科技有限公司 | I18: https://ad.bilibili.com/#/home | J18: kongqing@yige-group.com | K18: kongqing@yige-group.com | N18: 否 | O18: 否 | P18: 是 | Q18: 是 | R18: 否 | S18: =VLOOKUP(B18,'Sheet9'!$B$2:$G$191,3,FALSE) | T18: =VLOOKUP(B18,'Sheet9'!$B$2:$G$191,4,FALSE) | U18: =VLOOKUP(B18,'Sheet9'!$B$2:$G$191,5,FALSE) | V18: 内容投放组 | W18: =VLOOKUP(K18,'Sheet11'!$X$2:$AH$279,11,FALSE) | Y18: 贝果 | Z18: 甘草、清和 | AA18: 账号密码
A19: 站外 | B19: B站起飞加热 | C19: 杭州宜格化妆品有限公司 | D19: 暂停投放 | E19: B站 | F19: 自投 | G19: 北京新线中视文化传播有限公司 | I19: https://ad.bilibili.com/#/home | J19: gancao@yige-group.com | K19: gancao@yige-group.com | N19: 否 | O19: 否 | P19: 是 | Q19: 是 | R19: 否 | S19: =VLOOKUP(B19,'Sheet9'!$B$2:$G$191,3,FALSE) | T19: =VLOOKUP(B19,'Sheet9'!$B$2:$G$191,4,FALSE) | U19: =VLOOKUP(B19,'Sheet9'!$B$2:$G$191,5,FALSE) | V19: 内容投放组 | W19: =VLOOKUP(K19,'Sheet11'!$X$2:$AH$279,11,FALSE) | Y19: 贝果 | Z19: 甘草、清和 | AA19: 账号密码
A20: 站外 | B20: 微博推广 | C20: 杭州宜格化妆品有限公司 | D20: 正常使用 | E20: 微博 | F20: 自投 | G20: 上海宇枫电子商务有限公司 | I20: https://ad.weibo.com/ | J20: 花西子Florasis | K20: 6336556296 | N20: 否 | O20: 否 | P20: 是 | Q20: 否 | R20: 否 | S20: 品牌运营中心 | T20: 运营策略部 | U20: 天猫运营部 | V20: 推广中心组 | W20: =VLOOKUP(K20,'Sheet11'!$X$2:$AH$279,11,FALSE)
A21: 站外 | B21: 微博推广 | C21: 杭州宜格化妆品有限公司 | D21: 正常使用 | E21: 微博 | F21: 自投 | G21: 上海宇枫电子商务有限公司 | J21: 花西子美妆日记 | K21: 6965612965 | N21: 否 | O21: 否 | P21: 是 | Q21: 否 | R21: 否 | S21: 品牌运营中心 | T21: 运营策略部 | U21: 天猫运营部 | V21: 推广中心组 | W21: =VLOOKUP(K21,'Sheet11'!$X$2:$AH$279,11,FALSE)
A22: 站外 | B22: AD信息流 | C22: 杭州宜格化妆品有限公司 | D22: 正常使用 | F22: 自投 | G22: 广东省广告集团股份有限公司 | I22: https://ad.oceanengine.com/ | J22: huaxizi_xinxiliuad@163.com | K22: huaxizi_xinxiliuad@163.com | N22: 否 | O22: 否 | P22: 是 | Q22: 是 | R22: 是 | S22: =VLOOKUP(B22,'Sheet9'!$B$2:$G$191,3,FALSE) | T22: =VLOOKUP(B22,'Sheet9'!$B$2:$G$191,4,FALSE) | U22: =VLOOKUP(B22,'Sheet9'!$B$2:$G$191,5,FALSE) | V22: 推广中心组 | W22: =VLOOKUP(K22,'Sheet11'!$X$2:$AH$279,11,FALSE) | Y22: 贝果 | Z22: 白纸、阿布、志文、循安 | AA22: 账号密码
A23: 站外 | B23: AD信息流 | C23: 杭州宜格化妆品有限公司 | D23: 正常使用 | E23: 天猫抖音AD引流 | F23: 自投 | G23: 广东省广告集团股份有限公司 | I23: https://ad.oceanengine.com/ | J23: huaxizi_xinxiliuad4@163.com | K23: huaxizi_xinxiliuad4@163.com | N23: 否 | O23: 否 | P23: 是 | Q23: 是 | R23: 是 | S23: =VLOOKUP(B23,'Sheet9'!$B$2:$G$191,3,FALSE) | T23: =VLOOKUP(B23,'Sheet9'!$B$2:$G$191,4,FALSE) | U23: =VLOOKUP(B23,'Sheet9'!$B$2:$G$191,5,FALSE) | V23: 推广中心组 | W23: 白纸（张浩霖） | Y23: 贝果 | Z23: 白纸、阿布、志文、循安 | AA23: 账号密码
A24: 站外 | B24: AD信息流 | C24: 杭州宜格化妆品有限公司 | D24: 正常使用 | E24: 天猫抖音AD引流 | F24: 自投 | G24: 广东省广告集团股份有限公司 | I24: https://ad.oceanengine.com/ | J24: huaxizi_xinxliuad5@163.com | K24: huaxizi_xinxliuad5@163.com | N24: 否 | O24: 否 | P24: 是 | Q24: 是 | R24: 是 | S24: =VLOOKUP(B24,'Sheet9'!$B$2:$G$191,3,FALSE) | T24: =VLOOKUP(B24,'Sheet9'!$B$2:$G$191,4,FALSE) | U24: =VLOOKUP(B24,'Sheet9'!$B$2:$G$191,5,FALSE) | V24: 推广中心组 | W24: =VLOOKUP(K24,'Sheet11'!$X$2:$AH$279,11,FALSE) | Y24: 贝果 | Z24: 白纸、阿布、志文、循安 | AA24: 账号密码
A25: 站外 | B25: AD信息流 | C25: 杭州宜格化妆品有限公司 | D25: 正常使用 | E25: 天猫抖音AD引流 | F25: 自投 | G25: 广东省广告集团股份有限公司 | I25: https://ad.oceanengine.com/ | J25: huaxizi_xinxliuad7@163.com | K25: huaxizi_xinxliuad7@163.com | N25: 否 | O25: 否 | P25: 是 | Q25: 是 | R25: 是 | S25: =VLOOKUP(B25,'Sheet9'!$B$2:$G$191,3,FALSE) | T25: =VLOOKUP(B25,'Sheet9'!$B$2:$G$191,4,FALSE) | U25: =VLOOKUP(B25,'Sheet9'!$B$2:$G$191,5,FALSE) | V25: 推广中心组 | W25: =VLOOKUP(K25,'Sheet11'!$X$2:$AH$279,11,FALSE) | Y25: 贝果 | Z25: 白纸、阿布、志文、循安 | AA25: 账号密码
A26: 站外 | B26: AD信息流 | C26: 杭州宜格化妆品有限公司 | D26: 正常使用 | E26: 天猫抖音AD引流 | F26: 自投 | G26: 广东省广告集团股份有限公司 | I26: https://ad.oceanengine.com/ | J26: huaxizi_xinxliuad8@163.com | K26: huaxizi_xinxliuad8@163.com | N26: 否 | O26: 否 | P26: 是 | Q26: 是 | R26: 是 | S26: =VLOOKUP(B26,'Sheet9'!$B$2:$G$191,3,FALSE) | T26: =VLOOKUP(B26,'Sheet9'!$B$2:$G$191,4,FALSE) | U26: =VLOOKUP(B26,'Sheet9'!$B$2:$G$191,5,FALSE) | V26: 推广中心组 | W26: =VLOOKUP(K26,'Sheet11'!$X$2:$AH$279,11,FALSE) | Y26: 贝果 | Z26: 白纸、阿布、志文、循安 | AA26: 账号密码
A27: 站外 | B27: AD信息流 | C27: 杭州宜格化妆品有限公司 | D27: 正常使用 | E27: 天猫抖音AD引流 | F27: 自投 | G27: 群邑（上海）广告有限公司 | I27: https://ad.oceanengine.com/ | J27: huaxizi_xinxliuad9@163.com | K27: huaxizi_xinxliuad9@163.com | N27: 否 | O27: 否 | P27: 是 | Q27: 是 | R27: 是 | S27: =VLOOKUP(B27,'Sheet9'!$B$2:$G$191,3,FALSE) | T27: =VLOOKUP(B27,'Sheet9'!$B$2:$G$191,4,FALSE) | U27: =VLOOKUP(B27,'Sheet9'!$B$2:$G$191,5,FALSE) | V27: 推广中心组 | W27: =VLOOKUP(K27,'Sheet11'!$X$2:$AH$279,11,FALSE) | Y27: 贝果 | Z27: 白纸、阿布、志文、循安 | AA27: 账号密码
A28: 站外 | B28: AD信息流 | C28: 杭州宜格化妆品有限公司 | D28: 正常使用 | E28: 天猫抖音AD引流 | F28: 自投 | G28: 群邑（上海）广告有限公司 | I28: https://ad.oceanengine.com/ | J28: joy.du@mindshareworld.com | K28: joy.du@mindshareworld.com | N28: 否 | O28: 否 | P28: 是 | Q28: 是 | R28: 是 | S28: =VLOOKUP(B28,'Sheet9'!$B$2:$G$191,3,FALSE) | T28: =VLOOKUP(B28,'Sheet9'!$B$2:$G$191,4,FALSE) | U28: =VLOOKUP(B28,'Sheet9'!$B$2:$G$191,5,FALSE) | V28: 推广中心组 | W28: =VLOOKUP(K28,'Sheet11'!$X$2:$AH$279,11,FALSE) | Y28: 贝果 | Z28: 白纸、阿布、志文、循安 | AA28: 账号密码
A29: 站外 | B29: UD信息流 | C29: 杭州宜格化妆品有限公司 | D29: 正常使用 | E29: UD信息流引流 | F29: 自投 | G29: 北京九合互动文化传播有限公司 | I29: https://unidesk.taobao.com/index.html | J29: tb963892057577 | K29: tb963892057577 | N29: 否 | O29: 否 | P29: 是 | Q29: 是 | R29: 是 | S29: =VLOOKUP(B29,'Sheet9'!$B$2:$G$191,3,FALSE) | T29: =VLOOKUP(B29,'Sheet9'!$B$2:$G$191,4,FALSE) | U29: =VLOOKUP(B29,'Sheet9'!$B$2:$G$191,5,FALSE) | V29: 推广中心组 | W29: =VLOOKUP(K29,'Sheet11'!$X$2:$AH$279,11,FALSE) | Y29: 贝果 | Z29: 白纸、阿布、志文 | AA29: 账号密码
A30: 站外 | C30: 杭州宜格化妆品有限公司 | D30: 暂停投放 | E30: 微博信息流引流 | F30: 自投 | G30: 上海宇枫电子商务有限公司 | I30: https://ad.weibo.com/promote2/advertisements?customer_id=6336556296 | J30: adserving_ud0754@weibo.com | K30: adserving_ud0754@weibo.com | N30: 否 | O30: 否 | P30: 是 | Q30: 是 | R30: 是 | W30: =VLOOKUP(K30,'Sheet11'!$X$2:$AH$279,11,FALSE) | Y30: 贝果 | Z30: 白纸、阿布、志文 | AA30: 账号密码
A31: 站外 | C31: 杭州宜格化妆品有限公司 | D31: 正常使用 | E31: 百度信息流引流 | F31: 自投 | G31: 北京云锐国际文化传媒有限公司 | I31: https://cas.baidu.com/?tpl=www2&fromu=http%3A%2F%2Fwww2.b...ommon%2Fappinit.ajax | J31: 杭州宜格化妆品有限公司1（shvipyr花西子3） | K31: 杭州宜格化妆品有限公司1（shvipyr花西子3） | N31: 否 | O31: 否 | P31: 是 | Q31: 是 | R31: 是 | W31: =VLOOKUP(K31,'Sheet11'!$X$2:$AH$279,11,FALSE) | Y31: 贝果 | Z31: 白纸、阿布、循安 | AA31: 账号密码
A32: 站外 | B32: 磁力引擎 | C32: 杭州宜格化妆品有限公司 | D32: 正常使用 | E32: 快手信息流引流 | F32: 自投 | G32: 北京起量文化传媒有限公司 | I32: https://ad.e.kuaishou.com/manage?__accountId__=14861051 | J32: 13362198950 | K32: 13362198950 | N32: 否 | O32: 否 | P32: 是 | Q32: 是 | R32: 是 | S32: =VLOOKUP(B32,'Sheet9'!$B$2:$G$191,3,FALSE) | T32: =VLOOKUP(B32,'Sheet9'!$B$2:$G$191,4,FALSE) | U32: =VLOOKUP(B32,'Sheet9'!$B$2:$G$191,5,FALSE) | V32: 推广中心组 | W32: =VLOOKUP(K32,'Sheet11'!$X$2:$AH$279,11,FALSE) | Y32: 贝果 | Z32: 白纸、羽阳 | AA32: 账号密码
A33: 站外 | B33: 磁力金牛 | C33: 杭州宜格化妆品有限公司 | D33: 正常使用 | E33: 快手磁力金牛 | F33: 自投 | G33: 北京起量文化传媒有限公司 | I33: https://niu.e.kuaishou.com/manage?__accountId__=13304454 | J33: 13396586970 | K33: 13396586970 | N33: 否 | O33: 否 | P33: 是 | Q33: 是 | R33: 是 | S33: =VLOOKUP(B33,'Sheet9'!$B$2:$G$191,3,FALSE) | T33: =VLOOKUP(B33,'Sheet9'!$B$2:$G$191,4,FALSE) | U33: =VLOOKUP(B33,'Sheet9'!$B$2:$G$191,5,FALSE) | V33: 推广中心组 | W33: =VLOOKUP(K33,'Sheet11'!$X$2:$AH$279,11,FALSE) | Y33: 贝果 | Z33: 白纸、羽阳 | AA33: 账号密码
A34: 站外 | B34: 微信-ADQ推广 | C34: 杭州宜格化妆品有限公司 | D34: 正常使用 | E34: 微信渠道投放 | F34: 自投 | G34: 杭州炬美网络科技有限公司 | I34: https://ad.qq.com/atlas/23959502/index | J34: 微信扫码登录 | K34: 微信扫码登录 | N34: 否 | O34: 否 | P34: 是 | Q34: 是 | R34: 是 | S34: =VLOOKUP(B34,'Sheet9'!$B$2:$G$191,3,FALSE) | T34: =VLOOKUP(B34,'Sheet9'!$B$2:$G$191,4,FALSE) | U34: =VLOOKUP(B34,'Sheet9'!$B$2:$G$191,5,FALSE) | V34: 综合渠道推广部 | W34: =VLOOKUP(K34,'Sheet11'!$X$2:$AH$279,11,FALSE) | Y34: 贝果 | Z34: 白纸 | AA34: 账号密码
A35: 站外 | B35: 千川信息流 | C35: 杭州宜格化妆品有限公司 | F35: 自投 | G35: 北京云锐国际文化传媒有限公司 | J35: =VLOOKUP(K35,'Sheet5'!$J$3:$K$200,2,FALSE) | K35: 1727265617683469 | N35: 否 | S35: =VLOOKUP(B35,'Sheet9'!$B$2:$G$191,3,FALSE) | T35: =VLOOKUP(B35,'Sheet9'!$B$2:$G$191,4,FALSE) | U35: =VLOOKUP(B35,'Sheet9'!$B$2:$G$191,5,FALSE) | V35: 抖音推广部 | W35: 兴泉（韩兴泉）、流沙（俞君珠）、奶茶（唐丽）、榴莲（管晓辉）、三喜（王思雨）、白龙（樊苏北）
A36: 站外 | B36: AD信息流 | C36: 杭州宜格化妆品有限公司 | F36: 自投 | G36: 广东省广告集团股份有限公司 | J36: =VLOOKUP(K36,'Sheet5'!$J$3:$K$200,2,FALSE) | K36: 1762866886323341 | N36: 否 | P36: 否 | Q36: 否 | S36: =VLOOKUP(B36,'Sheet9'!$B$2:$G$191,3,FALSE) | T36: =VLOOKUP(B36,'Sheet9'!$B$2:$G$191,4,FALSE) | U36: =VLOOKUP(B36,'Sheet9'!$B$2:$G$191,5,FALSE) | V36: 推广中心组 | W36: =VLOOKUP(K36,'Sheet11'!$X$2:$AH$279,11,FALSE)
A37: 站外 | B37: AD信息流 | C37: 杭州宜格化妆品有限公司 | F37: 自投 | G37: 广东省广告集团股份有限公司 | J37: =VLOOKUP(K37,'Sheet5'!$J$3:$K$200,2,FALSE) | K37: 1758638395883534 | N37: 否 | P37: 否 | Q37: 否 | S37: =VLOOKUP(B37,'Sheet9'!$B$2:$G$191,3,FALSE) | T37: =VLOOKUP(B37,'Sheet9'!$B$2:$G$191,4,FALSE) | U37: =VLOOKUP(B37,'Sheet9'!$B$2:$G$191,5,FALSE) | V37: 推广中心组 | W37: =VLOOKUP(K37,'Sheet11'!$X$2:$AH$279,11,FALSE)
A38: 站外 | B38: AD信息流 | C38: 杭州宜格化妆品有限公司 | F38: 自投 | G38: 广东省广告集团股份有限公司 | J38: =VLOOKUP(K38,'Sheet5'!$J$3:$K$200,2,FALSE) | K38: 1744729041456135 | N38: 否 | P38: 否 | Q38: 否 | S38: =VLOOKUP(B38,'Sheet9'!$B$2:$G$191,3,FALSE) | T38: =VLOOKUP(B38,'Sheet9'!$B$2:$G$191,4,FALSE) | U38: =VLOOKUP(B38,'Sheet9'!$B$2:$G$191,5,FALSE) | V38: 推广中心组 | W38: =VLOOKUP(K38,'Sheet11'!$X$2:$AH$279,11,FALSE)
A39: 站外 | B39: AD信息流 | C39: 杭州宜格化妆品有限公司 | F39: 自投 | G39: 广东省广告集团股份有限公司 | J39: =VLOOKUP(K39,'Sheet5'!$J$3:$K$200,2,FALSE) | K39: 1744631353681928 | N39: 否 | P39: 否 | Q39: 否 | S39: =VLOOKUP(B39,'Sheet9'!$B$2:$G$191,3,FALSE) | T39: =VLOOKUP(B39,'Sheet9'!$B$2:$G$191,4,FALSE) | U39: =VLOOKUP(B39,'Sheet9'!$B$2:$G$191,5,FALSE) | V39: 推广中心组 | W39: =VLOOKUP(K39,'Sheet11'!$X$2:$AH$279,11,FALSE)
A40: 站外 | B40: AD信息流 | C40: 杭州宜格化妆品有限公司 | F40: 自投 | G40: 广东省广告集团股份有限公司 | J40: =VLOOKUP(K40,'Sheet5'!$J$3:$K$200,2,FALSE) | K40: 1752335658405895 | N40: 否 | P40: 否 | Q40: 否 | S40: =VLOOKUP(B40,'Sheet9'!$B$2:$G$191,3,FALSE) | T40: =VLOOKUP(B40,'Sheet9'!$B$2:$G$191,4,FALSE) | U40: =VLOOKUP(B40,'Sheet9'!$B$2:$G$191,5,FALSE) | V40: 推广中心组 | W40: =VLOOKUP(K40,'Sheet11'!$X$2:$AH$279,11,FALSE)
A41: 站外 | B41: AD信息流 | C41: 杭州宜格化妆品有限公司 | F41: 自投 | G41: 广东省广告集团股份有限公司 | J41: =VLOOKUP(K41,'Sheet5'!$J$3:$K$200,2,FALSE) | K41: 1752335657150542 | N41: 否 | P41: 否 | Q41: 否 | S41: =VLOOKUP(B41,'Sheet9'!$B$2:$G$191,3,FALSE) | T41: =VLOOKUP(B41,'Sheet9'!$B$2:$G$191,4,FALSE) | U41: =VLOOKUP(B41,'Sheet9'!$B$2:$G$191,5,FALSE) | V41: 推广中心组 | W41: =VLOOKUP(K41,'Sheet11'!$X$2:$AH$279,11,FALSE)
A42: 站外 | B42: AD信息流 | C42: 杭州宜格化妆品有限公司 | F42: 自投 | G42: 广东省广告集团股份有限公司 | J42: =VLOOKUP(K42,'Sheet5'!$J$3:$K$200,2,FALSE) | K42: 1750901317073991 | N42: 否 | P42: 否 | Q42: 否 | S42: =VLOOKUP(B42,'Sheet9'!$B$2:$G$191,3,FALSE) | T42: =VLOOKUP(B42,'Sheet9'!$B$2:$G$191,4,FALSE) | U42: =VLOOKUP(B42,'Sheet9'!$B$2:$G$191,5,FALSE) | V42: 推广中心组 | W42: =VLOOKUP(K42,'Sheet11'!$X$2:$AH$279,11,FALSE)
A43: 站外 | B43: AD信息流 | C43: 杭州宜格化妆品有限公司 | F43: 自投 | G43: 广东省广告集团股份有限公司 | J43: =VLOOKUP(K43,'Sheet5'!$J$3:$K$200,2,FALSE) | K43: 1747107074839566 | N43: 否 | P43: 否 | Q43: 否 | S43: =VLOOKUP(B43,'Sheet9'!$B$2:$G$191,3,FALSE) | T43: =VLOOKUP(B43,'Sheet9'!$B$2:$G$191,4,FALSE) | U43: =VLOOKUP(B43,'Sheet9'!$B$2:$G$191,5,FALSE) | V43: 推广中心组 | W43: =VLOOKUP(K43,'Sheet11'!$X$2:$AH$279,11,FALSE)
A44: 站外 | B44: AD信息流 | C44: 杭州宜格化妆品有限公司 | F44: 自投 | G44: 广东省广告集团股份有限公司 | J44: =VLOOKUP(K44,'Sheet5'!$J$3:$K$200,2,FALSE) | K44: 1750901319256072 | N44: 否 | P44: 否 | Q44: 否 | S44: =VLOOKUP(B44,'Sheet9'!$B$2:$G$191,3,FALSE) | T44: =VLOOKUP(B44,'Sheet9'!$B$2:$G$191,4,FALSE) | U44: =VLOOKUP(B44,'Sheet9'!$B$2:$G$191,5,FALSE) | V44: 推广中心组 | W44: =VLOOKUP(K44,'Sheet11'!$X$2:$AH$279,11,FALSE)
A45: 站外 | B45: AD信息流 | C45: 杭州宜格化妆品有限公司 | F45: 自投 | G45: 广东省广告集团股份有限公司 | J45: =VLOOKUP(K45,'Sheet5'!$J$3:$K$200,2,FALSE) | K45: 1750901314010184 | N45: 否 | P45: 否 | Q45: 否 | S45: =VLOOKUP(B45,'Sheet9'!$B$2:$G$191,3,FALSE) | T45: =VLOOKUP(B45,'Sheet9'!$B$2:$G$191,4,FALSE) | U45: =VLOOKUP(B45,'Sheet9'!$B$2:$G$191,5,FALSE) | V45: 推广中心组 | W45: =VLOOKUP(K45,'Sheet11'!$X$2:$AH$279,11,FALSE)
A46: 站外 | B46: AD信息流 | C46: 杭州宜格化妆品有限公司 | F46: 自投 | G46: 广东省广告集团股份有限公司 | J46: =VLOOKUP(K46,'Sheet5'!$J$3:$K$200,2,FALSE) | K46: 1758638396516360 | N46: 否 | P46: 否 | Q46: 否 | S46: =VLOOKUP(B46,'Sheet9'!$B$2:$G$191,3,FALSE) | T46: =VLOOKUP(B46,'Sheet9'!$B$2:$G$191,4,FALSE) | U46: =VLOOKUP(B46,'Sheet9'!$B$2:$G$191,5,FALSE) | V46: 推广中心组 | W46: =VLOOKUP(K46,'Sheet11'!$X$2:$AH$279,11,FALSE)
A47: 站外 | B47: AD信息流 | C47: 杭州宜格化妆品有限公司 | F47: 自投 | G47: 广东省广告集团股份有限公司 | J47: =VLOOKUP(K47,'Sheet5'!$J$3:$K$200,2,FALSE) | K47: 1750901317821447 | N47: 否 | P47: 否 | Q47: 否 | S47: =VLOOKUP(B47,'Sheet9'!$B$2:$G$191,3,FALSE) | T47: =VLOOKUP(B47,'Sheet9'!$B$2:$G$191,4,FALSE) | U47: =VLOOKUP(B47,'Sheet9'!$B$2:$G$191,5,FALSE) | V47: 推广中心组 | W47: =VLOOKUP(K47,'Sheet11'!$X$2:$AH$279,11,FALSE)
... A68: 站外 | B68: AD信息流 | C68: 杭州宜格化妆品有限公司 | F68: 自投 | G68: 广东省广告集团股份有限公司 | J68: =VLOOKUP(K68,'Sheet5'!$J$3:$K$200,2,FALSE) | K68: 1758638395143181 | N68: 否 | P68: 否 | Q68: 否 | S68: =VLOOKUP(B68,'Sheet9'!$B$2:$G$191,3,FALSE) | T68: =VLOOKUP(B68,'Sheet9'!$B$2:$G$191,4,FALSE) | U68: =VLOOKUP(B68,'Sheet9'!$B$2:$G$191,5,FALSE) | V68: 推广中心组 | W68: =VLOOKUP(K68,'Sheet11'!$X$2:$AH$279,11,FALSE)
A69: 站外 | B69: 千川信息流 | C69: 杭州宜格化妆品有限公司 | F69: 自投 | G69: 广东省广告集团股份有限公司 | J69: =VLOOKUP(K69,'Sheet5'!$J$3:$K$200,2,FALSE) | K69: 1727435690629127 | N69: 否 | S69: =VLOOKUP(B69,'Sheet9'!$B$2:$G$191,3,FALSE) | T69: =VLOOKUP(B69,'Sheet9'!$B$2:$G$191,4,FALSE) | U69: =VLOOKUP(B69,'Sheet9'!$B$2:$G$191,5,FALSE) | V69: 抖音推广部 | W69: 兴泉（韩兴泉）、流沙（俞君珠）、奶茶（唐丽）、榴莲（管晓辉）、三喜（王思雨）、白龙（樊苏北）
A70: 站外 | B70: 矩阵号千川信息流 | C70: 杭州宜格化妆品有限公司 | F70: 自投 | G70: 广东省广告集团股份有限公司 | J70: =VLOOKUP(K70,'Sheet5'!$J$3:$K$200,2,FALSE) | K70: 1747734628974605 | N70: 否 | S70: =VLOOKUP(B70,'Sheet9'!$B$2:$G$191,3,FALSE) | T70: =VLOOKUP(B70,'Sheet9'!$B$2:$G$191,4,FALSE) | U70: =VLOOKUP(B70,'Sheet9'!$B$2:$G$191,5,FALSE) | V70: 矩阵运营部 | W70: 兴泉（韩兴泉）、可乐（周许颖）、意琳（肖意琳）、皮卡（王岑）
A71: 站外 | B71: 小红书加热 | C71: 杭州宜格化妆品有限公司 | E71: 小红书(TFPT08) | F71: 自投 | G71: 上海博观瑞思传媒科技有限公司(VEN02000) | J71: 博观-花西子-3 | K71: 307497 | R71: 否 | S71: =VLOOKUP(B71,'Sheet9'!$B$2:$G$191,3,FALSE) | T71: =VLOOKUP(B71,'Sheet9'!$B$2:$G$191,4,FALSE) | U71: =VLOOKUP(B71,'Sheet9'!$B$2:$G$191,5,FALSE) | V71: 内容投放组 | W71: =VLOOKUP(K71,'Sheet11'!$X$2:$AH$279,11,FALSE)
A72: 站外 | B72: 小红书加热 | C72: 杭州宜格化妆品有限公司 | E72: 小红书(TFPT08) | F72: 自投 | G72: 上海剧星传媒股份有限公司(VEN00363) | J72: 剧星小红书投放账户 | K72: sd_xx@visionstar.cn | R72: 否 | S72: =VLOOKUP(B72,'Sheet9'!$B$2:$G$191,3,FALSE) | T72: =VLOOKUP(B72,'Sheet9'!$B$2:$G$191,4,FALSE) | U72: =VLOOKUP(B72,'Sheet9'!$B$2:$G$191,5,FALSE) | V72: 内容投放组 | W72: =VLOOKUP(K72,'Sheet11'!$X$2:$AH$279,11,FALSE)
A73: 站外 | B73: 小红书加热 | C73: 杭州宜格化妆品有限公司 | E73: 小红书(TFPT08) | F73: 代投 | G73: 上海博观瑞思传媒科技有限公司(VEN02000) | J73: 博观-花西子 | K73: 263697 | R73: 否 | S73: =VLOOKUP(B73,'Sheet9'!$B$2:$G$191,3,FALSE) | T73: =VLOOKUP(B73,'Sheet9'!$B$2:$G$191,4,FALSE) | U73: =VLOOKUP(B73,'Sheet9'!$B$2:$G$191,5,FALSE) | V73: 内容投放组 | W73: =VLOOKUP(K73,'Sheet11'!$X$2:$AH$279,11,FALSE)
A74: 站外 | B74: 磁力金牛 | C74: 杭州宜格化妆品有限公司 | F74: 自投 | G74: 北京起量文化传媒有限公司 | J74: =VLOOKUP(K74,'Sheet5'!$J$3:$K$200,2,FALSE) | K74: 17230613 | N74: 否 | S74: =VLOOKUP(B74,'Sheet9'!$B$2:$G$191,3,FALSE) | T74: 快手部 | U74: 快手运营推广部 | W74: =VLOOKUP(K74,'Sheet11'!$X$2:$AH$279,11,FALSE)
A75: 站外 | B75: AD信息流 | C75: 杭州宜格化妆品有限公司 | F75: 自投 | G75: 群邑（上海）广告有限公司 | J75: =VLOOKUP(K75,'Sheet5'!$J$3:$K$200,2,FALSE) | K75: 1754167001896968 | N75: 否 | P75: 否 | Q75: 否 | S75: =VLOOKUP(B75,'Sheet9'!$B$2:$G$191,3,FALSE) | T75: =VLOOKUP(B75,'Sheet9'!$B$2:$G$191,4,FALSE) | U75: =VLOOKUP(B75,'Sheet9'!$B$2:$G$191,5,FALSE) | V75: 推广中心组 | W75: =VLOOKUP(K75,'Sheet11'!$X$2:$AH$279,11,FALSE)
A76: 站外 | B76: AD信息流 | C76: 杭州宜格化妆品有限公司 | F76: 自投 | G76: 群邑（上海）广告有限公司 | J76: =VLOOKUP(K76,'Sheet5'!$J$3:$K$200,2,FALSE) | K76: 1744649914765325 | N76: 否 | P76: 否 | Q76: 否 | S76: =VLOOKUP(B76,'Sheet9'!$B$2:$G$191,3,FALSE) | T76: =VLOOKUP(B76,'Sheet9'!$B$2:$G$191,4,FALSE) | U76: =VLOOKUP(B76,'Sheet9'!$B$2:$G$191,5,FALSE) | V76: 推广中心组 | W76: =VLOOKUP(K76,'Sheet11'!$X$2:$AH$279,11,FALSE)
A77: 站外 | B77: AD信息流 | C77: 杭州宜格化妆品有限公司 | F77: 自投 | G77: 群邑（上海）广告有限公司 | J77: =VLOOKUP(K77,'Sheet5'!$J$3:$K$200,2,FALSE) | K77: 1754167001310215 | N77: 否 | P77: 否 | Q77: 否 | S77: =VLOOKUP(B77,'Sheet9'!$B$2:$G$191,3,FALSE) | T77: =VLOOKUP(B77,'Sheet9'!$B$2:$G$191,4,FALSE) | U77: =VLOOKUP(B77,'Sheet9'!$B$2:$G$191,5,FALSE) | V77: 推广中心组 | W77: =VLOOKUP(K77,'Sheet11'!$X$2:$AH$279,11,FALSE)
A78: 站外 | B78: AD信息流 | C78: 杭州宜格化妆品有限公司 | F78: 自投 | G78: 群邑（上海）广告有限公司 | J78: =VLOOKUP(K78,'Sheet5'!$J$3:$K$200,2,FALSE) | K78: 1761579156325383 | N78: 否 | P78: 否 | Q78: 否 | S78: =VLOOKUP(B78,'Sheet9'!$B$2:$G$191,3,FALSE) | T78: =VLOOKUP(B78,'Sheet9'!$B$2:$G$191,4,FALSE) | U78: =VLOOKUP(B78,'Sheet9'!$B$2:$G$191,5,FALSE) | V78: 推广中心组 | W78: =VLOOKUP(K78,'Sheet11'!$X$2:$AH$279,11,FALSE)
A79: 站外 | B79: AD信息流 | C79: 杭州宜格化妆品有限公司 | F79: 自投 | G79: 群邑（上海）广告有限公司 | J79: =VLOOKUP(K79,'Sheet5'!$J$3:$K$200,2,FALSE) | K79: 1761579155761230 | N79: 否 | P79: 否 | Q79: 否 | S79: =VLOOKUP(B79,'Sheet9'!$B$2:$G$191,3,FALSE) | T79: =VLOOKUP(B79,'Sheet9'!$B$2:$G$191,4,FALSE) | U79: =VLOOKUP(B79,'Sheet9'!$B$2:$G$191,5,FALSE) | V79: 推广中心组 | W79: =VLOOKUP(K79,'Sheet11'!$X$2:$AH$279,11,FALSE)
A80: 站外 | B80: AD信息流 | C80: 杭州宜格化妆品有限公司 | F80: 自投 | G80: 群邑（上海）广告有限公司 | J80: =VLOOKUP(K80,'Sheet5'!$J$3:$K$200,2,FALSE) | K80: 1761579155066888 | N80: 否 | P80: 否 | Q80: 否 | S80: =VLOOKUP(B80,'Sheet9'!$B$2:$G$191,3,FALSE) | T80: =VLOOKUP(B80,'Sheet9'!$B$2:$G$191,4,FALSE) | U80: =VLOOKUP(B80,'Sheet9'!$B$2:$G$191,5,FALSE) | V80: 推广中心组 | W80: =VLOOKUP(K80,'Sheet11'!$X$2:$AH$279,11,FALSE)
A81: 站外 | B81: AD信息流 | C81: 杭州宜格化妆品有限公司 | F81: 自投 | G81: 群邑（上海）广告有限公司 | J81: =VLOOKUP(K81,'Sheet5'!$J$3:$K$200,2,FALSE) | K81: 1754167002455111 | N81: 否 | P81: 否 | Q81: 否 | S81: =VLOOKUP(B81,'Sheet9'!$B$2:$G$191,3,FALSE) | T81: =VLOOKUP(B81,'Sheet9'!$B$2:$G$191,4,FALSE) | U81: =VLOOKUP(B81,'Sheet9'!$B$2:$G$191,5,FALSE) | V81: 推广中心组 | W81: =VLOOKUP(K81,'Sheet11'!$X$2:$AH$279,11,FALSE)
A82: 站外 | B82: AD信息流 | C82: 杭州宜格化妆品有限公司 | F82: 自投 | G82: 群邑（上海）广告有限公司 | J82: =VLOOKUP(K82,'Sheet5'!$J$3:$K$200,2,FALSE) | K82: 1754167000735758 | N82: 否 | P82: 否 | Q82: 否 | S82: =VLOOKUP(B82,'Sheet9'!$B$2:$G$191,3,FALSE) | T82: =VLOOKUP(B82,'Sheet9'!$B$2:$G$191,4,FALSE) | U82: =VLOOKUP(B82,'Sheet9'!$B$2:$G$191,5,FALSE) | V82: 推广中心组 | W82: =VLOOKUP(K82,'Sheet11'!$X$2:$AH$279,11,FALSE)
A83: 站外 | B83: AD信息流 | C83: 杭州宜格化妆品有限公司 | F83: 自投 | G83: 群邑（上海）广告有限公司 | J83: =VLOOKUP(K83,'Sheet5'!$J$3:$K$200,2,FALSE) | K83: 1734408229378061 | N83: 否 | P83: 否 | Q83: 否 | S83: =VLOOKUP(B83,'Sheet9'!$B$2:$G$191,3,FALSE) | T83: =VLOOKUP(B83,'Sheet9'!$B$2:$G$191,4,FALSE) | U83: =VLOOKUP(B83,'Sheet9'!$B$2:$G$191,5,FALSE) | V83: 推广中心组 | W83: =VLOOKUP(K83,'Sheet11'!$X$2:$AH$279,11,FALSE)
A84: 站外 | B84: AD信息流 | C84: 杭州宜格化妆品有限公司 | F84: 自投 | G84: 群邑（上海）广告有限公司 | J84: =VLOOKUP(K84,'Sheet5'!$J$3:$K$200,2,FALSE) | K84: 1727635338328078 | N84: 否 | P84: 否 | Q84: 否 | S84: =VLOOKUP(B84,'Sheet9'!$B$2:$G$191,3,FALSE) | T84: =VLOOKUP(B84,'Sheet9'!$B$2:$G$191,4,FALSE) | U84: =VLOOKUP(B84,'Sheet9'!$B$2:$G$191,5,FALSE) | V84: 推广中心组 | W84: =VLOOKUP(K84,'Sheet11'!$X$2:$AH$279,11,FALSE)
A85: 站外 | B85: 千川信息流 | C85: 杭州宜格化妆品有限公司 | F85: 自投 | G85: 群邑（上海）广告有限公司 | J85: =VLOOKUP(K85,'Sheet5'!$J$3:$K$200,2,FALSE) | K85: 1727535271575630 | N85: 否 | S85: =VLOOKUP(B85,'Sheet9'!$B$2:$G$191,3,FALSE) | T85: =VLOOKUP(B85,'Sheet9'!$B$2:$G$191,4,FALSE) | U85: =VLOOKUP(B85,'Sheet9'!$B$2:$G$191,5,FALSE) | V85: 抖音推广部 | W85: 兴泉（韩兴泉）、流沙（俞君珠）、奶茶（唐丽）、榴莲（管晓辉）、三喜（王思雨）、白龙（樊苏北）
A86: 站外 | B86: 磁力引擎 | C86: 杭州宜格化妆品有限公司 | F86: 自投 | G86: 群邑（上海）广告有限公司 | J86: =VLOOKUP(K86,'Sheet5'!$J$3:$K$200,2,FALSE) | K86: 17029747 | N86: 否 | P86: 否 | Q86: 否 | S86: =VLOOKUP(B86,'Sheet9'!$B$2:$G$191,3,FALSE) | T86: =VLOOKUP(B86,'Sheet9'!$B$2:$G$191,4,FALSE) | U86: =VLOOKUP(B86,'Sheet9'!$B$2:$G$191,5,FALSE) | V86: 推广中心组 | W86: =VLOOKUP(K86,'Sheet11'!$X$2:$AH$279,11,FALSE)
A87: 站外 | B87: 磁力引擎 | C87: 杭州宜格化妆品有限公司 | F87: 自投 | G87: 群邑（上海）广告有限公司 | J87: =VLOOKUP(K87,'Sheet5'!$J$3:$K$200,2,FALSE) | K87: 17029746 | N87: 否 | P87: 否 | Q87: 否 | S87: =VLOOKUP(B87,'Sheet9'!$B$2:$G$191,3,FALSE) | T87: =VLOOKUP(B87,'Sheet9'!$B$2:$G$191,4,FALSE) | U87: =VLOOKUP(B87,'Sheet9'!$B$2:$G$191,5,FALSE) | V87: 推广中心组 | W87: =VLOOKUP(K87,'Sheet11'!$X$2:$AH$279,11,FALSE)
A88: 站外 | B88: 磁力引擎 | C88: 杭州宜格化妆品有限公司 | F88: 自投 | G88: 群邑（上海）广告有限公司 | J88: =VLOOKUP(K88,'Sheet5'!$J$3:$K$200,2,FALSE) | K88: 17029745 | N88: 否 | P88: 否 | Q88: 否 | S88: =VLOOKUP(B88,'Sheet9'!$B$2:$G$191,3,FALSE) | T88: =VLOOKUP(B88,'Sheet9'!$B$2:$G$191,4,FALSE) | U88: =VLOOKUP(B88,'Sheet9'!$B$2:$G$191,5,FALSE) | V88: 推广中心组 | W88: =VLOOKUP(K88,'Sheet11'!$X$2:$AH$279,11,FALSE)
A89: 站外 | B89: 磁力引擎 | C89: 杭州宜格化妆品有限公司 | F89: 自投 | G89: 群邑（上海）广告有限公司 | J89: =VLOOKUP(K89,'Sheet5'!$J$3:$K$200,2,FALSE) | K89: 17029744 | N89: 否 | P89: 否 | Q89: 否 | S89: =VLOOKUP(B89,'Sheet9'!$B$2:$G$191,3,FALSE) | T89: =VLOOKUP(B89,'Sheet9'!$B$2:$G$191,4,FALSE) | U89: =VLOOKUP(B89,'Sheet9'!$B$2:$G$191,5,FALSE) | V89: 推广中心组 | W89: =VLOOKUP(K89,'Sheet11'!$X$2:$AH$279,11,FALSE)
A90: 站外 | B90: 磁力引擎 | C90: 杭州宜格化妆品有限公司 | F90: 自投 | G90: 群邑（上海）广告有限公司 | J90: =VLOOKUP(K90,'Sheet5'!$J$3:$K$200,2,FALSE) | K90: 17029743 | N90: 否 | P90: 否 | Q90: 否 | S90: =VLOOKUP(B90,'Sheet9'!$B$2:$G$191,3,FALSE) | T90: =VLOOKUP(B90,'Sheet9'!$B$2:$G$191,4,FALSE) | U90: =VLOOKUP(B90,'Sheet9'!$B$2:$G$191,5,FALSE) | V90: 推广中心组 | W90: =VLOOKUP(K90,'Sheet11'!$X$2:$AH$279,11,FALSE)
A91: 站外 | B91: 磁力引擎 | C91: 杭州宜格化妆品有限公司 | F91: 自投 | G91: 群邑（上海）广告有限公司 | J91: =VLOOKUP(K91,'Sheet5'!$J$3:$K$200,2,FALSE) | K91: 17029742 | N91: 否 | P91: 否 | Q91: 否 | S91: =VLOOKUP(B91,'Sheet9'!$B$2:$G$191,3,FALSE) | T91: =VLOOKUP(B91,'Sheet9'!$B$2:$G$191,4,FALSE) | U91: =VLOOKUP(B91,'Sheet9'!$B$2:$G$191,5,FALSE) | V91: 推广中心组 | W91: =VLOOKUP(K91,'Sheet11'!$X$2:$AH$279,11,FALSE)
A92: 站外 | B92: 磁力引擎 | C92: 杭州宜格化妆品有限公司 | F92: 自投 | G92: 群邑（上海）广告有限公司 | J92: =VLOOKUP(K92,'Sheet5'!$J$3:$K$200,2,FALSE) | K92: 17029741 | N92: 否 | P92: 否 | Q92: 否 | S92: =VLOOKUP(B92,'Sheet9'!$B$2:$G$191,3,FALSE) | T92: =VLOOKUP(B92,'Sheet9'!$B$2:$G$191,4,FALSE) | U92: =VLOOKUP(B92,'Sheet9'!$B$2:$G$191,5,FALSE) | V92: 推广中心组 | W92: =VLOOKUP(K92,'Sheet11'!$X$2:$AH$279,11,FALSE)
A93: 站外 | B93: 磁力引擎 | C93: 杭州宜格化妆品有限公司 | F93: 自投 | G93: 群邑（上海）广告有限公司 | J93: =VLOOKUP(K93,'Sheet5'!$J$3:$K$200,2,FALSE) | K93: 17029740 | N93: 否 | P93: 否 | Q93: 否 | S93: =VLOOKUP(B93,'Sheet9'!$B$2:$G$191,3,FALSE) | T93: =VLOOKUP(B93,'Sheet9'!$B$2:$G$191,4,FALSE) | U93: =VLOOKUP(B93,'Sheet9'!$B$2:$G$191,5,FALSE) | V93: 推广中心组 | W93: =VLOOKUP(K93,'Sheet11'!$X$2:$AH$279,11,FALSE)
A94: 站外 | B94: 磁力引擎 | C94: 杭州宜格化妆品有限公司 | F94: 自投 | G94: 群邑（上海）广告有限公司 | J94: =VLOOKUP(K94,'Sheet5'!$J$3:$K$200,2,FALSE) | K94: 17029739 | N94: 否 | P94: 否 | Q94: 否 | S94: =VLOOKUP(B94,'Sheet9'!$B$2:$G$191,3,FALSE) | T94: =VLOOKUP(B94,'Sheet9'!$B$2:$G$191,4,FALSE) | U94: =VLOOKUP(B94,'Sheet9'!$B$2:$G$191,5,FALSE) | V94: 推广中心组 | W94: =VLOOKUP(K94,'Sheet11'!$X$2:$AH$279,11,FALSE)
A95: 站外 | B95: 磁力引擎 | C95: 杭州宜格化妆品有限公司 | F95: 自投 | G95: 群邑（上海）广告有限公司 | J95: =VLOOKUP(K95,'Sheet5'!$J$3:$K$200,2,FALSE) | K95: 17026499 | N95: 否 | P95: 否 | Q95: 否 | S95: =VLOOKUP(B95,'Sheet9'!$B$2:$G$191,3,FALSE) | T95: =VLOOKUP(B95,'Sheet9'!$B$2:$G$191,4,FALSE) | U95: =VLOOKUP(B95,'Sheet9'!$B$2:$G$191,5,FALSE) | V95: 推广中心组 | W95: =VLOOKUP(K95,'Sheet11'!$X$2:$AH$279,11,FALSE)
A96: 站外 | B96: 磁力引擎 | C96: 杭州宜格化妆品有限公司 | F96: 自投 | G96: 群邑（上海）广告有限公司 | J96: =VLOOKUP(K96,'Sheet5'!$J$3:$K$200,2,FALSE) | K96: 16901306 | N96: 否 | P96: 否 | Q96: 否 | S96: =VLOOKUP(B96,'Sheet9'!$B$2:$G$191,3,FALSE) | T96: =VLOOKUP(B96,'Sheet9'!$B$2:$G$191,4,FALSE) | U96: =VLOOKUP(B96,'Sheet9'!$B$2:$G$191,5,FALSE) | V96: 推广中心组 | W96: =VLOOKUP(K96,'Sheet11'!$X$2:$AH$279,11,FALSE)
A97: 站外 | B97: 磁力引擎 | C97: 杭州宜格化妆品有限公司 | F97: 自投 | G97: 群邑（上海）广告有限公司 | J97: =VLOOKUP(K97,'Sheet5'!$J$3:$K$200,2,FALSE) | K97: 16901305 | N97: 否 | P97: 否 | Q97: 否 | S97: =VLOOKUP(B97,'Sheet9'!$B$2:$G$191,3,FALSE) | T97: =VLOOKUP(B97,'Sheet9'!$B$2:$G$191,4,FALSE) | U97: =VLOOKUP(B97,'Sheet9'!$B$2:$G$191,5,FALSE) | V97: 推广中心组 | W97: =VLOOKUP(K97,'Sheet11'!$X$2:$AH$279,11,FALSE)
... A105: 站外 | B105: 磁力引擎 | C105: 杭州宜格化妆品有限公司 | F105: 自投 | G105: 群邑（上海）广告有限公司 | J105: =VLOOKUP(K105,'Sheet5'!$J$3:$K$200,2,FALSE) | K105: 16896876 | N105: 否 | P105: 否 | Q105: 否 | S105: =VLOOKUP(B105,'Sheet9'!$B$2:$G$191,3,FALSE) | T105: =VLOOKUP(B105,'Sheet9'!$B$2:$G$191,4,FALSE) | U105: =VLOOKUP(B105,'Sheet9'!$B$2:$G$191,5,FALSE) | V105: 推广中心组 | W105: =VLOOKUP(K105,'Sheet11'!$X$2:$AH$279,11,FALSE)
A106: 站外 | B106: 磁力金牛 | C106: 杭州宜格化妆品有限公司 | F106: 自投 | G106: 群邑（上海）广告有限公司 | J106: =VLOOKUP(K106,'Sheet5'!$J$3:$K$200,2,FALSE) | K106: 16909142 | N106: 否 | S106: =VLOOKUP(B106,'Sheet9'!$B$2:$G$191,3,FALSE) | T106: 快手部 | U106: 快手运营推广部 | W106: =VLOOKUP(K106,'Sheet11'!$X$2:$AH$279,11,FALSE)
A107: 站外 | B107: 磁力金牛 | C107: 杭州宜格化妆品有限公司 | F107: 自投 | G107: 群邑（上海）广告有限公司 | J107: =VLOOKUP(K107,'Sheet5'!$J$3:$K$200,2,FALSE) | K107: 16907921 | N107: 否 | S107: =VLOOKUP(B107,'Sheet9'!$B$2:$G$191,3,FALSE) | T107: 快手部 | U107: 快手运营推广部 | W107: =VLOOKUP(K107,'Sheet11'!$X$2:$AH$279,11,FALSE)
A108: 站外 | B108: 磁力金牛 | C108: 杭州宜格化妆品有限公司 | F108: 自投 | G108: 群邑（上海）广告有限公司 | J108: =VLOOKUP(K108,'Sheet5'!$J$3:$K$200,2,FALSE) | K108: 16909145 | N108: 否 | S108: =VLOOKUP(B108,'Sheet9'!$B$2:$G$191,3,FALSE) | T108: 快手部 | U108: 快手运营推广部 | W108: =VLOOKUP(K108,'Sheet11'!$X$2:$AH$279,11,FALSE)
A109: 站外 | B109: 千川信息流 | C109: 杭州宜格化妆品有限公司 | F109: 自投 | G109: 上海博观瑞思传媒科技有限公司 | J109: =VLOOKUP(K109,'Sheet5'!$J$3:$K$200,2,FALSE) | K109: 1695557841246222 | N109: 否 | S109: =VLOOKUP(B109,'Sheet9'!$B$2:$G$191,3,FALSE) | T109: =VLOOKUP(B109,'Sheet9'!$B$2:$G$191,4,FALSE) | U109: =VLOOKUP(B109,'Sheet9'!$B$2:$G$191,5,FALSE) | V109: 抖音推广部 | W109: 兴泉（韩兴泉）、流沙（俞君珠）、奶茶（唐丽）、榴莲（管晓辉）、三喜（王思雨）、白龙（樊苏北）
A110: 站外 | B110: 千川信息流 | C110: 杭州宜格化妆品有限公司 | F110: 自投 | G110: 上海博观瑞思传媒科技有限公司 | J110: =VLOOKUP(K110,'Sheet5'!$J$3:$K$200,2,FALSE) | K110: 1760222811427847 | N110: 否 | S110: =VLOOKUP(B110,'Sheet9'!$B$2:$G$191,3,FALSE) | T110: =VLOOKUP(B110,'Sheet9'!$B$2:$G$191,4,FALSE) | U110: =VLOOKUP(B110,'Sheet9'!$B$2:$G$191,5,FALSE) | V110: 抖音推广部 | W110: 兴泉（韩兴泉）、三喜（王思雨）
A111: 站外 | B111: 千川信息流 | C111: 杭州宜格化妆品有限公司 | F111: 自投 | G111: 知定堂文化传媒（上海）有限公司 | J111: 凯丽隆-商品卡 | K111: 1761146745368653 | N111: 否 | S111: =VLOOKUP(B111,'Sheet9'!$B$2:$G$191,3,FALSE) | T111: =VLOOKUP(B111,'Sheet9'!$B$2:$G$191,4,FALSE) | U111: =VLOOKUP(B111,'Sheet9'!$B$2:$G$191,5,FALSE) | V111: 抖音推广部 | W111: 兴泉（韩兴泉）、三喜（王思雨）
A112: 站外 | B112: 矩阵号千川信息流 | C112: 杭州宜格化妆品有限公司 | F112: 自投 | G112: 上海博观瑞思传媒科技有限公司 | J112: =VLOOKUP(K112,'Sheet5'!$J$3:$K$200,2,FALSE) | K112: 1760519144208525 | N112: 否 | S112: =VLOOKUP(B112,'Sheet9'!$B$2:$G$191,3,FALSE) | T112: =VLOOKUP(B112,'Sheet9'!$B$2:$G$191,4,FALSE) | U112: =VLOOKUP(B112,'Sheet9'!$B$2:$G$191,5,FALSE) | V112: 矩阵运营部 | W112: 兴泉（韩兴泉）、可乐（周许颖）、意琳（肖意琳）、皮卡（王岑）
A113: 站外 | B113: 小红书加热 | C113: 杭州宜格化妆品有限公司 | E113: 小红书(TFPT08) | F113: 代投 | G113: 上海剧星传媒股份有限公司(VEN00363) | J113: 剧星小红书投放账户 | K113: 283885 | P113: 否(NO) | Q113: 是(YES) | R113: 否 | S113: =VLOOKUP(B113,'Sheet9'!$B$2:$G$191,3,FALSE) | T113: =VLOOKUP(B113,'Sheet9'!$B$2:$G$191,4,FALSE) | U113: =VLOOKUP(B113,'Sheet9'!$B$2:$G$191,5,FALSE) | V113: 内容投放组 | W113: =VLOOKUP(K113,'Sheet11'!$X$2:$AH$279,11,FALSE)
A114: 站外 | B114: AD信息流 | C114: 杭州宜格化妆品有限公司 | F114: 自投 | G114: 上海聚胜万合广告有限公司 | J114: =VLOOKUP(K114,'Sheet5'!$J$3:$K$200,2,FALSE) | K114: 1761595756097614 | N114: 否 | P114: 否 | Q114: 否 | S114: =VLOOKUP(B114,'Sheet9'!$B$2:$G$191,3,FALSE) | T114: =VLOOKUP(B114,'Sheet9'!$B$2:$G$191,4,FALSE) | U114: =VLOOKUP(B114,'Sheet9'!$B$2:$G$191,5,FALSE) | V114: 推广中心组 | W114: =VLOOKUP(K114,'Sheet11'!$X$2:$AH$279,11,FALSE)
A115: 站外 | B115: AD信息流 | C115: 杭州宜格化妆品有限公司 | F115: 自投 | G115: 上海聚胜万合广告有限公司 | J115: =VLOOKUP(K115,'Sheet5'!$J$3:$K$200,2,FALSE) | K115: 1761595755440142 | N115: 否 | P115: 否 | Q115: 否 | S115: =VLOOKUP(B115,'Sheet9'!$B$2:$G$191,3,FALSE) | T115: =VLOOKUP(B115,'Sheet9'!$B$2:$G$191,4,FALSE) | U115: =VLOOKUP(B115,'Sheet9'!$B$2:$G$191,5,FALSE) | V115: 推广中心组 | W115: =VLOOKUP(K115,'Sheet11'!$X$2:$AH$279,11,FALSE)
A116: 站外 | B116: AD信息流 | C116: 杭州宜格化妆品有限公司 | F116: 自投 | G116: 上海聚胜万合广告有限公司 | J116: =VLOOKUP(K116,'Sheet5'!$J$3:$K$200,2,FALSE) | K116: 1761595754924045 | N116: 否 | P116: 否 | Q116: 否 | S116: =VLOOKUP(B116,'Sheet9'!$B$2:$G$191,3,FALSE) | T116: =VLOOKUP(B116,'Sheet9'!$B$2:$G$191,4,FALSE) | U116: =VLOOKUP(B116,'Sheet9'!$B$2:$G$191,5,FALSE) | V116: 推广中心组 | W116: =VLOOKUP(K116,'Sheet11'!$X$2:$AH$279,11,FALSE)
A117: 站外 | B117: AD信息流 | C117: 杭州宜格化妆品有限公司 | F117: 自投 | G117: 上海聚胜万合广告有限公司 | J117: =VLOOKUP(K117,'Sheet5'!$J$3:$K$200,2,FALSE) | K117: 1761595756647431 | N117: 否 | P117: 否 | Q117: 否 | S117: =VLOOKUP(B117,'Sheet9'!$B$2:$G$191,3,FALSE) | T117: =VLOOKUP(B117,'Sheet9'!$B$2:$G$191,4,FALSE) | U117: =VLOOKUP(B117,'Sheet9'!$B$2:$G$191,5,FALSE) | V117: 推广中心组 | W117: =VLOOKUP(K117,'Sheet11'!$X$2:$AH$279,11,FALSE)
A118: 站外 | B118: AD信息流 | C118: 杭州宜格化妆品有限公司 | F118: 自投 | G118: 上海聚胜万合广告有限公司 | J118: =VLOOKUP(K118,'Sheet5'!$J$3:$K$200,2,FALSE) | K118: 1761595754386509 | N118: 否 | P118: 否 | Q118: 否 | S118: =VLOOKUP(B118,'Sheet9'!$B$2:$G$191,3,FALSE) | T118: =VLOOKUP(B118,'Sheet9'!$B$2:$G$191,4,FALSE) | U118: =VLOOKUP(B118,'Sheet9'!$B$2:$G$191,5,FALSE) | V118: 推广中心组 | W118: =VLOOKUP(K118,'Sheet11'!$X$2:$AH$279,11,FALSE)
A119: 站外 | B119: AD信息流 | C119: 杭州宜格化妆品有限公司 | F119: 自投 | G119: 上海聚胜万合广告有限公司 | J119: =VLOOKUP(K119,'Sheet5'!$J$3:$K$200,2,FALSE) | K119: 1761236891646989 | N119: 否 | P119: 否 | Q119: 否 | S119: =VLOOKUP(B119,'Sheet9'!$B$2:$G$191,3,FALSE) | T119: =VLOOKUP(B119,'Sheet9'!$B$2:$G$191,4,FALSE) | U119: =VLOOKUP(B119,'Sheet9'!$B$2:$G$191,5,FALSE) | V119: 推广中心组 | W119: =VLOOKUP(K119,'Sheet11'!$X$2:$AH$279,11,FALSE)
A120: 站外 | B120: UD信息流 | C120: 杭州宜格化妆品有限公司 | F120: 自投 | G120: 上海剧星传媒股份有限公司 | J120: =VLOOKUP(K120,'Sheet5'!$J$3:$K$200,2,FALSE) | K120: 1493959 | N120: 否 | P120: 否 | Q120: 否 | S120: =VLOOKUP(B120,'Sheet9'!$B$2:$G$191,3,FALSE) | T120: =VLOOKUP(B120,'Sheet9'!$B$2:$G$191,4,FALSE) | U120: =VLOOKUP(B120,'Sheet9'!$B$2:$G$191,5,FALSE) | V120: 推广中心组 | W120: =VLOOKUP(K120,'Sheet11'!$X$2:$AH$279,11,FALSE)
A121: 站外 | B121: 小红书加热 | C121: 杭州宜格化妆品有限公司 | E121: 小红书(TFPT08) | F121: 代投 | G121: 上海博观瑞思传媒科技有限公司(VEN02000) | J121: 博观-花西子-2 | K121: 294814 | P121: 否(NO) | Q121: 是(YES) | R121: 否 | S121: =VLOOKUP(B121,'Sheet9'!$B$2:$G$191,3,FALSE) | T121: =VLOOKUP(B121,'Sheet9'!$B$2:$G$191,4,FALSE) | U121: =VLOOKUP(B121,'Sheet9'!$B$2:$G$191,5,FALSE) | V121: 内容投放组 | W121: =VLOOKUP(K121,'Sheet11'!$X$2:$AH$279,11,FALSE)
A122: 站外 | B122: B站起飞加热 | C122: 杭州宜格化妆品有限公司 | F122: 自投 | G122: 杭州羽联信息科技有限公司 | J122: 火烧云3户 | K122: 火烧云3户 | N122: 否 | S122: =VLOOKUP(B122,'Sheet9'!$B$2:$G$191,3,FALSE) | T122: =VLOOKUP(B122,'Sheet9'!$B$2:$G$191,4,FALSE) | U122: =VLOOKUP(B122,'Sheet9'!$B$2:$G$191,5,FALSE) | V122: 内容投放组 | W122: =VLOOKUP(K122,'Sheet11'!$X$2:$AH$279,11,FALSE)
A123: 站外 | B123: B站起飞加热 | C123: 杭州宜格化妆品有限公司 | F123: 自投 | G123: 上海无堂网络科技有限公司 | J123: 无堂 | K123: 无堂 | N123: 否 | S123: =VLOOKUP(B123,'Sheet9'!$B$2:$G$191,3,FALSE) | T123: =VLOOKUP(B123,'Sheet9'!$B$2:$G$191,4,FALSE) | U123: =VLOOKUP(B123,'Sheet9'!$B$2:$G$191,5,FALSE) | V123: 内容投放组 | W123: =VLOOKUP(K123,'Sheet11'!$X$2:$AH$279,11,FALSE)
A124: 站内 | B124: 天猫-直通车 | C124: 杭州宜格化妆品有限公司 | D124: 正常使用 | E124: 直通车 | F124: 自投 | G124: 杭州阿里妈妈软件服务有限公司 | J124: 天猫花西子旗舰店-直通车 | K124: DP015-022 | N124: 是 | O124: 是 | P124: 否 | Q124: 否 | R124: 是 | S124: =VLOOKUP(B124,'Sheet9'!$B$2:$G$191,3,FALSE) | T124: =VLOOKUP(B124,'Sheet9'!$B$2:$G$191,4,FALSE) | U124: =VLOOKUP(B124,'Sheet9'!$B$2:$G$191,5,FALSE) | V124: 推广中心组 | W124: =VLOOKUP(K124,'Sheet11'!$X$2:$AH$279,11,FALSE) | Y124: 贝果 | Z124: 杜英晗、刘建旺、刘如敏、韦应峰 | AA124: 账号密码
A125: 站内 | B125: 天猫-引力魔方 | C125: 杭州宜格化妆品有限公司 | D125: 正常使用 | E125: 引力魔方 | F125: 自投 | G125: 杭州阿里妈妈软件服务有限公司 | J125: 天猫花西子旗舰店-引力魔方 | K125: DP015-023 | N125: 是 | O125: 是 | P125: 否 | Q125: 否 | R125: 是 | S125: =VLOOKUP(B125,'Sheet9'!$B$2:$G$191,3,FALSE) | T125: =VLOOKUP(B125,'Sheet9'!$B$2:$G$191,4,FALSE) | U125: =VLOOKUP(B125,'Sheet9'!$B$2:$G$191,5,FALSE) | V125: 推广中心组 | W125: =VLOOKUP(K125,'Sheet11'!$X$2:$AH$279,11,FALSE) | Y125: 贝果 | Z125: 杜英晗、刘建旺、刘如敏、韦应峰 | AA125: 账号密码
A126: 站内 | B126: 天猫-万相台-超级直播 | C126: 杭州宜格化妆品有限公司 | F126: 自投 | G126: 杭州阿里妈妈软件服务有限公司 | J126: 天猫花西子旗舰店-万相台-超级直播 | K126: DP015-017 | N126: 否 | S126: =VLOOKUP(B126,'Sheet9'!$B$2:$G$191,3,FALSE) | T126: =VLOOKUP(B126,'Sheet9'!$B$2:$G$191,4,FALSE) | U126: =VLOOKUP(B126,'Sheet9'!$B$2:$G$191,5,FALSE) | V126: 推广中心组 | W126: =VLOOKUP(K126,'Sheet11'!$X$2:$AH$279,11,FALSE)
A127: 站内 | B127: 天猫-万相台-超级短视频 | C127: 杭州宜格化妆品有限公司 | F127: 自投 | G127: 杭州阿里妈妈软件服务有限公司 | J127: 天猫花西子旗舰店-万相台-超级短视频 | K127: DP015-021 | N127: 否 | S127: =VLOOKUP(B127,'Sheet9'!$B$2:$G$191,3,FALSE) | T127: =VLOOKUP(B127,'Sheet9'!$B$2:$G$191,4,FALSE) | U127: =VLOOKUP(B127,'Sheet9'!$B$2:$G$191,5,FALSE) | V127: 推广中心组 | W127: =VLOOKUP(K127,'Sheet11'!$X$2:$AH$279,11,FALSE)
...

Sheet 充值账户-投放（维度数据）
B1: 公司主体 | C1: 投放平台 | D1: 投放方式 | E1: 平台对合作应供应商名称 | F1: 账号 | G1: 编码 | H1: 是否按消耗开票 | I1: 是否为充值账户 | J1: 是否能取到充值/消耗明细 | K1: 是否存在充值赠送金 | L1: 是否存在返利 | M1: 是否通过此账户申请开票 | N1: 使用中心 | O1: 使用二级部门 | P1: 使用三级部门 | Q1: 业务对接人 | R1: 财务对接人
B2: 杭州宜格化妆品有限公司 | C2: 天猫 | D2: 自投 | E2: 杭州阿里妈妈软件服务有限公司 | F2: 天猫花西子旗舰店-直通车 | G2: DP015-ZTC | I2: 是 | J2: 是 | K2: 否 | L2: 否 | M2: 是 | N2: 品牌运营中心 | O2: 广告投放部 | P2: 平台电商部 | Q2: 盐首（刘如敏） | R2: 贝果
B3: 杭州宜格化妆品有限公司 | C3: 天猫 | D3: 自投 | E3: 杭州阿里妈妈软件服务有限公司 | F3: 天猫花西子旗舰店-引力魔方 | G3: DP015-YLMF | I3: 是 | J3: 是 | K3: 否 | L3: 否 | M3: 是 | N3: 品牌运营中心 | O3: 广告投放部 | P3: 平台电商部 | Q3: 盐首（刘如敏） | R3: 贝果
B4: 杭州宜格化妆品有限公司 | C4: 天猫 | D4: 自投 | E4: 浙江阿里巴巴通信技术有限公司 | F4: 天猫花西子旗舰店-万相台 | G4: DP015-WXT | I4: 是 | J4: 是 | K4: 否 | L4: 否 | M4: 是 | N4: 品牌运营中心 | O4: 广告投放部 | P4: 平台电商部 | Q4: 洛竹（程铭） | R4: 贝果
A5: 淘宝匠泽-直通车 | B5: 杭州匠泽电子商务有限公司 | C5: 天猫 | D5: 自投 | E5: 杭州阿里妈妈软件服务有限公司 | F5: 天猫花西子匠泽店-直通车 | G5: DP001-ZTC | I5: 是 | J5: 是 | K5: 否 | L5: 否 | M5: 是 | N5: 品牌运营中心 | O5: 广告投放部 | P5: 平台电商部 | Q5: 盐首（刘如敏） | R5: 贝果
A6: 淘宝匠泽-引力魔方 | B6: 杭州匠泽电子商务有限公司 | C6: 天猫 | D6: 自投 | E6: 杭州阿里妈妈软件服务有限公司 | F6: 天猫花西子匠泽店-引力魔方 | G6: DP001-YLMF | I6: 是 | J6: 是 | K6: 否 | L6: 否 | M6: 是 | N6: 品牌运营中心 | O6: 广告投放部 | P6: 平台电商部 | Q6: 盐首（刘如敏） | R6: 贝果
B7: 杭州匠泽电子商务有限公司 | C7: 天猫 | D7: 自投 | E7: 浙江阿里巴巴通信技术有限公司 | F7: 天猫花西子匠泽店-万相台 | G7: DP001-WXT | I7: 是 | J7: 是 | K7: 否 | L7: 否 | M7: 是 | N7: 品牌运营中心 | O7: 广告投放部 | P7: 平台电商部 | Q7: 盐首（刘如敏） | R7: 贝果
B8: 杭州宜格化妆品有限公司 | C8: 天猫 | D8: 自投 | E8: 杭州阿里妈妈软件服务有限公司 | F8: 天猫花西子旗舰店-淘宝客 | G8: DP015-TBK | I8: 是 | J8: 是 | K8: 否 | L8: 否 | M8: 是 | Q8: 林胖（林玲）
B9: 杭州匠泽电子商务有限公司 | C9: 天猫 | D9: 自投 | E9: 杭州阿里妈妈软件服务有限公司 | F9: 天猫花西子匠泽店-淘宝客 | G9: DP001-TBK | I9: 是 | J9: 是 | K9: 否 | L9: 否 | M9: 是 | Q9: 林胖（林玲）
B10: 杭州匠泽电子商务有限公司 | C10: 京东 | D10: 自投 | E10: 重庆京东海嘉电子商务有限公司 | F10: 京东花西子自营店 | G10: DP033-JDZY | I10: 是 | J10: 是 | K10: 否 | L10: 否 | M10: 是 | N10: 品牌运营中心 | O10: 广告投放部 | P10: 平台电商部 | Q10: 大阳（徐庄南） | R10: 贝果
B11: 杭州匠泽电子商务有限公司 | C11: 京东 | D11: 自投 | E11: 重庆京东海嘉电子商务有限公司 | F11: 京东花西子旗舰店 | G11: DP002-JD | I11: 是 | J11: 是 | K11: 否 | L11: 否 | M11: 是 | N11: 品牌运营中心 | O11: 广告投放部 | P11: 平台电商部 | Q11: 大阳（徐庄南） | R11: 贝果
B12: 杭州匠泽电子商务有限公司 | C12: 唯品会 | D12: 自投 | E12: 广州海珠品唯信息服务有限公司 | F12: 唯品会花西子自营店 | G12: DP029-WPH | I12: 是 | J12: 是 | K12: 否 | L12: 是 | M12: 是 | N12: 品牌运营中心 | O12: 广告投放部 | P12: 平台电商部 | Q12: 立立夏（武雨环） | R12: 贝果
B13: 杭州匠泽电子商务有限公司 | C13: 拼多多 | D13: 自投 | E13: 上海寻梦信息技术有限公司 | F13: 拼多多花西子专卖店 | G13: DP011-PDD | I13: 是 | J13: 是 | Q13: 鹿其（俞麟峰）
B14: 杭州匠泽电子商务有限公司 | C14: 拼多多 | D14: 自投 | E14: 上海寻梦信息技术有限公司 | F14: 拼多多花西子美妆专卖店 | G14: DP069-PDD | I14: 是 | J14: 是 | Q14: 鹿其（俞麟峰）
B15: 杭州匠泽电子商务有限公司 | C15: 拼多多 | D15: 自投 | E15: 上海寻梦信息技术有限公司 | F15: 拼多多花西子美妆旗舰店 | G15: DP071-PDD | I15: 是 | J15: 是 | Q15: 鹿其（俞麟峰）
B16: 杭州匠泽电子商务有限公司 | C16: 拼多多 | D16: 自投 | E16: 上海寻梦信息技术有限公司 | F16: 拼多多花西子匠泽店 | G16: DP030-PDD | I16: 是 | J16: 是 | Q16: 鹿其（俞麟峰）
A17: DOU+ | B17: 杭州宜格化妆品有限公司 | C17: 抖音 | D17: 自投 | E17: 湖北巨量引擎科技有限公司 | F17: 戏曲红妆 | G17: 1713571308516366 | I17: 是 | J17: 是 | K17: 否 | L17: 否 | M17: 是 | N17: 品牌运营中心 | O17: 品牌运营中心-广告投放部-内容投放部 | Q17: 空青
A18: 抖音官号DOU+ | B18: 杭州宜格化妆品有限公司 | C18: 抖音 | D18: 自投 | E18: 湖北巨量引擎科技有限公司 | F18: 花西子在海外 | G18: 1710588438708239 | I18: 是 | J18: 是 | K18: 否 | L18: 否 | M18: 是 | N18: 品牌运营中心 | O18: 抖音部-内容部-综合账号运营组 | Q18: 南嘉
A19: 矩阵号DOU+ | B19: 杭州宜格化妆品有限公司 | C19: 抖音 | D19: 自投 | E19: 湖北巨量引擎科技有限公司 | F19: 花西子妆养旗舰店 | G19: 1689943229305863 | I19: 是 | J19: 是 | K19: 否 | L19: 否 | M19: 是 | N19: 品牌运营中心 | O19: 抖音部-内容部-综合账号运营组 | Q19: 海水
A20: 矩阵号DOU+ | B20: 杭州宜格化妆品有限公司 | C20: 抖音 | D20: 自投 | E20: 湖北巨量引擎科技有限公司 | F20: 花西子官方旗舰店底妆精选 | G20: 1673714311187471 | I20: 是 | J20: 是 | K20: 否 | L20: 否 | M20: 是 | N20: 品牌运营中心 | O20: 抖音部-内容部-综合账号运营组 | Q20: 奈雪/晚意
A21: 矩阵号DOU+ | B21: 杭州宜格化妆品有限公司 | C21: 抖音 | D21: 自投 | E21: 湖北巨量引擎科技有限公司 | F21: 花西子礼物精选 | G21: 1709154203629639 | I21: 是 | J21: 是 | K21: 否 | L21: 否 | M21: 是 | N21: 品牌运营中心 | O21: 抖音部-内容部-综合账号运营组 | Q21: 奈雪/晚意
A22: 矩阵号DOU+ | B22: 杭州宜格化妆品有限公司 | C22: 抖音 | D22: 自投 | E22: 湖北巨量引擎科技有限公司 | F22: 东方有佳人 | G22: 1676272771724301 | I22: 是 | J22: 是 | K22: 否 | L22: 否 | M22: 是 | N22: 品牌运营中心 | O22: 抖音部-内容部-综合账号运营组 | Q22: 海水
A23: 千川信息流 | B23: 杭州宜格化妆品有限公司 | C23: 抖音 | D23: 自投 | E23: 湖北巨量引擎科技有限公司 | F23: 花西子-小店随心推 | G23: 1695646517812232 | I23: 是 | N23: 品牌运营中心 | O23: 渠道运营部 | P23: 抖音部 | Q23: 韩兴泉、奶茶（唐丽）
B24: 杭州宜格化妆品有限公司 | C24: 巨量星图 | E24: 武汉巨量星图科技有限公司 | F24: jinyan@zhimei.us | G24: 1709153479960584 | I24: 是 | Q24: 杜若
A25: DOU+ | B25: 杭州宜格化妆品有限公司 | C25: 抖音 | D25: 自投 | E25: 湖北巨量引擎科技有限公司 | F25: 花西子官方旗舰店 | G25: 1601161499296772 | I25: 是 | N25: 品牌运营中心 | O25: 品牌运营中心-内容电商部-抖音部 | Q25: 空青、七禾、南嘉
B26: 杭州宜格化妆品有限公司 | C26: 天猫 | D26: 自投 | E26: 杭州阿里妈妈淘联信息技术有限公司 | F26: 天猫花西子旗舰店-星任务 | G26: DP015-XRW | Q26: 杜若
A27: 权益红包-直播间 | B27: 杭州宜格化妆品有限公司 | C27: 天猫 | D27: 自投 | E27: 杭州阿里妈妈软件服务有限公司 | F27: 天猫花西子旗舰店-权益红包 | G27: DP015-QYHB | Q27: 阿泽
B28: 杭州宜格化妆品有限公司 | C28: 小红书 | D28: 自投 | E28: 薯一薯二文化传媒（上海）有限公司 | F28: yigehzp@163.com | G28: 55d34272f5a26377d1b784dd

Sheet 基础信息
A1: 字段 | B1: 字段类别 | C1: 字段解释 | D1: 用途与诉求 | E1: 字段名 | F1: 字段长度 | G1: 是否主键 | H1: 字段备注
A2: 公司主体 | B2: 下拉-单选
A3: 营销活动 | B3: 下拉-多选
A4: 公司手机号 | B4: 文本
A5: 公司邮箱 | B5: 文本
A6: 账户ID | B6: 文本
A7: 账户名 | B7: 文本
A8: 账户持有人 | B8: 文本
A9: 供应商名称 | B9: 文本
A10: 投放平台 | B10: 下拉-多选
A11: 账户状态 | B11: 下拉-单选
A12: 充值类型 | B12: 下拉-单选
A13: 是否存在充值赠送 | B13: 下拉-单选
... A21: 数据是否已回收 | B21: 下拉-单选

Sheet 枚举值
A1: 字段 | B1: 是否必填 | C1: 枚举值Code | D1: 枚举值 | E1: 外键 | F1: 备注说明 | G1: 经分是否需要 | H1: 经分是否需要业务处理 | I1: 经分处理逻辑
A2: 账户状态 | B2: Y | C2: 01 | E2: NA | F2: 枚举值说明 | G2: Y | H2: Y
C3: 02
C4: 03
C5: 04
C6: 05
A7: 充值类型 | B7: Y | C7: 01 | E7: NA | F7: 枚举值说明 | G7: Y | H7: Y
C8: 02
C9: 03
C10: 04
C11: 05

Sheet Sheet5
A1: 站内/站外 | B1: 营销活动 | C1: 公司主体 | D1: =+++++H7 | E1: 平台 | F1: 投放方式 | G1: 平台对合作应供应商名称 | H1: 对应业务场景及用途 | I1: 登录网址 | J1: 编码 | K1: 账号 | M1: 编码 | N1: 是否为资金充值账户 | O1: 是否能取到充值/消耗明细 | P1: 是否存在充值赠送金 | Q1: 是否存在返利 | R1: 截止2022年10月31日余额（元） | S1: 是否通过此账户申请开票 | T1: 使用中心 | U1: 使用二级部门 | V1: 使用三级部门 | W1: 业务使用人 | X1: 备注 | Y1: 财务对接人 | Z1: 账户权限owner | AA1: 登录方式
D2: 正常使用/闲置 | E2: 平台的称呼，如： 抖音-巨量千川 抖音-巨量纵横 快手 淘宝AD | F2: 自投/代投 | G2: 供应商全称 | N2: 是/否 | O2: 是/否 | P2: 是/否 | Q2: 是/否 | R2: 不填 | S2: 是/否 | T2: 一级中心 | Z2: 管理密码人员 | AA2: 验证码/账户密码
A3: 站内 | B3: 天猫-直通车 | C3: 杭州宜格化妆品有限公司 | D3: 正常使用 | E3: 淘宝 | F3: 自投 | G3: 杭州阿里妈妈软件服务有限公司 | H3: 直通车 | I3: https://subway.simba.taobao.com/index.jsp?spm=..0.da0f51bf8.6f372030STYU7d&file=indexnew.jsp#!/manage/campaign/detail?campaignId=222191719&start=2022-12-06&end=2022-12-06 | K3: 花西子旗舰店:陈玄、花西子旗舰店:幽兰、花西子旗舰店:盐首、花西子旗舰店:丰垚 | M3: ADV01 | N3: 是 | O3: 是 | P3: 否 | Q3: 否 | R3: 不填 | S3: 是 | T3: 品牌运营中心 | U3: 广告投放部 | V3: 平台电商部 | W3: 杜英晗、刘建旺、刘如敏、韦应峰 | Y3: 贝果 | Z3: 杜英晗、刘建旺、刘如敏、韦应峰 | AA3: 账号密码
A4: 站内 | B4: 天猫-引力魔方 | C4: 杭州宜格化妆品有限公司 | D4: 正常使用 | E4: 淘宝 | F4: 自投 | G4: 杭州阿里妈妈软件服务有限公司 | H4: 引力魔方 | I4: https://tuijian.taobao.com/indexbp.html?spm=a2e1u0.13920195.cf7687754.d17068800.2ab94d63TTfrAB#!/manage/def?spm=a2e1u0.13920195.cf7687754.d17068800.2ab94d63TTfrAB&alias=def&startTime=2022-12-06&endTime=2022-12-06&campaignGroupId=12563920&marketScene=display_user_define&statusList=START%2CPAUSE%2CWAIT | K4: 花西子旗舰店:陈玄、花西子旗舰店:幽兰、花西子旗舰店:盐首、花西子旗舰店:丰垚 | M4: ADV02 | N4: 是 | O4: 是 | P4: 否 | Q4: 否 | R4: 不填 | S4: 是 | T4: 品牌运营中心 | U4: 广告投放部 | V4: 平台电商部 | W4: 杜英晗、刘建旺、刘如敏、韦应峰 | Y4: 贝果 | Z4: 杜英晗、刘建旺、刘如敏、韦应峰 | AA4: 账号密码
A5: 站内 | B5: 天猫-明星店铺 | C5: 杭州宜格化妆品有限公司 | D5: 正常使用 | E5: 淘宝 | F5: 自投 | G5: 杭州阿里妈妈软件服务有限公司 | H5: 明星店铺 | I5: https://branding.taobao.com/index.action?spm=a2e0z.13920195.cf7687754.ddb5ad158.d9df6c51tgUS2R&file=index.action#!/account/index | K5: 花西子旗舰店:陈玄、花西子旗舰店:幽兰、花西子旗舰店:盐首、花西子旗舰店:丰垚 | M5: ADV03 | N5: 是 | O5: 是 | P5: 否 | Q5: 否 | R5: 不填 | S5: 是 | T5: 品牌运营中心 | U5: 广告投放部 | V5: 平台电商部 | W5: 杜英晗、刘建旺、刘如敏、韦应峰 | Y5: 贝果 | Z5: 杜英晗、刘建旺、刘如敏、韦应峰 | AA5: 账号密码
A6: 站内 | B6: 天猫-万相台-超级直播 | C6: 杭州宜格化妆品有限公司 | D6: 正常使用 | E6: 淘宝 | F6: 自投 | G6: 浙江阿里巴巴通信技术有限公司 | H6: 超级直播 | I6: https://adbrain.taobao.com/indexbp.html?spm=a2etp.11817080.cf7687754.1.3cfc340cF6NZNK#!/live/report-rtp/index?alias=duration&bizCode=adStrategyDuration&perspective=report&startTime=2022-11-12&endTime=2022-12-05&vs=false&version=all&dateType=history&effect=15&effectType=click&tab=campaign&reportQuery=%5Bobject%20Object%5D&spm= | K6: 花西子旗舰店:陈玄、花西子旗舰店:幽兰、花西子旗舰店:盐首、花西子旗舰店:丰垚 | M6: ADV04 | N6: 是 | O6: 是 | P6: 否 | Q6: 否 | R6: 不填 | S6: 是 | T6: 品牌运营中心 | U6: 广告投放部 | V6: 平台电商部 | W6: 杜英晗、刘建旺、刘如敏、韦应峰 | Y6: 贝果 | Z6: 杜英晗、刘建旺、刘如敏、韦应峰 | AA6: 账号密码
A7: 站内 | B7: 天猫-万相台-超级短视频 | C7: 杭州宜格化妆品有限公司 | D7: 正常使用 | E7: 淘宝 | F7: 自投 | G7: 浙江阿里巴巴通信技术有限公司 | H7: 超级短视频 | I7: https://adbrain.taobao.com/indexbp.html?spm=a2etp.11817080.cf7687754.1.3cfc340cF6NZNK#!/live/report-rtp/index?alias=duration&bizCode=adStrategyDuration&perspective=report&startTime=2022-11-12&endTime=2022-12-05&vs=false&version=all&dateType=history&effect=15&effectType=click&tab=campaign&reportQuery=%5Bobject%20Object%5D&spm= | K7: 花西子旗舰店:陈玄、花西子旗舰店:幽兰、花西子旗舰店:盐首、花西子旗舰店:丰垚 | M7: ADV05 | N7: 是 | O7: 是 | P7: 否 | Q7: 否 | R7: 不填 | S7: 是 | T7: 品牌运营中心 | U7: 广告投放部 | V7: 平台电商部 | W7: 杜英晗、刘建旺、刘如敏、韦应峰 | Y7: 贝果 | Z7: 杜英晗、刘建旺、刘如敏、韦应峰 | AA7: 账号密码
A8: 站内 | C8: 杭州宜格化妆品有限公司 | D8: 正常使用 | E8: 淘宝 | F8: 自投 | G8: 浙江阿里巴巴通信技术有限公司 | H8: 万相台 | I8: https://adbrain.taobao.com/indexbp.html?spm=a2etp.11817080.cf7687754.1.3cfc340cF6NZNK#!/live/report-rtp/index?alias=duration&bizCode=adStrategyDuration&perspective=report&startTime=2022-11-12&endTime=2022-12-05&vs=false&version=all&dateType=history&effect=15&effectType=click&tab=campaign&reportQuery=%5Bobject%20Object%5D&spm= | K8: 花西子旗舰店:陈玄、花西子旗舰店:幽兰、花西子旗舰店:盐首、花西子旗舰店:丰垚 | M8: ADV06 | N8: 是 | O8: 是 | P8: 否 | Q8: 否 | R8: 不填 | S8: 是 | T8: 品牌运营中心 | U8: 广告投放部 | V8: 平台电商部 | W8: 杜英晗、刘建旺、刘如敏、韦应峰 | Y8: 贝果 | Z8: 杜英晗、刘建旺、刘如敏、韦应峰 | AA8: 账号密码
A9: 站内 | B9: 天猫-超级互动城 | C9: 杭州宜格化妆品有限公司 | D9: 正常使用 | E9: 淘宝 | F9: 自投 | G9: 浙江阿里巴巴通信技术有限公司 | H9: 超级互动城 | I9: https://chaojihudong.taobao.com/indexbp.html?spm=a2e10l.13920195.cf7687754.d17068800.53f4677930Jd7Q#!/manage/shop-guarantee?alias=shop-guarantee&perspective=manage | K9: 花西子旗舰店:陈玄、花西子旗舰店:幽兰、花西子旗舰店:盐首、花西子旗舰店:丰垚 | M9: ADV07 | N9: 是 | O9: 是 | P9: 否 | Q9: 否 | R9: 不填 | S9: 是 | T9: 品牌运营中心 | U9: 广告投放部 | V9: 平台电商部 | W9: 杜英晗、刘建旺、刘如敏、韦应峰 | Y9: 贝果 | Z9: 杜英晗、刘建旺、刘如敏、韦应峰 | AA9: 账号密码
A10: 站内 | C10: 杭州匠泽电子商务有限公司 | D10: 正常使用 | E10: 京东 | F10: 自投 | G10: 重庆京东海嘉电子商务有限公司 | H10: 京东自营 | I10: https://product.shop.jd.com/rest/ware/list/manage?wareStatusStr=onSale&firstQuery=1 | K10: wet67956637 | M10: ADV08 | N10: 是 | O10: 是 | P10: 否 | Q10: 否 | R10: 不填 | S10: 是 | T10: 品牌运营中心 | U10: 广告投放部 | V10: 平台电商部 | W10: 周薇 | Y10: 贝果 | Z10: 周薇 | AA10: 账号密码
A11: 站内 | C11: 杭州匠泽电子商务有限公司 | D11: 正常使用 | E11: 京东 | F11: 自投 | G11: 重庆京东海嘉电子商务有限公司 | H11: 京东自营 | I11: https://product.shop.jd.com/rest/ware/list/manage?wareStatusStr=onSale&firstQuery=1 | K11: 花西子自营-代理2 | M11: ADV09 | N11: 是 | O11: 是 | P11: 否 | Q11: 否 | R11: 不填 | S11: 是 | T11: 品牌运营中心 | U11: 广告投放部 | V11: 平台电商部 | W11: 樗里 | Y11: 贝果 | Z11: 樗里 | AA11: 账号密码
A12: 站内 | C12: 杭州匠泽电子商务有限公司 | D12: 正常使用 | E12: 京东 | F12: 自投 | G12: 重庆京东海嘉电子商务有限公司 | H12: 京东POP | I12: https://product.shop.jd.com/rest/ware/list/manage?wareStatusStr=onSale&firstQuery=1 | K12: 花西子pop委托 | M12: ADV10 | N12: 是 | O12: 是 | P12: 否 | Q12: 否 | R12: 不填 | S12: 是 | T12: 品牌运营中心 | U12: 广告投放部 | V12: 平台电商部 | W12: 樗里 | Y12: 贝果 | Z12: 樗里 | AA12: 账号密码
A13: 站内 | C13: 杭州匠泽电子商务有限公司 | D13: 正常使用 | E13: 京东 | F13: 自投 | G13: 重庆京东海嘉电子商务有限公司 | H13: 京东POP | I13: https://product.shop.jd.com/rest/ware/list/manage?wareStatusStr=onSale&firstQuery=1 | K13: 花西子-麒麟 | M13: ADV11 | N13: 是 | O13: 是 | P13: 否 | Q13: 否 | R13: 不填 | S13: 是 | T13: 品牌运营中心 | U13: 广告投放部 | V13: 平台电商部 | W13: 樗里 | Y13: 贝果 | Z13: 樗里 | AA13: 账号密码
A14: 站内 | C14: 杭州匠泽电子商务有限公司 | D14: 正常使用 | E14: 京东 | F14: 自投 | G14: 重庆京东海嘉电子商务有限公司 | H14: 京东POP | I14: https://product.shop.jd.com/rest/ware/list/manage?wareStatusStr=onSale&firstQuery=1 | K14: 花西子旗舰店 | M14: ADV12 | N14: 是 | O14: 是 | P14: 否 | Q14: 否 | R14: 不填 | S14: 是 | T14: 品牌运营中心 | U14: 广告投放部 | V14: 平台电商部 | W14: 徐庄南 | Y14: 贝果 | Z14: 徐庄南 | AA14: 账号密码
A15: 站内 | C15: 杭州匠泽电子商务有限公司 | D15: 正常使用 | E15: 唯品 | F15: 自投 | G15: 广州海珠品唯信息服务有限公司 | H15: 唯品会 | I15: https://passport.vip.com/login?whereFrom=vipotd&src=https%3A%2F%2Fe.vip.com%2Fmain.html | K15: 15990052165 | M15: ADV13 | N15: 是 | O15: 是 | P15: 否 | Q15: 是 | R15: 不填 | S15: 是 | T15: 品牌运营中心 | U15: 广告投放部 | V15: 平台电商部 | W15: 赵东 | Y15: 贝果 | Z15: 赵东 | AA15: 账号密码
A16: 站内 | C16: 杭州匠泽电子商务有限公司 | D16: 正常使用 | E16: 唯品 | F16: 自投 | G16: 广州海珠品唯信息服务有限公司 | H16: 唯品会 | I16: https://passport.vip.com/login?whereFrom=vipotd&src=https%3A%2F%2Fe.vip.com%2Fmain.html | K16: 15867105936 | M16: ADV14 | N16: 是 | O16: 是 | P16: 否 | Q16: 是 | R16: 不填 | S16: 是 | T16: 品牌运营中心 | U16: 广告投放部 | V16: 平台电商部 | W16: 赵东 | Y16: 贝果 | Z16: 赵东 | AA16: 账号密码
A17: 站内 | C17: 杭州匠泽电子商务有限公司 | D17: 正常使用 | E17: 抖音-巨量纵横 | F17: 自投 | G17: 广东省广告集团股份有限公司 | H17: 京东自营抖音AD引流（CID） | I17: https://business.oceanengine.com/site/promotion?#/account | K17: huaxizi_xinxliuad2@163.com | M17: ADV15 | N17: 是 | O17: 是 | P17: 是 | Q17: 是 | R17: 不填 | S17: 是 | T17: 品牌运营中心 | U17: 广告投放部 | V17: 平台电商部 | W17: 徐庄南 | Y17: 贝果 | Z17: 徐庄南 | AA17: 账号密码
A18: 站内 | C18: 杭州匠泽电子商务有限公司 | D18: 正常使用 | E18: 考拉 | F18: 自投 | G18: 考拉海购（杭州）科技有限公司 | H18: 考拉 | I18: https://partner.kaola.com/index | K18: 18069829269 | M18: ADV16 | N18: 是 | O18: 是 | P18: 否 | Q18: 否 | R18: 不填 | S18: 是 | T18: 品牌运营中心 | U18: 广告投放部 | V18: 平台电商部 | W18: 徐庄南 | Y18: 贝果 | Z18: 徐庄南 | AA18: 账号密码
A19: 站内 | C19: 杭州匠泽电子商务有限公司 | D19: 正常使用 | E19: 京东到家 | F19: 自投 | G19: 上海京东到家元信信息技术有限公司 | H19: 京准通 | I19: https://jzt.jd.com/home/#/index | K19: 杭州匠泽电子商务 | M19: ADV17 | N19: 是 | O19: 是 | P19: 是 | Q19: 否 | R19: 不填 | S19: 是 | T19: 品牌运营中心 | U19: 广告投放部 | V19: 平台电商部 | W19: 徐庄南 | Y19: 贝果 | Z19: 徐庄南 | AA19: 账号密码
A20: 站内 | B20: 天猫-直通车 | C20: 杭州匠泽电子商务有限公司 | D20: 正常使用 | E20: 淘宝 | F20: 自投 | G20: 杭州阿里妈妈软件服务有限公司 | H20: 直通车 | I20: https://subway.simba.taobao.com/index.jsp?spm=..0.da0f51bf8.6f372030STYU7d&file=indexnew.jsp#!/manage/campaign/detail?campaignId=222191719&start=2022-12-06&end=2022-12-06 | K20: 花西子匠泽专卖店:大阳 | M20: ADV18 | N20: 是 | O20: 是 | P20: 否 | Q20: 否 | R20: 不填 | S20: 是 | T20: 品牌运营中心 | U20: 广告投放部 | V20: 平台电商部 | W20: 徐庄南 | Y20: 贝果 | Z20: 徐庄南 | AA20: 账号密码
A21: 站内 | C21: 杭州宜格化妆品有限公司 | D21: 正常使用 | E21: 小红书 | F21: 自投 | G21: 江苏拾光宝盒信息技术有限公司 | H21: 内容加热 | I21: https://ad.xiaohongshu.com/ | K21: shiguang2251@ten-box.cn | M21: ADV20 | N21: 是 | O21: 是 | P21: 是 | Q21: 是 | R21: 不填 | S21: 否 | T21: 品牌运营中心 | U21: 广告投放部 | V21: 内容投放部 | W21: 甘草 | Y21: 贝果 | Z21: 甘草、清和 | AA21: 账号密码
A22: 站内 | C22: 杭州宜格化妆品有限公司 | D22: 正常使用 | E22: 小红书 | F22: 自投 | G22: 江苏拾光宝盒信息技术有限公司 | H22: 内容加热 | I22: https://ad.xiaohongshu.com/ | K22: shiguang1450@ten-box.cn | M22: ADV21 | N22: 是 | O22: 是 | P22: 是 | Q22: 是 | R22: 不填 | S22: 否 | T22: 品牌运营中心 | U22: 广告投放部 | V22: 内容投放部 | W22: 甘草 | Y22: 贝果 | Z22: 甘草、清和 | AA22: 账号密码
A23: 站内 | C23: 杭州宜格化妆品有限公司 | D23: 正常使用 | E23: 小红书 | F23: 自投 | G23: 江苏拾光宝盒信息技术有限公司 | H23: 内容加热 | I23: https://ad.xiaohongshu.com/ | K23: shiguang2272@ten-box.cn | M23: ADV22 | N23: 是 | O23: 是 | P23: 是 | Q23: 是 | R23: 不填 | S23: 否 | T23: 品牌运营中心 | U23: 广告投放部 | V23: 内容投放部 | W23: 甘草 | Y23: 贝果 | Z23: 甘草、清和 | AA23: 账号密码
A24: 站内 | C24: 杭州宜格化妆品有限公司 | D24: 正常使用 | E24: 小红书 | F24: 自投 | G24: 江苏拾光宝盒信息技术有限公司 | H24: 内容加热 | I24: https://ad.xiaohongshu.com/ | K24: shiguang2824@ten-box.cn | M24: ADV24 | N24: 是 | O24: 是 | P24: 是 | Q24: 是 | R24: 不填 | S24: 否 | T24: 品牌运营中心 | U24: 广告投放部 | V24: 内容投放部 | W24: 甘草 | Y24: 贝果 | Z24: 甘草、清和 | AA24: 账号密码
A25: 站内 | C25: 杭州宜格化妆品有限公司 | D25: 正常使用 | E25: 小红书 | F25: 自投 | G25: 广东省广告集团股份有限公司 | H25: 内容加热 | I25: https://ad.xiaohongshu.com/ | K25: huaxizi_xhongshu2@163.com | M25: ADV26 | N25: 是 | O25: 是 | P25: 是 | Q25: 是 | R25: 不填 | S25: 否 | T25: 品牌运营中心 | U25: 广告投放部 | V25: 内容投放部 | W25: 甘草 | Y25: 贝果 | Z25: 甘草、清和 | AA25: 账号密码
A26: 站内 | C26: 杭州宜格化妆品有限公司 | D26: 正常使用 | E26: 小红书 | F26: 自投 | G26: 广东省广告集团股份有限公司 | H26: 内容加热 | I26: https://ad.xiaohongshu.com/ | K26: huaxizi_xhongshu4@163.com | M26: ADV28 | N26: 是 | O26: 是 | P26: 是 | Q26: 是 | R26: 不填 | S26: 否 | T26: 品牌运营中心 | U26: 广告投放部 | V26: 内容投放部 | W26: 甘草 | Y26: 贝果 | Z26: 甘草、清和 | AA26: 账号密码
A27: 站内 | C27: 杭州宜格化妆品有限公司 | D27: 正常使用 | E27: 微博 | F27: 自投 | G27: 上海宇枫 | H27: 微博信息流 | I27: https://ad.weibo.com/ | K27: 花西子Florasis | M27: ADV35 | N27: 是 | O27: 是 | P27: 是 | Q27: 否 | S27: 否 | T27: 品牌运营中心 | U27: 广告投放部 | V27: 内容投放部 | W27: 柏倩倩 | Y27: 贝果 | Z27: 柏倩倩 | AA27: 账号密码
A28: 站内 | C28: 杭州宜格化妆品有限公司 | D28: 正常使用 | E28: 抖音 | F28: 自投 | G28: 上海博观瑞思传媒科技有限公司 | H28: DOU+ | I28: https://doujia.douyin.com/ | K28: 花西子官方旗舰店 | M28: ADV36 | N28: 是 | O28: 是 | P28: 否 | Q28: 否 | S28: 是 | T28: 品牌运营中心 | U28: 广告投放部 | V28: 内容投放部 | W28: 柏倩倩 | Y28: 贝果 | Z28: 柏倩倩 | AA28: 账号密码
A29: 站内 | B29: AD信息流 | C29: 杭州宜格化妆品有限公司 | D29: 正常使用 | E29: 抖音-巨量纵横 | F29: 自投 | G29: 广东省广告集团股份有限公司 | H29: 天猫抖音AD引流 | I29: https://ad.oceanengine.com/ | K29: huaxizi_xinxiliuad@163.com | M29: ADV37 | N29: 是 | O29: 是 | P29: 是 | Q29: 是 | R29: 不填 | S29: 是 | T29: 品牌运营中心 | U29: 广告投放部 | V29: 站外投放部 | W29: 白纸、阿布、志文、循安 | Y29: 贝果 | Z29: 白纸、阿布、志文、循安 | AA29: 账号密码
A30: 站内 | B30: AD信息流 | C30: 杭州宜格化妆品有限公司 | D30: 正常使用 | E30: 抖音-巨量纵横 | F30: 自投 | G30: 广东省广告集团股份有限公司 | H30: 天猫抖音AD引流 | I30: https://ad.oceanengine.com/ | K30: huaxizi_xinxiliuad4@163.com | M30: ADV38 | N30: 是 | O30: 是 | P30: 是 | Q30: 是 | R30: 不填 | S30: 是 | T30: 品牌运营中心 | U30: 广告投放部 | V30: 站外投放部 | W30: 白纸、阿布、志文、循安 | Y30: 贝果 | Z30: 白纸、阿布、志文、循安 | AA30: 账号密码
A31: 站内 | B31: AD信息流 | C31: 杭州宜格化妆品有限公司 | D31: 正常使用 | E31: 抖音-巨量纵横 | F31: 自投 | G31: 广东省广告集团股份有限公司 | H31: 天猫抖音AD引流 | I31: https://ad.oceanengine.com/ | K31: huaxizi_xinxliuad5@163.com | M31: ADV39 | N31: 是 | O31: 是 | P31: 是 | Q31: 是 | R31: 不填 | S31: 是 | T31: 品牌运营中心 | U31: 广告投放部 | V31: 站外投放部 | W31: 白纸、阿布、志文、循安 | Y31: 贝果 | Z31: 白纸、阿布、志文、循安 | AA31: 账号密码
A32: 站内 | B32: AD信息流 | C32: 杭州宜格化妆品有限公司 | D32: 正常使用 | E32: 抖音-巨量纵横 | F32: 自投 | G32: 广东省广告集团股份有限公司 | H32: 天猫抖音AD引流 | I32: https://ad.oceanengine.com/ | K32: huaxizi_xinxliuad7@163.com | M32: ADV40 | N32: 是 | O32: 是 | P32: 是 | Q32: 是 | R32: 不填 | S32: 是 | T32: 品牌运营中心 | U32: 广告投放部 | V32: 站外投放部 | W32: 白纸、阿布、志文、循安 | Y32: 贝果 | Z32: 白纸、阿布、志文、循安 | AA32: 账号密码
A33: 站内 | B33: AD信息流 | C33: 杭州宜格化妆品有限公司 | D33: 正常使用 | E33: 抖音-巨量纵横 | F33: 自投 | G33: 广东省广告集团股份有限公司 | H33: 天猫抖音AD引流 | I33: https://ad.oceanengine.com/ | K33: huaxizi_xinxliuad8@163.com | M33: ADV41 | N33: 是 | O33: 是 | P33: 是 | Q33: 是 | R33: 不填 | S33: 是 | T33: 品牌运营中心 | U33: 广告投放部 | V33: 站外投放部 | W33: 白纸、阿布、志文、循安 | Y33: 贝果 | Z33: 白纸、阿布、志文、循安 | AA33: 账号密码
A34: 站内 | B34: AD信息流 | C34: 杭州宜格化妆品有限公司 | D34: 正常使用 | E34: 抖音-巨量纵横 | F34: 自投 | G34: 群邑（上海）广告有限公司 | H34: 天猫抖音AD引流 | I34: https://ad.oceanengine.com/ | K34: huaxizi_xinxliuad9@163.com | M34: ADV42 | N34: 是 | O34: 是 | P34: 是 | Q34: 是 | R34: 不填 | S34: 是 | T34: 品牌运营中心 | U34: 广告投放部 | V34: 站外投放部 | W34: 白纸、阿布、志文、循安 | Y34: 贝果 | Z34: 白纸、阿布、志文、循安 | AA34: 账号密码
A35: 站内 | B35: AD信息流 | C35: 杭州宜格化妆品有限公司 | D35: 正常使用 | E35: 抖音-巨量纵横 | F35: 自投 | G35: 群邑（上海）广告有限公司 | H35: 天猫抖音AD引流 | I35: https://ad.oceanengine.com/ | K35: joy.du@mindshareworld.com | M35: ADV43 | N35: 是 | O35: 是 | P35: 是 | Q35: 是 | R35: 不填 | S35: 是 | T35: 品牌运营中心 | U35: 广告投放部 | V35: 站外投放部 | W35: 白纸、阿布、志文、循安 | Y35: 贝果 | Z35: 白纸、阿布、志文、循安 | AA35: 账号密码
A36: 站内 | B36: UD信息流 | C36: 杭州宜格化妆品有限公司 | D36: 正常使用 | E36: Uni Desk | F36: 自投 | G36: 北京九合互动文化传播有限公司 | H36: UD信息流引流 | I36: https://unidesk.taobao.com/index.html | K36: tb963892057577 | M36: ADV44 | N36: 是 | O36: 是 | P36: 是 | Q36: 是 | R36: 不填 | S36: 是 | T36: 品牌运营中心 | U36: 广告投放部 | V36: 站外投放部 | W36: 白纸、阿布、志文 | Y36: 贝果 | Z36: 白纸、阿布、志文 | AA36: 账号密码
A37: 站内 | C37: 杭州宜格化妆品有限公司 | D37: 正常使用 | E37: 百度营销 | F37: 自投 | G37: 北京云锐国际文化传媒有限公司 | H37: 百度信息流引流 | I37: https://cas.baidu.com/?tpl=www2&fromu=http%3A%2F%2Fwww2.b...ommon%2Fappinit.ajax | K37: 杭州宜格化妆品有限公司1（shvipyr花西子3） | M37: ADV46 | N37: 是 | O37: 是 | P37: 是 | Q37: 是 | R37: 不填 | S37: 是 | T37: 品牌运营中心 | U37: 广告投放部 | V37: 站外投放部 | W37: 白纸、阿布、循安 | Y37: 贝果 | Z37: 白纸、阿布、循安 | AA37: 账号密码
A38: 站内 | C38: 杭州宜格化妆品有限公司 | D38: 正常使用 | E38: 磁力引擎 | F38: 自投 | G38: 北京起量文化传媒有限公司 | H38: 快手信息流引流 | I38: https://ad.e.kuaishou.com/manage?__accountId__=14861051 | K38: 13362198950 | M38: ADV47 | N38: 是 | O38: 是 | P38: 是 | Q38: 是 | R38: 不填 | S38: 是 | T38: 品牌运营中心 | U38: 广告投放部 | V38: 站外投放部 | W38: 白纸、羽阳 | Y38: 贝果 | Z38: 白纸、羽阳 | AA38: 账号密码
A39: 站内 | B39: 磁力金牛 | C39: 杭州宜格化妆品有限公司 | D39: 正常使用 | E39: 磁力金牛 | F39: 自投 | G39: 北京起量文化传媒有限公司 | H39: 快手磁力金牛 | I39: https://niu.e.kuaishou.com/manage?__accountId__=13304454 | K39: 13396586970 | M39: ADV48 | N39: 是 | O39: 是 | P39: 是 | Q39: 是 | R39: 不填 | S39: 是 | T39: 品牌运营中心 | U39: 广告投放部 | V39: 站外投放部 | W39: 白纸、羽阳 | Y39: 贝果 | Z39: 白纸、羽阳 | AA39: 账号密码
A40: 站内 | C40: 杭州宜格化妆品有限公司 | D40: 正常使用 | E40: 腾讯ADQ | F40: 自投 | G40: 群邑（上海）广告有限公司 | H40: 微信渠道投放 | I40: https://ad.qq.com/atlas/23959502/index | K40: 微信扫码登录 | M40: ADV49 | N40: 是 | O40: 是 | P40: 是 | Q40: 是 | R40: 不填 | S40: 是 | T40: 品牌运营中心 | U40: 广告投放部 | V40: 站外投放部 | W40: 白纸 | Y40: 贝果 | Z40: 白纸 | AA40: 账号密码
A41: 站外 | B41: 千川信息流 | C41: 杭州宜格化妆品有限公司 | G41: 北京云锐国际文化传媒有限公司 | J41: 1727265617683469 | K41: 云锐-直播-官号2
A42: 站外 | B42: 磁力金牛 | G42: 北京云锐国际文化传媒有限公司 | J42: 13304453 | K42: 花西子Florasis-云锐测试
A43: 站外 | B43: AD信息流 | C43: 杭州宜格化妆品有限公司 | E43: 抖音 | G43: 广东省广告集团股份有限公司 | J43: 1762866886323341 | K43: abuHZP-天猫AD-省广-CID玉养气垫 | P43: 否 | Q43: 否
A44: 站外 | B44: AD信息流 | C44: 杭州宜格化妆品有限公司 | E44: 抖音 | G44: 广东省广告集团股份有限公司 | J44: 1758638395883534 | K44: abuHZP-天猫AD-省广-CID23玉容轻妆出行组合 | P44: 否 | Q44: 否
A45: 站外 | B45: AD信息流 | C45: 杭州宜格化妆品有限公司 | E45: 抖音 | G45: 广东省广告集团股份有限公司 | J45: 1744729041456135 | K45: HZP-天猫AD信息流-省广-CID9（X眉笔） | P45: 否 | Q45: 否
A46: 站外 | B46: AD信息流 | C46: 杭州宜格化妆品有限公司 | E46: 抖音 | G46: 广东省广告集团股份有限公司 | J46: 1744631353681928 | K46: HZP-天猫AD信息流-省广-CID4小黛伞防晒 | P46: 否 | Q46: 否
A47: 站外 | B47: AD信息流 | C47: 杭州宜格化妆品有限公司 | E47: 抖音 | G47: 广东省广告集团股份有限公司 | J47: 1752335658405895 | K47: 定妆花西子-杭州宜格CID投放-16玉养蜜粉 | P47: 否 | Q47: 否
A48: 站外 | B48: AD信息流 | C48: 杭州宜格化妆品有限公司 | E48: 抖音 | G48: 广东省广告集团股份有限公司 | J48: 1752335657150542 | K48: 定妆花西子-杭州宜格CID投放-14有色粉饼 | P48: 否 | Q48: 否
A49: 站外 | B49: AD信息流 | C49: 杭州宜格化妆品有限公司 | E49: 抖音 | G49: 广东省广告集团股份有限公司 | J49: 1750901317073991 | K49: 花西子-杭州宜格CID投放-6X持色唇纱 | P49: 否 | Q49: 否
A50: 站外 | B50: AD信息流 | C50: 杭州宜格化妆品有限公司 | E50: 抖音 | G50: 广东省广告集团股份有限公司 | J50: 1747107074839566 | K50: abuHZP-天猫AD信息流-省广-CID19素颜出行组合 | P50: 否 | Q50: 否
A51: 站外 | B51: AD信息流 | C51: 杭州宜格化妆品有限公司 | E51: 抖音 | G51: 广东省广告集团股份有限公司 | J51: 1750901319256072 | K51: 定妆花西子-杭州宜格CID投放-9玉养蜜粉 | P51: 否 | Q51: 否
A52: 站外 | B52: AD信息流 | C52: 杭州宜格化妆品有限公司 | E52: 抖音 | G52: 广东省广告集团股份有限公司 | J52: 1750901314010184 | K52: abu花西子-杭州宜格CID投放-2私模气垫 | P52: 否 | Q52: 否
A53: 站外 | B53: AD信息流 | C53: 杭州宜格化妆品有限公司 | E53: 抖音 | G53: 广东省广告集团股份有限公司 | J53: 1758638396516360 | K53: 花西子-杭州宜格CID投放-24X持色唇纱4P | P53: 否 | Q53: 否
A54: 站外 | B54: AD信息流 | C54: 杭州宜格化妆品有限公司 | E54: 抖音 | G54: 广东省广告集团股份有限公司 | J54: 1750901317821447 | K54: 花西子-杭州宜格CID投放-7X眉粉笔 | P54: 否 | Q54: 否
... A75: 站外 | B75: AD信息流 | C75: 杭州宜格化妆品有限公司 | E75: 抖音 | G75: 广东省广告集团股份有限公司 | J75: 1758638395143181 | K75: abuHZP-天猫AD-省广-CID22素颜出行组合(营销4P) | P75: 否 | Q75: 否
A76: 站外 | B76: 千川信息流 | C76: 杭州宜格化妆品有限公司 | E76: 抖音 | G76: 广东省广告集团股份有限公司 | J76: 1727435690629127 | K76: 省广-直播-官号1
A77: 站外 | B77: 矩阵号千川信息流 | C77: 杭州宜格化妆品有限公司 | E77: 抖音 | G77: 广东省广告集团股份有限公司 | J77: 1747734628974605 | K77: 省广数字集合-矩阵直播-花西子礼物精选
A78: 站外 | B78: 小红书加热 | C78: 杭州宜格化妆品有限公司 | E78: 小红书 | G78: 江苏拾光宝盒信息技术有限公司 | J78: 119989 | K78: 拾光宝盒（花西子Florasis3）
A79: 站外 | B79: 小红书加热 | C79: 杭州宜格化妆品有限公司 | E79: 小红书 | G79: 江苏拾光宝盒信息技术有限公司 | J79: 65933 | K79: 拾光宝盒（花西子Florasis）
A80: 站外 | B80: 小红书加热 | C80: 杭州宜格化妆品有限公司 | E80: 小红书 | G80: 江苏拾光宝盒信息技术有限公司 | J80: 119990 | K80: 拾光宝盒（花西子Florasis2）
A81: 站外 | B81: 磁力金牛 | C81: 杭州宜格化妆品有限公司 | E81: 快手 | G81: 快手 | J81: 17230613 | K81: 花西子官方旗舰店
A82: 站外 | B82: AD信息流 | C82: 杭州宜格化妆品有限公司 | E82: 抖音 | G82: 群邑（上海）广告有限公司 | J82: 1754167001896968 | K82: 杭州宜格化妆品-群邑天猫引流竞价-CID14-有色粉饼 | P82: 否 | Q82: 否
A83: 站外 | B83: AD信息流 | C83: 杭州宜格化妆品有限公司 | E83: 抖音 | G83: 群邑（上海）广告有限公司 | J83: 1744649914765325 | K83: 杭州宜格化妆品-群邑天猫引流竞价-CID07-玉养蜜粉 | P83: 否 | Q83: 否
A84: 站外 | B84: AD信息流 | C84: 杭州宜格化妆品有限公司 | E84: 抖音 | G84: 群邑（上海）广告有限公司 | J84: 1754167001310215 | K84: 杭州宜格化妆品-群邑天猫引流竞价-CID13-蜜粉饼 | P84: 否 | Q84: 否
A85: 站外 | B85: AD信息流 | C85: 杭州宜格化妆品有限公司 | E85: 抖音 | G85: 群邑（上海）广告有限公司 | J85: 1761579156325383 | K85: 群邑定妆-杭州宜格CID-14玉养喷雾 | P85: 否 | Q85: 否
A86: 站外 | B86: AD信息流 | C86: 杭州宜格化妆品有限公司 | E86: 抖音 | G86: 群邑（上海）广告有限公司 | J86: 1761579155761230 | K86: 群邑定妆-杭州宜格CID-13私模蜜粉 | P86: 否 | Q86: 否
A87: 站外 | B87: AD信息流 | C87: 杭州宜格化妆品有限公司 | E87: 抖音 | G87: 群邑（上海）广告有限公司 | J87: 1761579155066888 | K87: 群邑定妆-杭州宜格CID-12玉养蜜粉 | P87: 否 | Q87: 否
A88: 站外 | B88: AD信息流 | C88: 杭州宜格化妆品有限公司 | E88: 抖音 | G88: 群邑（上海）广告有限公司 | J88: 1754167002455111 | K88: 杭州宜格化妆品-群邑天猫引流竞价-CID15-定妆喷雾 | P88: 否 | Q88: 否
A89: 站外 | B89: AD信息流 | C89: 杭州宜格化妆品有限公司 | E89: 抖音 | G89: 群邑（上海）广告有限公司 | J89: 1754167000735758 | K89: 杭州宜格化妆品-群邑天猫引流竞价-CID12-私模蜜粉 | P89: 否 | Q89: 否
A90: 站外 | B90: AD信息流 | C90: 杭州宜格化妆品有限公司 | E90: 抖音 | G90: 群邑（上海）广告有限公司 | J90: 1734408229378061 | K90: 杭州宜格化妆品-天猫AD信息流-群邑12-代运营-玉养蜜粉 | P90: 否 | Q90: 否
A91: 站外 | B91: AD信息流 | C91: 杭州宜格化妆品有限公司 | E91: 抖音 | G91: 群邑（上海）广告有限公司 | J91: 1727635338328078 | K91: 杭州宜格化妆品-天猫AD信息流-群邑-05（备款） | P91: 否 | Q91: 否
A92: 站外 | B92: 千川信息流 | C92: 杭州宜格化妆品有限公司 | G92: 群邑（上海）广告有限公司 | J92: 1727535271575630 | K92: 群邑-直播-官号1
A93: 站外 | B93: 磁力引擎 | C93: 杭州宜格化妆品有限公司 | E93: 抖音 | G93: 群邑（上海）广告有限公司 | J93: 17029747 | K93: 花西子-QY2-小黛伞防晒 | P93: 否 | Q93: 否
A94: 站外 | B94: 磁力引擎 | C94: 杭州宜格化妆品有限公司 | E94: 抖音 | G94: 群邑（上海）广告有限公司 | J94: 17029746 | K94: 花西子-QY2-玉养蜜粉 | P94: 否 | Q94: 否
A95: 站外 | B95: 磁力引擎 | C95: 杭州宜格化妆品有限公司 | E95: 抖音 | G95: 群邑（上海）广告有限公司 | J95: 17029745 | K95: 花西子-QY2-丝柔唇纱 | P95: 否 | Q95: 否
A96: 站外 | B96: 磁力引擎 | C96: 杭州宜格化妆品有限公司 | E96: 抖音 | G96: 群邑（上海）广告有限公司 | J96: 17029744 | K96: 花西子-QY2-玉养气垫 | P96: 否 | Q96: 否
A97: 站外 | B97: 磁力引擎 | C97: 杭州宜格化妆品有限公司 | E97: 抖音 | G97: 群邑（上海）广告有限公司 | J97: 17029743 | K97: 花西子-QY2-私模蜜粉 | P97: 否 | Q97: 否
A98: 站外 | B98: 磁力引擎 | C98: 杭州宜格化妆品有限公司 | E98: 抖音 | G98: 群邑（上海）广告有限公司 | J98: 17029742 | K98: 花西子-QY2-素颜出行组合 | P98: 否 | Q98: 否
A99: 站外 | B99: 磁力引擎 | C99: 杭州宜格化妆品有限公司 | E99: 抖音 | G99: 群邑（上海）广告有限公司 | J99: 17029741 | K99: 花西子-QY2-同心锁口红 | P99: 否 | Q99: 否
A100: 站外 | B100: 磁力引擎 | C100: 杭州宜格化妆品有限公司 | E100: 抖音 | G100: 群邑（上海）广告有限公司 | J100: 17029740 | K100: 花西子彩妆 | P100: 否 | Q100: 否
A101: 站外 | B101: 磁力引擎 | C101: 杭州宜格化妆品有限公司 | E101: 抖音 | G101: 群邑（上海）广告有限公司 | J101: 17029739 | K101: 花西子彩妆 | P101: 否 | Q101: 否
A102: 站外 | B102: 磁力引擎 | C102: 杭州宜格化妆品有限公司 | E102: 抖音 | G102: 群邑（上海）广告有限公司 | J102: 17026499 | K102: 花西子彩妆 | P102: 否 | Q102: 否
A103: 站外 | B103: 磁力引擎 | C103: 杭州宜格化妆品有限公司 | E103: 抖音 | G103: 群邑（上海）广告有限公司 | J103: 16901306 | K103: 花西子-QY-私模蜜粉-DDN | P103: 否 | Q103: 否
A104: 站外 | B104: 磁力引擎 | C104: 杭州宜格化妆品有限公司 | E104: 抖音 | G104: 群邑（上海）广告有限公司 | J104: 16901305 | K104: 花西子-QY-玉养蜜粉-DDN | P104: 否 | Q104: 否
... A112: 站外 | B112: 磁力引擎 | C112: 杭州宜格化妆品有限公司 | E112: 抖音 | G112: 群邑（上海）广告有限公司 | J112: 16896876 | K112: 花西子彩妆 | P112: 否 | Q112: 否
A113: 站外 | B113: 磁力金牛 | C113: 杭州宜格化妆品有限公司 | E113: 快手 | G113: 群邑（上海）广告有限公司 | J113: 16909143 | K113: 花西子官方旗舰店-群邑2
A114: 站外 | B114: 磁力金牛 | C114: 杭州宜格化妆品有限公司 | E114: 快手 | G114: 群邑（上海）广告有限公司 | J114: 16909144 | K114: 花西子官方旗舰店-群邑3
A115: 站外 | B115: 磁力金牛 | C115: 杭州宜格化妆品有限公司 | E115: 快手 | G115: 群邑（上海）广告有限公司 | J115: 16909142 | K115: 花西子官方旗舰店-群邑1
A116: 站外 | B116: 磁力金牛 | C116: 杭州宜格化妆品有限公司 | E116: 快手 | G116: 群邑（上海）广告有限公司 | J116: 16909146 | K116: 花西子官方旗舰店-全站ROI
A117: 站外 | B117: 磁力金牛 | C117: 杭州宜格化妆品有限公司 | E117: 快手 | G117: 群邑（上海）广告有限公司 | J117: 16909147 | K117: 花西子官方旗舰店-群邑4
A118: 站外 | B118: 磁力金牛 | C118: 杭州宜格化妆品有限公司 | E118: 快手 | G118: 群邑（上海）广告有限公司 | J118: 16909148 | K118: 花西子官方旗舰店
A119: 站外 | B119: 磁力金牛 | C119: 杭州宜格化妆品有限公司 | E119: 快手 | G119: 群邑（上海）广告有限公司 | J119: 16907921 | K119: 花西子官方旗舰店
A120: 站外 | B120: 磁力金牛 | C120: 杭州宜格化妆品有限公司 | E120: 快手 | G120: 群邑（上海）广告有限公司 | J120: 16909145 | K120: 花西子官方旗舰店-群邑-RSH代投
A121: 站外 | B121: 千川信息流 | C121: 杭州宜格化妆品有限公司 | E121: 抖音 | G121: 上海博观瑞思传媒科技有限公司 | J121: 1695557841246222 | K121: 博观-直播-官号1
A122: 站外 | B122: 千川信息流 | C122: 杭州宜格化妆品有限公司 | E122: 抖音 | G122: 上海博观瑞思传媒科技有限公司 | J122: 1760222811427847 | K122: 博观-图文1-引流
A123: 站外 | B123: 千川信息流 | C123: 杭州宜格化妆品有限公司 | E123: 抖音 | G123: 知定堂 | J123: 1761146745368653 | K123: 知定堂-图文1-引流
A124: 站外 | B124: 千川信息流 | C124: 杭州宜格化妆品有限公司 | E124: 抖音 | J124: 1695646517812232 | K124: 花西子-小店随心推
A125: 站外 | B125: 矩阵号千川信息流 | C125: 杭州宜格化妆品有限公司 | E125: 抖音 | G125: 上海博观瑞思传媒科技有限公司 | J125: 1760519091540999 | K125: 博观-花西子-千川-3
A126: 站外 | B126: 矩阵号千川信息流 | C126: 杭州宜格化妆品有限公司 | E126: 抖音 | G126: 上海博观瑞思传媒科技有限公司 | J126: 1760519144208525 | K126: 博观-花西子-千川-4
A127: 站外 | B127: 矩阵号千川信息流 | C127: 杭州宜格化妆品有限公司 | E127: 抖音 | G127: 上海博观瑞思传媒科技有限公司 | J127: 1761057229537293 | K127: 博观-花西子-千川-5
...

Sheet Sheet9
A1: 营销活动分类 | B1: 营销活动场景 | C1: 编码 | D1: 一级部门 | E1: 二级部门 | F1: 三级部门 | G1: 四级部门
A2: IP明星内容合作 | B2: IP合作 | C2: YXHD01 | D2: 品牌运营中心 | E2: 市场广告推广部 | F2: 市场推广部 | G2: 市场PR组
A3: IP明星内容合作 | B3: 明星差旅 | C3: YXHD02 | D3: 品牌运营中心 | E3: 市场广告推广部 | F3: 市场推广部 | G3: 娱乐营销组
A4: IP明星内容合作 | B4: 明星代言单次合作 | C4: YXHD03 | D4: 品牌运营中心 | E4: 市场广告推广部 | F4: 市场推广部 | G4: 娱乐营销组
A5: IP明星内容合作 | B5: 明星代言合作 | C5: YXHD04 | D5: 品牌运营中心 | E5: 市场广告推广部 | F5: 市场推广部 | G5: 娱乐营销组
A6: IP明星内容合作 | B6: 明星拍摄 | C6: YXHD05 | D6: 品牌运营中心 | E6: 市场广告推广部 | F6: 市场推广部 | G6: 娱乐营销组
A7: IP明星内容合作 | B7: 明星影综营销号 | C7: YXHD06 | D7: 品牌运营中心 | E7: 市场广告推广部 | F7: 市场推广部 | G7: 娱乐营销组
A8: IP明星内容合作 | B8: 明星妆发造 | C8: YXHD07 | D8: 品牌运营中心 | E8: 市场广告推广部 | F8: 市场推广部 | G8: 娱乐营销组
A9: IP明星内容合作 | B9: 明星综艺线下活动 | C9: YXHD08 | D9: 品牌运营中心 | E9: 市场广告推广部 | F9: 市场推广部 | G9: 娱乐营销组
A10: IP明星内容合作 | B10: 影视综艺植入 | C10: YXHD09 | D10: 品牌运营中心 | E10: 市场广告推广部 | F10: 市场推广部 | G10: 娱乐营销组
A11: 其他达人直播 | B11: 抖音直播服务费-抖音其他 | C11: YXHD10 | D11: 品牌运营中心 | E11: 市场广告推广部 | F11: 达播2部
A12: SKA达人 | B12: 抖音直播服务费-抖音其他 | C12: YXHD11 | D12: 品牌运营中心 | E12: 市场广告推广部 | F12: 达播2部
A13: 田恬 | B13: 抖音直播服务费-田恬 | C13: YXHD12 | D13: 品牌运营中心 | E13: 直播运营部 | F13: 达播BD部
A14: 其他达人直播 | B14: 抖音直播服务费-团长计划 | C14: YXHD13 | D14: 品牌运营中心 | E14: 市场广告推广部 | F14: 达播2部
A15: 其他达人直播 | B15: 抖音直播坑位费-抖音其他 | C15: YXHD14 | D15: 品牌运营中心 | E15: 市场广告推广部 | F15: 达播2部
A16: SKA达人 | B16: 抖音直播坑位费-抖音其他 | C16: YXHD15 | D16: 品牌运营中心 | E16: 市场广告推广部 | F16: 达播2部
A17: 田恬 | B17: 抖音直播坑位费-田恬 | C17: YXHD16 | D17: 品牌运营中心 | E17: 直播运营部 | F17: 达播BD部
A18: 其他达人直播 | B18: 抖音直播坑位费-团长计划 | C18: YXHD17 | D18: 品牌运营中心 | E18: 市场广告推广部 | F18: 达播2部
A19: 其他达人直播 | B19: 快手直播服务费 | C19: YXHD18 | D19: 品牌运营中心 | E19: 市场广告推广部 | F19: 达播2部
A20: SKA达人 | B20: 快手直播服务费 | C20: YXHD19 | D20: 品牌运营中心 | E20: 市场广告推广部 | F20: 达播2部
A21: 其他达人直播 | B21: 快手直播坑位费 | C21: YXHD20 | D21: 品牌运营中心 | E21: 市场广告推广部 | F21: 达播2部
A22: SKA达人 | B22: 快手直播坑位费 | C22: YXHD21 | D22: 品牌运营中心 | E22: 市场广告推广部 | F22: 达播2部
... A28: SKA达人 | B28: 天猫直播坑位费-其他 | C28: YXHD27 | D28: 品牌运营中心 | E28: 直播运营部 | F28: 达播BD部
A29: 素材创意制作 | B29: AD竞价内容创意-场地租赁 | C29: YXHD28 | D29: 品牌运营中心 | E29: 市场广告推广部 | F29: 广告投放部 | G29: 内容策划组
A30: 素材创意制作 | B30: AD竞价内容创意-动画制作 | C30: YXHD29 | D30: 品牌运营中心 | E30: 市场广告推广部 | F30: 广告投放部 | G30: 内容策划组
A31: 素材创意制作 | B31: AD竞价内容创意-服化道费 | C31: YXHD30 | D31: 品牌运营中心 | E31: 市场广告推广部 | F31: 广告投放部 | G31: 内容策划组
A32: 素材创意制作 | B32: AD竞价内容创意-建模服务 | C32: YXHD31 | D32: 品牌运营中心 | E32: 市场广告推广部 | F32: 广告投放部 | G32: 内容策划组
A33: 素材创意制作 | B33: AD竞价内容创意-模特服务 | C33: YXHD32 | D33: 品牌运营中心 | E33: 市场广告推广部 | F33: 广告投放部 | G33: 内容策划组
A34: 素材创意制作 | B34: AD竞价内容创意-内容制作 | C34: YXHD33 | D34: 品牌运营中心 | E34: 市场广告推广部 | F34: 广告投放部 | G34: 内容策划组
A35: 素材创意制作 | B35: AD竞价内容创意-拍摄服务 | C35: YXHD34 | D35: 品牌运营中心 | E35: 市场广告推广部 | F35: 广告投放部 | G35: 内容策划组
A36: 素材创意制作 | B36: AD竞价内容创意-拍摄物料 | C36: YXHD35 | D36: 品牌运营中心 | E36: 市场广告推广部 | F36: 广告投放部 | G36: 内容策划组
A37: 素材创意制作 | B37: AD竞价内容创意-设备租赁 | C37: YXHD36 | D37: 品牌运营中心 | E37: 市场广告推广部 | F37: 广告投放部 | G37: 内容策划组
A38: 素材创意制作 | B38: AD竞价内容创意-视频制作 | C38: YXHD37 | D38: 品牌运营中心 | E38: 市场广告推广部 | F38: 广告投放部 | G38: 内容策划组
A39: 素材创意制作 | B39: AD竞价内容创意-图文平面制作 | C39: YXHD38 | D39: 品牌运营中心 | E39: 市场广告推广部 | F39: 广告投放部 | G39: 内容策划组
A40: 素材创意制作 | B40: AD竞价内容创意-舞台场地 | C40: YXHD39 | D40: 品牌运营中心 | E40: 市场广告推广部 | F40: 广告投放部 | G40: 内容策划组
... A77: 内容加热 | B77: 内容热推 | C77: YXHD76 | D77: 品牌运营中心 | E77: 市场广告推广部 | F77: 市场推广部 | G77: 内容投放组
A78: 素材创意制作 | B78: 天猫淘内内容 | C78: YXHD77 | D78: 品牌运营中心 | E78: 直播运营部 | F78: 达播BD部
A79: 内容加热 | B79: 微博粉条 | C79: YXHD78 | D79: 品牌运营中心 | E79: 市场广告推广部 | F79: 市场推广部 | G79: 内容投放组
A80: 内容加热 | B80: 微博搜索 | C80: YXHD79 | D80: 品牌运营中心 | E80: 市场广告推广部 | F80: 市场推广部 | G80: 内容投放组
A81: 内容加热 | B81: 小红书加热 | C81: YXHD80 | D81: 品牌运营中心 | E81: 市场广告推广部 | F81: 市场推广部 | G81: 内容投放组
A82: 内容加热 | B82: 星聚力 | C82: YXHD81 | D82: 品牌运营中心 | E82: 市场广告推广部 | F82: 市场推广部 | G82: 内容投放组
A83: 素材创意制作 | B83: 虚拟IP | C83: YXHD82 | D83: 品牌运营中心 | E83: 渠道运营部 | F83: 抖音部 | G83: 内容部
A84: 素材创意制作 | B84: 直播间视觉设计费 | C84: YXHD83 | D84: 品牌运营中心 | E84: 渠道运营部 | F84: 抖音部 | G84: 内容部
A85: 线上品宣 | B85: OTT广告 | C85: YXHD84 | D85: 品牌运营中心 | E85: 市场广告推广部 | F85: 广告投放部 | G85: 媒介部
A86: 线上品宣 | B86: OTV广告 | C86: YXHD85 | D86: 品牌运营中心 | E86: 市场广告推广部 | F86: 广告投放部 | G86: 媒介部
A87: 线上品宣 | B87: 程序化投放 | C87: YXHD86 | D87: 品牌运营中心 | E87: 市场广告推广部 | F87: 广告投放部 | G87: 媒介部
A88: 线下品宣 | B88: 地标广告 | C88: YXHD87 | D88: 品牌运营中心 | E88: 市场广告推广部 | F88: 广告投放部 | G88: 媒介部
A89: 线下品宣 | B89: 电梯广告 | C89: YXHD88 | D89: 品牌运营中心 | E89: 市场广告推广部 | F89: 广告投放部 | G89: 媒介部
A90: 线下品宣 | B90: 电影院广告 | C90: YXHD89 | D90: 品牌运营中心 | E90: 市场广告推广部 | F90: 广告投放部 | G90: 媒介部
... A95: 线上品宣 | B95: 商业化资源包合作 | C95: YXHD94 | D95: 品牌运营中心 | E95: 市场广告推广部 | F95: 广告投放部 | G95: 媒介部
A96: 线上品宣 | B96: 投放策略调研 | C96: YXHD95 | D96: 品牌运营中心 | E96: 市场广告推广部 | F96: 策略部
A97: IMC国妆 | B97: IMC国妆 | C97: YXHD96 | D97: 品牌产品中心 | E97: 品牌营销部
A98: IMC花养 | B98: IMC花养 | C98: YXHD97 | D98: 品牌产品中心 | E98: 品牌营销部
A99: IMC文化 | B99: IMC文化 | C99: YXHD98 | D99: 品牌产品中心 | E99: 品牌营销部
A100: 日常-创意与物料 | B100: 日常-创意与物料 | C100: YXHD99 | D100: 品牌产品中心 | E100: 品牌营销部
A101: 调研费 | B101: 数据采买和调研费 | C101: YXHD100 | D101: 品牌产品中心 | E101: 品牌营销部
A102: 新媒体费用 | B102: 私域代运营费用 | C102: YXHD101 | D102: 品牌产品中心 | E102: 品牌营销部
A103: 新媒体费用 | B103: 私域视频制作 | C103: YXHD102 | D103: 品牌产品中心 | E103: 品牌营销部
A104: 新媒体费用 | B104: 私域图文制作费 | C104: YXHD103 | D104: 品牌产品中心 | E104: 品牌营销部
A105: 新媒体费用 | B105: 私域账号运营费 | C105: YXHD104 | D105: 品牌产品中心 | E105: 品牌营销部
A106: 李佳琦全案 | B106: 佳琦全案-服务费 | C106: YXHD105 | D106: 品牌运营中心 | E106: 直播运营部 | F106: 达播BD部
A107: 李佳琦全案 | B107: 佳琦全案-设计费 | C107: YXHD106 | D107: 品牌运营中心 | E107: 直播运营部 | F107: 达播BD部
A108: 直播公关费 | B108: 李佳琦公关礼 | C108: YXHD107 | D108: 品牌运营中心 | E108: 直播运营部 | F108: 达播BD部
A109: 直播公关费 | B109: 直播公关礼-外采-达播二部 | C109: YXHD108 | D109: 品牌运营中心 | E109: 市场广告推广部 | F109: 达播2部
A110: 直播公关费 | B110: 直播公关礼-外采-淘宝其他 | C110: YXHD109 | D110: 品牌运营中心 | E110: 市场广告推广部 | F110: 达播2部
A111: 直播公关费 | B111: 直播公关礼-外采-田恬 | C111: YXHD110 | D111: 品牌运营中心 | E111: 直播运营部 | F111: 达播BD部
A112: 直播公关费 | B112: 直播公关礼-自有-达播二部 | C112: YXHD111 | D112: 品牌运营中心 | E112: 市场广告推广部 | F112: 达播2部
A113: 直播公关费 | B113: 直播公关礼-自有-淘宝其他 | C113: YXHD112 | D113: 品牌运营中心 | E113: 市场广告推广部 | F113: 达播2部
A114: 直播公关费 | B114: 直播公关礼-自有-田恬 | C114: YXHD113 | D114: 品牌运营中心 | E114: 直播运营部 | F114: 达播BD部
A115: 品牌营销-跨中心协同 | B115: 项目推广协同 | C115: YXHD114
A116: 天猫站外推广 | B116: AD信息流 | C116: YXHD115 | D116: 品牌运营中心 | E116: 运营策略部 | F116: 天猫运营部 | G116: 天猫推广组
A117: 天猫站外推广 | B117: UD信息流 | C117: YXHD116 | D117: 品牌运营中心 | E117: 运营策略部 | F117: 天猫运营部 | G117: 天猫推广组
A118: 天猫站外推广 | B118: 百度SEO竞价广告 | C118: YXHD117 | D118: 品牌运营中心 | E118: 运营策略部 | F118: 天猫运营部 | G118: 天猫推广组
A119: 天猫站外推广 | B119: 百度SEO搜索广告 | C119: YXHD118 | D119: 品牌运营中心 | E119: 运营策略部 | F119: 天猫运营部 | G119: 天猫推广组
A120: 天猫站外推广 | B120: 磁力引擎 | C120: YXHD119 | D120: 品牌运营中心 | E120: 运营策略部 | F120: 天猫运营部 | G120: 天猫推广组
A121: 京东渠道推广-POP | B121: 京东POP-合约展位 | C121: YXHD120 | D121: 品牌运营中心 | E121: 渠道运营部 | F121: 特色电商部 | G121: 京东唯品推广组
A122: 京东渠道推广-POP | B122: 京东POP-京桥 | C122: YXHD121 | D122: 品牌运营中心 | E122: 渠道运营部 | F122: 特色电商部 | G122: 京东唯品推广组
A123: 京东渠道推广-POP | B123: 京东POP-京任务 | C123: YXHD122 | D123: 品牌运营中心 | E123: 渠道运营部 | F123: 特色电商部 | G123: 京东唯品推广组
A124: 京东渠道推广-POP | B124: 京东POP-京挑客 | C124: YXHD123 | D124: 品牌运营中心 | E124: 渠道运营部 | F124: 特色电商部 | G124: 京东唯品推广组
A125: 京东渠道推广-POP | B125: 京东POP-京准通常规投放 | C125: YXHD124 | D125: 品牌运营中心 | E125: 渠道运营部 | F125: 特色电商部 | G125: 京东唯品推广组
A126: 京东渠道推广-POP | B126: 京东POP-联合活动 | C126: YXHD125 | D126: 品牌运营中心 | E126: 渠道运营部 | F126: 特色电商部 | G126: 京东唯品推广组
A127: 京东渠道推广-自营 | B127: 京东自播服务 | C127: YXHD126 | D127: 品牌运营中心 | E127: 渠道运营部 | F127: 特色电商部 | G127: 京东部
... A160: 微信渠道推广 | B160: 微信号代投费 | C160: YXHD158 | D160: 品牌运营中心 | E160: 渠道运营部 | F160: 综合渠道运营部 | G160: 综合渠道推广部
A161: 达人推广 | B161: 达人合作 | C161: YXHD159 | D161: 品牌运营中心 | E161: 市场广告推广部 | F161: 市场推广部
A162: 达人推广 | B162: 达人佣金 | C162: YXHD160 | D162: 品牌运营中心 | E162: 市场广告推广部 | F162: 市场推广部
A163: 市场公关费 | B163: 公关礼策划服务 | C163: YXHD161 | D163: 品牌运营中心 | E163: 市场广告推广部 | F163: 市场推广部 | G163: 市场PR组
A164: 市场公关费 | B164: 公关舆情服务 | C164: YXHD162 | D164: 品牌运营中心 | E164: 市场广告推广部 | F164: 市场推广部
A165: 市场公关费 | B165: 市场公关整合营销 | C165: YXHD163 | D165: 品牌运营中心 | E165: 市场广告推广部 | F165: 市场推广部 | G165: 市场PR组
A166: 市场公关费 | B166: 市场公关礼-外采 | C166: YXHD164 | D166: 品牌运营中心 | E166: 市场广告推广部 | F166: 市场推广部
A167: 市场公关费 | B167: 市场公关礼-自有 | C167: YXHD165 | D167: 品牌运营中心 | E167: 市场广告推广部 | F167: 市场推广部
A168: 市场公关费 | B168: 市场公关线下活动 | C168: YXHD166 | D168: 品牌运营中心 | E168: 市场广告推广部 | F168: 市场推广部 | G168: 市场PR组
A169: 特殊渠道推广 | B169: 特渠运营 | C169: YXHD167 | D169: 品牌运营中心 | E169: 渠道运营部
A170: 快手渠道推广 | B170: 磁力金牛 | C170: YXHD168 | D170: 品牌运营中心 | E170: 运营策略部 | F170: 天猫运营部 | G170: 天猫推广组
A171: 内容加热 | B171: 抖音官号DOU+ | C171: YXHD169 | D171: 品牌运营中心 | E171: 渠道运营部 | F171: 抖音部 | G171: 抖音推广部
A172: 矩阵代运营 | B172: 矩阵号服务费 | C172: YXHD170 | D172: 品牌运营中心 | E172: 渠道运营部 | F172: 抖音部 | G172: 矩阵运营部
A173: 矩阵号千川信息流 | B173: 矩阵号千川信息流 | C173: YXHD171 | D173: 品牌运营中心 | E173: 渠道运营部 | F173: 抖音部 | G173: 矩阵运营部
A174: 矩阵代运营 | B174: 矩阵号佣金 | C174: YXHD172 | D174: 品牌运营中心 | E174: 渠道运营部 | F174: 抖音部 | G174: 矩阵运营部
A175: 快手人设号 | B175: 快手人设号-服务费 | C175: YXHD173 | D175: 品牌运营中心 | E175: 渠道运营部 | F175: 创新部
A176: 快手人设号 | B176: 快手人设号-内容制作 | C176: YXHD174 | D176: 品牌运营中心 | E176: 渠道运营部 | F176: 创新部
A177: 快手人设号 | B177: 快手人设号-视频制作 | C177: YXHD175 | D177: 品牌运营中心 | E177: 渠道运营部 | F177: 创新部
...

Sheet Sheet10
A1: 店铺 | B1: 抖音号 | C1: 千川账户名称 | D1: 千川账户id
A2: 花西子官方旗舰店 | B2: 花西子官方旗舰店 | C2: 群邑-直播-官号1 | D2: 1727535271575630
C3: 云锐-直播-官号2 | D3: 1727265617683469
C4: 博观-直播-官号1 | D4: 1695557841246222
C5: 省广-直播-官号1 | D5: 1727435690629127
C6: 博观7-花西子-官号 | D6: 1765947662124040
C7: 知定堂-图文1-引流 | D7: 1761146745368653
C8: 博观-图文1-引流 | D8: 1760222811427847
C9: 花西子-小店随心推 | D9: 1695646517812232
B10: 东方有佳人 | C10: 知定堂3户-东方有佳人 | D10: 1766564041175070
C11: 博观4户-东方有佳人 | D11: 1760519144208525
B12: 花西子礼物精选 | C12: 博观5户-礼物精选 | D12: 1761057229537293
B13: 花西子官旗彩妆甄选 | C13: 博观6户-彩妆有术 | D13: 1761057340544014
C14: 博观3户-彩妆有术 | D14: 1760519091540999
B15: 妆养旗舰店 | C15: 知定堂1户-妆养 | D15: 1761153809509390
C16: 省广-矩阵直播-妆养 | D16: 1743277556435982
C17: 知定堂2户-妆养 | D17: 1766309736108040
A20: 投放账户 | B20: 名称 | C20: 业务对接人 | D20: 站内/站外 | E20: 营销活动（可从营销活动sheet页中查看营销活动全集） | F20: 公司主体 | G20: 平台 | H20: 投放方式（自投/代投） | I20: 平台对合作应供应商名称 | J20: 是否存在充值赠送金 | K20: 是否存在返利 | L20: 是否通过此账户申请开票 | M20: 使用中心 | N20: 使用二级部门 | O20: 使用三级部门 | P20: 财务对接人（如有）
A21: 16909143 | B21: 花西子官方旗舰店-群邑2 | C21: 难却 | E21: 磁力金牛 | F21: 杭州宜格化妆品有限公司 | G21: 快手 | H21: 自投 | I21: 群邑（上海）广告有限公司 | J21: 否 | K21: 是 | L21: 否 | M21: 品牌运营中心 | N21: 快手部 | O21: 快手运营推广部
A22: 16909147 | B22: 花西子官方旗舰店-群邑4 | C22: 难却 | E22: 磁力金牛 | F22: 杭州宜格化妆品有限公司 | G22: 快手 | H22: 自投 | I22: 群邑（上海）广告有限公司 | J22: 否 | K22: 是 | L22: 否 | M22: 品牌运营中心 | N22: 快手部 | O22: 快手运营推广部
A23: 16909144 | B23: 花西子官方旗舰店-群邑3 | C23: 难却 | E23: 磁力金牛 | F23: 杭州宜格化妆品有限公司 | G23: 快手 | H23: 自投 | I23: 群邑（上海）广告有限公司 | J23: 否 | K23: 是 | L23: 否 | M23: 品牌运营中心 | N23: 快手部 | O23: 快手运营推广部
A24: 16909146 | B24: 花西子官方旗舰店-全站ROI | C24: 难却 | E24: 磁力金牛 | F24: 杭州宜格化妆品有限公司 | G24: 快手 | H24: 自投 | I24: 群邑（上海）广告有限公司 | J24: 否 | K24: 是 | L24: 否 | M24: 品牌运营中心 | N24: 快手部 | O24: 快手运营推广部
A25: 13304453 | B25: 花西子Florasis-云锐测试 | C25: 难却 | E25: 磁力金牛 | F25: 杭州宜格化妆品有限公司 | G25: 快手 | H25: 自投 | I25: 快手平台 | J25: 否 | K25: 否 | L25: 否 | M25: 品牌运营中心 | N25: 快手部 | O25: 快手运营推广部
A26: 16909148 | B26: 花西子官方旗舰店-返货2户 | C26: 难却 | E26: 磁力金牛 | F26: 杭州宜格化妆品有限公司 | G26: 快手 | H26: 自投 | I26: 快手平台 | J26: 否 | K26: 否 | L26: 否 | M26: 品牌运营中心 | N26: 快手部 | O26: 快手运营推广部
A27: 16481647 | B27: 花西子官方旗舰店（浅度账户） | C27: 难却 | E27: 磁力金牛 | F27: 杭州宜格化妆品有限公司 | G27: 快手 | H27: 自投 | I27: 快手平台 | J27: 否 | K27: 否 | L27: 否 | M27: 品牌运营中心 | N27: 快手部 | O27: 快手运营推广部
A28: 17553440 | B28: 花西子官方旗舰店-直播托管对投-李楠楠 | C28: 难却 | E28: 磁力金牛 | F28: 杭州宜格化妆品有限公司 | G28: 快手 | H28: 自投 | I28: 快手平台 | J28: 否 | K28: 否 | L28: 否 | M28: 品牌运营中心 | N28: 快手部 | O28: 快手运营推广部
A29: 16909145 | B29: 花西子官方旗舰店-群邑-RSH代投 | C29: 难却 | E29: 磁力金牛 | F29: 杭州宜格化妆品有限公司 | G29: 快手 | H29: 自投 | I29: 群邑（上海）广告有限公司 | J29: 否 | K29: 是 | L29: 否 | M29: 品牌运营中心 | N29: 快手部 | O29: 快手运营推广部
A33: 投放账户 | B33: 名称 | C33: 业务对接人 | D33: 站内/站外 | E33: 营销活动（可从营销活动sheet页中查看营销活动全集） | F33: 公司主体 | G33: 平台 | H33: 投放方式（自投/代投） | I33: 平台对合作应供应商名称 | J33: 是否存在充值赠送金 | K33: 是否存在返利 | L33: 是否通过此账户申请开票 | M33: 使用中心 | N33: 使用二级部门 | O33: 使用三级部门 | P33: 财务对接人（如有）
A34: huaxizicai1@eastgarden.com | B34: huaxizicai1@eastgarden.com | C34: 一样 | D34: 站外 | E34: B站起飞加热 | F34: 杭州宜格化妆品有限公司 | G34: B站 | H34: 代投 | I34: 上海小花猫文化传播有限公司 | J34: 是 | K34: 否 | L34: 是 | M34: 品牌运营中心 | N34: 市场推广部 | O34: 内容加热 | P34: 洛一
A35: huaxizicai2@eastgarden.com | B35: huaxizicai2@eastgarden.com | C35: 一样 | D35: 站外 | E35: B站起飞加热 | F35: 杭州宜格化妆品有限公司 | G35: B站 | H35: 代投 | I35: 上海无堂网络科技有限公司 | J35: 是 | K35: 否 | L35: 是 | M35: 品牌运营中心 | N35: 市场推广部 | O35: 内容加热 | P35: 洛一
A36: hxzcaizhuang10@eastgarden.com | B36: hxzcaizhuang10@eastgarden.com | C36: 一样 | D36: 站外 | E36: B站起飞加热 | F36: 杭州宜格化妆品有限公司 | G36: B站 | H36: 代投 | I36: 上海无堂网络科技有限公司 | J36: 是 | K36: 否 | L36: 是 | M36: 品牌运营中心 | N36: 市场推广部 | O36: 内容加热 | P36: 洛一
A37: yige18072932996@163.com | B37: yige18072932996@163.com | C37: 一样 | D37: 无账户 | E37: B站起飞加热 | G37: B站
A38: 263697 | B38: 博观-花西子 | C38: 一样 | D38: 站外 | E38: 小红书加热 | G38: 小红书 | H38: 代投 | I38: 上海博观瑞思传媒科技有限公司 | J38: 无 | K38: 是 | L38: 是 | M38: 品牌运营中心 | N38: 市场推广部 | O38: 内容加热 | P38: 洛一
A39: 283885 | B39: 剧星小红书投放账户 | C39: 一样 | D39: 站外 | E39: 小红书加热 | G39: 小红书 | H39: 代投 | I39: 剧星 | J39: 无 | K39: 是 | L39: 是 | M39: 品牌运营中心 | N39: 市场推广部 | O39: 内容加热 | P39: 洛一
A40: 294814 | B40: 博观-花西子-2 | C40: 一样 | D40: 站外 | E40: 小红书加热 | G40: 小红书 | H40: 代投 | I40: 上海博观瑞思传媒科技有限公司 | J40: 无 | K40: 是 | L40: 是 | M40: 品牌运营中心 | N40: 市场推广部 | O40: 内容加热 | P40: 洛一

Sheet Sheet11
A1: 主键 | B1: 单据编号 | C1: 单据名称 | D1: 创建人[名称] | E1: 使用人[名称] | F1: 业务日期 | G1: 总额 | H1: 总额币种[名称(编码)] | I1: 占用金额 | J1: 占用金额币种[名称(编码)] | K1: 已用金额 | L1: 已用金额币种[名称(编码)] | M1: 还回金额 | N1: 还回金额币种[名称(编码)] | O1: 可用金额 | P1: 可用金额币种[名称(编码)] | Q1: 期初金额 | R1: 期初金额币种[名称(编码)] | S1: 完结状态 | T1: 公司手机号[名称] | U1: 公司邮箱[名称] | V1: 供应商名称[名称] | W1: 投放平台[名称] | X1: 投放账户ID | Y1: 营销活动[名称] | Z1: 充值方式[名称] | AA1: 是否存在充值赠送[名称] | AB1: 是否存在返利[名称] | AC1: 是否做余额管理[名称] | AD1: 是否通过此账户申请开票[名称] | AE1: 数据已全部回收[名称] | AF1: 投放账户已清帐[名称] | AG1: 投放账户状态[名称] | AH1: 业务对接人[名称] | AI1: 财务对接人[名称] | AJ1: 核算主体[名称] | AK1: 数据是否需要回收[名称] | AL1: 是否做过变更[名称] | AM1: 是否存在折扣[名称] | AN1: 投放方式[名称] | AO1: 投放方式生效时间 | AP1: 站内/站外[名称] | AQ1: 充值投放账户 | AR1: 营销活动计划分类[名称] | AS1: 投放账户名称 | AT1: 品牌[名称]
A2: 0317ac13e37b7b5620cd9637bc410001 | D2: ycss02; | G2: 0.00 | I2: 0.00 | K2: 0.00 | M2: 0.00 | O2: 0.00 | Q2: 0.00 | S2: 未完结 | V2: 上海小花猫文化传播有限公司 | W2: 小红书 | X2: 436489 | Y2: 小红书加热 | AA2: 是 | AB2: 是 | AC2: 否 | AD2: 否 | AH2: 一样（谢炀） | AJ2: 杭州宜格化妆品有限公司 | AN2: 自投 | AO2: 36526 | AP2: 站内 | AQ2: 436489 | AS2: 小花猫（花西子Florasis）5 | AT2: 花西子
A3: 0317abf06e8b7b5620cd9637bc410002 | D3: ycss02; | G3: 0.00 | I3: 0.00 | K3: 0.00 | M3: 0.00 | O3: 0.00 | Q3: 0.00 | S3: 未完结 | V3: 上海小花猫文化传播有限公司 | W3: 小红书 | X3: 436491 | Y3: 小红书加热 | AA3: 是 | AB3: 是 | AC3: 否 | AD3: 否 | AH3: 一样（谢炀） | AJ3: 杭州宜格化妆品有限公司 | AN3: 自投 | AO3: 36526 | AP3: 站内 | AQ3: 436491 | AS3: 小花猫（花西子Florasis）4 | AT3: 花西子
A4: 0317a77380fb7b5620cd9637bc410001 | D4: ycss02; | G4: 0.00 | I4: 0.00 | K4: 0.00 | M4: 0.00 | O4: 0.00 | Q4: 0.00 | S4: 未完结 | V4: 湖北巨量引擎科技有限公司 | W4: 抖音 | X4: 1601161499296772 | Y4: DOU+ | AC4: 是 | AJ4: 杭州宜格化妆品有限公司 | AN4: 自投 | AO4: 36526 | AP4: 站内 | AQ4: 1601161499296772 | AS4: 花西子官方旗舰店 | AT4: 花西子
A5: 03156c6a65c21d98ea897767e9600001 | D5: ycss02; | G5: 0.00 | I5: 0.00 | K5: 0.00 | M5: 0.00 | O5: 0.00 | Q5: 0.00 | S5: 未完结 | V5: 江苏拾光宝盒信息技术有限公司 | W5: 小红书 | X5: 117315 | Y5: 小红书加热 | AA5: 是 | AB5: 是 | AC5: 否 | AD5: 否 | AH5: 一样（谢炀） | AJ5: 杭州宜格化妆品有限公司 | AN5: 自投 | AO5: 36526 | AP5: 站内 | AQ5: 117315 | AS5: 拾光宝盒（花西子美妆） | AT5: 花西子
A6: 03156c6a68821d98ea897767e9600001 | D6: ycss02; | G6: 0.00 | I6: 0.00 | K6: 0.00 | M6: 0.00 | O6: 0.00 | Q6: 0.00 | S6: 未完结 | V6: 江苏拾光宝盒信息技术有限公司 | W6: 小红书 | X6: 168640 | Y6: 小红书加热 | AA6: 是 | AB6: 是 | AC6: 否 | AD6: 否 | AH6: 一样（谢炀） | AJ6: 杭州宜格化妆品有限公司 | AN6: 自投 | AO6: 36526 | AP6: 站内 | AQ6: 168640 | AS6: 拾光宝盒（花西子Florasis4） | AT6: 花西子
A7: 03156c6a68e21d98ea897767e9600001 | D7: ycss02; | G7: 0.00 | I7: 0.00 | K7: 0.00 | M7: 0.00 | O7: 0.00 | Q7: 0.00 | S7: 未完结 | V7: 广东省广告集团股份有限公司 | W7: 小红书 | X7: 113409 | Y7: 小红书加热 | AA7: 是 | AB7: 是 | AC7: 否 | AD7: 否 | AH7: 一样（谢炀） | AJ7: 杭州宜格化妆品有限公司 | AN7: 自投 | AO7: 36526 | AP7: 站内 | AQ7: 113409 | AS7: 省广集团（花西子Florasis） | AT7: 花西子
A8: 03156c6a69421d98ea897767e9600001 | D8: ycss02; | G8: 0.00 | I8: 0.00 | K8: 0.00 | M8: 0.00 | O8: 0.00 | Q8: 0.00 | S8: 未完结 | V8: 广东省广告集团股份有限公司 | W8: 小红书 | X8: huaxizi_xhongshu2@163.com | Y8: 小红书加热 | AA8: 是 | AB8: 是 | AC8: 否 | AD8: 否 | AH8: 一样（谢炀） | AJ8: 杭州宜格化妆品有限公司 | AN8: 自投 | AO8: 36526 | AP8: 站内 | AQ8: huaxizi_xhongshu2@163.com | AS8: 省广-美妆 | AT8: 花西子
A9: 03156c6a6b021d98ea897767e9600001 | D9: ycss02; | G9: 0.00 | I9: 0.00 | K9: 0.00 | M9: 0.00 | O9: 0.00 | Q9: 0.00 | S9: 未完结 | V9: 广东省广告集团股份有限公司 | W9: 小红书 | X9: 117993 | Y9: 小红书加热 | AA9: 是 | AB9: 是 | AC9: 否 | AD9: 否 | AH9: 一样（谢炀） | AJ9: 杭州宜格化妆品有限公司 | AN9: 自投 | AO9: 36526 | AP9: 站内 | AQ9: 117993 | AS9: 省广集团（花西子Florasis）02 | AT9: 花西子
A10: 03156c6a6b521d98ea897767e9600001 | D10: ycss02; | G10: 0.00 | I10: 0.00 | K10: 0.00 | M10: 0.00 | O10: 0.00 | Q10: 0.00 | S10: 未完结 | V10: 广东省广告集团股份有限公司 | W10: 小红书 | X10: 117992 | Y10: 小红书加热 | AA10: 是 | AB10: 是 | AC10: 否 | AD10: 否 | AH10: 一样（谢炀） | AJ10: 杭州宜格化妆品有限公司 | AN10: 自投 | AO10: 36526 | AP10: 站内 | AQ10: 117992 | AS10: 省广集团（花西子Florasis）03 | AT10: 花西子
A11: 03156c6a6b921d98ea897767e9600001 | D11: ycss02; | G11: 0.00 | I11: 0.00 | K11: 0.00 | M11: 0.00 | O11: 0.00 | Q11: 0.00 | S11: 未完结 | V11: 江苏拾光宝盒信息技术有限公司 | W11: 小红书 | X11: 119989 | Y11: 小红书加热 | AC11: 否 | AD11: 否 | AH11: 一样（谢炀） | AJ11: 杭州宜格化妆品有限公司 | AN11: 自投 | AO11: 36526 | AP11: 站外 | AQ11: 119989 | AS11: 拾光宝盒（花西子Florasis3） | AT11: 花西子
A12: 03156c6a6c321d98ea897767e9600001 | D12: ycss02; | G12: 0.00 | I12: 0.00 | K12: 0.00 | M12: 0.00 | O12: 0.00 | Q12: 0.00 | S12: 未完结 | V12: 江苏拾光宝盒信息技术有限公司 | W12: 小红书 | X12: 65933 | Y12: 小红书加热 | AC12: 否 | AD12: 否 | AH12: 一样（谢炀） | AJ12: 杭州宜格化妆品有限公司 | AN12: 自投 | AO12: 36526 | AP12: 站外 | AQ12: 65933 | AS12: 拾光宝盒（花西子Florasis） | AT12: 花西子
A13: 03156c6a6c721d98ea897767e9600001 | D13: ycss02; | G13: 0.00 | I13: 0.00 | K13: 0.00 | M13: 0.00 | O13: 0.00 | Q13: 0.00 | S13: 未完结 | V13: 江苏拾光宝盒信息技术有限公司 | W13: 小红书 | X13: 119990 | Y13: 小红书加热 | AC13: 否 | AD13: 否 | AH13: 一样（谢炀） | AJ13: 杭州宜格化妆品有限公司 | AN13: 自投 | AO13: 36526 | AP13: 站外 | AQ13: 119990 | AS13: 拾光宝盒（花西子Florasis2） | AT13: 花西子
A14: 03156c6a6cc21d98ea897767e9600001 | D14: ycss02; | G14: 0.00 | I14: 0.00 | K14: 0.00 | M14: 0.00 | O14: 0.00 | Q14: 0.00 | S14: 未完结 | V14: 上海博观瑞思传媒科技有限公司 | W14: 小红书 | X14: 307497 | Y14: 小红书加热 | AC14: 否 | AD14: 否 | AH14: 一样（谢炀） | AJ14: 杭州宜格化妆品有限公司 | AN14: 自投 | AO14: 36526 | AP14: 站外 | AQ14: 307497 | AS14: 博观-花西子-3 | AT14: 花西子
A15: 03156c6a6d021d98ea897767e9600001 | D15: ycss02; | G15: 0.00 | I15: 0.00 | K15: 0.00 | M15: 0.00 | O15: 0.00 | Q15: 0.00 | S15: 未完结 | V15: 上海剧星传媒股份有限公司 | W15: 小红书 | X15: sd_xx@visionstar.cn | Y15: 小红书加热 | AC15: 否 | AD15: 否 | AH15: 一样（谢炀） | AJ15: 杭州宜格化妆品有限公司 | AN15: 自投 | AO15: 36526 | AP15: 站外 | AQ15: sd_xx@visionstar.cn | AS15: 剧星小红书投放账户 | AT15: 花西子
A16: 03156c6a6d421d98ea897767e9600001 | D16: ycss02; | G16: 0.00 | I16: 0.00 | K16: 0.00 | M16: 0.00 | O16: 0.00 | Q16: 0.00 | S16: 未完结 | V16: 上海博观瑞思传媒科技有限公司 | W16: 小红书 | X16: 263697 | Y16: 小红书加热 | AC16: 否 | AD16: 否 | AH16: 一样（谢炀） | AJ16: 杭州宜格化妆品有限公司 | AN16: 代投 | AO16: 36526 | AP16: 站外 | AQ16: 263697 | AS16: 博观-花西子 | AT16: 花西子
A17: 03156c6a6d921d98ea897767e9600001 | D17: ycss02; | G17: 0.00 | I17: 0.00 | K17: 0.00 | M17: 0.00 | O17: 0.00 | Q17: 0.00 | S17: 未完结 | V17: 上海剧星传媒股份有限公司 | W17: 小红书 | X17: 283885 | Y17: 小红书加热 | AA17: 否 | AB17: 是 | AC17: 否 | AD17: 否 | AH17: 一样（谢炀） | AJ17: 杭州宜格化妆品有限公司 | AN17: 代投 | AO17: 36526 | AP17: 站外 | AQ17: 283885 | AS17: 剧星小红书投放账户 | AT17: 花西子
A18: 03156c6a6dd21d98ea897767e9600002 | D18: ycss02; | G18: 0.00 | I18: 0.00 | K18: 0.00 | M18: 0.00 | O18: 0.00 | Q18: 0.00 | S18: 未完结 | V18: 上海博观瑞思传媒科技有限公司 | W18: 小红书 | X18: 294814 | Y18: 小红书加热 | AA18: 否 | AB18: 是 | AC18: 否 | AD18: 否 | AH18: 一样（谢炀） | AJ18: 杭州宜格化妆品有限公司 | AN18: 代投 | AO18: 36526 | AP18: 站外 | AQ18: 294814 | AS18: 博观-花西子-2 | AT18: 花西子
A19: 03156c6a6e121d98ea897767e9600002 | D19: ycss02; | G19: 0.00 | I19: 0.00 | K19: 0.00 | M19: 0.00 | O19: 0.00 | Q19: 0.00 | S19: 未完结 | V19: 江苏拾光宝盒信息技术有限公司 | W19: 小红书 | X19: 395388 | Y19: 小红书加热 | AA19: 是 | AB19: 是 | AC19: 否 | AD19: 否 | AH19: 一样（谢炀） | AJ19: 杭州宜格化妆品有限公司 | AN19: 自投 | AO19: 36526 | AP19: 站内 | AQ19: 395388 | AS19: 拾光宝盒（花西子Florasis5） | AT19: 花西子
A20: 03156c6a6e621d98ea897767e9600002 | D20: ycss02; | G20: 0.00 | I20: 0.00 | K20: 0.00 | M20: 0.00 | O20: 0.00 | Q20: 0.00 | S20: 未完结 | V20: 江苏拾光宝盒信息技术有限公司 | W20: 小红书 | X20: 395353 | Y20: 小红书加热 | AA20: 是 | AB20: 是 | AC20: 否 | AD20: 否 | AJ20: 杭州宜格化妆品有限公司 | AN20: 自投 | AO20: 36526 | AP20: 站内 | AQ20: 395353 | AS20: 拾光宝盒（花西子Florasis6） | AT20: 花西子
A21: 03156c6a6ef21d98ea897767e9600002 | D21: ycss02; | G21: 0.00 | I21: 0.00 | K21: 0.00 | M21: 0.00 | O21: 0.00 | Q21: 0.00 | S21: 未完结 | V21: 江苏拾光宝盒信息技术有限公司 | W21: 小红书 | X21: 395350 | Y21: 小红书加热 | AA21: 是 | AB21: 是 | AC21: 否 | AD21: 否 | AH21: 一样（谢炀） | AJ21: 杭州宜格化妆品有限公司 | AN21: 自投 | AO21: 36526 | AP21: 站内 | AQ21: 395350 | AS21: 拾光宝盒（花西子Florasis7） | AT21: 花西子
A22: 03156c6a6f421d98ea897767e9600002 | D22: ycss02; | G22: 0.00 | I22: 0.00 | K22: 0.00 | M22: 0.00 | O22: 0.00 | Q22: 0.00 | S22: 未完结 | V22: 江苏拾光宝盒信息技术有限公司 | W22: 小红书 | X22: 409695 | Y22: 小红书加热 | AA22: 是 | AB22: 是 | AC22: 否 | AD22: 否 | AH22: 一样（谢炀） | AJ22: 杭州宜格化妆品有限公司 | AN22: 自投 | AO22: 36526 | AP22: 站内 | AQ22: 409695 | AS22: 拾光宝盒（花西子Florasis8） | AT22: 花西子
A23: 03156c6a6f821d98ea897767e9600002 | D23: ycss02; | G23: 0.00 | I23: 0.00 | K23: 0.00 | M23: 0.00 | O23: 0.00 | Q23: 0.00 | S23: 未完结 | V23: 江苏拾光宝盒信息技术有限公司 | W23: 小红书 | X23: 409688 | Y23: 小红书加热 | AA23: 是 | AB23: 是 | AC23: 否 | AD23: 否 | AH23: 一样（谢炀） | AJ23: 杭州宜格化妆品有限公司 | AN23: 自投 | AO23: 36526 | AP23: 站内 | AQ23: 409688 | AS23: 拾光宝盒（花西子Florasis9） | AT23: 花西子
A24: 03156c6a6fc21d98ea897767e9600002 | D24: ycss02; | G24: 0.00 | I24: 0.00 | K24: 0.00 | M24: 0.00 | O24: 0.00 | Q24: 0.00 | S24: 未完结 | V24: 江苏拾光宝盒信息技术有限公司 | W24: 小红书 | X24: 409687 | Y24: 小红书加热 | AA24: 是 | AB24: 是 | AC24: 否 | AD24: 否 | AH24: 一样（谢炀） | AJ24: 杭州宜格化妆品有限公司 | AN24: 自投 | AO24: 36526 | AP24: 站内 | AQ24: 409687 | AS24: 拾光宝盒（花西子Florasis10） | AT24: 花西子
A25: 03156c6a70021d98ea897767e9600002 | D25: ycss02; | G25: 0.00 | I25: 0.00 | K25: 0.00 | M25: 0.00 | O25: 0.00 | Q25: 0.00 | S25: 未完结 | V25: 广东省广告集团股份有限公司 | W25: 小红书 | X25: 118100 | Y25: 小红书加热 | AA25: 是 | AB25: 是 | AC25: 否 | AD25: 否 | AH25: 一样（谢炀） | AJ25: 杭州宜格化妆品有限公司 | AN25: 自投 | AO25: 36526 | AP25: 站内 | AQ25: 118100 | AS25: 省广集团（花西子美妆）03 | AT25: 花西子
A26: 03156c6a70521d98ea897767e9600000 | D26: ycss02; | G26: 0.00 | I26: 0.00 | K26: 0.00 | M26: 0.00 | O26: 0.00 | Q26: 0.00 | S26: 未完结 | V26: 上海小花猫文化传播有限公司 | W26: 小红书 | X26: 435968 | Y26: 小红书加热 | AA26: 是 | AB26: 是 | AC26: 否 | AD26: 否 | AH26: 一样（谢炀） | AJ26: 杭州宜格化妆品有限公司 | AN26: 自投 | AO26: 36526 | AP26: 站内 | AQ26: 435968 | AS26: 小花猫（花西子Florasis）6 | AT26: 花西子
A27: 03156c6a70921d98ea897767e9600001 | D27: ycss02; | G27: 0.00 | I27: 0.00 | K27: 0.00 | M27: 0.00 | O27: 0.00 | Q27: 0.00 | S27: 未完结 | V27: 上海小花猫文化传播有限公司 | W27: 小红书 | X27: 424140 | Y27: 小红书加热 | AA27: 是 | AB27: 是 | AC27: 否 | AD27: 否 | AH27: 一样（谢炀） | AJ27: 杭州宜格化妆品有限公司 | AN27: 自投 | AO27: 36526 | AP27: 站内 | AQ27: 424140 | AS27: 小花猫（花西子Florasis）3 | AT27: 花西子
A28: 03156c6a70d21d98ea897767e9600001 | D28: ycss02; | G28: 0.00 | I28: 0.00 | K28: 0.00 | M28: 0.00 | O28: 0.00 | Q28: 0.00 | S28: 未完结 | V28: 上海小花猫文化传播有限公司 | W28: 小红书 | X28: 424127 | Y28: 小红书加热 | AA28: 是 | AB28: 是 | AC28: 否 | AD28: 否 | AH28: 一样（谢炀） | AJ28: 杭州宜格化妆品有限公司 | AN28: 自投 | AO28: 36526 | AP28: 站内 | AQ28: 424127 | AS28: xhm_huaxizi02@163.com | AT28: 花西子
A29: 03156c6a71121d98ea897767e9600001 | D29: ycss02; | G29: 0.00 | I29: 0.00 | K29: 0.00 | M29: 0.00 | O29: 0.00 | Q29: 0.00 | S29: 未完结 | V29: 上海小花猫文化传播有限公司 | W29: 小红书 | X29: 424132 | Y29: 小红书加热 | AA29: 是 | AB29: 是 | AC29: 否 | AD29: 否 | AH29: 一样（谢炀） | AJ29: 杭州宜格化妆品有限公司 | AN29: 自投 | AO29: 36526 | AP29: 站内 | AQ29: 424132 | AS29: 小花猫（花西子Florasis）1 | AT29: 花西子
A30: 03156c6a71621d98ea897767e9600001 | D30: ycss02; | G30: 0.00 | I30: 0.00 | K30: 0.00 | M30: 0.00 | O30: 0.00 | Q30: 0.00 | S30: 未完结 | V30: 杭州凡淳品牌管理有限公司 | W30: 小红书 | X30: 433696 | Y30: 小红书加热 | AC30: 否 | AD30: 否 | AH30: 一样（谢炀） | AJ30: 杭州宜格化妆品有限公司 | AN30: 自投 | AO30: 36526 | AP30: 站内 | AQ30: 433696 | AS30: （FC）花西子小黛伞 | AT30: 花西子
A31: 03156c6a71a21d98ea897767e9600001 | D31: ycss02; | G31: 0.00 | I31: 0.00 | K31: 0.00 | M31: 0.00 | O31: 0.00 | Q31: 0.00 | S31: 未完结 | V31: 杭州凡淳品牌管理有限公司 | W31: 小红书 | X31: 436678 | Y31: 小红书加热 | AC31: 否 | AD31: 否 | AH31: 一样（谢炀） | AJ31: 杭州宜格化妆品有限公司 | AN31: 自投 | AO31: 36526 | AP31: 站内 | AQ31: 436678 | AS31: （FC）花西子三花喷雾 | AT31: 花西子
A32: 03156c6a72121d98ea897767e9600001 | D32: ycss02; | G32: 0.00 | I32: 0.00 | K32: 0.00 | M32: 0.00 | O32: 0.00 | Q32: 0.00 | S32: 未完结 | V32: 杭州凡淳品牌管理有限公司 | W32: 小红书 | X32: 423721 | Y32: 小红书加热 | AC32: 否 | AD32: 否 | AH32: 一样（谢炀） | AJ32: 杭州宜格化妆品有限公司 | AN32: 自投 | AO32: 36526 | AP32: 站内 | AQ32: 423721 | AS32: （FC）花西子 | AT32: 花西子
A33: 03147392a8f8ffcff3f0d6cfb2be0002 | D33: ycss02; | G33: 0.00 | I33: 0.00 | K33: 0.00 | M33: 0.00 | O33: 0.00 | Q33: 0.00 | S33: 未完结 | V33: 杭州阿里妈妈软件服务有限公司 | W33: 天猫 | X33: DP015-034 | Y33: 天猫-万相台-常规投放 | AH33: 洛竹（程铭） | AJ33: 杭州宜格化妆品有限公司 | AN33: 自投 | AO33: 36526 | AP33: 站内 | AQ33: 天猫花西子旗舰店-万相台 | AS33: 天猫花西子旗舰店-万相台-会员快 | AT33: 花西子
A34: 03147392aa78ffcff3f0d6cfb2be0002 | D34: ycss02; | G34: 0.00 | I34: 0.00 | K34: 0.00 | M34: 0.00 | O34: 0.00 | Q34: 0.00 | S34: 未完结 | V34: 浙江阿里巴巴通信技术有限公司 | W34: 天猫 | X34: DP001-034 | Y34: 天猫-万相台-常规投放 | AH34: 盐首（刘如敏） | AJ34: 杭州匠泽电子商务有限公司 | AN34: 自投 | AO34: 36526 | AP34: 站内 | AQ34: 天猫花西子旗舰店-万相台 | AS34: 天猫花西子匠泽店-万相台-会员快 | AT34: 花西子
A35: 0314402379c8ffcff3f0d6cfb2be0002 | D35: ycss02; | G35: 0.00 | I35: 0.00 | K35: 0.00 | M35: 0.00 | O35: 0.00 | Q35: 0.00 | S35: 未完结 | V35: 广东省广告集团股份有限公司 | W35: 抖音-巨量纵横 | X35: huaxizi_xinxiliuad4@163.com | Y35: AD信息流 | AA35: 是 | AB35: 是 | AC35: 否 | AD35: 是 | AH35: 白纸（张浩霖） | AJ35: 杭州宜格化妆品有限公司 | AN35: 自投 | AO35: 36526 | AP35: 站外 | AQ35: huaxizi_xinxiliuad4@163.com | AS35: huaxizi_xinxiliuad4@163.com | AT35: 花西子
A36: 031440237ac8ffcff3f0d6cfb2be0002 | D36: ycss02; | G36: 0.00 | I36: 0.00 | K36: 0.00 | M36: 0.00 | O36: 0.00 | Q36: 0.00 | S36: 未完结 | V36: 广东省广告集团股份有限公司 | W36: 抖音-巨量纵横 | X36: huaxizi_xinxliuad5@163.com | Y36: AD信息流 | AA36: 是 | AB36: 是 | AC36: 否 | AD36: 是 | AH36: 白纸（张浩霖） | AJ36: 杭州宜格化妆品有限公司 | AN36: 自投 | AO36: 36526 | AP36: 站外 | AQ36: huaxizi_xinxliuad5@163.com | AS36: huaxizi_xinxliuad5@163.com | AT36: 花西子
A37: 031440237bb8ffcff3f0d6cfb2be0002 | D37: ycss02; | G37: 0.00 | I37: 0.00 | K37: 0.00 | M37: 0.00 | O37: 0.00 | Q37: 0.00 | S37: 未完结 | V37: 广东省广告集团股份有限公司 | W37: 抖音-巨量纵横 | X37: huaxizi_xinxliuad7@163.com | Y37: AD信息流 | AA37: 是 | AB37: 是 | AC37: 否 | AD37: 是 | AH37: 白纸（张浩霖） | AJ37: 杭州宜格化妆品有限公司 | AN37: 自投 | AO37: 36526 | AP37: 站外 | AQ37: huaxizi_xinxliuad7@163.com | AS37: huaxizi_xinxliuad7@163.com | AT37: 花西子
A38: 031440237cb8ffcff3f0d6cfb2be0002 | D38: ycss02; | G38: 0.00 | I38: 0.00 | K38: 0.00 | M38: 0.00 | O38: 0.00 | Q38: 0.00 | S38: 未完结 | V38: 广东省广告集团股份有限公司 | W38: 抖音-巨量纵横 | X38: huaxizi_xinxliuad8@163.com | Y38: AD信息流 | AA38: 是 | AB38: 是 | AC38: 否 | AD38: 是 | AH38: 白纸（张浩霖） | AJ38: 杭州宜格化妆品有限公司 | AN38: 自投 | AO38: 36526 | AP38: 站外 | AQ38: huaxizi_xinxliuad8@163.com | AS38: huaxizi_xinxliuad8@163.com | AT38: 花西子
A39: 031440237db8ffcff3f0d6cfb2be0002 | D39: ycss02; | G39: 0.00 | I39: 0.00 | K39: 0.00 | M39: 0.00 | O39: 0.00 | Q39: 0.00 | S39: 未完结 | V39: 群邑（上海）广告有限公司 | W39: 抖音-巨量纵横 | X39: huaxizi_xinxliuad9@163.com | Y39: AD信息流 | AA39: 是 | AB39: 是 | AC39: 否 | AD39: 是 | AH39: 白纸（张浩霖） | AJ39: 杭州宜格化妆品有限公司 | AN39: 自投 | AO39: 36526 | AP39: 站外 | AQ39: huaxizi_xinxliuad9@163.com | AS39: huaxizi_xinxliuad9@163.com | AT39: 花西子
A40: 031440237eb8ffcff3f0d6cfb2be0002 | D40: ycss02; | G40: 0.00 | I40: 0.00 | K40: 0.00 | M40: 0.00 | O40: 0.00 | Q40: 0.00 | S40: 未完结 | V40: 群邑（上海）广告有限公司 | W40: 抖音-巨量纵横 | X40: joy.du@mindshareworld.com | Y40: AD信息流 | AA40: 是 | AB40: 是 | AC40: 否 | AD40: 是 | AH40: 白纸（张浩霖） | AJ40: 杭州宜格化妆品有限公司 | AN40: 自投 | AO40: 36526 | AP40: 站外 | AQ40: joy.du@mindshareworld.com | AS40: joy.du@mindshareworld.com | AT40: 花西子
A41: 031440237fa8ffcff3f0d6cfb2be0002 | D41: ycss02; | G41: 0.00 | I41: 0.00 | K41: 0.00 | M41: 0.00 | O41: 0.00 | Q41: 0.00 | S41: 未完结 | V41: 北京九合互动文化传播有限公司 | W41: Uni Desk | X41: tb963892057577 | Y41: UD信息流 | AA41: 是 | AB41: 是 | AC41: 否 | AD41: 是 | AH41: 白纸（张浩霖） | AJ41: 杭州宜格化妆品有限公司 | AN41: 自投 | AO41: 36526 | AP41: 站外 | AQ41: tb963892057577 | AS41: tb963892057577 | AT41: 花西子
A42: 0314402380a8ffcff3f0d6cfb2be0002 | D42: ycss02; | G42: 0.00 | I42: 0.00 | K42: 0.00 | M42: 0.00 | O42: 0.00 | Q42: 0.00 | S42: 未完结 | V42: 上海宇枫电子商务有限公司 | W42: 超级粉丝通 | X42: adserving_ud0754@weibo.com | AA42: 是 | AB42: 是 | AC42: 否 | AD42: 是 | AH42: 白纸（张浩霖） | AJ42: 杭州宜格化妆品有限公司 | AN42: 自投 | AO42: 36526 | AP42: 站外 | AQ42: adserving_ud0754@weibo.com | AS42: adserving_ud0754@weibo.com | AT42: 花西子
A43: 0314402381a8ffcff3f0d6cfb2be0002 | D43: ycss02; | G43: 0.00 | I43: 0.00 | K43: 0.00 | M43: 0.00 | O43: 0.00 | Q43: 0.00 | S43: 未完结 | V43: 北京云锐国际文化传媒有限公司 | W43: 百度营销 | X43: 杭州宜格化妆品有限公司1（shvipyr花西子3） | AA43: 是 | AB43: 是 | AC43: 否 | AD43: 是 | AH43: 白纸（张浩霖） | AJ43: 杭州宜格化妆品有限公司 | AN43: 自投 | AO43: 36526 | AP43: 站外 | AQ43: 杭州宜格化妆品有限公司1（shvipyr花西子3） | AS43: 杭州宜格化妆品有限公司1（shvipyr花西子3） | AT43: 花西子
A44: 031440238298ffcff3f0d6cfb2be0002 | D44: ycss02; | G44: 0.00 | I44: 0.00 | K44: 0.00 | M44: 0.00 | O44: 0.00 | Q44: 0.00 | S44: 未完结 | V44: 北京起量文化传媒有限公司 | W44: 磁力引擎 | X44: 13362198950 | Y44: 磁力引擎 | AA44: 是 | AB44: 是 | AC44: 否 | AD44: 是 | AH44: 白纸（张浩霖） | AJ44: 杭州宜格化妆品有限公司 | AN44: 自投 | AO44: 36526 | AP44: 站外 | AQ44: 13362198950 | AS44: 13362198950 | AT44: 花西子
A45: 031440238388ffcff3f0d6cfb2be0002 | D45: ycss02; | G45: 0.00 | I45: 0.00 | K45: 0.00 | M45: 0.00 | O45: 0.00 | Q45: 0.00 | S45: 未完结 | V45: 北京起量文化传媒有限公司 | W45: 快手 | X45: 13396586970 | Y45: 磁力金牛 | AA45: 是 | AB45: 是 | AC45: 否 | AD45: 是 | AH45: 白纸（张浩霖） | AJ45: 杭州宜格化妆品有限公司 | AN45: 自投 | AO45: 36526 | AP45: 站外 | AQ45: 13396586970 | AS45: 13396586970 | AT45: 花西子
A46: 031440238488ffcff3f0d6cfb2be0002 | D46: ycss02; | G46: 0.00 | I46: 0.00 | K46: 0.00 | M46: 0.00 | O46: 0.00 | Q46: 0.00 | S46: 未完结 | V46: 杭州炬美网络科技有限公司 | W46: 腾讯ADQ | X46: 微信扫码登录 | Y46: 微信-ADQ推广 | AA46: 是 | AB46: 是 | AC46: 否 | AD46: 是 | AH46: 白纸（张浩霖） | AJ46: 杭州宜格化妆品有限公司 | AN46: 自投 | AO46: 36526 | AP46: 站外 | AQ46: 微信扫码登录 | AS46: 微信扫码登录 | AT46: 花西子
A47: 031440238598ffcff3f0d6cfb2be0002 | D47: ycss02; | G47: 0.00 | I47: 0.00 | K47: 0.00 | M47: 0.00 | O47: 0.00 | Q47: 0.00 | S47: 未完结 | V47: 北京云锐国际文化传媒有限公司 | W47: 抖音 | X47: 1727265617683469 | Y47: 千川信息流 | AC47: 否 | AH47: 兴泉（韩兴泉） | AJ47: 杭州宜格化妆品有限公司 | AN47: 自投 | AO47: 36526 | AP47: 站外 | AQ47: 1727265617683469 | AS47: 云锐-直播-官号2 | AT47: 花西子
A48: 031440238688ffcff3f0d6cfb2be0002 | D48: ycss02; | G48: 0.00 | I48: 0.00 | K48: 0.00 | M48: 0.00 | O48: 0.00 | Q48: 0.00 | S48: 未完结 | V48: 北京云锐国际文化传媒有限公司 | W48: 快手 | X48: 13304453 | Y48: 磁力金牛 | AC48: 否 | AH48: 难却（楼俞成达） | AJ48: 杭州宜格化妆品有限公司 | AN48: 自投 | AO48: 36526 | AP48: 站外 | AQ48: 13304453 | AS48: 花西子Florasis-云锐测试 | AT48: 花西子
A49: 031440238788ffcff3f0d6cfb2be0002 | D49: ycss02; | G49: 0.00 | I49: 0.00 | K49: 0.00 | M49: 0.00 | O49: 0.00 | Q49: 0.00 | S49: 未完结 | V49: 广东省广告集团股份有限公司 | W49: 抖音 | X49: 1762866886323341 | Y49: AD信息流 | AA49: 否 | AB49: 否 | AC49: 否 | AH49: 阿布（胡晓伟） | AJ49: 杭州宜格化妆品有限公司 | AN49: 自投 | AO49: 36526 | AP49: 站外 | AQ49: 1762866886323341 | AS49: abuHZP-天猫AD-省广-CID玉养气垫 | AT49: 花西子
A50: 031440238888ffcff3f0d6cfb2be0002 | D50: ycss02; | G50: 0.00 | I50: 0.00 | K50: 0.00 | M50: 0.00 | O50: 0.00 | Q50: 0.00 | S50: 未完结 | V50: 广东省广告集团股份有限公司 | W50: 抖音 | X50: 1758638395883534 | Y50: AD信息流 | AA50: 否 | AB50: 否 | AC50: 否 | AH50: 阿布（胡晓伟） | AJ50: 杭州宜格化妆品有限公司 | AN50: 自投 | AO50: 36526 | AP50: 站外 | AQ50: 1758638395883534 | AS50: abuHZP-天猫AD-省广-CID23玉容轻妆出行组合 | AT50: 花西子
A51: 031440238978ffcff3f0d6cfb2be0002 | D51: ycss02; | G51: 0.00 | I51: 0.00 | K51: 0.00 | M51: 0.00 | O51: 0.00 | Q51: 0.00 | S51: 未完结 | V51: 广东省广告集团股份有限公司 | W51: 抖音 | X51: 1744729041456135 | Y51: AD信息流 | AA51: 否 | AB51: 否 | AC51: 否 | AH51: 白纸（张浩霖） | AJ51: 杭州宜格化妆品有限公司 | AN51: 自投 | AO51: 36526 | AP51: 站外 | AQ51: 1744729041456135 | AS51: HZP-天猫AD信息流-省广-CID9（X眉笔） | AT51: 花西子
A52: 031440238a78ffcff3f0d6cfb2be0002 | D52: ycss02; | G52: 0.00 | I52: 0.00 | K52: 0.00 | M52: 0.00 | O52: 0.00 | Q52: 0.00 | S52: 未完结 | V52: 广东省广告集团股份有限公司 | W52: 抖音 | X52: 1744631353681928 | Y52: AD信息流 | AA52: 否 | AB52: 否 | AC52: 否 | AH52: 阿布（胡晓伟） | AJ52: 杭州宜格化妆品有限公司 | AN52: 自投 | AO52: 36526 | AP52: 站外 | AQ52: 1744631353681928 | AS52: HZP-天猫AD信息流-省广-CID4小黛伞防晒 | AT52: 花西子
A53: 031440238b78ffcff3f0d6cfb2be0002 | D53: ycss02; | G53: 0.00 | I53: 0.00 | K53: 0.00 | M53: 0.00 | O53: 0.00 | Q53: 0.00 | S53: 未完结 | V53: 广东省广告集团股份有限公司 | W53: 抖音 | X53: 1752335658405895 | Y53: AD信息流 | AA53: 否 | AB53: 否 | AC53: 否 | AH53: 志文（罗志文） | AJ53: 杭州宜格化妆品有限公司 | AN53: 自投 | AO53: 36526 | AP53: 站外 | AQ53: 1752335658405895 | AS53: 定妆花西子-杭州宜格CID投放-16玉养蜜粉 | AT53: 花西子
A54: 031440238c78ffcff3f0d6cfb2be0002 | D54: ycss02; | G54: 0.00 | I54: 0.00 | K54: 0.00 | M54: 0.00 | O54: 0.00 | Q54: 0.00 | S54: 未完结 | V54: 广东省广告集团股份有限公司 | W54: 抖音 | X54: 1752335657150542 | Y54: AD信息流 | AA54: 否 | AB54: 否 | AC54: 否 | AH54: 志文（罗志文） | AJ54: 杭州宜格化妆品有限公司 | AN54: 自投 | AO54: 36526 | AP54: 站外 | AQ54: 1752335657150542 | AS54: 定妆花西子-杭州宜格CID投放-14有色粉饼 | AT54: 花西子
A55: 031440238d78ffcff3f0d6cfb2be0002 | D55: ycss02; | G55: 0.00 | I55: 0.00 | K55: 0.00 | M55: 0.00 | O55: 0.00 | Q55: 0.00 | S55: 未完结 | V55: 广东省广告集团股份有限公司 | W55: 抖音 | X55: 1750901317073991 | Y55: AD信息流 | AA55: 否 | AB55: 否 | AC55: 否 | AH55: 白纸（张浩霖） | AJ55: 杭州宜格化妆品有限公司 | AN55: 自投 | AO55: 36526 | AP55: 站外 | AQ55: 1750901317073991 | AS55: 花西子-杭州宜格CID投放-6X持色唇纱 | AT55: 花西子
A56: 031440238e78ffcff3f0d6cfb2be0002 | D56: ycss02; | G56: 0.00 | I56: 0.00 | K56: 0.00 | M56: 0.00 | O56: 0.00 | Q56: 0.00 | S56: 未完结 | V56: 广东省广告集团股份有限公司 | W56: 抖音 | X56: 1747107074839566 | Y56: AD信息流 | AA56: 否 | AB56: 否 | AC56: 否 | AH56: 阿布（胡晓伟） | AJ56: 杭州宜格化妆品有限公司 | AN56: 自投 | AO56: 36526 | AP56: 站外 | AQ56: 1747107074839566 | AS56: abuHZP-天猫AD信息流-省广-CID19素颜出行组合 | AT56: 花西子
A57: 031440238f68ffcff3f0d6cfb2be0002 | D57: ycss02; | G57: 0.00 | I57: 0.00 | K57: 0.00 | M57: 0.00 | O57: 0.00 | Q57: 0.00 | S57: 未完结 | V57: 广东省广告集团股份有限公司 | W57: 抖音 | X57: 1750901319256072 | Y57: AD信息流 | AA57: 否 | AB57: 否 | AC57: 否 | AH57: 志文（罗志文） | AJ57: 杭州宜格化妆品有限公司 | AN57: 自投 | AO57: 36526 | AP57: 站外 | AQ57: 1750901319256072 | AS57: 定妆花西子-杭州宜格CID投放-9玉养蜜粉 | AT57: 花西子
A58: 031440239068ffcff3f0d6cfb2be0002 | D58: ycss02; | G58: 0.00 | I58: 0.00 | K58: 0.00 | M58: 0.00 | O58: 0.00 | Q58: 0.00 | S58: 未完结 | V58: 广东省广告集团股份有限公司 | W58: 抖音 | X58: 1750901314010184 | Y58: AD信息流 | AA58: 否 | AB58: 否 | AC58: 否 | AH58: 阿布（胡晓伟） | AJ58: 杭州宜格化妆品有限公司 | AN58: 自投 | AO58: 36526 | AP58: 站外 | AQ58: 1750901314010184 | AS58: abu花西子-杭州宜格CID投放-2私模气垫 | AT58: 花西子
A59: 031440239168ffcff3f0d6cfb2be0002 | D59: ycss02; | G59: 0.00 | I59: 0.00 | K59: 0.00 | M59: 0.00 | O59: 0.00 | Q59: 0.00 | S59: 未完结 | V59: 广东省广告集团股份有限公司 | W59: 抖音 | X59: 1758638396516360 | Y59: AD信息流 | AA59: 否 | AB59: 否 | AC59: 否 | AH59: 白纸（张浩霖） | AJ59: 杭州宜格化妆品有限公司 | AN59: 自投 | AO59: 36526 | AP59: 站外 | AQ59: 1758638396516360 | AS59: 花西子-杭州宜格CID投放-24X持色唇纱4P | AT59: 花西子
A60: 031440239258ffcff3f0d6cfb2be0002 | D60: ycss02; | G60: 0.00 | I60: 0.00 | K60: 0.00 | M60: 0.00 | O60: 0.00 | Q60: 0.00 | S60: 未完结 | V60: 广东省广告集团股份有限公司 | W60: 抖音 | X60: 1750901317821447 | Y60: AD信息流 | AA60: 否 | AB60: 否 | AC60: 否 | AH60: 白纸（张浩霖） | AJ60: 杭州宜格化妆品有限公司 | AN60: 自投 | AO60: 36526 | AP60: 站外 | AQ60: 1750901317821447 | AS60: 花西子-杭州宜格CID投放-7X眉粉笔 | AT60: 花西子
... A81: 03144023a6e8ffcff3f0d6cfb2be0002 | D81: ycss02; | G81: 0.00 | I81: 0.00 | K81: 0.00 | M81: 0.00 | O81: 0.00 | Q81: 0.00 | S81: 未完结 | V81: 广东省广告集团股份有限公司 | W81: 抖音 | X81: 1758638395143181 | Y81: AD信息流 | AA81: 否 | AB81: 否 | AC81: 否 | AH81: 阿布（胡晓伟） | AJ81: 杭州宜格化妆品有限公司 | AN81: 自投 | AO81: 36526 | AP81: 站外 | AQ81: 1758638395143181 | AS81: abuHZP-天猫AD-省广-CID22素颜出行组合(营销4P) | AT81: 花西子
A82: 03144023a7d8ffcff3f0d6cfb2be0002 | D82: ycss02; | G82: 0.00 | I82: 0.00 | K82: 0.00 | M82: 0.00 | O82: 0.00 | Q82: 0.00 | S82: 未完结 | V82: 广东省广告集团股份有限公司 | W82: 抖音 | X82: 1727435690629127 | Y82: 千川信息流 | AC82: 否 | AH82: 兴泉（韩兴泉） | AJ82: 杭州宜格化妆品有限公司 | AN82: 自投 | AO82: 36526 | AP82: 站外 | AQ82: 1727435690629127 | AS82: 省广-直播-官号1 | AT82: 花西子
A83: 03144023a8c8ffcff3f0d6cfb2be0002 | D83: ycss02; | G83: 0.00 | I83: 0.00 | K83: 0.00 | M83: 0.00 | O83: 0.00 | Q83: 0.00 | S83: 未完结 | V83: 广东省广告集团股份有限公司 | W83: 抖音 | X83: 1747734628974605 | Y83: 矩阵号千川信息流 | AC83: 否 | AH83: 兴泉（韩兴泉） | AJ83: 杭州宜格化妆品有限公司 | AN83: 自投 | AO83: 36526 | AP83: 站外 | AQ83: 1747734628974605 | AS83: 省广数字集合-矩阵直播-花西子礼物精选 | AT83: 花西子
A84: 031440233b58ffcff3f0d6cfb2be0001 | D84: ycss02; | G84: 0.00 | I84: 0.00 | K84: 0.00 | M84: 0.00 | O84: 0.00 | Q84: 0.00 | S84: 未完结 | V84: 杭州阿里妈妈软件服务有限公司 | W84: 天猫 | X84: DP015-YLMF | Y84: 天猫-引力魔方 | AA84: 否 | AB84: 否 | AC84: 是 | AD84: 是 | AJ84: 杭州宜格化妆品有限公司 | AN84: 自投 | AO84: 36526 | AP84: 站内 | AQ84: DP015-YLMF | AS84: 天猫花西子旗舰店-引力魔方 | AT84: 花西子
A85: 031440233c48ffcff3f0d6cfb2be0001 | D85: ycss02; | G85: 0.00 | I85: 0.00 | K85: 0.00 | M85: 0.00 | O85: 0.00 | Q85: 0.00 | S85: 未完结 | V85: 杭州阿里妈妈软件服务有限公司 | W85: 天猫 | X85: DP001-ZTC | Y85: 淘宝匠泽-直通车 | AA85: 否 | AB85: 否 | AC85: 是 | AD85: 是 | AJ85: 杭州匠泽电子商务有限公司 | AN85: 自投 | AO85: 36526 | AP85: 站内 | AQ85: DP001-ZTC | AS85: 天猫花西子匠泽店-直通车 | AT85: 花西子
A86: 031440233d48ffcff3f0d6cfb2be0001 | D86: ycss02; | G86: 0.00 | I86: 0.00 | K86: 0.00 | M86: 0.00 | O86: 0.00 | Q86: 0.00 | S86: 未完结 | V86: 杭州阿里妈妈软件服务有限公司 | W86: 天猫 | X86: DP001-YLMF | Y86: 淘宝匠泽-引力魔方 | AA86: 否 | AB86: 否 | AC86: 是 | AD86: 是 | AJ86: 杭州匠泽电子商务有限公司 | AN86: 自投 | AO86: 36526 | AP86: 站内 | AQ86: DP001-YLMF | AS86: 天猫花西子匠泽店-引力魔方 | AT86: 花西子
A87: 031440233e48ffcff3f0d6cfb2be0001 | D87: ycss02; | G87: 0.00 | I87: 0.00 | K87: 0.00 | M87: 0.00 | O87: 0.00 | Q87: 0.00 | S87: 未完结 | V87: 杭州阿里妈妈软件服务有限公司 | W87: 天猫 | X87: DP015-TBK | AA87: 否 | AB87: 否 | AC87: 是 | AD87: 是 | AJ87: 杭州宜格化妆品有限公司 | AN87: 自投 | AO87: 36526 | AP87: 站内 | AQ87: DP015-TBK | AS87: 天猫花西子旗舰店-淘宝客 | AT87: 花西子
A88: 031440233f38ffcff3f0d6cfb2be0001 | D88: ycss02; | G88: 0.00 | I88: 0.00 | K88: 0.00 | M88: 0.00 | O88: 0.00 | Q88: 0.00 | S88: 未完结 | V88: 杭州阿里妈妈软件服务有限公司 | W88: 天猫 | X88: DP001-TBK | AA88: 否 | AB88: 否 | AC88: 是 | AD88: 是 | AJ88: 杭州匠泽电子商务有限公司 | AN88: 自投 | AO88: 36526 | AP88: 站内 | AQ88: DP001-TBK | AS88: 天猫花西子匠泽店-淘宝客 | AT88: 花西子
A89: 031440234038ffcff3f0d6cfb2be0001 | D89: ycss02; | G89: 0.00 | I89: 0.00 | K89: 0.00 | M89: 0.00 | O89: 0.00 | Q89: 0.00 | S89: 未完结 | V89: 杭州阿里妈妈软件服务有限公司 | W89: 天猫 | X89: DP001-022 | Y89: 淘宝匠泽-直通车 | AA89: 否 | AB89: 否 | AC89: 是 | AD89: 是 | AH89: 盐首（刘如敏） | AJ89: 杭州匠泽电子商务有限公司 | AN89: 自投 | AO89: 36526 | AP89: 站内 | AQ89: DP001-ZTC | AS89: 天猫花西子匠泽店-直通车 | AT89: 花西子
A90: 031440234138ffcff3f0d6cfb2be0001 | D90: ycss02; | G90: 0.00 | I90: 0.00 | K90: 0.00 | M90: 0.00 | O90: 0.00 | Q90: 0.00 | S90: 未完结 | V90: 杭州阿里妈妈软件服务有限公司 | W90: 天猫 | X90: DP001-023 | Y90: 淘宝匠泽-引力魔方 | AA90: 否 | AB90: 否 | AC90: 是 | AD90: 是 | AH90: 盐首（刘如敏） | AJ90: 杭州匠泽电子商务有限公司 | AN90: 自投 | AO90: 36526 | AP90: 站内 | AQ90: DP001-YLMF | AS90: 天猫花西子匠泽店-引力魔方 | AT90: 花西子
A91: 031440234228ffcff3f0d6cfb2be0001 | D91: ycss02; | G91: 0.00 | I91: 0.00 | K91: 0.00 | M91: 0.00 | O91: 0.00 | Q91: 0.00 | S91: 未完结 | V91: 浙江阿里巴巴通信技术有限公司 | W91: 天猫 | X91: DP001-WXT | AA91: 否 | AB91: 否 | AC91: 是 | AD91: 是 | AJ91: 杭州匠泽电子商务有限公司 | AN91: 自投 | AO91: 36526 | AP91: 站内 | AQ91: DP001-WXT | AS91: 天猫花西子匠泽店-万相台 | AT91: 花西子
A92: 031440234328ffcff3f0d6cfb2be0001 | D92: ycss02; | G92: 0.00 | I92: 0.00 | K92: 0.00 | M92: 0.00 | O92: 0.00 | Q92: 0.00 | S92: 未完结 | V92: 杭州阿里妈妈软件服务有限公司 | W92: 天猫 | X92: DP015-025 | Y92: 淘宝客-佳琦 | AA92: 否 | AB92: 否 | AC92: 是 | AD92: 是 | AH92: 林胖（林玲） | AJ92: 杭州宜格化妆品有限公司 | AN92: 自投 | AO92: 36526 | AP92: 站内 | AQ92: DP015-TBK | AS92: 天猫花西子旗舰店-淘宝客 | AT92: 花西子
A93: 031440234418ffcff3f0d6cfb2be0001 | D93: ycss02; | G93: 0.00 | I93: 0.00 | K93: 0.00 | M93: 0.00 | O93: 0.00 | Q93: 0.00 | S93: 未完结 | V93: 杭州阿里妈妈软件服务有限公司 | W93: 天猫 | X93: DP015-025 | Y93: 淘宝客-其他挂链 | AA93: 否 | AB93: 否 | AC93: 是 | AD93: 是 | AH93: 林胖（林玲） | AJ93: 杭州宜格化妆品有限公司 | AN93: 自投 | AO93: 36526 | AP93: 站内 | AQ93: DP015-TBK | AS93: 天猫花西子旗舰店-淘宝客 | AT93: 花西子
A94: 031440234518ffcff3f0d6cfb2be0001 | D94: ycss02; | G94: 0.00 | I94: 0.00 | K94: 0.00 | M94: 0.00 | O94: 0.00 | Q94: 0.00 | S94: 未完结 | V94: 杭州阿里妈妈软件服务有限公司 | W94: 天猫 | X94: DP001-025 | Y94: 淘宝客-佳琦 | AA94: 否 | AB94: 否 | AC94: 是 | AD94: 是 | AH94: 林胖（林玲） | AJ94: 杭州匠泽电子商务有限公司 | AN94: 自投 | AO94: 36526 | AP94: 站内 | AQ94: DP001-TBK | AS94: 天猫花西子匠泽店-淘宝客 | AT94: 花西子
A95: 031440234618ffcff3f0d6cfb2be0001 | D95: ycss02; | G95: 0.00 | I95: 0.00 | K95: 0.00 | M95: 0.00 | O95: 0.00 | Q95: 0.00 | S95: 未完结 | V95: 杭州阿里妈妈软件服务有限公司 | W95: 天猫 | X95: DP001-025 | Y95: 淘宝客-其他挂链 | AA95: 否 | AB95: 否 | AC95: 是 | AD95: 是 | AH95: 林胖（林玲） | AJ95: 杭州匠泽电子商务有限公司 | AN95: 自投 | AO95: 36526 | AP95: 站内 | AQ95: DP001-TBK | AS95: 天猫花西子匠泽店-淘宝客 | AT95: 花西子
A96: 031440234718ffcff3f0d6cfb2be0001 | D96: ycss02; | G96: 0.00 | I96: 0.00 | K96: 0.00 | M96: 0.00 | O96: 0.00 | Q96: 0.00 | S96: 未完结 | V96: 重庆京东海嘉电子商务有限公司 | W96: 京东 | X96: DP033-JDZY | Y96: 京东自营-京准通常规投放 | AA96: 否 | AB96: 否 | AC96: 是 | AD96: 是 | AJ96: 杭州匠泽电子商务有限公司 | AN96: 自投 | AO96: 36526 | AP96: 站内 | AQ96: DP033-JDZY | AS96: 京东花西子自营店 | AT96: 花西子
A97: 031440234808ffcff3f0d6cfb2be0001 | D97: ycss02; | G97: 0.00 | I97: 0.00 | K97: 0.00 | M97: 0.00 | O97: 0.00 | Q97: 0.00 | S97: 未完结 | V97: 重庆京东海嘉电子商务有限公司 | W97: 京东 | X97: DP002-JD | Y97: 京东POP-京准通常规投放 | AA97: 否 | AB97: 否 | AC97: 是 | AD97: 是 | AJ97: 杭州匠泽电子商务有限公司 | AN97: 自投 | AO97: 36526 | AP97: 站内 | AQ97: DP002-JD | AS97: 京东花西子旗舰店 | AT97: 花西子
A98: 0314402348f8ffcff3f0d6cfb2be0001 | D98: ycss02; | G98: 0.00 | I98: 0.00 | K98: 0.00 | M98: 0.00 | O98: 0.00 | Q98: 0.00 | S98: 未完结 | V98: 广州海珠品唯信息服务有限公司 | W98: 唯品会 | X98: DP029-WPH | Y98: 唯品会-唯品常规投放 | AA98: 否 | AB98: 是 | AC98: 是 | AD98: 是 | AJ98: 杭州匠泽电子商务有限公司 | AN98: 自投 | AO98: 36526 | AP98: 站内 | AQ98: DP029-WPH | AS98: 唯品会花西子自营店 | AT98: 花西子
A99: 0314402349f8ffcff3f0d6cfb2be0001 | D99: ycss02; | G99: 0.00 | I99: 0.00 | K99: 0.00 | M99: 0.00 | O99: 0.00 | Q99: 0.00 | S99: 未完结 | V99: 杭州阿里妈妈软件服务有限公司 | W99: 天猫 | X99: DP015-017 | Y99: 天猫-万相台-超级直播 | AC99: 否 | AH99: 洛竹（程铭） | AJ99: 杭州宜格化妆品有限公司 | AN99: 自投 | AO99: 36526 | AP99: 站内 | AQ99: DP015-WXT | AS99: 天猫花西子旗舰店-万相台-超级直播 | AT99: 花西子
A100: 031440234ae8ffcff3f0d6cfb2be0001 | D100: ycss02; | G100: 0.00 | I100: 0.00 | K100: 0.00 | M100: 0.00 | O100: 0.00 | Q100: 0.00 | S100: 未完结 | V100: 杭州阿里妈妈软件服务有限公司 | W100: 天猫 | X100: DP015-021 | Y100: 天猫-万相台-超级短视频 | AC100: 否 | AH100: 洛竹（程铭） | AJ100: 杭州宜格化妆品有限公司 | AN100: 自投 | AO100: 36526 | AP100: 站内 | AQ100: DP015-WXT | AS100: 天猫花西子旗舰店-万相台-超级短视频 | AT100: 花西子
A101: 031440234be8ffcff3f0d6cfb2be0001 | D101: ycss02; | G101: 0.00 | I101: 0.00 | K101: 0.00 | M101: 0.00 | O101: 0.00 | Q101: 0.00 | S101: 未完结 | V101: 杭州阿里妈妈软件服务有限公司 | W101: 天猫 | X101: DP015-019 | Y101: 天猫-万相台-常规投放 | AC101: 否 | AH101: 洛竹（程铭） | AJ101: 杭州宜格化妆品有限公司 | AN101: 自投 | AO101: 36526 | AP101: 站内 | AQ101: DP015-WXT | AS101: 天猫花西子旗舰店-万相台-拉新快 | AT101: 花西子
A102: 031440234cf8ffcff3f0d6cfb2be0001 | D102: ycss02; | G102: 0.00 | I102: 0.00 | K102: 0.00 | M102: 0.00 | O102: 0.00 | Q102: 0.00 | S102: 未完结 | V102: 杭州阿里妈妈软件服务有限公司 | W102: 天猫 | X102: DP015-020 | Y102: 天猫-万相台-常规投放 | AC102: 否 | AH102: 洛竹（程铭） | AJ102: 杭州宜格化妆品有限公司 | AN102: 自投 | AO102: 36526 | AP102: 站内 | AQ102: DP015-WXT | AS102: 天猫花西子旗舰店-万相台-上新快 | AT102: 花西子
A103: 031440234de8ffcff3f0d6cfb2be0001 | D103: ycss02; | G103: 0.00 | I103: 0.00 | K103: 0.00 | M103: 0.00 | O103: 0.00 | Q103: 0.00 | S103: 未完结 | V103: 杭州阿里妈妈软件服务有限公司 | W103: 天猫 | X103: DP015-018 | Y103: 天猫-万相台-常规投放 | AC103: 否 | AH103: 洛竹（程铭） | AJ103: 杭州宜格化妆品有限公司 | AN103: 自投 | AO103: 36526 | AP103: 站内 | AQ103: DP015-WXT | AS103: 天猫花西子旗舰店-万相台-货品加速 | AT103: 花西子
A104: 031440234ee8ffcff3f0d6cfb2be0001 | D104: ycss02; | G104: 0.00 | I104: 0.00 | K104: 0.00 | M104: 0.00 | O104: 0.00 | Q104: 0.00 | S104: 未完结 | V104: 杭州阿里妈妈软件服务有限公司 | W104: 天猫 | X104: DP015-016 | Y104: 天猫-万相台-常规投放 | AC104: 否 | AH104: 洛竹（程铭） | AJ104: 杭州宜格化妆品有限公司 | AN104: 自投 | AO104: 36526 | AP104: 站内 | AQ104: DP015-WXT | AS104: 天猫花西子旗舰店-万相台-活动加速 | AT104: 花西子
A105: 031440234fd8ffcff3f0d6cfb2be0001 | D105: ycss02; | G105: 0.00 | I105: 0.00 | K105: 0.00 | M105: 0.00 | O105: 0.00 | Q105: 0.00 | S105: 未完结 | V105: 浙江阿里巴巴通信技术有限公司 | W105: 天猫 | X105: DP001-017 | Y105: 天猫-万相台-超级直播 | AC105: 否 | AH105: 盐首（刘如敏） | AJ105: 杭州匠泽电子商务有限公司 | AN105: 自投 | AO105: 36526 | AP105: 站内 | AQ105: DP001-WXT | AS105: 天猫花西子匠泽店-万相台-超级直播 | AT105: 花西子
A106: 0314402350c8ffcff3f0d6cfb2be0001 | D106: ycss02; | G106: 0.00 | I106: 0.00 | K106: 0.00 | M106: 0.00 | O106: 0.00 | Q106: 0.00 | S106: 未完结 | V106: 浙江阿里巴巴通信技术有限公司 | W106: 天猫 | X106: DP001-021 | Y106: 天猫-万相台-超级短视频 | AC106: 否 | AH106: 盐首（刘如敏） | AJ106: 杭州匠泽电子商务有限公司 | AN106: 自投 | AO106: 36526 | AP106: 站内 | AQ106: DP001-WXT | AS106: 天猫花西子匠泽店-万相台-超级短视频 | AT106: 花西子
A107: 0314402351c8ffcff3f0d6cfb2be0001 | D107: ycss02; | G107: 0.00 | I107: 0.00 | K107: 0.00 | M107: 0.00 | O107: 0.00 | Q107: 0.00 | S107: 未完结 | V107: 浙江阿里巴巴通信技术有限公司 | W107: 天猫 | X107: DP001-019 | Y107: 天猫-万相台-常规投放 | AC107: 否 | AH107: 盐首（刘如敏） | AJ107: 杭州匠泽电子商务有限公司 | AN107: 自投 | AO107: 36526 | AP107: 站内 | AQ107: DP001-WXT | AS107: 天猫花西子匠泽店-万相台-拉新快 | AT107: 花西子
A108: 0314402352c8ffcff3f0d6cfb2be0001 | D108: ycss02; | G108: 0.00 | I108: 0.00 | K108: 0.00 | M108: 0.00 | O108: 0.00 | Q108: 0.00 | S108: 未完结 | V108: 浙江阿里巴巴通信技术有限公司 | W108: 天猫 | X108: DP001-020 | Y108: 天猫-万相台-常规投放 | AC108: 否 | AH108: 盐首（刘如敏） | AJ108: 杭州匠泽电子商务有限公司 | AN108: 自投 | AO108: 36526 | AP108: 站内 | AQ108: DP001-WXT | AS108: 天猫花西子匠泽店-万相台-上新快 | AT108: 花西子
A109: 0314402353c8ffcff3f0d6cfb2be0001 | D109: ycss02; | G109: 0.00 | I109: 0.00 | K109: 0.00 | M109: 0.00 | O109: 0.00 | Q109: 0.00 | S109: 未完结 | V109: 浙江阿里巴巴通信技术有限公司 | W109: 天猫 | X109: DP001-018 | Y109: 天猫-万相台-常规投放 | AC109: 否 | AH109: 盐首（刘如敏） | AJ109: 杭州匠泽电子商务有限公司 | AN109: 自投 | AO109: 36526 | AP109: 站内 | AQ109: DP001-WXT | AS109: 天猫花西子匠泽店-万相台-货品加速 | AT109: 花西子
A110: 0314402354c8ffcff3f0d6cfb2be0001 | D110: ycss02; | G110: 0.00 | I110: 0.00 | K110: 0.00 | M110: 0.00 | O110: 0.00 | Q110: 0.00 | S110: 未完结 | V110: 浙江阿里巴巴通信技术有限公司 | W110: 天猫 | X110: DP001-016 | Y110: 天猫-万相台-常规投放 | AC110: 否 | AH110: 盐首（刘如敏） | AJ110: 杭州匠泽电子商务有限公司 | AN110: 自投 | AO110: 36526 | AP110: 站内 | AQ110: DP001-WXT | AS110: 天猫花西子匠泽店-万相台-活动加速 | AT110: 花西子
... A128: 031440236658ffcff3f0d6cfb2be0002 | D128: ycss02; | G128: 0.00 | I128: 0.00 | K128: 0.00 | M128: 0.00 | O128: 0.00 | Q128: 0.00 | S128: 未完结 | V128: 广州海珠品唯信息服务有限公司 | W128: 唯品会 | X128: DP029-033 | Y128: 唯品会-达人卖货 | AC128: 否 | AH128: 立立夏（武雨环） | AJ128: 杭州匠泽电子商务有限公司 | AN128: 自投 | AO128: 36526 | AP128: 站内 | AQ128: DP029-WPH | AS128: 唯品会花西子自营店-达人卖货 | AT128: 花西子
A129: 031440236748ffcff3f0d6cfb2be0002 | D129: ycss02; | G129: 0.00 | I129: 0.00 | K129: 0.00 | M129: 0.00 | O129: 0.00 | Q129: 0.00 | S129: 未完结 | V129: 考拉海购（杭州）科技有限公司 | W129: 考拉 | X129: 18069829269 | Y129: 考拉-常规投放 | AA129: 否 | AB129: 否 | AC129: 否 | AD129: 是 | AH129: 羽阳（杨雨晨） | AJ129: 杭州匠泽电子商务有限公司 | AN129: 自投 | AO129: 36526 | AP129: 站内 | AQ129: 18069829269 | AS129: 18069829269 | AT129: 花西子
A130: 031440236848ffcff3f0d6cfb2be0002 | D130: ycss02; | G130: 0.00 | I130: 0.00 | K130: 0.00 | M130: 0.00 | O130: 0.00 | Q130: 0.00 | S130: 未完结 | V130: 广东省广告集团股份有限公司 | W130: 抖音 | X130: huaxizi_xinxliuad2@163.com | Y130: AD信息流 | AA130: 是 | AB130: 是 | AC130: 否 | AD130: 是 | AH130: 大阳（徐庄南） | AJ130: 杭州宜格化妆品有限公司 | AN130: 自投 | AO130: 36526 | AP130: 站外 | AQ130: huaxizi_xinxliuad2@163.com | AS130: huaxizi_xinxliuad2@163.com | AT130: 花西子
A131: 0314402371f8ffcff3f0d6cfb2be0002 | D131: ycss02; | G131: 0.00 | I131: 0.00 | K131: 0.00 | M131: 0.00 | O131: 0.00 | Q131: 0.00 | S131: 未完结 | V131: 杭州羽联信息科技有限公司 | W131: B站 | X131: hongjin@yige-group.com | Y131: B站起飞加热 | AA131: 是 | AB131: 是 | AC131: 否 | AD131: 否 | AH131: 一样（谢炀） | AJ131: 杭州宜格化妆品有限公司 | AN131: 自投 | AO131: 36526 | AP131: 站外 | AQ131: hongjin@yige-group.com | AS131: hongjin@yige-group.com | AT131: 花西子
A132: 0314402372e8ffcff3f0d6cfb2be0002 | D132: ycss02; | G132: 0.00 | I132: 0.00 | K132: 0.00 | M132: 0.00 | O132: 0.00 | Q132: 0.00 | S132: 未完结 | V132: 上海无堂网络科技有限公司 | W132: B站 | X132: wanwan@yige-group.com | Y132: B站起飞加热 | AA132: 是 | AB132: 是 | AC132: 否 | AD132: 否 | AH132: 一样（谢炀） | AJ132: 杭州宜格化妆品有限公司 | AN132: 自投 | AO132: 36526 | AP132: 站外 | AQ132: wanwan@yige-group.com | AS132: wanwan@yige-group.com | AT132: 花西子
A133: 0314402373e8ffcff3f0d6cfb2be0002 | D133: ycss02; | G133: 0.00 | I133: 0.00 | K133: 0.00 | M133: 0.00 | O133: 0.00 | Q133: 0.00 | S133: 未完结 | V133: 上海无堂网络科技有限公司 | W133: B站 | X133: tangli@yige.us | Y133: B站起飞加热 | AA133: 是 | AB133: 是 | AC133: 否 | AD133: 否 | AH133: 一样（谢炀） | AJ133: 杭州宜格化妆品有限公司 | AN133: 自投 | AO133: 36526 | AP133: 站外 | AQ133: tangli@yige.us | AS133: tangli@yige.us | AT133: 花西子
A134: 0314402374d8ffcff3f0d6cfb2be0002 | D134: ycss02; | G134: 0.00 | I134: 0.00 | K134: 0.00 | M134: 0.00 | O134: 0.00 | Q134: 0.00 | S134: 未完结 | V134: 上海无堂网络科技有限公司 | W134: B站 | X134: qinghe@zhimei.us | Y134: B站起飞加热 | AA134: 是 | AB134: 是 | AC134: 否 | AD134: 否 | AH134: 一样（谢炀） | AJ134: 杭州宜格化妆品有限公司 | AN134: 自投 | AO134: 36526 | AP134: 站外 | AQ134: qinghe@zhimei.us | AS134: qinghe@zhimei.us | AT134: 花西子
A135: 0314402375e8ffcff3f0d6cfb2be0002 | D135: ycss02; | G135: 0.00 | I135: 0.00 | K135: 0.00 | M135: 0.00 | O135: 0.00 | Q135: 0.00 | S135: 未完结 | V135: 上海无堂网络科技有限公司 | W135: B站 | X135: kongqing@yige-group.com | Y135: B站起飞加热 | AA135: 是 | AB135: 是 | AC135: 否 | AD135: 否 | AH135: 一样（谢炀） | AJ135: 杭州宜格化妆品有限公司 | AN135: 自投 | AO135: 36526 | AP135: 站外 | AQ135: kongqing@yige-group.com | AS135: kongqing@yige-group.com | AT135: 花西子
A136: 0314402376d8ffcff3f0d6cfb2be0002 | D136: ycss02; | G136: 0.00 | I136: 0.00 | K136: 0.00 | M136: 0.00 | O136: 0.00 | Q136: 0.00 | S136: 未完结 | V136: 北京新线中视文化传播有限公司 | W136: B站 | X136: gancao@yige-group.com | Y136: B站起飞加热 | AA136: 是 | AB136: 是 | AC136: 否 | AD136: 否 | AH136: 一样（谢炀） | AJ136: 杭州宜格化妆品有限公司 | AN136: 自投 | AO136: 36526 | AP136: 站外 | AQ136: gancao@yige-group.com | AS136: gancao@yige-group.com | AT136: 花西子
A137: 0314402377d8ffcff3f0d6cfb2be0002 | D137: ycss02; | G137: 0.00 | I137: 0.00 | K137: 0.00 | M137: 0.00 | O137: 0.00 | Q137: 0.00 | S137: 未完结 | V137: 上海宇枫电子商务有限公司 | W137: 微博 | X137: 6336556296 | Y137: 微博推广 | AA137: 是 | AB137: 否 | AC137: 否 | AD137: 否 | AH137: 白纸（张浩霖） | AJ137: 杭州宜格化妆品有限公司 | AN137: 自投 | AO137: 36526 | AP137: 站外 | AQ137: 6336556296 | AS137: 花西子Florasis | AT137: 花西子
...
