Workbook

Sheet 营销活动7.7
A1: 营销活动分类 | B1: 编码 | C1: 营销活动 | D1: 一级预算科目 | E1: 二级预算科目 | F1: 状态 | G1: 能否到店铺 | H1: 店铺 | I1: 店铺编码 | J1: 渠道 | K1: 业务来源 | L1: 业务单元 | M1: 能否到品类（单品简称） | N1: 能否到SKU | O1: 是否允许个人报销 | P1: 是否允许无票报销 | Q1: 费用类型 | R1: 费用大类 | S1: 费用小类 | T1: 一级部门 | U1: 二级部门 | V1: 三级部门 | W1: 四级部门 | X1: 核算科目
A2: IP明星内容合作 | B2: YXHD01 | C2: IP合作 | D2: IP明星内容合作 | E2: 品牌IP及娱乐营销 | F2: 启用 | G2: 否 | M2: 否 | N2: 否 | O2: 否 | P2: 否 | Q2: 营销费用 | R2: 品牌宣传费 | S2: 创意策划服务费 | T2: 品牌运营中心 | U2: 市场广告推广部 | V2: 市场推广部 | W2: 市场PR组
A3: IP明星内容合作 | B3: YXHD02 | C3: 明星差旅 | D3: IP明星内容合作 | E3: 明星差旅 | F3: 启用 | G3: 否 | M3: 否 | N3: 否 | O3: 是 | P3: 是 | Q3: 营销费用 | R3: 其他费用 | S3: 明星差旅费 | T3: 品牌运营中心 | U3: 市场广告推广部 | V3: 市场推广部 | W3: 娱乐营销组
A4: IP明星内容合作 | B4: YXHD03 | C4: 明星代言单次合作 | D4: IP明星内容合作 | E4: 明星代言单次 | F4: 启用 | G4: 否 | M4: 否 | N4: 否 | O4: 否 | P4: 否 | Q4: 营销费用 | R4: 品牌宣传费 | S4: 明星合作费 | T4: 品牌运营中心 | U4: 市场广告推广部 | V4: 市场推广部 | W4: 娱乐营销组
A5: IP明星内容合作 | B5: YXHD04 | C5: 明星代言合作 | D5: IP明星内容合作 | E5: 明星代言摊销 | F5: 启用 | G5: 否 | M5: 否 | N5: 否 | O5: 否 | P5: 否 | Q5: 营销费用 | R5: 品牌宣传费 | S5: 明星合作费 | T5: 品牌运营中心 | U5: 市场广告推广部 | V5: 市场推广部 | W5: 娱乐营销组
A6: IP明星内容合作 | B6: YXHD05 | C6: 明星拍摄 | D6: IP明星内容合作 | E6: 明星拍摄 | F6: 启用 | G6: 否 | M6: 否 | N6: 否 | O6: 是 | P6: 是 | Q6: 营销费用 | R6: 其他费用 | S6: 场地租赁费 | T6: 品牌运营中心 | U6: 市场广告推广部 | V6: 市场推广部 | W6: 娱乐营销组
A7: IP明星内容合作 | B7: YXHD06 | C7: 明星影综营销号 | D7: IP明星内容合作 | E7: 品牌IP及娱乐营销 | F7: 启用 | G7: 否 | M7: 否 | N7: 否 | O7: 否 | P7: 否 | Q7: 营销费用 | R7: 品牌宣传费 | S7: 营销宣传费 | T7: 品牌运营中心 | U7: 市场广告推广部 | V7: 市场推广部 | W7: 娱乐营销组
A8: IP明星内容合作 | B8: YXHD07 | C8: 明星妆发造 | D8: IP明星内容合作 | E8: 明星妆发造 | F8: 启用 | G8: 否 | M8: 否 | N8: 否 | O8: 是 | P8: 是 | Q8: 营销费用 | R8: 内容制作费 | S8: 服化道费用 | T8: 品牌运营中心 | U8: 市场广告推广部 | V8: 市场推广部 | W8: 娱乐营销组
A9: IP明星内容合作 | B9: YXHD08 | C9: 明星综艺线下活动 | D9: IP明星内容合作 | E9: 明星代言单次 | F9: 启用 | G9: 否 | M9: 否 | N9: 否 | O9: 否 | P9: 否 | Q9: 营销费用 | R9: 品牌宣传费 | S9: 创意策划服务费 | T9: 品牌运营中心 | U9: 市场广告推广部 | V9: 市场推广部 | W9: 娱乐营销组
A10: IP明星内容合作 | B10: YXHD09 | C10: 影视综艺植入 | D10: IP明星内容合作 | E10: 品牌IP及娱乐营销 | F10: 启用 | G10: 否 | M10: 否 | N10: 否 | O10: 否 | P10: 否 | Q10: 营销费用 | R10: 品牌宣传费 | S10: 品牌植入费 | T10: 品牌运营中心 | U10: 市场广告推广部 | V10: 市场推广部 | W10: 娱乐营销组
A11: 其他达人直播 | B11: YXHD10 | C11: 抖音直播服务费-抖音其他 | D11: 达人直播 | E11: 佣金-抖音其他 | F11: 启用 | G11: 是 | H11: 抖音花西子旗舰店 | I11: DP007 | J11: 抖音 | K11: 达播-其他 | L11: 达播-其他 | M11: 是 | N11: 否 | O11: 否 | P11: 否 | Q11: 营销费用 | R11: 渠道推广费 | S11: 直播服务费 | T11: 品牌运营中心 | U11: 市场广告推广部 | V11: 达播2部
A12: 田恬 | B12: YXHD12 | C12: 抖音直播服务费-田恬 | E12: 佣金-田恬 | F12: 启用 | G12: 是 | H12: 抖音花西子旗舰店 | I12: DP007 | J12: 抖音 | K12: 达播-田恬 | L12: 达播-田恬 | M12: 是 | N12: 是 | O12: 否 | P12: 否 | Q12: 营销费用 | R12: 渠道推广费 | S12: 直播服务费 | T12: 品牌运营中心 | U12: 直播运营部 | V12: SKA达播部
A13: 其他达人直播 | B13: YXHD13 | C13: 抖音直播服务费-团长计划 | D13: 达人直播 | E13: 佣金-团长计划 | F13: 启用 | G13: 是 | H13: 抖音花西子旗舰店 | I13: DP007 | J13: 抖音 | K13: 达播-其他 | L13: 达播-其他 | M13: 是 | N13: 否 | O13: 否 | P13: 否 | Q13: 营销费用 | R13: 渠道推广费 | S13: 直播服务费 | T13: 品牌运营中心 | U13: 市场广告推广部 | V13: 达播2部
A14: 其他达人直播 | B14: YXHD14 | C14: 抖音直播坑位费-抖音其他 | D14: 达人直播 | E14: 服务费-抖音其他 | F14: 启用 | G14: 是 | H14: 抖音花西子旗舰店 | I14: DP007 | J14: 抖音 | K14: 达播-其他 | L14: 达播-其他 | M14: 否 | N14: 否 | O14: 否 | P14: 否 | Q14: 营销费用 | R14: 渠道推广费 | S14: 直播坑位费 | T14: 品牌运营中心 | U14: 市场广告推广部 | V14: 达播2部
A15: 田恬 | B15: YXHD16 | C15: 抖音直播坑位费-田恬 | D15: 达人直播 | E15: 服务费-田恬 | F15: 启用 | G15: 是 | H15: 抖音花西子旗舰店 | I15: DP007 | J15: 抖音 | K15: 达播-田恬 | L15: 达播-田恬 | M15: 否 | N15: 否 | O15: 否 | P15: 否 | Q15: 营销费用 | R15: 渠道推广费 | S15: 直播坑位费 | T15: 品牌运营中心 | U15: 直播运营部 | V15: SKA达播部
A16: 其他达人直播 | B16: YXHD17 | C16: 抖音直播坑位费-团长计划 | D16: 达人直播 | E16: 服务费-团长计划 | F16: 启用 | G16: 是 | H16: 抖音花西子旗舰店 | I16: DP007 | J16: 抖音 | K16: 达播-其他 | L16: 达播-其他 | M16: 否 | N16: 否 | O16: 否 | P16: 否 | Q16: 营销费用 | R16: 渠道推广费 | S16: 直播坑位费 | T16: 品牌运营中心 | U16: 市场广告推广部 | V16: 达播2部
A17: 其他达人直播 | B17: YXHD18 | C17: 快手直播服务费 | D17: 达人直播 | E17: 佣金-快手 | F17: 启用 | G17: 是 | H17: 快手花西子旗舰店 | I17: DP031 | J17: 快手 | K17: 快手达播 | L17: 快手达播 | M17: 是 | N17: 是 | O17: 否 | P17: 否 | Q17: 营销费用 | R17: 渠道推广费 | S17: 直播服务费 | T17: 品牌运营中心 | U17: 市场广告推广部 | V17: 达播2部
A18: 其他达人直播 | B18: YXHD20 | C18: 快手直播坑位费 | D18: 达人直播 | E18: 服务费-快手 | F18: 启用 | G18: 是 | H18: 快手花西子旗舰店 | I18: DP031 | J18: 快手 | K18: 快手达播 | L18: 快手达播 | M18: 否 | N18: 否 | O18: 否 | P18: 否 | Q18: 营销费用 | R18: 渠道推广费 | S18: 直播坑位费 | T18: 品牌运营中心 | U18: 市场广告推广部 | V18: 达播2部
A19: 李佳琦 | B19: YXHD22 | C19: 天猫直播服务费-李佳琦 | D19: 达人直播 | E19: 佣金-佳琦 | F19: 启用 | G19: 是 | H19: 天猫花西子旗舰店 | I19: DP015 | J19: 天猫 | K19: 天猫达播-LJQ | L19: 天猫达播-LJQ | M19: 是 | N19: 是 | O19: 否 | P19: 否 | Q19: 营销费用 | R19: 渠道推广费 | S19: 直播服务费 | T19: 品牌运营中心 | U19: 直播运营部 | V19: SKA达播部
A20: 其他达人直播 | B20: YXHD23 | C20: 天猫直播服务费-其他 | D20: 达人直播 | E20: 佣金-淘内其他 | F20: 启用 | G20: 是 | H20: 天猫花西子旗舰店 | I20: DP015 | J20: 天猫 | K20: 天猫达播-其他 | L20: 天猫达播-其他 | M20: 是 | N20: 是 | O20: 否 | P20: 否 | Q20: 营销费用 | R20: 渠道推广费 | S20: 直播服务费 | T20: 品牌运营中心 | U20: 市场广告推广部 | V20: 达播2部
A21: 李佳琦 | B21: YXHD25 | C21: 天猫直播坑位费-李佳琦 | D21: 达人直播 | E21: 服务费-佳琦 | F21: 启用 | G21: 是 | H21: 天猫花西子旗舰店 | I21: DP015 | J21: 天猫 | K21: 天猫达播-LJQ | L21: 天猫达播-LJQ | M21: 否 | N21: 否 | O21: 否 | P21: 否 | Q21: 营销费用 | R21: 渠道推广费 | S21: 直播坑位费 | T21: 品牌运营中心 | U21: 直播运营部 | V21: SKA达播部
A22: 其他达人直播 | B22: YXHD26 | C22: 天猫直播坑位费-其他 | D22: 达人直播 | E22: 服务费-淘内其他 | F22: 启用 | G22: 是 | H22: 天猫花西子旗舰店 | I22: DP015 | J22: 天猫 | K22: 天猫达播-其他 | L22: 天猫达播-其他 | M22: 否 | N22: 否 | O22: 否 | P22: 否 | Q22: 营销费用 | R22: 渠道推广费 | S22: 直播坑位费 | T22: 品牌运营中心 | U22: 市场广告推广部 | V22: 达播2部
A23: 素材创意制作 | B23: YXHD28 | C23: AD竞价内容创意-场地租赁 | D23: 品类内容推广 | E23: AD竞价内容创意 | F23: 启用 | G23: 否 | M23: 否 | N23: 否 | O23: 是 | P23: 是 | Q23: 营销费用 | R23: 其他费用 | S23: 场地租赁费 | T23: 品牌运营中心 | U23: 市场广告推广部 | V23: 广告投放部 | W23: 内容策划组
A24: 素材创意制作 | B24: YXHD29 | C24: AD竞价内容创意-动画制作 | D24: 品类内容推广 | E24: AD竞价内容创意 | F24: 启用 | G24: 否 | M24: 否 | N24: 否 | O24: 是 | P24: 是 | Q24: 营销费用 | R24: 内容制作费 | S24: 动画制作费 | T24: 品牌运营中心 | U24: 市场广告推广部 | V24: 广告投放部 | W24: 内容策划组
A25: 素材创意制作 | B25: YXHD30 | C25: AD竞价内容创意-服化道费 | D25: 品类内容推广 | E25: AD竞价内容创意 | F25: 启用 | G25: 否 | M25: 否 | N25: 否 | O25: 是 | P25: 是 | Q25: 营销费用 | R25: 内容制作费 | S25: 服化道费用 | T25: 品牌运营中心 | U25: 市场广告推广部 | V25: 广告投放部 | W25: 内容策划组
A26: 素材创意制作 | B26: YXHD31 | C26: AD竞价内容创意-建模服务 | D26: 品类内容推广 | E26: AD竞价内容创意 | F26: 启用 | G26: 否 | M26: 否 | N26: 否 | O26: 是 | P26: 是 | Q26: 营销费用 | R26: 内容制作费 | S26: 建模服务费 | T26: 品牌运营中心 | U26: 市场广告推广部 | V26: 广告投放部 | W26: 内容策划组
A27: 素材创意制作 | B27: YXHD32 | C27: AD竞价内容创意-模特服务 | D27: 品类内容推广 | E27: AD竞价内容创意 | F27: 启用 | G27: 否 | M27: 否 | N27: 否 | O27: 是 | P27: 是 | Q27: 营销费用 | R27: 内容制作费 | S27: 模特服务费 | T27: 品牌运营中心 | U27: 市场广告推广部 | V27: 广告投放部 | W27: 内容策划组
A28: 素材创意制作 | B28: YXHD33 | C28: AD竞价内容创意-内容制作 | D28: 品类内容推广 | E28: AD竞价内容创意 | F28: 启用 | G28: 否 | M28: 否 | N28: 否 | O28: 是 | P28: 是 | Q28: 营销费用 | R28: 内容制作费 | S28: 内容制作费 | T28: 品牌运营中心 | U28: 市场广告推广部 | V28: 广告投放部 | W28: 内容策划组
A29: 素材创意制作 | B29: YXHD34 | C29: AD竞价内容创意-拍摄服务 | D29: 品类内容推广 | E29: AD竞价内容创意 | F29: 启用 | G29: 否 | M29: 否 | N29: 否 | O29: 是 | P29: 是 | Q29: 营销费用 | R29: 内容制作费 | S29: 拍摄服务费 | T29: 品牌运营中心 | U29: 市场广告推广部 | V29: 广告投放部 | W29: 内容策划组
A30: 素材创意制作 | B30: YXHD35 | C30: AD竞价内容创意-拍摄物料 | D30: 品类内容推广 | E30: AD竞价内容创意 | F30: 启用 | G30: 否 | M30: 否 | N30: 否 | O30: 是 | P30: 是 | Q30: 营销费用 | R30: 内容制作费 | S30: 拍摄物料费 | T30: 品牌运营中心 | U30: 市场广告推广部 | V30: 广告投放部 | W30: 内容策划组
A31: 素材创意制作 | B31: YXHD36 | C31: AD竞价内容创意-设备租赁 | D31: 品类内容推广 | E31: AD竞价内容创意 | F31: 启用 | G31: 否 | M31: 否 | N31: 否 | O31: 是 | P31: 是 | Q31: 营销费用 | R31: 其他费用 | S31: 设备租赁费 | T31: 品牌运营中心 | U31: 市场广告推广部 | V31: 广告投放部 | W31: 内容策划组
A32: 素材创意制作 | B32: YXHD37 | C32: AD竞价内容创意-视频制作 | D32: 品类内容推广 | E32: AD竞价内容创意 | F32: 启用 | G32: 否 | M32: 否 | N32: 否 | O32: 是 | P32: 是 | Q32: 营销费用 | R32: 内容制作费 | S32: 视频制作费 | T32: 品牌运营中心 | U32: 市场广告推广部 | V32: 广告投放部 | W32: 内容策划组
A33: 素材创意制作 | B33: YXHD38 | C33: AD竞价内容创意-图文平面制作 | D33: 品类内容推广 | E33: AD竞价内容创意 | F33: 启用 | G33: 否 | M33: 否 | N33: 否 | O33: 是 | P33: 是 | Q33: 营销费用 | R33: 内容制作费 | S33: 图文平面制作费 | T33: 品牌运营中心 | U33: 市场广告推广部 | V33: 广告投放部 | W33: 内容策划组
A34: 素材创意制作 | B34: YXHD39 | C34: AD竞价内容创意-舞台场地 | D34: 品类内容推广 | E34: AD竞价内容创意 | F34: 启用 | G34: 否 | M34: 否 | N34: 否 | O34: 是 | P34: 是 | Q34: 营销费用 | R34: 其他费用 | S34: 舞台场地搭建费 | T34: 品牌运营中心 | U34: 市场广告推广部 | V34: 广告投放部 | W34: 内容策划组
... A38: 内容加热 | B38: YXHD43 | C38: DOU+ | D38: 品类内容推广 | E38: 内容加热 | F38: 启用 | G38: 否 | M38: 否 | N38: 否 | O38: 否 | P38: 否 | Q38: 营销费用 | R38: 达人推广费 | S38: 内容推广费 | T38: 品牌运营中心 | U38: 市场广告推广部 | V38: 市场推广部 | W38: 内容投放组
A39: 素材创意制作 | B39: YXHD44 | C39: 抖音视频创意-店铺-场地租赁 | D39: 品类内容推广 | E39: 抖音视频创意-店铺 | F39: 启用 | G39: 是 | H39: 抖音花西子旗舰店 | I39: DP007 | J39: 抖音 | K39: 抖音自播 | L39: 抖音自播 | M39: 否 | N39: 否 | O39: 是 | P39: 是 | Q39: 营销费用 | R39: 其他费用 | S39: 场地租赁费 | T39: 品牌运营中心 | U39: 内容电商部 | V39: 抖音部 | W39: 内容部
A40: 素材创意制作 | B40: YXHD45 | C40: 抖音视频创意-店铺-动画制作 | D40: 品类内容推广 | E40: 抖音视频创意-店铺 | F40: 启用 | G40: 是 | H40: 抖音花西子旗舰店 | I40: DP007 | J40: 抖音 | K40: 抖音自播 | L40: 抖音自播 | M40: 否 | N40: 否 | O40: 是 | P40: 是 | Q40: 营销费用 | R40: 内容制作费 | S40: 动画制作费 | T40: 品牌运营中心 | U40: 内容电商部 | V40: 抖音部 | W40: 内容部
A41: 素材创意制作 | B41: YXHD46 | C41: 抖音视频创意-店铺-服化道费 | D41: 品类内容推广 | E41: 抖音视频创意-店铺 | F41: 启用 | G41: 是 | H41: 抖音花西子旗舰店 | I41: DP007 | J41: 抖音 | K41: 抖音自播 | L41: 抖音自播 | M41: 否 | N41: 否 | O41: 是 | P41: 是 | Q41: 营销费用 | R41: 内容制作费 | S41: 服化道费用 | T41: 品牌运营中心 | U41: 内容电商部 | V41: 抖音部 | W41: 内容部
A42: 素材创意制作 | B42: YXHD47 | C42: 抖音视频创意-店铺-建模服务 | D42: 品类内容推广 | E42: 抖音视频创意-店铺 | F42: 启用 | G42: 是 | H42: 抖音花西子旗舰店 | I42: DP007 | J42: 抖音 | K42: 抖音自播 | L42: 抖音自播 | M42: 否 | N42: 否 | O42: 是 | P42: 是 | Q42: 营销费用 | R42: 内容制作费 | S42: 建模服务费 | T42: 品牌运营中心 | U42: 内容电商部 | V42: 抖音部 | W42: 内容部
A43: 素材创意制作 | B43: YXHD48 | C43: 抖音视频创意-店铺-模特服务 | D43: 品类内容推广 | E43: 抖音视频创意-店铺 | F43: 启用 | G43: 是 | H43: 抖音花西子旗舰店 | I43: DP007 | J43: 抖音 | K43: 抖音自播 | L43: 抖音自播 | M43: 否 | N43: 否 | O43: 是 | P43: 是 | Q43: 营销费用 | R43: 内容制作费 | S43: 模特服务费 | T43: 品牌运营中心 | U43: 内容电商部 | V43: 抖音部 | W43: 内容部
A44: 素材创意制作 | B44: YXHD49 | C44: 抖音视频创意-店铺-内容制作 | D44: 品类内容推广 | E44: 抖音视频创意-店铺 | F44: 启用 | G44: 是 | H44: 抖音花西子旗舰店 | I44: DP007 | J44: 抖音 | K44: 抖音自播 | L44: 抖音自播 | M44: 否 | N44: 否 | O44: 是 | P44: 是 | Q44: 营销费用 | R44: 内容制作费 | S44: 内容制作费 | T44: 品牌运营中心 | U44: 内容电商部 | V44: 抖音部 | W44: 内容部
A45: 素材创意制作 | B45: YXHD50 | C45: 抖音视频创意-店铺-拍摄服务 | D45: 品类内容推广 | E45: 抖音视频创意-店铺 | F45: 启用 | G45: 是 | H45: 抖音花西子旗舰店 | I45: DP007 | J45: 抖音 | K45: 抖音自播 | L45: 抖音自播 | M45: 否 | N45: 否 | O45: 是 | P45: 是 | Q45: 营销费用 | R45: 内容制作费 | S45: 拍摄服务费 | T45: 品牌运营中心 | U45: 内容电商部 | V45: 抖音部 | W45: 内容部
A46: 素材创意制作 | B46: YXHD51 | C46: 抖音视频创意-店铺-拍摄物料 | D46: 品类内容推广 | E46: 抖音视频创意-店铺 | F46: 启用 | G46: 是 | H46: 抖音花西子旗舰店 | I46: DP007 | J46: 抖音 | K46: 抖音自播 | L46: 抖音自播 | M46: 否 | N46: 否 | O46: 是 | P46: 是 | Q46: 营销费用 | R46: 内容制作费 | S46: 拍摄物料费 | T46: 品牌运营中心 | U46: 内容电商部 | V46: 抖音部 | W46: 内容部
A47: 素材创意制作 | B47: YXHD52 | C47: 抖音视频创意-店铺-设备租赁 | D47: 品类内容推广 | E47: 抖音视频创意-店铺 | F47: 启用 | G47: 是 | H47: 抖音花西子旗舰店 | I47: DP007 | J47: 抖音 | K47: 抖音自播 | L47: 抖音自播 | M47: 否 | N47: 否 | O47: 是 | P47: 是 | Q47: 营销费用 | R47: 其他费用 | S47: 设备租赁费 | T47: 品牌运营中心 | U47: 内容电商部 | V47: 抖音部 | W47: 内容部
A48: 素材创意制作 | B48: YXHD53 | C48: 抖音视频创意-店铺-视频制作 | D48: 品类内容推广 | E48: 抖音视频创意-店铺 | F48: 启用 | G48: 是 | H48: 抖音花西子旗舰店 | I48: DP007 | J48: 抖音 | K48: 抖音自播 | L48: 抖音自播 | M48: 否 | N48: 否 | O48: 是 | P48: 是 | Q48: 营销费用 | R48: 内容制作费 | S48: 视频制作费 | T48: 品牌运营中心 | U48: 内容电商部 | V48: 抖音部 | W48: 内容部
A49: 素材创意制作 | B49: YXHD54 | C49: 抖音视频创意-店铺-图文平面制作 | D49: 品类内容推广 | E49: 抖音视频创意-店铺 | F49: 启用 | G49: 是 | H49: 抖音花西子旗舰店 | I49: DP007 | J49: 抖音 | K49: 抖音自播 | L49: 抖音自播 | M49: 否 | N49: 否 | O49: 是 | P49: 是 | Q49: 营销费用 | R49: 内容制作费 | S49: 图文平面制作费 | T49: 品牌运营中心 | U49: 内容电商部 | V49: 抖音部 | W49: 内容部
A50: 素材创意制作 | B50: YXHD55 | C50: 抖音视频创意-店铺-舞台场地搭建 | D50: 品类内容推广 | E50: 抖音视频创意-店铺 | F50: 启用 | G50: 是 | H50: 抖音花西子旗舰店 | I50: DP007 | J50: 抖音 | K50: 抖音自播 | L50: 抖音自播 | M50: 否 | N50: 否 | O50: 是 | P50: 是 | Q50: 营销费用 | R50: 其他费用 | S50: 舞台场地搭建费 | T50: 品牌运营中心 | U50: 内容电商部 | V50: 抖音部 | W50: 内容部
... A52: 素材创意制作 | B52: YXHD57 | C52: 抖音视频创意-店铺-专业人物合作 | D52: 品类内容推广 | E52: 抖音视频创意-店铺 | F52: 启用 | G52: 是 | H52: 抖音花西子旗舰店 | I52: DP007 | J52: 抖音 | K52: 抖音自播 | L52: 抖音自播 | M52: 否 | N52: 否 | O52: 是 | P52: 是 | Q52: 营销费用 | R52: 内容制作费 | S52: 专业人物合作费 | T52: 品牌运营中心 | U52: 内容电商部 | V52: 抖音部 | W52: 内容部
A53: 素材创意制作 | B53: YXHD58 | C53: 抖音视频创意-矩阵号-场地租赁 | D53: 品类内容推广 | E53: 抖音视频创意-矩阵号 | F53: 启用 | G53: 是 | H53: 抖音花西子旗舰店 | I53: DP007 | J53: 抖音 | K53: 抖音矩阵号 | M53: 否 | N53: 否 | O53: 是 | P53: 是 | Q53: 营销费用 | R53: 其他费用 | S53: 场地租赁费 | T53: 品牌运营中心 | U53: 内容电商部 | V53: 抖音部 | W53: 矩阵运营部
A54: 素材创意制作 | B54: YXHD59 | C54: 抖音视频创意-矩阵号-动画制作 | D54: 品类内容推广 | E54: 抖音视频创意-矩阵号 | F54: 启用 | G54: 是 | H54: 抖音花西子旗舰店 | I54: DP007 | J54: 抖音 | K54: 抖音矩阵号 | M54: 否 | N54: 否 | O54: 是 | P54: 是 | Q54: 营销费用 | R54: 内容制作费 | S54: 动画制作费 | T54: 品牌运营中心 | U54: 内容电商部 | V54: 抖音部 | W54: 矩阵运营部
A55: 素材创意制作 | B55: YXHD60 | C55: 抖音视频创意-矩阵号-服化道费 | D55: 品类内容推广 | E55: 抖音视频创意-矩阵号 | F55: 启用 | G55: 是 | H55: 抖音花西子旗舰店 | I55: DP007 | J55: 抖音 | K55: 抖音矩阵号 | M55: 否 | N55: 否 | O55: 是 | P55: 是 | Q55: 营销费用 | R55: 内容制作费 | S55: 服化道费用 | T55: 品牌运营中心 | U55: 内容电商部 | V55: 抖音部 | W55: 矩阵运营部
A56: 素材创意制作 | B56: YXHD61 | C56: 抖音视频创意-矩阵号-建模服务 | D56: 品类内容推广 | E56: 抖音视频创意-矩阵号 | F56: 启用 | G56: 是 | H56: 抖音花西子旗舰店 | I56: DP007 | J56: 抖音 | K56: 抖音矩阵号 | M56: 否 | N56: 否 | O56: 是 | P56: 是 | Q56: 营销费用 | R56: 内容制作费 | S56: 建模服务费 | T56: 品牌运营中心 | U56: 内容电商部 | V56: 抖音部 | W56: 矩阵运营部
A57: 素材创意制作 | B57: YXHD62 | C57: 抖音视频创意-矩阵号-模特服务 | D57: 品类内容推广 | E57: 抖音视频创意-矩阵号 | F57: 启用 | G57: 是 | H57: 抖音花西子旗舰店 | I57: DP007 | J57: 抖音 | K57: 抖音矩阵号 | M57: 否 | N57: 否 | O57: 是 | P57: 是 | Q57: 营销费用 | R57: 内容制作费 | S57: 模特服务费 | T57: 品牌运营中心 | U57: 内容电商部 | V57: 抖音部 | W57: 矩阵运营部
A58: 素材创意制作 | B58: YXHD63 | C58: 抖音视频创意-矩阵号-内容制作 | D58: 品类内容推广 | E58: 抖音视频创意-矩阵号 | F58: 启用 | G58: 是 | H58: 抖音花西子旗舰店 | I58: DP007 | J58: 抖音 | K58: 抖音矩阵号 | M58: 否 | N58: 否 | O58: 是 | P58: 是 | Q58: 营销费用 | R58: 内容制作费 | S58: 内容制作费 | T58: 品牌运营中心 | U58: 内容电商部 | V58: 抖音部 | W58: 矩阵运营部
A59: 素材创意制作 | B59: YXHD64 | C59: 抖音视频创意-矩阵号-拍摄服务 | D59: 品类内容推广 | E59: 抖音视频创意-矩阵号 | F59: 启用 | G59: 是 | H59: 抖音花西子旗舰店 | I59: DP007 | J59: 抖音 | K59: 抖音矩阵号 | M59: 否 | N59: 否 | O59: 是 | P59: 是 | Q59: 营销费用 | R59: 内容制作费 | S59: 拍摄服务费 | T59: 品牌运营中心 | U59: 内容电商部 | V59: 抖音部 | W59: 矩阵运营部
A60: 素材创意制作 | B60: YXHD65 | C60: 抖音视频创意-矩阵号-拍摄物料 | D60: 品类内容推广 | E60: 抖音视频创意-矩阵号 | F60: 启用 | G60: 是 | H60: 抖音花西子旗舰店 | I60: DP007 | J60: 抖音 | K60: 抖音矩阵号 | M60: 否 | N60: 否 | O60: 是 | P60: 是 | Q60: 营销费用 | R60: 内容制作费 | S60: 拍摄物料费 | T60: 品牌运营中心 | U60: 内容电商部 | V60: 抖音部 | W60: 矩阵运营部
A61: 素材创意制作 | B61: YXHD66 | C61: 抖音视频创意-矩阵号-设备租赁 | D61: 品类内容推广 | E61: 抖音视频创意-矩阵号 | F61: 启用 | G61: 是 | H61: 抖音花西子旗舰店 | I61: DP007 | J61: 抖音 | K61: 抖音矩阵号 | M61: 否 | N61: 否 | O61: 是 | P61: 是 | Q61: 营销费用 | R61: 其他费用 | S61: 设备租赁费 | T61: 品牌运营中心 | U61: 内容电商部 | V61: 抖音部 | W61: 矩阵运营部
A62: 素材创意制作 | B62: YXHD67 | C62: 抖音视频创意-矩阵号-视频制作 | D62: 品类内容推广 | E62: 抖音视频创意-矩阵号 | F62: 启用 | G62: 是 | H62: 抖音花西子旗舰店 | I62: DP007 | J62: 抖音 | K62: 抖音矩阵号 | M62: 否 | N62: 否 | O62: 是 | P62: 是 | Q62: 营销费用 | R62: 内容制作费 | S62: 视频制作费 | T62: 品牌运营中心 | U62: 内容电商部 | V62: 抖音部 | W62: 矩阵运营部
A63: 素材创意制作 | B63: YXHD68 | C63: 抖音视频创意-矩阵号-图文平面制作 | D63: 品类内容推广 | E63: 抖音视频创意-矩阵号 | F63: 启用 | G63: 是 | H63: 抖音花西子旗舰店 | I63: DP007 | J63: 抖音 | K63: 抖音矩阵号 | M63: 否 | N63: 否 | O63: 是 | P63: 是 | Q63: 营销费用 | R63: 内容制作费 | S63: 图文平面制作费 | T63: 品牌运营中心 | U63: 内容电商部 | V63: 抖音部 | W63: 矩阵运营部
A64: 素材创意制作 | B64: YXHD69 | C64: 抖音视频创意-矩阵号-舞台场地搭建 | D64: 品类内容推广 | E64: 抖音视频创意-矩阵号 | F64: 启用 | G64: 是 | H64: 抖音花西子旗舰店 | I64: DP007 | J64: 抖音 | K64: 抖音矩阵号 | M64: 否 | N64: 否 | O64: 是 | P64: 是 | Q64: 营销费用 | R64: 其他费用 | S64: 舞台场地搭建费 | T64: 品牌运营中心 | U64: 内容电商部 | V64: 抖音部 | W64: 矩阵运营部
... A66: 素材创意制作 | B66: YXHD71 | C66: 抖音视频创意-矩阵号-专业人物合作 | D66: 品类内容推广 | E66: 抖音视频创意-矩阵号 | F66: 启用 | G66: 是 | H66: 抖音花西子旗舰店 | I66: DP007 | J66: 抖音 | K66: 抖音矩阵号 | M66: 否 | N66: 否 | O66: 是 | P66: 是 | Q66: 营销费用 | R66: 内容制作费 | S66: 专业人物合作费 | T66: 品牌运营中心 | U66: 内容电商部 | V66: 抖音部 | W66: 矩阵运营部
A67: 内容加热 | B67: YXHD72 | C67: 粉丝通 | D67: 品类内容推广 | E67: 其他新媒体加热 | F67: 启用 | G67: 否 | M67: 否 | N67: 否 | O67: 否 | P67: 否 | Q67: 营销费用 | R67: 达人推广费 | S67: 内容推广费 | T67: 品牌运营中心 | U67: 市场广告推广部 | V67: 市场推广部 | W67: 内容投放组
A68: 内容加热 | B68: YXHD73 | C68: 矩阵号DOU+ | D68: 品类内容推广 | E68: 抖音矩阵号渠道推广 | F68: 启用 | G68: 是 | H68: 抖音花西子旗舰店 | I68: DP007 | J68: 抖音 | K68: 抖音矩阵号 | M68: 否 | N68: 否 | O68: 否 | P68: 否 | Q68: 营销费用 | R68: 达人推广费 | S68: 内容推广费 | T68: 品牌运营中心 | U68: 内容电商部 | V68: 抖音部 | W68: 矩阵运营部
A69: 内容加热 | B69: YXHD74 | C69: 快手作品推荐 | D69: 品类内容推广 | E69: 内容加热 | F69: 启用 | G69: 否 | M69: 否 | N69: 否 | O69: 否 | P69: 否 | Q69: 营销费用 | R69: 达人推广费 | S69: 内容推广费 | T69: 品牌运营中心 | U69: 市场广告推广部 | V69: 市场推广部 | W69: 内容投放组
A70: 内容加热 | B70: YXHD75 | C70: 内容服务 | D70: 品类内容推广 | E70: 内容加热 | F70: 启用 | G70: 否 | M70: 否 | N70: 否 | O70: 否 | P70: 否 | Q70: 营销费用 | R70: 达人推广费 | S70: 内容推广费 | T70: 品牌运营中心 | U70: 市场广告推广部 | V70: 市场推广部 | W70: 内容投放组
A71: 内容加热 | B71: YXHD76 | C71: 内容热推 | D71: 品类内容推广 | E71: 内容加热 | F71: 启用 | G71: 否 | M71: 否 | N71: 否 | O71: 否 | P71: 否 | Q71: 营销费用 | R71: 达人推广费 | S71: 内容推广费 | T71: 品牌运营中心 | U71: 市场广告推广部 | V71: 市场推广部 | W71: 内容投放组
A72: 素材创意制作 | B72: YXHD77 | C72: 天猫淘内内容 | D72: 品类内容推广 | E72: 天猫淘内内容 | F72: 启用 | G72: 是 | H72: 天猫花西子旗舰店 | I72: DP015 | J72: 天猫 | K72: 天猫货架 | L72: 天猫货架 | M72: 否 | N72: 否 | O72: 否 | P72: 否 | Q72: 营销费用 | R72: 内容制作费 | S72: 视频制作费 | T72: 品牌运营中心 | U72: 市场广告推广部 | V72: 达播2部
A73: 内容加热 | B73: YXHD78 | C73: 微博粉条 | D73: 品类内容推广 | E73: 其他新媒体加热 | F73: 启用 | G73: 否 | M73: 否 | N73: 否 | O73: 否 | P73: 否 | Q73: 营销费用 | R73: 达人推广费 | S73: 内容推广费 | T73: 品牌运营中心 | U73: 市场广告推广部 | V73: 市场推广部 | W73: 内容投放组
A74: 内容加热 | B74: YXHD79 | C74: 微博搜索 | D74: 品类内容推广 | E74: 其他新媒体加热 | F74: 启用 | G74: 否 | M74: 否 | N74: 否 | O74: 否 | P74: 否 | Q74: 营销费用 | R74: 达人推广费 | S74: 内容推广费 | T74: 品牌运营中心 | U74: 市场广告推广部 | V74: 市场推广部 | W74: 内容投放组
A75: 内容加热 | B75: YXHD80 | C75: 小红书加热 | D75: 品类内容推广 | E75: 其他新媒体加热 | F75: 启用 | G75: 否 | M75: 否 | N75: 否 | O75: 否 | P75: 否 | Q75: 营销费用 | R75: 达人推广费 | S75: 内容推广费 | T75: 品牌运营中心 | U75: 市场广告推广部 | V75: 市场推广部 | W75: 内容投放组
A76: 内容加热 | B76: YXHD81 | C76: 星聚力 | D76: 品类内容推广 | E76: 内容加热 | F76: 启用 | G76: 否 | M76: 否 | N76: 否 | O76: 否 | P76: 否 | Q76: 营销费用 | R76: 达人推广费 | S76: 内容推广费 | T76: 品牌运营中心 | U76: 市场广告推广部 | V76: 市场推广部 | W76: 内容投放组
A77: 素材创意制作 | B77: YXHD82 | C77: 虚拟IP | D77: 品类内容推广 | E77: 虚拟IP &直播间视觉设计 | F77: 启用 | G77: 否 | M77: 否 | N77: 否 | O77: 否 | P77: 否 | Q77: 营销费用 | R77: 内容制作费 | S77: 视频制作费 | T77: 品牌运营中心 | U77: 内容电商部 | V77: 抖音部 | W77: 内容部
A78: 素材创意制作 | B78: YXHD83 | C78: 直播间视觉设计费 | D78: 品类内容推广 | E78: 虚拟IP &直播间视觉设计 | F78: 启用 | G78: 否 | M78: 否 | N78: 否 | O78: 否 | P78: 否 | Q78: 营销费用 | R78: 内容制作费 | S78: 视觉设计费 | T78: 品牌运营中心 | U78: 内容电商部 | V78: 抖音部 | W78: 内容部
A79: 线上品宣 | B79: YXHD84 | C79: OTT广告 | D79: 品牌媒介 | E79: 线上品宣媒介 | F79: 启用 | G79: 否 | M79: 否 | N79: 否 | O79: 否 | P79: 否 | Q79: 营销费用 | R79: 媒介宣传费 | S79: 线上媒介费 | T79: 品牌运营中心 | U79: 市场广告推广部 | V79: 广告投放部 | W79: 媒介组
A80: 线上品宣 | B80: YXHD85 | C80: OTV广告 | D80: 品牌媒介 | E80: 线上品宣媒介 | F80: 启用 | G80: 否 | M80: 否 | N80: 否 | O80: 否 | P80: 否 | Q80: 营销费用 | R80: 媒介宣传费 | S80: 线上媒介费 | T80: 品牌运营中心 | U80: 市场广告推广部 | V80: 广告投放部 | W80: 媒介组
A81: 线上品宣 | B81: YXHD86 | C81: 程序化投放 | D81: 品牌媒介 | E81: 线上品宣媒介 | F81: 启用 | G81: 否 | M81: 否 | N81: 否 | O81: 否 | P81: 否 | Q81: 营销费用 | R81: 媒介宣传费 | S81: 线上媒介费 | T81: 品牌运营中心 | U81: 市场广告推广部 | V81: 广告投放部 | W81: 媒介组
A82: 线下品宣 | B82: YXHD87 | C82: 地标广告 | D82: 品牌媒介 | E82: 线下品宣媒介 | F82: 启用 | G82: 否 | M82: 否 | N82: 否 | O82: 否 | P82: 否 | Q82: 营销费用 | R82: 媒介宣传费 | S82: 线下媒介费 | T82: 品牌运营中心 | U82: 市场广告推广部 | V82: 广告投放部 | W82: 媒介组
A83: 线下品宣 | B83: YXHD88 | C83: 电梯广告 | D83: 品牌媒介 | E83: 线下品宣媒介 | F83: 启用 | G83: 否 | M83: 否 | N83: 否 | O83: 否 | P83: 否 | Q83: 营销费用 | R83: 媒介宣传费 | S83: 线下媒介费 | T83: 品牌运营中心 | U83: 市场广告推广部 | V83: 广告投放部 | W83: 媒介组
A84: 线下品宣 | B84: YXHD89 | C84: 电影院广告 | D84: 品牌媒介 | E84: 线下品宣媒介 | F84: 启用 | G84: 否 | M84: 否 | N84: 否 | O84: 否 | P84: 否 | Q84: 营销费用 | R84: 媒介宣传费 | S84: 线下媒介费 | T84: 品牌运营中心 | U84: 市场广告推广部 | V84: 广告投放部 | W84: 媒介组
... A89: 线上品宣 | B89: YXHD94 | C89: 商业化资源包合作 | D89: 品牌媒介 | E89: 线上品宣媒介 | F89: 启用 | G89: 否 | M89: 否 | N89: 否 | O89: 否 | P89: 否 | Q89: 营销费用 | R89: 媒介宣传费 | S89: 线上媒介费 | T89: 品牌运营中心 | U89: 市场广告推广部 | V89: 广告投放部 | W89: 媒介组
A90: 线上品宣 | B90: YXHD95 | C90: 投放策略调研 | D90: 品牌媒介 | E90: 调研费（其他非标） | F90: 启用 | G90: 否 | M90: 否 | N90: 否 | O90: 否 | P90: 否 | Q90: 营销费用 | R90: 品牌宣传费 | S90: 市场调研费 | T90: 品牌运营中心 | U90: 市场广告推广部 | V90: 策略部
A91: IMC国妆 | B91: YXHD96 | C91: IMC国妆 | D91: 品牌项目 | E91: IMC国妆 | F91: 禁用 | G91: 否 | M91: 否 | N91: 否 | O91: 是 | P91: 是 | Q91: 营销费用 | R91: 内容制作费 | S91: 视频制作费 | T91: 品牌产品中心 | U91: 品牌营销部
A92: IMC花养 | B92: YXHD97 | C92: IMC花养 | D92: 品牌项目 | E92: IMC花养 | F92: 禁用 | G92: 否 | M92: 否 | N92: 否 | O92: 是 | P92: 是 | Q92: 营销费用 | R92: 内容制作费 | S92: 视频制作费 | T92: 品牌产品中心 | U92: 品牌营销部
A93: IMC文化 | B93: YXHD98 | C93: IMC文化 | D93: 品牌项目 | E93: IMC文化 | F93: 禁用 | G93: 否 | M93: 否 | N93: 否 | O93: 是 | P93: 是 | Q93: 营销费用 | R93: 内容制作费 | S93: 视频制作费 | T93: 品牌产品中心 | U93: 品牌营销部
A94: 日常-创意与物料 | B94: YXHD99 | C94: 日常-创意与物料 | D94: 品牌项目 | E94: 日常-创意与物料 | F94: 禁用 | G94: 否 | M94: 否 | N94: 否 | O94: 否 | P94: 否 | Q94: 营销费用 | R94: 品牌宣传费 | S94: 明星合作费 | T94: 品牌产品中心 | U94: 品牌营销部
A95: 调研费 | B95: YXHD100 | C95: 数据采买和调研费 | D95: 品牌项目 | E95: 日常-测试 | F95: 禁用 | G95: 否 | M95: 否 | N95: 否 | O95: 否 | P95: 否 | Q95: 营销费用 | R95: 品牌宣传费 | S95: 市场调研费 | T95: 品牌产品中心 | U95: 品牌营销部
A96: 新媒体费用 | B96: YXHD101 | C96: 私域代运营费用 | D96: 品牌项目 | E96: 日常-私域 | F96: 禁用 | G96: 否 | M96: 否 | N96: 否 | O96: 否 | P96: 否 | Q96: 营销费用 | R96: 渠道推广费 | S96: 代运营服务费 | T96: 品牌产品中心 | U96: 品牌营销部
A97: 新媒体费用 | B97: YXHD102 | C97: 私域视频制作 | D97: 品牌项目 | E97: 日常-私域 | F97: 禁用 | G97: 否 | M97: 否 | N97: 否 | O97: 否 | P97: 否 | Q97: 营销费用 | R97: 内容制作费 | S97: 视频制作费 | T97: 品牌产品中心 | U97: 品牌营销部
A98: 新媒体费用 | B98: YXHD103 | C98: 私域图文制作费 | D98: 品牌项目 | E98: 日常-私域 | F98: 禁用 | G98: 否 | M98: 否 | N98: 否 | O98: 否 | P98: 否 | Q98: 营销费用 | R98: 内容制作费 | S98: 图文平面制作费 | T98: 品牌产品中心 | U98: 品牌营销部
A99: 新媒体费用 | B99: YXHD104 | C99: 私域账号运营费 | D99: 品牌项目 | E99: 日常-私域 | F99: 禁用 | G99: 否 | M99: 否 | N99: 否 | O99: 否 | P99: 否 | Q99: 营销费用 | R99: 其他费用 | S99: 日常营运费用 | T99: 品牌产品中心 | U99: 品牌营销部
A100: 李佳琦全案 | B100: YXHD105 | C100: 佳琦全案-服务费 | D100: 品牌营销直播专项 | E100: 佳琦全案 | F100: 启用 | G100: 否 | M100: 否 | N100: 否 | O100: 否 | P100: 否 | Q100: 营销费用 | R100: 内容制作费 | S100: 拍摄服务费 | T100: 品牌运营中心 | U100: 直播运营部 | V100: SKA达播部
A101: 李佳琦全案 | B101: YXHD106 | C101: 佳琦全案-设计费 | D101: 品牌营销直播专项 | E101: 佳琦全案 | F101: 启用 | G101: 否 | M101: 否 | N101: 否 | O101: 否 | P101: 否 | Q101: 营销费用 | R101: 内容制作费 | S101: 视频制作费 | T101: 品牌运营中心 | U101: 直播运营部 | V101: SKA达播部
A102: 直播公关费 | B102: YXHD107 | C102: 李佳琦公关礼 | D102: 品牌营销直播专项 | E102: BD公关费-李佳琦专项 | F102: 启用 | G102: 否 | M102: 否 | N102: 否 | O102: 是 | P102: 是 | Q102: 营销费用 | R102: 其他费用 | S102: 公关礼品费 | T102: 品牌运营中心 | U102: 直播运营部 | V102: SKA达播部
A103: 直播公关费 | B103: YXHD108 | C103: 直播公关礼-外采-达播二部 | D103: 品牌营销直播专项 | E103: BD公关费-达播二部 | F103: 启用 | G103: 否 | M103: 否 | N103: 否 | O103: 是 | P103: 是 | Q103: 营销费用 | R103: 其他费用 | S103: 公关礼品费 | T103: 品牌运营中心 | U103: 市场广告推广部 | V103: 达播2部
A104: 直播公关费 | B104: YXHD109 | C104: 直播公关礼-外采-淘宝其他 | D104: 品牌营销直播专项 | E104: BD公关费-淘宝其他 | F104: 启用 | G104: 否 | M104: 否 | N104: 否 | O104: 是 | P104: 是 | Q104: 营销费用 | R104: 其他费用 | S104: 公关礼品费 | T104: 品牌运营中心 | U104: 市场广告推广部 | V104: 达播2部
A105: 直播公关费 | B105: YXHD110 | C105: 直播公关礼-外采-田恬 | D105: 品牌营销直播专项 | E105: BD公关费-田恬 | F105: 启用 | G105: 否 | M105: 否 | N105: 否 | O105: 是 | P105: 是 | Q105: 营销费用 | R105: 其他费用 | S105: 公关礼品费 | T105: 品牌运营中心 | U105: 直播运营部 | V105: SKA达播部
A106: 直播公关费 | B106: YXHD111 | C106: 直播公关礼-自有-达播二部 | D106: 品牌营销直播专项 | E106: BD公关费-达播二部 | F106: 启用 | G106: 否 | M106: 否 | N106: 否 | O106: 是 | P106: 是 | Q106: 营销费用 | R106: 其他费用 | S106: 公关礼品费 | T106: 品牌运营中心 | U106: 市场广告推广部 | V106: 达播2部
A107: 直播公关费 | B107: YXHD112 | C107: 直播公关礼-自有-淘宝其他 | D107: 品牌营销直播专项 | E107: BD公关费-淘宝其他 | F107: 启用 | G107: 否 | M107: 否 | N107: 否 | O107: 是 | P107: 是 | Q107: 营销费用 | R107: 其他费用 | S107: 公关礼品费 | T107: 品牌运营中心 | U107: 市场广告推广部 | V107: 达播2部
A108: 直播公关费 | B108: YXHD113 | C108: 直播公关礼-自有-田恬 | D108: 品牌营销直播专项 | E108: BD公关费-田恬 | F108: 启用 | G108: 否 | M108: 否 | N108: 否 | O108: 是 | P108: 是 | Q108: 营销费用 | R108: 其他费用 | S108: 公关礼品费 | T108: 品牌运营中心 | U108: 直播运营部 | V108: SKA达播部
A109: 品牌营销-跨中心协同 | B109: YXHD114 | C109: 项目推广协同 | D109: 品牌运营其他 | E109: 市场价值营销 | F109: 启用 | G109: 否 | M109: 否 | N109: 否 | O109: 否 | P109: 否 | Q109: 营销费用 | R109: 内容制作费 | S109: 视频制作费 | T109: 品牌运营中心 | U109: 市场广告推广部 | V109: 市场推广部
...

Sheet 营销活动计划分类
A1: 营销活动计划分类 | B1: 编码
A2: IP明星内容合作 | B2: HDFL01
A3: 其他达人直播 | B3: HDFL02
A4: SKA达人 | B4: HDFL03
A5: 田恬 | B5: HDFL04
A6: 李佳琦 | B6: HDFL05
A7: 素材创意制作 | B7: HDFL06
A8: 内容加热 | B8: HDFL07
A9: 线上品宣 | B9: HDFL08
A10: 线下品宣 | B10: HDFL09
A11: IMC国妆 | B11: HDFL10
A12: IMC花养 | B12: HDFL11
... A44: GWP外采 | B44: HDFL43

Sheet 待确认
A1: 营销活动分类 | B1: 营销活动场景 | C1: 编码 | D1: 一级预算科目 | E1: 二级预算科目 | F1: 能否到店铺 | G1: 店铺 | I1: 渠道 | J1: 业务来源 | K1: 业务单元 | L1: 能否到品类（单品简称） | M1: 能否到SKU | N1: 是否允许个人报销 | O1: 是否允许无票报销 | P1: 费用类型 | Q1: 费用大类 | R1: 费用小类 | S1: 一级部门 | T1: 二级部门 | U1: 三级部门 | V1: 四级部门
A2: 平台与媒介公关费 | E2: 市场公关运营 | F2: 否 | L2: 否 | M2: 否 | N2: 是 | O2: 是 | P2: 营销费用 | Q2: 其他费用 | R2: 公关礼品费 | S2: 品牌运营中心 | T2: 渠道运营部
A3: 平台与媒介公关费 | E3: 市场公关运营 | F3: 否 | L3: 否 | M3: 否 | N3: 是 | O3: 是 | P3: 营销费用 | Q3: 其他费用 | R3: 公关礼品费 | S3: 品牌运营中心 | T3: 市场广告推广部 | U3: 广告投放部 | V3: 媒介部
A4: 平台与媒介公关费 | E4: 市场公关运营 | F4: 否 | L4: 否 | M4: 否 | N4: 是 | O4: 是 | P4: 营销费用 | Q4: 其他费用 | R4: 公关礼品费 | S4: 品牌运营中心 | T4: 运营策略部 | U4: 天猫运营部

Sheet 基础信息
A1: 字段 | B1: 字段属性 | C1: 字段解释 | D1: 用途与诉求 | E1: 字段名 | F1: 字段长度 | G1: 是否主键 | H1: 字段备注
A2: 营销活动场景 | B2: 文本
A3: 营销活动场景编码 | B3: 文本
A4: 能否到店铺 | B4: 下拉-单选
A5: 能否到品类 | B5: 下拉-单选
A6: 能否到SKU | B6: 下拉-单选
A7: 是否允许个人报销 | B7: 下拉-单选
A8: 是否允许无票报销 | B8: 下拉-单选
A9: 预算科目 | B9: 下拉-单选
A10: 营销活动类型 | B10: 文本

Sheet 营销活动与费用类型关联关系
A1: 序号 | B1: 费用大类 | C1: 费用小类 | D1: 费用类别 | E1: 营销活动场景 | G1: 一级预算科目 | H1: 二级预算科目 | I1: 一级部门 | J1: 二级部门 | K1: 三级部门 | L1: 四级部门 | M1: 会计科目（新） | N1: 科目编码（新） | O1: 是否允许无票 | P1: 发票类目建议 | Q1: 费控系统表单字段要求 | W1: 财务入账科目字段要求
F2: 是否允许个人垫付 | Q2: 项目 | R2: 一级部门 | S2: 二级部门 | T2: 品牌 | U2: 店铺 | V2: 广宣 | W2: 项目 | X2: 一级部门 | Y2: 二级部门 | Z2: 品牌 | AA2: 店铺 | AB2: 广宣
A3: =ROW(B3)-2 | B3: 媒介宣传费 | C3: 线上媒介费 | D3: 营销费用 | E3: 抖音品牌信息流 | F3: =VLOOKUP(E3,'收集数据表'!A:K,6,0) | G3: 品牌媒介 | H3: 线上品宣媒介 | I3: 品牌运营中心 | J3: 市场广告推广部 | K3: 广告投放部 | L3: 媒介部 | M3: 销售费用_营销费用_线上推广费 | N3: 6601.36.24 | P3: 技术服务费？服务费？
A4: =ROW(B4)-2 | B4: 媒介宣传费 | C4: 线上媒介费 | D4: 营销费用 | E4: 快手品牌信息流 | F4: =VLOOKUP(E4,'收集数据表'!A:K,6,0) | G4: 品牌媒介 | H4: 线上品宣媒介 | I4: 品牌运营中心 | J4: 市场广告推广部 | K4: 广告投放部 | L4: 媒介部 | M4: 销售费用_营销费用_线上推广费 | N4: 6601.36.24
A5: =ROW(B5)-2 | B5: 媒介宣传费 | C5: 线上媒介费 | D5: 营销费用 | E5: 开屏类广告 | F5: =VLOOKUP(E5,'收集数据表'!A:K,6,0) | G5: 品牌媒介 | H5: 线上品宣媒介 | I5: 品牌运营中心 | J5: 市场广告推广部 | K5: 广告投放部 | L5: 媒介部 | M5: 销售费用_营销费用_线上推广费 | N5: 6601.36.24 | P5: 广告发布费
A6: =ROW(B6)-2 | B6: 媒介宣传费 | C6: 线上媒介费 | D6: 营销费用 | E6: 程序化投放 | F6: =VLOOKUP(E6,'收集数据表'!A:K,6,0) | G6: 品牌媒介 | H6: 线上品宣媒介 | I6: 品牌运营中心 | J6: 市场广告推广部 | K6: 广告投放部 | L6: 媒介部 | M6: 销售费用_营销费用_线上推广费 | N6: 6601.36.24 | P6: 广告发布费
A7: =ROW(B7)-2 | B7: 媒介宣传费 | C7: 线上媒介费 | D7: 营销费用 | E7: OTT广告 | F7: =VLOOKUP(E7,'收集数据表'!A:K,6,0) | G7: 品牌媒介 | H7: 线上品宣媒介 | I7: 品牌运营中心 | J7: 市场广告推广部 | K7: 广告投放部 | L7: 媒介部 | M7: 销售费用_营销费用_线上推广费 | N7: 6601.36.24 | P7: 广告发布费
A8: =ROW(B8)-2 | B8: 媒介宣传费 | C8: 线上媒介费 | D8: 营销费用 | E8: OTV广告 | F8: =VLOOKUP(E8,'收集数据表'!A:K,6,0) | G8: 品牌媒介 | H8: 线上品宣媒介 | I8: 品牌运营中心 | J8: 市场广告推广部 | K8: 广告投放部 | L8: 媒介部 | M8: 销售费用_营销费用_线上推广费 | N8: 6601.36.24 | P8: 广告发布费
A9: =ROW(B9)-2 | B9: 媒介宣传费 | C9: 线上媒介费 | D9: 营销费用 | E9: 商业化资源包合作 | F9: =VLOOKUP(E9,'收集数据表'!A:K,6,0) | G9: 品牌媒介 | H9: 线上品宣媒介 | I9: 品牌运营中心 | J9: 市场广告推广部 | K9: 广告投放部 | L9: 媒介部 | M9: 销售费用_营销费用_线上推广费 | N9: 6601.36.24 | P9: 广告发布费
A10: =ROW(B10)-2 | B10: 媒介宣传费 | C10: 线上媒介费 | D10: 营销费用 | E10: 广告效果监测 | F10: =VLOOKUP(E10,'收集数据表'!A:K,6,0) | G10: 品牌媒介 | H10: 线上品宣媒介 | I10: 品牌运营中心 | J10: 市场广告推广部 | K10: 广告投放部 | L10: 媒介部 | M10: 销售费用_营销费用_线上推广费 | N10: 6601.36.24 | P10: 广告发布费
A11: =ROW(B11)-2 | B11: 媒介宣传费 | C11: 线下媒介费 | D11: 营销费用 | E11: 电梯广告 | F11: =VLOOKUP(E11,'收集数据表'!A:K,6,0) | G11: 品牌媒介 | H11: 线下品宣媒介 | I11: 品牌运营中心 | J11: 市场广告推广部 | K11: 广告投放部 | L11: 媒介部 | M11: 销售费用_营销费用_线下推广费 | N11: 6601.36.25 | P11: 广告发布费
A12: =ROW(B12)-2 | B12: 媒介宣传费 | C12: 线下媒介费 | D12: 营销费用 | E12: 电影院广告 | F12: =VLOOKUP(E12,'收集数据表'!A:K,6,0) | G12: 品牌媒介 | H12: 线下品宣媒介 | I12: 品牌运营中心 | J12: 市场广告推广部 | K12: 广告投放部 | L12: 媒介部 | M12: 销售费用_营销费用_线下推广费 | N12: 6601.36.25 | P12: 广告发布费
A13: =ROW(B13)-2 | B13: 媒介宣传费 | C13: 线下媒介费 | D13: 营销费用 | E13: 地标广告 | F13: =VLOOKUP(E13,'收集数据表'!A:K,6,0) | G13: 品牌媒介 | H13: 线下品宣媒介 | I13: 品牌运营中心 | J13: 市场广告推广部 | K13: 广告投放部 | L13: 媒介部 | M13: 销售费用_营销费用_线下推广费 | N13: 6601.36.25 | P13: 广告发布费
A14: =ROW(B14)-2 | B14: 品牌宣传费 | C14: 市场调研费 | D14: 营销费用 | E14: 投放策略调研 | F14: =VLOOKUP(E14,'收集数据表'!A:K,6,0) | G14: 品牌媒介 | H14: 调研费（其他非标） | I14: 品牌运营中心 | J14: 市场广告推广部 | K14: 策略部 | M14: ="销售费用_"&D14&"_"&C14 | N14: 6601.36.20 | P14: 调研服务费
A15: =ROW(B15)-2 | B15: 内容制作费 | C15: 视频制作费 | D15: 营销费用 | E15: =H15&"-"&LEFT(C15,4) | F15: =VLOOKUP(E15,'收集数据表'!A:K,6,0) | G15: 品类内容推广 | H15: AD竞价内容创意 | I15: 品牌运营中心 | J15: 市场广告推广部 | K15: 广告投放部 | L15: 内容策划组 | M15: ="销售费用_"&D15&"_"&C15 | N15: 6601.36.21 | P15: =C15
A16: =ROW(B16)-2 | B16: 内容制作费 | C16: 动画制作费 | D16: 营销费用 | E16: =H16&"-"&LEFT(C16,4) | F16: =VLOOKUP(E16,'收集数据表'!A:K,6,0) | G16: 品类内容推广 | H16: AD竞价内容创意 | I16: 品牌运营中心 | J16: 市场广告推广部 | K16: 广告投放部 | L16: 内容策划组 | M16: ="销售费用_"&D16&"_"&C16 | N16: 6601.36.07 | P16: =C16
A17: =ROW(B17)-2 | B17: 内容制作费 | C17: 图文平面制作费 | D17: 营销费用 | E17: =H17&"-"&LEFT(C17,6) | F17: =VLOOKUP(E17,'收集数据表'!A:K,6,0) | G17: 品类内容推广 | H17: AD竞价内容创意 | I17: 品牌运营中心 | J17: 市场广告推广部 | K17: 广告投放部 | L17: 内容策划组 | M17: ="销售费用_"&D17&"_"&C17 | N17: 6601.36.22 | P17: =C17
A18: =ROW(B18)-2 | B18: 内容制作费 | C18: 建模服务费 | D18: 营销费用 | E18: =H18&"-"&LEFT(C18,4) | F18: =VLOOKUP(E18,'收集数据表'!A:K,6,0) | G18: 品类内容推广 | H18: AD竞价内容创意 | I18: 品牌运营中心 | J18: 市场广告推广部 | K18: 广告投放部 | L18: 内容策划组 | M18: ="销售费用_"&D18&"_"&C18 | N18: 6601.36.10 | P18: =C18
A19: =ROW(B19)-2 | B19: 内容制作费 | C19: 渲染服务费 | D19: 营销费用 | E19: =H19&"-"&LEFT(C19,4) | F19: =VLOOKUP(E19,'收集数据表'!A:K,6,0) | G19: 品类内容推广 | H19: AD竞价内容创意 | I19: 品牌运营中心 | J19: 市场广告推广部 | K19: 广告投放部 | L19: 内容策划组 | M19: ="销售费用_"&D19&"_"&C19 | N19: 6601.36.26 | P19: =C19
A20: =ROW(B20)-2 | B20: 内容制作费 | C20: 模特服务费 | D20: 营销费用 | E20: =H20&"-"&LEFT(C20,4) | F20: =VLOOKUP(E20,'收集数据表'!A:K,6,0) | G20: 品类内容推广 | H20: AD竞价内容创意 | I20: 品牌运营中心 | J20: 市场广告推广部 | K20: 广告投放部 | L20: 内容策划组 | M20: ="销售费用_"&D20&"_"&C20 | N20: 6601.36.13 | P20: =C20
A21: =ROW(B21)-2 | B21: 内容制作费 | C21: 专业人物合作费 | D21: 营销费用 | E21: =H21&"-"&LEFT(C21,6) | F21: =VLOOKUP(E21,'收集数据表'!A:K,6,0) | G21: 品类内容推广 | H21: AD竞价内容创意 | I21: 品牌运营中心 | J21: 市场广告推广部 | K21: 广告投放部 | L21: 内容策划组 | M21: ="销售费用_"&D21&"_"&C21 | N21: 6601.36.32 | P21: =C21
A22: =ROW(B22)-2 | B22: 内容制作费 | C22: 服化道费用 | D22: 营销费用 | E22: =H22&"-"&LEFT(C22,4) | F22: =VLOOKUP(E22,'收集数据表'!A:K,6,0) | G22: 品类内容推广 | H22: AD竞价内容创意 | I22: 品牌运营中心 | J22: 市场广告推广部 | K22: 广告投放部 | L22: 内容策划组 | M22: ="销售费用_"&D22&"_"&C22 | N22: 6601.36.08 | P22: 服装费、化妆费、道具费
A23: =ROW(B23)-2 | B23: 内容制作费 | C23: 拍摄服务费 | D23: 营销费用 | E23: =H23&"-"&LEFT(C23,4) | F23: =VLOOKUP(E23,'收集数据表'!A:K,6,0) | G23: 品类内容推广 | H23: AD竞价内容创意 | I23: 品牌运营中心 | J23: 市场广告推广部 | K23: 广告投放部 | L23: 内容策划组 | M23: ="销售费用_"&D23&"_"&C23 | N23: 6601.36.15 | P23: =C23
A24: =ROW(B24)-2 | B24: 内容制作费 | C24: 拍摄物料费 | D24: 营销费用 | E24: =H24&"-"&LEFT(C24,4) | F24: =VLOOKUP(E24,'收集数据表'!A:K,6,0) | G24: 品类内容推广 | H24: AD竞价内容创意 | I24: 品牌运营中心 | J24: 市场广告推广部 | K24: 广告投放部 | L24: 内容策划组 | M24: ="销售费用_"&D24&"_"&C24 | N24: 6601.36.16 | P24: =C24
A25: =ROW(B25)-2 | B25: 内容制作费 | C25: 内容制作费 | D25: 营销费用 | E25: =H25&"-"&LEFT(C25,4) | F25: =VLOOKUP(E25,'收集数据表'!A:K,6,0) | G25: 品类内容推广 | H25: AD竞价内容创意 | I25: 品牌运营中心 | J25: 市场广告推广部 | K25: 广告投放部 | L25: 内容策划组 | M25: ="销售费用_"&D25&"_"&C25 | N25: 6601.36.14 | P25: =C25
A26: =ROW(B26)-2 | B26: 达人推广费 | C26: 内容推广费 | D26: 营销费用 | E26: DOU+ | F26: =VLOOKUP(E26,'收集数据表'!A:K,6,0) | G26: 品类内容推广 | H26: 内容加热 | I26: 品牌运营中心 | J26: 市场广告推广部 | K26: 市场推广部 | L26: 内容投放组 | M26: 销售费用_营销费用_线上推广费 | N26: 6601.36.24 | P26: 技术服务费？服务费？
A27: =ROW(B27)-2 | B27: 达人推广费 | C27: 内容推广费 | D27: 营销费用 | E27: 快手作品推荐 | F27: =VLOOKUP(E27,'收集数据表'!A:K,6,0) | G27: 品类内容推广 | H27: 内容加热 | I27: 品牌运营中心 | J27: 市场广告推广部 | K27: 市场推广部 | L27: 内容投放组 | M27: 销售费用_营销费用_线上推广费 | N27: 6601.36.24 | P27: 技术服务费？服务费？
A28: =ROW(B28)-2 | B28: 达人推广费 | C28: 内容推广费 | D28: 营销费用 | E28: 内容热推 | F28: =VLOOKUP(E28,'收集数据表'!A:K,6,0) | G28: 品类内容推广 | H28: 内容加热 | I28: 品牌运营中心 | J28: 市场广告推广部 | K28: 市场推广部 | L28: 内容投放组 | M28: 销售费用_营销费用_线上推广费 | N28: 6601.36.24 | P28: 技术服务费？服务费？
A29: =ROW(B29)-2 | B29: 达人推广费 | C29: 内容推广费 | D29: 营销费用 | E29: 内容服务 | F29: =VLOOKUP(E29,'收集数据表'!A:K,6,0) | G29: 品类内容推广 | H29: 内容加热 | I29: 品牌运营中心 | J29: 市场广告推广部 | K29: 市场推广部 | L29: 内容投放组 | M29: 销售费用_营销费用_线上推广费 | N29: 6601.36.24 | P29: 技术服务费？服务费？
A30: =ROW(B30)-2 | B30: 达人推广费 | C30: 内容推广费 | D30: 营销费用 | E30: 星聚力 | F30: =VLOOKUP(E30,'收集数据表'!A:K,6,0) | G30: 品类内容推广 | H30: 内容加热 | I30: 品牌运营中心 | J30: 市场广告推广部 | K30: 市场推广部 | L30: 内容投放组 | M30: 销售费用_营销费用_线上推广费 | N30: 6601.36.24 | P30: 技术服务费？服务费？
A31: =ROW(B31)-2 | B31: 达人推广费 | C31: 内容推广费 | D31: 营销费用 | E31: 小红书加热 | F31: =VLOOKUP(E31,'收集数据表'!A:K,6,0) | G31: 品类内容推广 | H31: 其他新媒体加热 | I31: 品牌运营中心 | J31: 市场广告推广部 | K31: 市场推广部 | L31: 内容投放组 | M31: 销售费用_营销费用_线上推广费 | N31: 6601.36.24 | P31: 技术服务费？服务费？
A32: =ROW(B32)-2 | B32: 达人推广费 | C32: 内容推广费 | D32: 营销费用 | E32: B站起飞加热 | F32: =VLOOKUP(E32,'收集数据表'!A:K,6,0) | G32: 品类内容推广 | H32: 其他新媒体加热 | I32: 品牌运营中心 | J32: 市场广告推广部 | K32: 市场推广部 | L32: 内容投放组 | M32: 销售费用_营销费用_线上推广费 | N32: 6601.36.24 | P32: 技术服务费？服务费？
A33: =ROW(B33)-2 | B33: 达人推广费 | C33: 内容推广费 | D33: 营销费用 | E33: 微博粉条 | F33: =VLOOKUP(E33,'收集数据表'!A:K,6,0) | G33: 品类内容推广 | H33: 其他新媒体加热 | I33: 品牌运营中心 | J33: 市场广告推广部 | K33: 市场推广部 | L33: 内容投放组 | M33: 销售费用_营销费用_线上推广费 | N33: 6601.36.24 | P33: 技术服务费？服务费？
A34: =ROW(B34)-2 | B34: 达人推广费 | C34: 内容推广费 | D34: 营销费用 | E34: 粉丝通 | F34: =VLOOKUP(E34,'收集数据表'!A:K,6,0) | G34: 品类内容推广 | H34: 其他新媒体加热 | I34: 品牌运营中心 | J34: 市场广告推广部 | K34: 市场推广部 | L34: 内容投放组 | M34: 销售费用_营销费用_线上推广费 | N34: 6601.36.24 | P34: 技术服务费？服务费？
A35: =ROW(B35)-2 | B35: 达人推广费 | C35: 内容推广费 | D35: 营销费用 | E35: 微博搜索 | F35: =VLOOKUP(E35,'收集数据表'!A:K,6,0) | G35: 品类内容推广 | H35: 其他新媒体加热 | I35: 品牌运营中心 | J35: 市场广告推广部 | K35: 市场推广部 | L35: 内容投放组 | M35: 销售费用_营销费用_线上推广费 | N35: 6601.36.24 | P35: 技术服务费？服务费？
A36: =ROW(B36)-2 | B36: 渠道推广费 | C36: 站内推广费 | D36: 营销费用 | E36: 天猫-直通车 | F36: =VLOOKUP(E36,'收集数据表'!A:K,6,0) | G36: 平台电商推广 | H36: 淘内-推广 | I36: 品牌运营中心 | J36: 运营策略部 | K36: 天猫运营部 | L36: 天猫推广组 | M36: 销售费用_营销费用_线上推广费 | N36: 6601.36.24 | P36: 技术服务费？服务费？
A37: =ROW(B37)-2 | B37: 渠道推广费 | C37: 站内推广费 | D37: 营销费用 | E37: 天猫-引力魔方 | F37: =VLOOKUP(E37,'收集数据表'!A:K,6,0) | G37: 平台电商推广 | H37: 淘内-推广 | I37: 品牌运营中心 | J37: 运营策略部 | K37: 天猫运营部 | L37: 天猫推广组 | M37: 销售费用_营销费用_线上推广费 | N37: 6601.36.24 | P37: 技术服务费？服务费？
... A58: =ROW(B58)-2 | B58: 渠道推广费 | C58: 站内推广费 | D58: 营销费用 | E58: 京东POP-联合活动 | F58: =VLOOKUP(E58,'收集数据表'!A:K,6,0) | G58: 平台电商推广 | H58: 京东渠道推广（POP） | I58: 品牌运营中心 | J58: 渠道运营部 | K58: 特色电商部 | L58: 京东唯品推广组 | M58: 销售费用_营销费用_线上推广费 | N58: 6601.36.24 | P58: 技术服务费？服务费？广告费？
A59: =ROW(B59)-2 | B59: 品牌宣传费 | C59: 明星合作费 | D59: 营销费用 | E59: =H59 | F59: =VLOOKUP(E59,'收集数据表'!A:K,6,0) | G59: 品牌项目 | H59: 日常-创意与物料 | I59: 品牌产品中心 | J59: 品牌营销部 | M59: 销售费用_营销费用_明星合作费 | N59: 6601.36.12 | P59: 代言费 | Q59: Y
A60: =ROW(B60)-2 | B60: 渠道推广费 | C60: 站内推广费 | D60: 营销费用 | E60: 唯品会-唯品常规投放 | F60: =VLOOKUP(E60,'收集数据表'!A:K,6,0) | G60: 平台电商推广 | H60: 唯品渠道推广 | I60: 品牌运营中心 | J60: 渠道运营部 | K60: 特色电商部 | L60: 京东唯品推广组 | M60: 销售费用_营销费用_线上推广费 | N60: 6601.36.24 | P60: 技术服务费？服务费？
A61: =ROW(B61)-2 | B61: 渠道推广费 | C61: 站内推广费 | D61: 营销费用 | E61: 唯品会-达人卖货 | F61: =VLOOKUP(E61,'收集数据表'!A:K,6,0) | G61: 平台电商推广 | H61: 唯品渠道推广 | I61: 品牌运营中心 | J61: 渠道运营部 | K61: 特色电商部 | L61: 京东唯品推广组 | M61: 销售费用_营销费用_线上推广费 | N61: 6601.36.24 | P61: 技术服务费？服务费？
A62: =ROW(B62)-2 | B62: 渠道推广费 | C62: 站内推广费 | D62: 营销费用 | E62: 自营其他 | F62: =VLOOKUP(E62,'收集数据表'!A:K,6,0) | G62: 平台电商推广 | H62: 自营其他渠道推广 | I62: 品牌运营中心 | J62: 渠道运营部 | K62: 综合渠道运营部 | L62: 综合渠道推广部 | M62: 销售费用_营销费用_线上推广费 | N62: 6601.36.24
A63: =ROW(B63)-2 | B63: 渠道推广费 | C63: 站内推广费 | D63: 营销费用 | E63: 拼多多 | F63: =VLOOKUP(E63,'收集数据表'!A:K,6,0) | G63: 平台电商推广 | H63: 拼多多渠道推广 | I63: 品牌运营中心 | J63: 渠道运营部 | K63: 综合渠道运营部 | L63: 综合渠道推广部 | M63: 销售费用_营销费用_线上推广费 | N63: 6601.36.24
A64: =ROW(B64)-2 | B64: 渠道推广费 | C64: 站外推广费 | D64: 营销费用 | E64: AD信息流 | F64: =VLOOKUP(E64,'收集数据表'!A:K,6,0) | G64: 平台电商推广 | H64: 竞价信息流-天猫 | I64: 品牌运营中心 | J64: 运营策略部 | K64: 天猫运营部 | L64: 天猫推广组 | M64: 销售费用_营销费用_线上推广费 | N64: 6601.36.24 | P64: 技术服务费？服务费？
A65: =ROW(B65)-2 | B65: 渠道推广费 | C65: 站外推广费 | D65: 营销费用 | E65: UD信息流 | F65: =VLOOKUP(E65,'收集数据表'!A:K,6,0) | G65: 平台电商推广 | H65: 竞价信息流-天猫 | I65: 品牌运营中心 | J65: 运营策略部 | K65: 天猫运营部 | L65: 天猫推广组 | M65: 销售费用_营销费用_线上推广费 | N65: 6601.36.24 | P65: 技术服务费？服务费？
A66: =ROW(B66)-2 | B66: 渠道推广费 | C66: 站外推广费 | D66: 营销费用 | E66: 磁力引擎 | F66: =VLOOKUP(E66,'收集数据表'!A:K,6,0) | G66: 平台电商推广 | H66: 竞价信息流-天猫 | I66: 品牌运营中心 | J66: 运营策略部 | K66: 天猫运营部 | L66: 天猫推广组 | M66: 销售费用_营销费用_线上推广费 | N66: 6601.36.24 | P66: 技术服务费？服务费？
A67: =ROW(B67)-2 | B67: 渠道推广费 | C67: 站内推广费 | D67: 营销费用 | E67: 磁力金牛 | F67: =VLOOKUP(E67,'收集数据表'!A:K,6,0) | G67: 直播电商推广 | H67: 快手电商渠道推广 | I67: 品牌运营中心 | J67: 运营策略部 | K67: 天猫运营部 | L67: 天猫推广组 | M67: 销售费用_营销费用_线上推广费 | N67: 6601.36.24 | P67: 技术服务费？服务费？
A68: =ROW(B68)-2 | B68: 渠道推广费 | C68: 站外推广费 | D68: 营销费用 | E68: 百度SEO竞价广告 | F68: =VLOOKUP(E68,'收集数据表'!A:K,6,0) | G68: 平台电商推广 | H68: 竞价信息流-天猫 | I68: 品牌运营中心 | J68: 运营策略部 | K68: 天猫运营部 | L68: 天猫推广组 | M68: 销售费用_营销费用_线上推广费 | N68: 6601.36.24 | P68: 技术服务费？服务费？
A69: =ROW(B69)-2 | B69: 渠道推广费 | C69: 站外推广费 | D69: 营销费用 | E69: 百度SEO搜索广告 | F69: =VLOOKUP(E69,'收集数据表'!A:K,6,0) | G69: 平台电商推广 | H69: 竞价信息流-天猫 | I69: 品牌运营中心 | J69: 运营策略部 | K69: 天猫运营部 | L69: 天猫推广组 | M69: 销售费用_营销费用_线上推广费 | N69: 6601.36.24 | P69: 技术服务费？服务费？
A70: =ROW(B70)-2 | B70: 渠道推广费 | C70: 站内推广费 | D70: 营销费用 | E70: 微信-店铺 | F70: =VLOOKUP(E70,'收集数据表'!A:K,6,0) | G70: 社交电商推广 | H70: 微信-店铺 | I70: 品牌运营中心 | J70: 渠道运营部 | K70: 综合渠道运营部 | L70: 综合渠道推广部 | M70: 销售费用_营销费用_线上推广费 | N70: 6601.36.24
A71: =ROW(B71)-2 | B71: 其他费用 | C71: 场地租赁费 | D71: 营销费用 | E71: =H71&"-"&LEFT(C71,4) | F71: =VLOOKUP(E71,'收集数据表'!A:K,6,0) | G71: 品类内容推广 | H71: AD竞价内容创意 | I71: 品牌运营中心 | J71: 市场广告推广部 | K71: 广告投放部 | L71: 内容策划组 | M71: ="销售费用_"&D71&"_"&C71 | N71: 6601.36.02 | P71: =C71
A72: =ROW(B72)-2 | B72: 其他费用 | C72: 舞台场地搭建费 | D72: 营销费用 | E72: =H72&"-"&LEFT(C72,4) | F72: =VLOOKUP(E72,'收集数据表'!A:K,6,0) | G72: 品类内容推广 | H72: AD竞价内容创意 | I72: 品牌运营中心 | J72: 市场广告推广部 | K72: 广告投放部 | L72: 内容策划组 | M72: 销售费用_营销费用_搭建服务费 | N72: 6601.36.03 | P72: 搭建服务费
A73: =ROW(B73)-2 | B73: 其他费用 | C73: 设备租赁费 | D73: 营销费用 | E73: =H73&"-"&LEFT(C73,4) | F73: =VLOOKUP(E73,'收集数据表'!A:K,6,0) | G73: 品类内容推广 | H73: AD竞价内容创意 | I73: 品牌运营中心 | J73: 市场广告推广部 | K73: 广告投放部 | L73: 内容策划组 | M73: ="销售费用_"&D73&"_"&C73 | N73: 6601.36.19 | P73: =C73
A74: =ROW(B74)-2 | B74: 内容制作费 | C74: 视频制作费 | D74: 营销费用 | E74: =H74 | F74: =VLOOKUP(E74,'收集数据表'!A:K,6,0) | G74: 品牌项目 | H74: IMC花养 | I74: 品牌产品中心 | J74: 品牌营销部 | M74: ="销售费用_"&D74&"_"&C74 | N74: 6601.36.21 | P74: =C74 | Q74: Y
A75: =ROW(B75)-2 | B75: 内容制作费 | C75: 视频制作费 | D75: 营销费用 | E75: =H75 | F75: =VLOOKUP(E75,'收集数据表'!A:K,6,0) | G75: 品牌项目 | H75: IMC国妆 | I75: 品牌产品中心 | J75: 品牌营销部 | M75: ="销售费用_"&D75&"_"&C75 | N75: 6601.36.21 | P75: =C75 | Q75: Y
A76: =ROW(B76)-2 | B76: 内容制作费 | C76: 视频制作费 | D76: 营销费用 | E76: =H76 | F76: =VLOOKUP(E76,'收集数据表'!A:K,6,0) | G76: 品牌项目 | H76: IMC文化 | I76: 品牌产品中心 | J76: 品牌营销部 | M76: ="销售费用_"&D76&"_"&C76 | N76: 6601.36.21 | P76: =C76 | Q76: Y
A77: =ROW(B77)-2 | B77: 内容制作费 | C77: 视频制作费 | D77: 营销费用 | E77: =H77 | F77: =VLOOKUP(E77,'收集数据表'!A:K,6,0) | G77: 品牌项目 | H77: 日常-创意与物料 | I77: 品牌产品中心 | J77: 品牌营销部 | M77: ="销售费用_"&D77&"_"&C77 | N77: 6601.36.21 | P77: =C77 | Q77: Y
A78: =ROW(B78)-2 | B78: 内容制作费 | C78: 动画制作费 | D78: 营销费用 | E78: =H78 | F78: =VLOOKUP(E78,'收集数据表'!A:K,6,0) | G78: 品牌项目 | H78: IMC花养 | I78: 品牌产品中心 | J78: 品牌营销部 | M78: ="销售费用_"&D78&"_"&C78 | N78: 6601.36.07 | P78: =C78 | Q78: Y
A79: =ROW(B79)-2 | B79: 内容制作费 | C79: 动画制作费 | D79: 营销费用 | E79: =H79 | F79: =VLOOKUP(E79,'收集数据表'!A:K,6,0) | G79: 品牌项目 | H79: IMC国妆 | I79: 品牌产品中心 | J79: 品牌营销部 | M79: ="销售费用_"&D79&"_"&C79 | N79: 6601.36.07 | P79: =C79 | Q79: Y
A80: =ROW(B80)-2 | B80: 内容制作费 | C80: 动画制作费 | D80: 营销费用 | E80: =H80 | F80: =VLOOKUP(E80,'收集数据表'!A:K,6,0) | G80: 品牌项目 | H80: IMC文化 | I80: 品牌产品中心 | J80: 品牌营销部 | M80: ="销售费用_"&D80&"_"&C80 | N80: 6601.36.07 | P80: =C80 | Q80: Y
A81: =ROW(B81)-2 | B81: 内容制作费 | C81: 动画制作费 | D81: 营销费用 | E81: =H81 | F81: =VLOOKUP(E81,'收集数据表'!A:K,6,0) | G81: 品牌项目 | H81: 日常-创意与物料 | I81: 品牌产品中心 | J81: 品牌营销部 | M81: ="销售费用_"&D81&"_"&C81 | N81: 6601.36.07 | P81: =C81 | Q81: Y
A82: =ROW(B82)-2 | B82: 内容制作费 | C82: 图文平面制作费 | D82: 营销费用 | E82: =H82 | F82: =VLOOKUP(E82,'收集数据表'!A:K,6,0) | G82: 品牌项目 | H82: IMC花养 | I82: 品牌产品中心 | J82: 品牌营销部 | M82: ="销售费用_"&D82&"_"&C82 | N82: 6601.36.22 | P82: =C82 | Q82: Y
A83: =ROW(B83)-2 | B83: 内容制作费 | C83: 图文平面制作费 | D83: 营销费用 | E83: =H83 | F83: =VLOOKUP(E83,'收集数据表'!A:K,6,0) | G83: 品牌项目 | H83: IMC国妆 | I83: 品牌产品中心 | J83: 品牌营销部 | M83: ="销售费用_"&D83&"_"&C83 | N83: 6601.36.22 | P83: =C83 | Q83: Y
A84: =ROW(B84)-2 | B84: 内容制作费 | C84: 图文平面制作费 | D84: 营销费用 | E84: =H84 | F84: =VLOOKUP(E84,'收集数据表'!A:K,6,0) | G84: 品牌项目 | H84: IMC文化 | I84: 品牌产品中心 | J84: 品牌营销部 | M84: ="销售费用_"&D84&"_"&C84 | N84: 6601.36.22 | P84: =C84 | Q84: Y
A85: =ROW(B85)-2 | B85: 内容制作费 | C85: 图文平面制作费 | D85: 营销费用 | E85: =H85 | F85: =VLOOKUP(E85,'收集数据表'!A:K,6,0) | G85: 品牌项目 | H85: 日常-创意与物料 | I85: 品牌产品中心 | J85: 品牌营销部 | M85: ="销售费用_"&D85&"_"&C85 | N85: 6601.36.22 | P85: =C85 | Q85: Y
... A101: =ROW(B101)-2 | B101: 内容制作费 | C101: 专业人物合作费 | D101: 营销费用 | E101: =H101 | F101: =VLOOKUP(E101,'收集数据表'!A:K,6,0) | G101: 品牌项目 | H101: 日常-创意与物料 | I101: 品牌产品中心 | J101: 品牌营销部 | M101: ="销售费用_"&D101&"_"&C101 | N101: 6601.36.32 | P101: =C101 | Q101: Y
A102: =ROW(B102)-2 | B102: 内容制作费 | C102: 服化道费用 | D102: 营销费用 | E102: =H102 | F102: =VLOOKUP(E102,'收集数据表'!A:K,6,0) | G102: 品牌项目 | H102: IMC花养 | I102: 品牌产品中心 | J102: 品牌营销部 | M102: ="销售费用_"&D102&"_"&C102 | N102: 6601.36.08 | P102: 服装费、化妆费、道具费 | Q102: Y
A103: =ROW(B103)-2 | B103: 内容制作费 | C103: 服化道费用 | D103: 营销费用 | E103: =H103 | F103: =VLOOKUP(E103,'收集数据表'!A:K,6,0) | G103: 品牌项目 | H103: IMC国妆 | I103: 品牌产品中心 | J103: 品牌营销部 | M103: ="销售费用_"&D103&"_"&C103 | N103: 6601.36.08 | P103: 服装费、化妆费、道具费 | Q103: Y
A104: =ROW(B104)-2 | B104: 内容制作费 | C104: 服化道费用 | D104: 营销费用 | E104: =H104 | F104: =VLOOKUP(E104,'收集数据表'!A:K,6,0) | G104: 品牌项目 | H104: IMC文化 | I104: 品牌产品中心 | J104: 品牌营销部 | M104: ="销售费用_"&D104&"_"&C104 | N104: 6601.36.08 | P104: 服装费、化妆费、道具费 | Q104: Y
A105: =ROW(B105)-2 | B105: 内容制作费 | C105: 服化道费用 | D105: 营销费用 | E105: =H105 | F105: =VLOOKUP(E105,'收集数据表'!A:K,6,0) | G105: 品牌项目 | H105: 日常-创意与物料 | I105: 品牌产品中心 | J105: 品牌营销部 | M105: ="销售费用_"&D105&"_"&C105 | N105: 6601.36.08 | P105: 服装费、化妆费、道具费 | Q105: Y
A106: =ROW(B106)-2 | B106: 内容制作费 | C106: 拍摄服务费 | D106: 营销费用 | E106: =H106 | F106: =VLOOKUP(E106,'收集数据表'!A:K,6,0) | G106: 品牌项目 | H106: IMC花养 | I106: 品牌产品中心 | J106: 品牌营销部 | M106: ="销售费用_"&D106&"_"&C106 | N106: 6601.36.15 | P106: =C106 | Q106: Y
A107: =ROW(B107)-2 | B107: 内容制作费 | C107: 拍摄服务费 | D107: 营销费用 | E107: =H107 | F107: =VLOOKUP(E107,'收集数据表'!A:K,6,0) | G107: 品牌项目 | H107: IMC国妆 | I107: 品牌产品中心 | J107: 品牌营销部 | M107: ="销售费用_"&D107&"_"&C107 | N107: 6601.36.15 | P107: =C107 | Q107: Y
A108: =ROW(B108)-2 | B108: 内容制作费 | C108: 拍摄服务费 | D108: 营销费用 | E108: =H108 | F108: =VLOOKUP(E108,'收集数据表'!A:K,6,0) | G108: 品牌项目 | H108: IMC文化 | I108: 品牌产品中心 | J108: 品牌营销部 | M108: ="销售费用_"&D108&"_"&C108 | N108: 6601.36.15 | P108: =C108 | Q108: Y
A109: =ROW(B109)-2 | B109: 内容制作费 | C109: 拍摄服务费 | D109: 营销费用 | E109: =H109 | F109: =VLOOKUP(E109,'收集数据表'!A:K,6,0) | G109: 品牌项目 | H109: 日常-创意与物料 | I109: 品牌产品中心 | J109: 品牌营销部 | M109: ="销售费用_"&D109&"_"&C109 | N109: 6601.36.15 | P109: =C109 | Q109: Y
A110: =ROW(B110)-2 | B110: 内容制作费 | C110: 拍摄物料费 | D110: 营销费用 | E110: =H110 | F110: =VLOOKUP(E110,'收集数据表'!A:K,6,0) | G110: 品牌项目 | H110: IMC花养 | I110: 品牌产品中心 | J110: 品牌营销部 | M110: ="销售费用_"&D110&"_"&C110 | N110: 6601.36.16 | P110: =C110 | Q110: Y
A111: =ROW(B111)-2 | B111: 内容制作费 | C111: 拍摄物料费 | D111: 营销费用 | E111: =H111 | F111: =VLOOKUP(E111,'收集数据表'!A:K,6,0) | G111: 品牌项目 | H111: IMC国妆 | I111: 品牌产品中心 | J111: 品牌营销部 | M111: ="销售费用_"&D111&"_"&C111 | N111: 6601.36.16 | P111: =C111 | Q111: Y
A112: =ROW(B112)-2 | B112: 内容制作费 | C112: 拍摄物料费 | D112: 营销费用 | E112: =H112 | F112: =VLOOKUP(E112,'收集数据表'!A:K,6,0) | G112: 品牌项目 | H112: IMC文化 | I112: 品牌产品中心 | J112: 品牌营销部 | M112: ="销售费用_"&D112&"_"&C112 | N112: 6601.36.16 | P112: =C112 | Q112: Y
A113: =ROW(B113)-2 | B113: 内容制作费 | C113: 拍摄物料费 | D113: 营销费用 | E113: =H113 | F113: =VLOOKUP(E113,'收集数据表'!A:K,6,0) | G113: 品牌项目 | H113: 日常-创意与物料 | I113: 品牌产品中心 | J113: 品牌营销部 | M113: ="销售费用_"&D113&"_"&C113 | N113: 6601.36.16 | P113: =C113 | Q113: Y
A114: =ROW(B114)-2 | B114: 内容制作费 | C114: 内容制作费 | D114: 营销费用 | E114: =H114 | F114: =VLOOKUP(E114,'收集数据表'!A:K,6,0) | G114: 品牌项目 | H114: IMC花养 | I114: 品牌产品中心 | J114: 品牌营销部 | M114: ="销售费用_"&D114&"_"&C114 | N114: 6601.36.14 | P114: =C114 | Q114: Y
A115: =ROW(B115)-2 | B115: 内容制作费 | C115: 内容制作费 | D115: 营销费用 | E115: =H115 | F115: =VLOOKUP(E115,'收集数据表'!A:K,6,0) | G115: 品牌项目 | H115: IMC国妆 | I115: 品牌产品中心 | J115: 品牌营销部 | M115: ="销售费用_"&D115&"_"&C115 | N115: 6601.36.14 | P115: =C115 | Q115: Y
A116: =ROW(B116)-2 | B116: 内容制作费 | C116: 内容制作费 | D116: 营销费用 | E116: =H116 | F116: =VLOOKUP(E116,'收集数据表'!A:K,6,0) | G116: 品牌项目 | H116: IMC文化 | I116: 品牌产品中心 | J116: 品牌营销部 | M116: ="销售费用_"&D116&"_"&C116 | N116: 6601.36.14 | P116: =C116 | Q116: Y
A117: =ROW(B117)-2 | B117: 内容制作费 | C117: 内容制作费 | D117: 营销费用 | E117: =H117 | F117: =VLOOKUP(E117,'收集数据表'!A:K,6,0) | G117: 品牌项目 | H117: 日常-创意与物料 | I117: 品牌产品中心 | J117: 品牌营销部 | M117: ="销售费用_"&D117&"_"&C117 | N117: 6601.36.14 | P117: =C117 | Q117: Y
A118: =ROW(B118)-2 | B118: 品牌宣传费 | C118: 创意策划服务费 | D118: 营销费用 | E118: =H118 | F118: =VLOOKUP(E118,'收集数据表'!A:K,6,0) | G118: 品牌项目 | H118: IMC花养 | I118: 品牌产品中心 | J118: 品牌营销部 | M118: 销售费用_营销费用_策划服务费 | N118: 6601.36.01 | P118: 策划服务费 | Q118: Y
A119: =ROW(B119)-2 | B119: 品牌宣传费 | C119: 创意策划服务费 | D119: 营销费用 | E119: =H119 | F119: =VLOOKUP(E119,'收集数据表'!A:K,6,0) | G119: 品牌项目 | H119: IMC国妆 | I119: 品牌产品中心 | J119: 品牌营销部 | M119: 销售费用_营销费用_策划服务费 | N119: 6601.36.01 | P119: 策划服务费 | Q119: Y
A120: =ROW(B120)-2 | B120: 品牌宣传费 | C120: 创意策划服务费 | D120: 营销费用 | E120: =H120 | F120: =VLOOKUP(E120,'收集数据表'!A:K,6,0) | G120: 品牌项目 | H120: IMC文化 | I120: 品牌产品中心 | J120: 品牌营销部 | M120: 销售费用_营销费用_策划服务费 | N120: 6601.36.01 | P120: 策划服务费 | Q120: Y
A121: =ROW(B121)-2 | B121: 品牌宣传费 | C121: 创意策划服务费 | D121: 营销费用 | E121: =H121 | F121: =VLOOKUP(E121,'收集数据表'!A:K,6,0) | G121: 品牌项目 | H121: 日常-创意与物料 | I121: 品牌产品中心 | J121: 品牌营销部 | M121: 销售费用_营销费用_策划服务费 | N121: 6601.36.01 | P121: 策划服务费 | Q121: Y
A122: =ROW(B122)-2 | B122: 品牌宣传费 | C122: 市场调研费 | D122: 营销费用 | E122: 数据采买和调研费 | F122: =VLOOKUP(E122,'收集数据表'!A:K,6,0) | G122: 品牌项目 | H122: 日常-测试 | I122: 品牌产品中心 | J122: 品牌营销部 | M122: ="销售费用_"&D122&"_"&C122 | N122: 6601.36.20 | P122: =C122 | Q122: Y
A123: =ROW(B123)-2 | B123: 品牌宣传费 | C123: 明星合作费 | D123: 营销费用 | E123: =H123 | F123: =VLOOKUP(E123,'收集数据表'!A:K,6,0) | G123: 品牌项目 | H123: IMC花养 | I123: 品牌产品中心 | J123: 品牌营销部 | M123: 销售费用_营销费用_明星合作费 | N123: 6601.36.12 | P123: 代言费 | Q123: Y
A124: =ROW(B124)-2 | B124: 品牌宣传费 | C124: 明星合作费 | D124: 营销费用 | E124: =H124 | F124: =VLOOKUP(E124,'收集数据表'!A:K,6,0) | G124: 品牌项目 | H124: IMC国妆 | I124: 品牌产品中心 | J124: 品牌营销部 | M124: 销售费用_营销费用_明星合作费 | N124: 6601.36.12 | P124: 代言费 | Q124: Y
A125: =ROW(B125)-2 | B125: 品牌宣传费 | C125: 明星合作费 | D125: 营销费用 | E125: =H125 | F125: =VLOOKUP(E125,'收集数据表'!A:K,6,0) | G125: 品牌项目 | H125: IMC文化 | I125: 品牌产品中心 | J125: 品牌营销部 | M125: 销售费用_营销费用_明星合作费 | N125: 6601.36.12 | P125: 代言费 | Q125: Y
A126: =ROW(B126)-2 | B126: 品牌宣传费 | C126: 活动策划服务费 | D126: 营销费用 | E126: =H126 | F126: =VLOOKUP(E126,'收集数据表'!A:K,6,0) | G126: 品牌项目 | H126: IMC花养 | I126: 品牌产品中心 | J126: 品牌营销部 | M126: 销售费用_营销费用_策划服务费 | N126: 6601.36.01 | P126: 策划服务费 | Q126: Y
A127: =ROW(B127)-2 | B127: 品牌宣传费 | C127: 活动策划服务费 | D127: 营销费用 | E127: =H127 | F127: =VLOOKUP(E127,'收集数据表'!A:K,6,0) | G127: 品牌项目 | H127: IMC国妆 | I127: 品牌产品中心 | J127: 品牌营销部 | M127: 销售费用_营销费用_策划服务费 | N127: 6601.36.01 | P127: 策划服务费 | Q127: Y
A128: =ROW(B128)-2 | B128: 品牌宣传费 | C128: 活动策划服务费 | D128: 营销费用 | E128: =H128 | F128: =VLOOKUP(E128,'收集数据表'!A:K,6,0) | G128: 品牌项目 | H128: IMC文化 | I128: 品牌产品中心 | J128: 品牌营销部 | M128: 销售费用_营销费用_策划服务费 | N128: 6601.36.01 | P128: 策划服务费 | Q128: Y
A129: =ROW(B129)-2 | B129: 品牌宣传费 | C129: 活动策划服务费 | D129: 营销费用 | E129: =H129 | F129: =VLOOKUP(E129,'收集数据表'!A:K,6,0) | G129: 品牌项目 | H129: 日常-创意与物料 | I129: 品牌产品中心 | J129: 品牌营销部 | M129: 销售费用_营销费用_策划服务费 | N129: 6601.36.01 | P129: 策划服务费 | Q129: Y
A130: =ROW(B130)-2 | B130: 媒介宣传费 | C130: 媒体宣发费 | D130: 营销费用 | E130: =H130 | F130: =VLOOKUP(E130,'收集数据表'!A:K,6,0) | G130: 品牌项目 | H130: IMC花养 | I130: 品牌产品中心 | J130: 品牌营销部 | M130: ="销售费用_"&D130&"_"&C130 | N130: #N/A | P130: =C130 | Q130: Y
A131: =ROW(B131)-2 | B131: 媒介宣传费 | C131: 媒体宣发费 | D131: 营销费用 | E131: =H131 | F131: =VLOOKUP(E131,'收集数据表'!A:K,6,0) | G131: 品牌项目 | H131: IMC国妆 | I131: 品牌产品中心 | J131: 品牌营销部 | M131: ="销售费用_"&D131&"_"&C131 | N131: #N/A | P131: =C131 | Q131: Y
A132: =ROW(B132)-2 | B132: 媒介宣传费 | C132: 媒体宣发费 | D132: 营销费用 | E132: =H132 | F132: =VLOOKUP(E132,'收集数据表'!A:K,6,0) | G132: 品牌项目 | H132: IMC文化 | I132: 品牌产品中心 | J132: 品牌营销部 | M132: ="销售费用_"&D132&"_"&C132 | N132: #N/A | P132: =C132 | Q132: Y
A133: =ROW(B133)-2 | B133: 媒介宣传费 | C133: 媒体宣发费 | D133: 营销费用 | E133: =H133 | F133: =VLOOKUP(E133,'收集数据表'!A:K,6,0) | G133: 品牌项目 | H133: 日常-创意与物料 | I133: 品牌产品中心 | J133: 品牌营销部 | M133: ="销售费用_"&D133&"_"&C133 | N133: #N/A | P133: =C133 | Q133: Y
A134: =ROW(B134)-2 | B134: 其他费用 | C134: 场地租赁费 | D134: 营销费用 | E134: =H134 | F134: =VLOOKUP(E134,'收集数据表'!A:K,6,0) | G134: 品牌项目 | H134: IMC花养 | I134: 品牌产品中心 | J134: 品牌营销部 | M134: ="销售费用_"&D134&"_"&C134 | N134: 6601.36.02 | P134: =C134 | Q134: Y
A135: =ROW(B135)-2 | B135: 其他费用 | C135: 场地租赁费 | D135: 营销费用 | E135: =H135 | F135: =VLOOKUP(E135,'收集数据表'!A:K,6,0) | G135: 品牌项目 | H135: IMC国妆 | I135: 品牌产品中心 | J135: 品牌营销部 | M135: ="销售费用_"&D135&"_"&C135 | N135: 6601.36.02 | P135: =C135 | Q135: Y
...

Sheet 营销计划（活动-更新）
A1: 营销活动分类 | B1: 营销活动场景 | C1: 判断是否新增 | D1: 一级预算科目 | E1: 二级预算科目 | G1: 能否到店铺 | H1: 店铺 | I1: 渠道 | J1: 业务来源 | K1: 业务单元 | L1: 能否到品类（单品简称） | M1: 能否到SKU | N1: 是否允许个人报销 | O1: 是否允许无票报销 | P1: 费用类型 | Q1: 费用大类 | R1: 费用小类 | S1: 一级部门 | T1: 二级部门 | U1: 三级部门 | V1: 四级部门
A2: IP明星内容合作 | B2: IP合作 | C2: =VLOOKUP(B2,'收集数据表'!$A$2:$A$201,1,FALSE) | D2: IP明星内容合作 | E2: 品牌IP及娱乐营销 | F2: 品牌IP及娱乐营销 | G2: 否 | L2: 否 | M2: 否 | N2: 否 | O2: 否 | P2: 营销费用 | Q2: 品牌宣传费 | R2: 创意策划服务费 | S2: 品牌运营中心 | T2: 市场广告推广部 | U2: 市场推广部 | V2: 市场PR部
A3: IP明星内容合作 | B3: 明星差旅 | C3: =VLOOKUP(B3,'收集数据表'!$A$2:$A$201,1,FALSE) | D3: IP明星内容合作 | E3: 明星差旅 | F3: 明星差旅 | G3: 否 | L3: 否 | M3: 否 | N3: 是 | O3: 是 | P3: 营销费用 | Q3: 其他费用 | R3: 明星差旅费 | S3: 品牌运营中心 | T3: 市场广告推广部 | U3: 市场推广部 | V3: 娱乐营销部
A4: IP明星内容合作 | B4: 明星代言单次合作 | C4: =VLOOKUP(B4,'收集数据表'!$A$2:$A$201,1,FALSE) | D4: IP明星内容合作 | E4: 明星代言单次 | F4: 明星代言单次 | G4: 否 | L4: 否 | M4: 否 | N4: 否 | O4: 否 | P4: 营销费用 | Q4: 品牌宣传费 | R4: 明星合作费 | S4: 品牌运营中心 | T4: 市场广告推广部 | U4: 市场推广部 | V4: 娱乐营销部
A5: IP明星内容合作 | B5: 明星代言合作 | C5: =VLOOKUP(B5,'收集数据表'!$A$2:$A$201,1,FALSE) | D5: IP明星内容合作 | E5: 明星代言摊销 | F5: 明星代言摊销 | G5: 否 | L5: 否 | M5: 否 | N5: 否 | O5: 否 | P5: 营销费用 | Q5: 品牌宣传费 | R5: 明星合作费 | S5: 品牌运营中心 | T5: 市场广告推广部 | U5: 市场推广部 | V5: 娱乐营销部
A6: IP明星内容合作 | B6: 明星拍摄 | C6: =VLOOKUP(B6,'收集数据表'!$A$2:$A$201,1,FALSE) | D6: IP明星内容合作 | E6: 明星拍摄 | F6: 明星拍摄 | G6: 否 | L6: 否 | M6: 否 | N6: 是 | O6: 是 | P6: 营销费用 | Q6: 其他费用 | R6: 场地租赁费 | S6: 品牌运营中心 | T6: 市场广告推广部 | U6: 市场推广部 | V6: 娱乐营销部
A7: IP明星内容合作 | B7: 明星影综营销号 | C7: =VLOOKUP(B7,'收集数据表'!$A$2:$A$201,1,FALSE) | D7: IP明星内容合作 | E7: 品牌IP及娱乐营销 | F7: 品牌IP及娱乐营销 | G7: 否 | L7: 否 | M7: 否 | N7: 否 | O7: 否 | P7: 营销费用 | Q7: 品牌宣传费 | R7: 营销宣传费 | S7: 品牌运营中心 | T7: 市场广告推广部 | U7: 市场推广部 | V7: 娱乐营销部
A8: IP明星内容合作 | B8: 明星妆发造 | C8: =VLOOKUP(B8,'收集数据表'!$A$2:$A$201,1,FALSE) | D8: IP明星内容合作 | E8: 明星妆发造 | F8: 明星妆发造 | G8: 否 | L8: 否 | M8: 否 | N8: 是 | O8: 是 | P8: 营销费用 | Q8: 内容制作费 | R8: 服化道费用 | S8: 品牌运营中心 | T8: 市场广告推广部 | U8: 市场推广部 | V8: 娱乐营销部
A9: IP明星内容合作 | B9: 明星综艺线下活动 | C9: =VLOOKUP(B9,'收集数据表'!$A$2:$A$201,1,FALSE) | D9: IP明星内容合作 | E9: 明星代言单次 | F9: 明星代言单次 | G9: 否 | L9: 否 | M9: 否 | N9: 否 | O9: 否 | P9: 营销费用 | Q9: 品牌宣传费 | R9: 创意策划服务费 | S9: 品牌运营中心 | T9: 市场广告推广部 | U9: 市场推广部 | V9: 娱乐营销部
A10: IP明星内容合作 | B10: 影视综艺植入 | C10: =VLOOKUP(B10,'收集数据表'!$A$2:$A$201,1,FALSE) | D10: IP明星内容合作 | E10: 品牌IP及娱乐营销 | F10: 品牌IP及娱乐营销 | G10: 否 | L10: 否 | M10: 否 | N10: 否 | O10: 否 | P10: 营销费用 | Q10: 品牌宣传费 | R10: 品牌植入费 | S10: 品牌运营中心 | T10: 市场广告推广部 | U10: 市场推广部 | V10: 娱乐营销部
A11: 其他达人直播 | B11: 抖音直播服务费-抖音其他 | C11: =VLOOKUP(B11,'收集数据表'!$A$2:$A$201,1,FALSE) | D11: 达人直播 | E11: 服务费-抖音其他 | F11: 服务费-抖音其他 | G11: 是 | H11: 抖音花西子官方旗舰店 | I11: 抖音渠道 | J11: 抖音达播 | L11: 是 | M11: 否 | N11: 否 | O11: 否 | P11: 营销费用 | Q11: 渠道推广费 | R11: 直播服务费 | S11: 品牌运营中心 | T11: 市场广告推广部 | U11: 达播2部
A12: SKA达人 | B12: 抖音直播服务费-抖音其他 | C12: =VLOOKUP(B12,'收集数据表'!$A$2:$A$201,1,FALSE) | D12: 达人直播 | E12: 服务费-抖音其他 | F12: 服务费-抖音其他 | G12: 是 | H12: 抖音花西子官方旗舰店 | I12: 抖音渠道 | J12: 抖音达播 | L12: 是 | M12: 否 | N12: 否 | O12: 否 | P12: 营销费用 | Q12: 渠道推广费 | R12: 直播服务费 | S12: 品牌运营中心 | T12: 市场广告推广部 | U12: 达播2部
A13: 田恬 | B13: 抖音直播服务费-田恬 | C13: =VLOOKUP(B13,'收集数据表'!$A$2:$A$201,1,FALSE) | D13: 达人直播 | E13: 佣金-田恬 | F13: 佣金-田恬 | G13: 是 | H13: 抖音花西子官方旗舰店 | I13: 抖音渠道 | J13: 抖音达播 | L13: 是 | M13: 是 | N13: 否 | O13: 否 | P13: 营销费用 | Q13: 渠道推广费 | R13: 直播服务费 | S13: 品牌运营中心 | T13: 直播运营部 | U13: 达播BD部
A14: 其他达人直播 | B14: 抖音直播服务费-团长计划 | C14: =VLOOKUP(B14,'收集数据表'!$A$2:$A$201,1,FALSE) | D14: 达人直播 | E14: 服务费-团长计划 | F14: 服务费-团长计划 | G14: 是 | H14: 抖音花西子官方旗舰店 | I14: 抖音渠道 | J14: 抖音达播 | L14: 是 | M14: 否 | N14: 否 | O14: 否 | P14: 营销费用 | Q14: 渠道推广费 | R14: 直播服务费 | S14: 品牌运营中心 | T14: 市场广告推广部 | U14: 达播2部
A15: 其他达人直播 | B15: 抖音直播坑位费-抖音其他 | C15: =VLOOKUP(B15,'收集数据表'!$A$2:$A$201,1,FALSE) | D15: 达人直播 | E15: 佣金-抖音其他 | F15: 佣金-抖音其他 | G15: 是 | H15: 抖音花西子官方旗舰店 | I15: 抖音渠道 | J15: 抖音达播 | L15: 否 | M15: 否 | N15: 否 | O15: 否 | P15: 营销费用 | Q15: 渠道推广费 | R15: 直播坑位费 | S15: 品牌运营中心 | T15: 市场广告推广部 | U15: 达播2部
A16: SKA达人 | B16: 抖音直播坑位费-抖音其他 | C16: =VLOOKUP(B16,'收集数据表'!$A$2:$A$201,1,FALSE) | D16: 达人直播 | E16: 佣金-抖音其他 | F16: 佣金-抖音其他 | G16: 是 | H16: 抖音花西子官方旗舰店 | I16: 抖音渠道 | J16: 抖音达播 | L16: 否 | M16: 否 | N16: 否 | O16: 否 | P16: 营销费用 | Q16: 渠道推广费 | R16: 直播坑位费 | S16: 品牌运营中心 | T16: 市场广告推广部 | U16: 达播2部
A17: 田恬 | B17: 抖音直播坑位费-田恬 | C17: =VLOOKUP(B17,'收集数据表'!$A$2:$A$201,1,FALSE) | D17: 达人直播 | E17: 服务费-田恬 | F17: 服务费-田恬 | G17: 是 | H17: 抖音花西子官方旗舰店 | I17: 抖音渠道 | J17: 抖音达播 | L17: 否 | M17: 否 | N17: 否 | O17: 否 | P17: 营销费用 | Q17: 渠道推广费 | R17: 直播坑位费 | S17: 品牌运营中心 | T17: 直播运营部 | U17: 达播BD部
A18: 其他达人直播 | B18: 抖音直播坑位费-团长计划 | C18: =VLOOKUP(B18,'收集数据表'!$A$2:$A$201,1,FALSE) | D18: 达人直播 | E18: 佣金-团长计划 | F18: 佣金-团长计划 | G18: 是 | H18: 抖音花西子官方旗舰店 | I18: 抖音渠道 | J18: 抖音达播 | L18: 否 | M18: 否 | N18: 否 | O18: 否 | P18: 营销费用 | Q18: 渠道推广费 | R18: 直播坑位费 | S18: 品牌运营中心 | T18: 市场广告推广部 | U18: 达播2部
A19: 其他达人直播 | B19: 快手直播服务费 | C19: =VLOOKUP(B19,'收集数据表'!$A$2:$A$201,1,FALSE) | D19: 达人直播 | E19: 佣金-快手 | F19: 佣金-快手 | G19: 是 | H19: 快手花西子旗舰店 | I19: 快手渠道 | J19: 快手达播 | L19: 是 | M19: 是 | N19: 否 | O19: 否 | P19: 营销费用 | Q19: 渠道推广费 | R19: 直播服务费 | S19: 品牌运营中心 | T19: 市场广告推广部 | U19: 达播2部
A20: SKA达人 | B20: 快手直播服务费 | C20: =VLOOKUP(B20,'收集数据表'!$A$2:$A$201,1,FALSE) | D20: 达人直播 | E20: 佣金-快手 | F20: 佣金-快手 | G20: 是 | H20: 快手花西子旗舰店 | I20: 快手渠道 | J20: 快手达播 | L20: 是 | M20: 是 | N20: 否 | O20: 否 | P20: 营销费用 | Q20: 渠道推广费 | R20: 直播服务费 | S20: 品牌运营中心 | T20: 市场广告推广部 | U20: 达播2部
A21: 其他达人直播 | B21: 快手直播坑位费 | C21: =VLOOKUP(B21,'收集数据表'!$A$2:$A$201,1,FALSE) | D21: 达人直播 | E21: 服务费-快手 | F21: 服务费-快手 | G21: 是 | H21: 快手花西子旗舰店 | I21: 快手渠道 | J21: 快手达播 | L21: 否 | M21: 否 | N21: 否 | O21: 否 | P21: 营销费用 | Q21: 渠道推广费 | R21: 直播坑位费 | S21: 品牌运营中心 | T21: 市场广告推广部 | U21: 达播2部
A22: SKA达人 | B22: 快手直播坑位费 | C22: =VLOOKUP(B22,'收集数据表'!$A$2:$A$201,1,FALSE) | D22: 达人直播 | E22: 服务费-快手 | F22: 服务费-快手 | G22: 是 | H22: 快手花西子旗舰店 | I22: 快手渠道 | J22: 快手达播 | L22: 否 | M22: 否 | N22: 否 | O22: 否 | P22: 营销费用 | Q22: 渠道推广费 | R22: 直播坑位费 | S22: 品牌运营中心 | T22: 市场广告推广部 | U22: 达播2部
A23: 其他达人直播 | B23: 明星直播合作 | C23: =VLOOKUP(B23,'收集数据表'!$A$2:$A$201,1,FALSE) | D23: 达人直播 | E23: 服务费 | F23: 服务费 | G23: 是 | L23: 否 | M23: 否 | N23: 否 | O23: 否 | P23: 营销费用 | Q23: 品牌宣传费 | R23: 明星合作费 | S23: 品牌运营中心 | T23: 直播运营部 | U23: 达播BD部
A24: 其他达人直播 | B24: 其他直播服务费 | C24: =VLOOKUP(B24,'收集数据表'!$A$2:$A$201,1,FALSE) | D24: 达人直播 | E24: 佣金-其他 | F24: 佣金-其他 | G24: 是 | L24: 是 | M24: 是 | N24: 否 | O24: 否 | P24: 营销费用 | Q24: 渠道推广费 | R24: 直播服务费 | S24: 品牌运营中心 | T24: 直播运营部 | U24: 达播BD部
A25: 其他达人直播 | B25: 其他直播坑位费 | C25: =VLOOKUP(B25,'收集数据表'!$A$2:$A$201,1,FALSE) | D25: 达人直播 | E25: 服务费-其他 | F25: 服务费-其他 | G25: 是 | L25: 否 | M25: 否 | N25: 否 | O25: 否 | P25: 营销费用 | Q25: 渠道推广费 | R25: 直播坑位费 | S25: 品牌运营中心 | T25: 直播运营部 | U25: 达播BD部
A26: 李佳琦 | B26: 天猫直播服务费-李佳琦 | C26: =VLOOKUP(B26,'收集数据表'!$A$2:$A$201,1,FALSE) | D26: 达人直播 | E26: 佣金-佳琦 | F26: 佣金-佳琦 | G26: 是 | H26: 天猫花西子旗舰店 | I26: 天猫渠道 | J26: 天猫达播 | L26: 是 | M26: 是 | N26: 否 | O26: 否 | P26: 营销费用 | Q26: 渠道推广费 | R26: 直播服务费 | S26: 品牌运营中心 | T26: 直播运营部 | U26: 达播BD部
A27: 其他达人直播 | B27: 天猫直播服务费-其他 | C27: =VLOOKUP(B27,'收集数据表'!$A$2:$A$201,1,FALSE) | D27: 达人直播 | E27: 佣金-淘内其他 | F27: 佣金-淘内其他 | G27: 是 | H27: 天猫花西子旗舰店 | I27: 天猫渠道 | J27: 天猫达播 | L27: 是 | M27: 是 | N27: 否 | O27: 否 | P27: 营销费用 | Q27: 渠道推广费 | R27: 直播服务费 | S27: 品牌运营中心 | T27: 直播运营部 | U27: 达播BD部
A28: SKA达人 | B28: 天猫直播服务费-其他 | C28: =VLOOKUP(B28,'收集数据表'!$A$2:$A$201,1,FALSE) | D28: 达人直播 | E28: 佣金-淘内其他 | F28: 佣金-淘内其他 | G28: 是 | H28: 天猫花西子旗舰店 | I28: 天猫渠道 | J28: 天猫达播 | L28: 是 | M28: 是 | N28: 否 | O28: 否 | P28: 营销费用 | Q28: 渠道推广费 | R28: 直播服务费 | S28: 品牌运营中心 | T28: 直播运营部 | U28: 达播BD部
A29: 李佳琦 | B29: 天猫直播坑位费-李佳琦 | C29: =VLOOKUP(B29,'收集数据表'!$A$2:$A$201,1,FALSE) | D29: 达人直播 | E29: 服务费-佳琦 | F29: 服务费-佳琦 | G29: 是 | H29: 天猫花西子旗舰店 | I29: 天猫渠道 | J29: 天猫达播 | L29: 否 | M29: 否 | N29: 否 | O29: 否 | P29: 营销费用 | Q29: 渠道推广费 | R29: 直播坑位费 | S29: 品牌运营中心 | T29: 直播运营部 | U29: 达播BD部
A30: 其他达人直播 | B30: 天猫直播坑位费-其他 | C30: =VLOOKUP(B30,'收集数据表'!$A$2:$A$201,1,FALSE) | D30: 达人直播 | E30: 服务费-淘内其他 | F30: 服务费-淘内其他 | G30: 是 | H30: 天猫花西子旗舰店 | I30: 天猫渠道 | J30: 天猫达播 | L30: 否 | M30: 否 | N30: 否 | O30: 否 | P30: 营销费用 | Q30: 渠道推广费 | R30: 直播坑位费 | S30: 品牌运营中心 | T30: 直播运营部 | U30: 达播BD部
A31: SKA达人 | B31: 天猫直播坑位费-其他 | C31: =VLOOKUP(B31,'收集数据表'!$A$2:$A$201,1,FALSE) | D31: 达人直播 | E31: 服务费-淘内其他 | F31: 服务费-淘内其他 | G31: 是 | H31: 天猫花西子旗舰店 | I31: 天猫渠道 | J31: 天猫达播 | L31: 否 | M31: 否 | N31: 否 | O31: 否 | P31: 营销费用 | Q31: 渠道推广费 | R31: 直播坑位费 | S31: 品牌运营中心 | T31: 直播运营部 | U31: 达播BD部
A32: 达人直播 | B32: 直播专场服务 | C32: =VLOOKUP(B32,'收集数据表'!$A$2:$A$201,1,FALSE) | D32: 达人直播 | E32: 服务费-淘内其他 | F32: 服务费-淘内其他 | G32: 是 | L32: 否 | M32: 否 | N32: 否 | O32: 否 | P32: 营销费用 | Q32: 内容制作费 | R32: 专业人物合作费 | S32: 品牌运营中心 | T32: 直播运营部 | U32: 达播BD部
A33: 素材创意制作 | B33: AD竞价内容创意-场地租赁 | C33: =VLOOKUP(B33,'收集数据表'!$A$2:$A$201,1,FALSE) | D33: 品类内容推广 | E33: AD竞价内容创意 | F33: AD竞价内容创意 | G33: 否 | L33: 否 | M33: 否 | N33: 是 | O33: 是 | P33: 营销费用 | Q33: 其他费用 | R33: 场地租赁费 | S33: 品牌运营中心 | T33: 市场广告推广部 | U33: 广告投放部 | V33: 内容策划组
A34: 素材创意制作 | B34: AD竞价内容创意-动画制作 | C34: =VLOOKUP(B34,'收集数据表'!$A$2:$A$201,1,FALSE) | D34: 品类内容推广 | E34: AD竞价内容创意 | F34: AD竞价内容创意 | G34: 否 | L34: 否 | M34: 否 | N34: 是 | O34: 是 | P34: 营销费用 | Q34: 内容制作费 | R34: 动画制作费 | S34: 品牌运营中心 | T34: 市场广告推广部 | U34: 广告投放部 | V34: 内容策划组
A35: 素材创意制作 | B35: AD竞价内容创意-服化道费 | C35: =VLOOKUP(B35,'收集数据表'!$A$2:$A$201,1,FALSE) | D35: 品类内容推广 | E35: AD竞价内容创意 | F35: AD竞价内容创意 | G35: 否 | L35: 否 | M35: 否 | N35: 是 | O35: 是 | P35: 营销费用 | Q35: 内容制作费 | R35: 服化道费用 | S35: 品牌运营中心 | T35: 市场广告推广部 | U35: 广告投放部 | V35: 内容策划组
A36: 素材创意制作 | B36: AD竞价内容创意-建模服务 | C36: =VLOOKUP(B36,'收集数据表'!$A$2:$A$201,1,FALSE) | D36: 品类内容推广 | E36: AD竞价内容创意 | F36: AD竞价内容创意 | G36: 否 | L36: 否 | M36: 否 | N36: 是 | O36: 是 | P36: 营销费用 | Q36: 内容制作费 | R36: 建模服务费 | S36: 品牌运营中心 | T36: 市场广告推广部 | U36: 广告投放部 | V36: 内容策划组
A37: 素材创意制作 | B37: AD竞价内容创意-模特服务 | C37: =VLOOKUP(B37,'收集数据表'!$A$2:$A$201,1,FALSE) | D37: 品类内容推广 | E37: AD竞价内容创意 | F37: AD竞价内容创意 | G37: 否 | L37: 否 | M37: 否 | N37: 是 | O37: 是 | P37: 营销费用 | Q37: 内容制作费 | R37: 模特服务费 | S37: 品牌运营中心 | T37: 市场广告推广部 | U37: 广告投放部 | V37: 内容策划组
A38: 素材创意制作 | B38: AD竞价内容创意-内容制作 | C38: =VLOOKUP(B38,'收集数据表'!$A$2:$A$201,1,FALSE) | D38: 品类内容推广 | E38: AD竞价内容创意 | F38: AD竞价内容创意 | G38: 否 | L38: 否 | M38: 否 | N38: 是 | O38: 是 | P38: 营销费用 | Q38: 内容制作费 | R38: 内容制作费 | S38: 品牌运营中心 | T38: 市场广告推广部 | U38: 广告投放部 | V38: 内容策划组
A39: 素材创意制作 | B39: AD竞价内容创意-拍摄服务 | C39: =VLOOKUP(B39,'收集数据表'!$A$2:$A$201,1,FALSE) | D39: 品类内容推广 | E39: AD竞价内容创意 | F39: AD竞价内容创意 | G39: 否 | L39: 否 | M39: 否 | N39: 是 | O39: 是 | P39: 营销费用 | Q39: 内容制作费 | R39: 拍摄服务费 | S39: 品牌运营中心 | T39: 市场广告推广部 | U39: 广告投放部 | V39: 内容策划组
A40: 素材创意制作 | B40: AD竞价内容创意-拍摄物料 | C40: =VLOOKUP(B40,'收集数据表'!$A$2:$A$201,1,FALSE) | D40: 品类内容推广 | E40: AD竞价内容创意 | F40: AD竞价内容创意 | G40: 否 | L40: 否 | M40: 否 | N40: 是 | O40: 是 | P40: 营销费用 | Q40: 内容制作费 | R40: 拍摄物料费 | S40: 品牌运营中心 | T40: 市场广告推广部 | U40: 广告投放部 | V40: 内容策划组
A41: 素材创意制作 | B41: AD竞价内容创意-设备租赁 | C41: =VLOOKUP(B41,'收集数据表'!$A$2:$A$201,1,FALSE) | D41: 品类内容推广 | E41: AD竞价内容创意 | F41: AD竞价内容创意 | G41: 否 | L41: 否 | M41: 否 | N41: 是 | O41: 是 | P41: 营销费用 | Q41: 其他费用 | R41: 设备租赁费 | S41: 品牌运营中心 | T41: 市场广告推广部 | U41: 广告投放部 | V41: 内容策划组
A42: 素材创意制作 | B42: AD竞价内容创意-视频制作 | C42: =VLOOKUP(B42,'收集数据表'!$A$2:$A$201,1,FALSE) | D42: 品类内容推广 | E42: AD竞价内容创意 | F42: AD竞价内容创意 | G42: 否 | L42: 否 | M42: 否 | N42: 是 | O42: 是 | P42: 营销费用 | Q42: 内容制作费 | R42: 视频制作费 | S42: 品牌运营中心 | T42: 市场广告推广部 | U42: 广告投放部 | V42: 内容策划组
A43: 素材创意制作 | B43: AD竞价内容创意-图文平面制作 | C43: =VLOOKUP(B43,'收集数据表'!$A$2:$A$201,1,FALSE) | D43: 品类内容推广 | E43: AD竞价内容创意 | F43: AD竞价内容创意 | G43: 否 | L43: 否 | M43: 否 | N43: 是 | O43: 是 | P43: 营销费用 | Q43: 内容制作费 | R43: 图文平面制作费 | S43: 品牌运营中心 | T43: 市场广告推广部 | U43: 广告投放部 | V43: 内容策划组
A44: 素材创意制作 | B44: AD竞价内容创意-舞台场地 | C44: =VLOOKUP(B44,'收集数据表'!$A$2:$A$201,1,FALSE) | D44: 品类内容推广 | E44: AD竞价内容创意 | F44: AD竞价内容创意 | G44: 否 | L44: 否 | M44: 否 | N44: 是 | O44: 是 | P44: 营销费用 | Q44: 其他费用 | R44: 舞台场地搭建费 | S44: 品牌运营中心 | T44: 市场广告推广部 | U44: 广告投放部 | V44: 内容策划组
... A48: 内容加热 | B48: DOU+ | C48: =VLOOKUP(B48,'收集数据表'!$A$2:$A$201,1,FALSE) | D48: 品类内容推广 | E48: 内容加热 | F48: 内容加热 | G48: 否 | L48: 否 | M48: 否 | N48: 否 | O48: 否 | P48: 营销费用 | Q48: 达人推广费 | R48: 内容推广费 | S48: 品牌运营中心 | T48: 市场广告推广部 | U48: 市场推广部 | V48: 内容投放组
A49: 素材创意制作 | B49: 抖音视频创意-店铺-场地租赁 | C49: =VLOOKUP(B49,'收集数据表'!$A$2:$A$201,1,FALSE) | D49: 品类内容推广 | E49: 抖音视频创意-店铺 | F49: 抖音视频创意-店铺 | G49: 是 | H49: 抖音花西子官方旗舰店 | I49: 抖音渠道 | J49: 抖音自播 | L49: 否 | M49: 否 | N49: 是 | O49: 是 | P49: 营销费用 | Q49: 其他费用 | R49: 场地租赁费 | S49: 品牌运营中心 | T49: 渠道运营部 | U49: 抖音部 | V49: 内容部
A50: 素材创意制作 | B50: 抖音视频创意-店铺-动画制作 | C50: =VLOOKUP(B50,'收集数据表'!$A$2:$A$201,1,FALSE) | D50: 品类内容推广 | E50: 抖音视频创意-店铺 | F50: 抖音视频创意-店铺 | G50: 是 | H50: 抖音花西子官方旗舰店 | I50: 抖音渠道 | J50: 抖音自播 | L50: 否 | M50: 否 | N50: 是 | O50: 是 | P50: 营销费用 | Q50: 内容制作费 | R50: 动画制作费 | S50: 品牌运营中心 | T50: 渠道运营部 | U50: 抖音部 | V50: 内容部
A51: 素材创意制作 | B51: 抖音视频创意-店铺-服化道费 | C51: =VLOOKUP(B51,'收集数据表'!$A$2:$A$201,1,FALSE) | D51: 品类内容推广 | E51: 抖音视频创意-店铺 | F51: 抖音视频创意-店铺 | G51: 是 | H51: 抖音花西子官方旗舰店 | I51: 抖音渠道 | J51: 抖音自播 | L51: 否 | M51: 否 | N51: 是 | O51: 是 | P51: 营销费用 | Q51: 内容制作费 | R51: 服化道费用 | S51: 品牌运营中心 | T51: 渠道运营部 | U51: 抖音部 | V51: 内容部
A52: 素材创意制作 | B52: 抖音视频创意-店铺-建模服务 | C52: =VLOOKUP(B52,'收集数据表'!$A$2:$A$201,1,FALSE) | D52: 品类内容推广 | E52: 抖音视频创意-店铺 | F52: 抖音视频创意-店铺 | G52: 是 | H52: 抖音花西子官方旗舰店 | I52: 抖音渠道 | J52: 抖音自播 | L52: 否 | M52: 否 | N52: 是 | O52: 是 | P52: 营销费用 | Q52: 内容制作费 | R52: 建模服务费 | S52: 品牌运营中心 | T52: 渠道运营部 | U52: 抖音部 | V52: 内容部
A53: 素材创意制作 | B53: 抖音视频创意-店铺-模特服务 | C53: =VLOOKUP(B53,'收集数据表'!$A$2:$A$201,1,FALSE) | D53: 品类内容推广 | E53: 抖音视频创意-店铺 | F53: 抖音视频创意-店铺 | G53: 是 | H53: 抖音花西子官方旗舰店 | I53: 抖音渠道 | J53: 抖音自播 | L53: 否 | M53: 否 | N53: 是 | O53: 是 | P53: 营销费用 | Q53: 内容制作费 | R53: 模特服务费 | S53: 品牌运营中心 | T53: 渠道运营部 | U53: 抖音部 | V53: 内容部
A54: 素材创意制作 | B54: 抖音视频创意-店铺-内容制作 | C54: =VLOOKUP(B54,'收集数据表'!$A$2:$A$201,1,FALSE) | D54: 品类内容推广 | E54: 抖音视频创意-店铺 | F54: 抖音视频创意-店铺 | G54: 是 | H54: 抖音花西子官方旗舰店 | I54: 抖音渠道 | J54: 抖音自播 | L54: 否 | M54: 否 | N54: 是 | O54: 是 | P54: 营销费用 | Q54: 内容制作费 | R54: 内容制作费 | S54: 品牌运营中心 | T54: 渠道运营部 | U54: 抖音部 | V54: 内容部
A55: 素材创意制作 | B55: 抖音视频创意-店铺-拍摄服务 | C55: =VLOOKUP(B55,'收集数据表'!$A$2:$A$201,1,FALSE) | D55: 品类内容推广 | E55: 抖音视频创意-店铺 | F55: 抖音视频创意-店铺 | G55: 是 | H55: 抖音花西子官方旗舰店 | I55: 抖音渠道 | J55: 抖音自播 | L55: 否 | M55: 否 | N55: 是 | O55: 是 | P55: 营销费用 | Q55: 内容制作费 | R55: 拍摄服务费 | S55: 品牌运营中心 | T55: 渠道运营部 | U55: 抖音部 | V55: 内容部
A56: 素材创意制作 | B56: 抖音视频创意-店铺-拍摄物料 | C56: =VLOOKUP(B56,'收集数据表'!$A$2:$A$201,1,FALSE) | D56: 品类内容推广 | E56: 抖音视频创意-店铺 | F56: 抖音视频创意-店铺 | G56: 是 | H56: 抖音花西子官方旗舰店 | I56: 抖音渠道 | J56: 抖音自播 | L56: 否 | M56: 否 | N56: 是 | O56: 是 | P56: 营销费用 | Q56: 内容制作费 | R56: 拍摄物料费 | S56: 品牌运营中心 | T56: 渠道运营部 | U56: 抖音部 | V56: 内容部
A57: 素材创意制作 | B57: 抖音视频创意-店铺-设备租赁 | C57: =VLOOKUP(B57,'收集数据表'!$A$2:$A$201,1,FALSE) | D57: 品类内容推广 | E57: 抖音视频创意-店铺 | F57: 抖音视频创意-店铺 | G57: 是 | H57: 抖音花西子官方旗舰店 | I57: 抖音渠道 | J57: 抖音自播 | L57: 否 | M57: 否 | N57: 是 | O57: 是 | P57: 营销费用 | Q57: 其他费用 | R57: 设备租赁费 | S57: 品牌运营中心 | T57: 渠道运营部 | U57: 抖音部 | V57: 内容部
A58: 素材创意制作 | B58: 抖音视频创意-店铺-视频制作 | C58: =VLOOKUP(B58,'收集数据表'!$A$2:$A$201,1,FALSE) | D58: 品类内容推广 | E58: 抖音视频创意-店铺 | F58: 抖音视频创意-店铺 | G58: 是 | H58: 抖音花西子官方旗舰店 | I58: 抖音渠道 | J58: 抖音自播 | L58: 否 | M58: 否 | N58: 是 | O58: 是 | P58: 营销费用 | Q58: 内容制作费 | R58: 视频制作费 | S58: 品牌运营中心 | T58: 渠道运营部 | U58: 抖音部 | V58: 内容部
A59: 素材创意制作 | B59: 抖音视频创意-店铺-图文平面制作 | C59: =VLOOKUP(B59,'收集数据表'!$A$2:$A$201,1,FALSE) | D59: 品类内容推广 | E59: 抖音视频创意-店铺 | F59: 抖音视频创意-店铺 | G59: 是 | H59: 抖音花西子官方旗舰店 | I59: 抖音渠道 | J59: 抖音自播 | L59: 否 | M59: 否 | N59: 是 | O59: 是 | P59: 营销费用 | Q59: 内容制作费 | R59: 图文平面制作费 | S59: 品牌运营中心 | T59: 渠道运营部 | U59: 抖音部 | V59: 内容部
A60: 素材创意制作 | B60: 抖音视频创意-店铺-舞台场地搭建 | C60: =VLOOKUP(B60,'收集数据表'!$A$2:$A$201,1,FALSE) | D60: 品类内容推广 | E60: 抖音视频创意-店铺 | F60: 抖音视频创意-店铺 | G60: 是 | H60: 抖音花西子官方旗舰店 | I60: 抖音渠道 | J60: 抖音自播 | L60: 否 | M60: 否 | N60: 是 | O60: 是 | P60: 营销费用 | Q60: 其他费用 | R60: 舞台场地搭建费 | S60: 品牌运营中心 | T60: 渠道运营部 | U60: 抖音部 | V60: 内容部
... A76: 素材创意制作 | B76: 抖音视频创意-矩阵号-专业人物合作 | C76: =VLOOKUP(B76,'收集数据表'!$A$2:$A$201,1,FALSE) | D76: 品类内容推广 | E76: 抖音视频创意-矩阵号 | F76: 抖音视频创意-矩阵号 | G76: 是 | H76: 抖音花西子官方旗舰店 | I76: 抖音渠道 | J76: 抖音矩阵号 | L76: 否 | M76: 否 | N76: 是 | O76: 是 | P76: 营销费用 | Q76: 内容制作费 | R76: 专业人物合作费 | S76: 品牌运营中心 | T76: 渠道运营部 | U76: 抖音部 | V76: 矩阵部
A77: 内容加热 | B77: 粉丝通 | C77: =VLOOKUP(B77,'收集数据表'!$A$2:$A$201,1,FALSE) | D77: 品类内容推广 | E77: 其他新媒体加热 | F77: 其他新媒体加热 | G77: 否 | L77: 否 | M77: 否 | N77: 否 | O77: 否 | P77: 营销费用 | Q77: 达人推广费 | R77: 内容推广费 | S77: 品牌运营中心 | T77: 市场广告推广部 | U77: 市场推广部 | V77: 内容投放组
A78: 内容加热 | B78: 矩阵号DOU+ | C78: =VLOOKUP(B78,'收集数据表'!$A$2:$A$201,1,FALSE) | D78: 品类内容推广 | E78: 抖音矩阵号渠道推广 | F78: 抖音矩阵号渠道推广 | G78: 是 | H78: 抖音花西子官方旗舰店 | I78: 抖音渠道 | J78: 抖音矩阵号 | L78: 否 | M78: 否 | N78: 否 | O78: 否 | P78: 营销费用 | Q78: 达人推广费 | R78: 内容推广费 | S78: 品牌运营中心 | T78: 渠道运营部 | U78: 抖音部 | V78: 矩阵部
A79: 内容加热 | B79: 快手作品推荐 | C79: =VLOOKUP(B79,'收集数据表'!$A$2:$A$201,1,FALSE) | D79: 品类内容推广 | E79: 内容加热 | F79: 内容加热 | G79: 否 | L79: 否 | M79: 否 | N79: 否 | O79: 否 | P79: 营销费用 | Q79: 达人推广费 | R79: 内容推广费 | S79: 品牌运营中心 | T79: 市场广告推广部 | U79: 市场推广部 | V79: 内容投放组
A80: 内容加热 | B80: 内容服务 | C80: =VLOOKUP(B80,'收集数据表'!$A$2:$A$201,1,FALSE) | D80: 品类内容推广 | E80: 内容加热 | F80: 内容加热 | G80: 否 | L80: 否 | M80: 否 | N80: 否 | O80: 否 | P80: 营销费用 | Q80: 达人推广费 | R80: 内容推广费 | S80: 品牌运营中心 | T80: 市场广告推广部 | U80: 市场推广部 | V80: 内容投放组
A81: 内容加热 | B81: 内容热推 | C81: =VLOOKUP(B81,'收集数据表'!$A$2:$A$201,1,FALSE) | D81: 品类内容推广 | E81: 内容加热 | F81: 内容加热 | G81: 否 | L81: 否 | M81: 否 | N81: 否 | O81: 否 | P81: 营销费用 | Q81: 达人推广费 | R81: 内容推广费 | S81: 品牌运营中心 | T81: 市场广告推广部 | U81: 市场推广部 | V81: 内容投放组
A82: 素材创意制作 | B82: 天猫淘内内容 | C82: =VLOOKUP(B82,'收集数据表'!$A$2:$A$201,1,FALSE) | D82: 品类内容推广 | E82: 天猫淘内内容 | F82: 天猫淘内内容 | G82: 是 | H82: 天猫花西子旗舰店 | I82: 天猫渠道 | J82: 天猫货架 | L82: 否 | M82: 否 | N82: 否 | O82: 否 | P82: 营销费用 | Q82: 内容制作费 | R82: 视频制作费 | S82: 品牌运营中心 | T82: 直播运营部 | U82: 达播BD部
A83: 内容加热 | B83: 微博粉条 | C83: =VLOOKUP(B83,'收集数据表'!$A$2:$A$201,1,FALSE) | D83: 品类内容推广 | E83: 其他新媒体加热 | F83: 其他新媒体加热 | G83: 否 | L83: 否 | M83: 否 | N83: 否 | O83: 否 | P83: 营销费用 | Q83: 达人推广费 | R83: 内容推广费 | S83: 品牌运营中心 | T83: 市场广告推广部 | U83: 市场推广部 | V83: 内容投放组
A84: 内容加热 | B84: 微博搜索 | C84: =VLOOKUP(B84,'收集数据表'!$A$2:$A$201,1,FALSE) | D84: 品类内容推广 | E84: 其他新媒体加热 | F84: 其他新媒体加热 | G84: 否 | L84: 否 | M84: 否 | N84: 否 | O84: 否 | P84: 营销费用 | Q84: 达人推广费 | R84: 内容推广费 | S84: 品牌运营中心 | T84: 市场广告推广部 | U84: 市场推广部 | V84: 内容投放组
A85: 内容加热 | B85: 小红书加热 | C85: =VLOOKUP(B85,'收集数据表'!$A$2:$A$201,1,FALSE) | D85: 品类内容推广 | E85: 其他新媒体加热 | F85: 其他新媒体加热 | G85: 否 | L85: 否 | M85: 否 | N85: 否 | O85: 否 | P85: 营销费用 | Q85: 达人推广费 | R85: 内容推广费 | S85: 品牌运营中心 | T85: 市场广告推广部 | U85: 市场推广部 | V85: 内容投放组
A86: 内容加热 | B86: 星聚力 | C86: =VLOOKUP(B86,'收集数据表'!$A$2:$A$201,1,FALSE) | D86: 品类内容推广 | E86: 内容加热 | F86: 内容加热 | G86: 否 | L86: 否 | M86: 否 | N86: 否 | O86: 否 | P86: 营销费用 | Q86: 达人推广费 | R86: 内容推广费 | S86: 品牌运营中心 | T86: 市场广告推广部 | U86: 市场推广部 | V86: 内容投放组
A87: 素材创意制作 | B87: 虚拟IP | C87: =VLOOKUP(B87,'收集数据表'!$A$2:$A$201,1,FALSE) | D87: 品类内容推广 | E87: 虚拟IP &直播间视觉设计 | F87: 虚拟IP &直播间视觉设计 | G87: 否 | L87: 否 | M87: 否 | N87: 否 | O87: 否 | P87: 营销费用 | Q87: 内容制作费 | R87: 视频制作费 | S87: 品牌运营中心 | T87: 渠道运营部 | U87: 抖音部 | V87: 内容部
A88: 素材创意制作 | B88: 直播间视觉设计费 | C88: =VLOOKUP(B88,'收集数据表'!$A$2:$A$201,1,FALSE) | D88: 品类内容推广 | E88: 虚拟IP &直播间视觉设计 | F88: 虚拟IP &直播间视觉设计 | G88: 否 | L88: 否 | M88: 否 | N88: 否 | O88: 否 | P88: 营销费用 | Q88: 内容制作费 | R88: 视觉设计费 | S88: 品牌运营中心 | T88: 渠道运营部 | U88: 抖音部 | V88: 内容部
A89: 线上品宣 | B89: OTT广告 | C89: =VLOOKUP(B89,'收集数据表'!$A$2:$A$201,1,FALSE) | D89: 品牌媒介 | E89: 线上品宣媒介 | F89: 线上品宣媒介 | G89: 否 | L89: 否 | M89: 否 | N89: 否 | O89: 否 | P89: 营销费用 | Q89: 媒介宣传费 | R89: 线上媒介费 | S89: 品牌运营中心 | T89: 市场广告推广部 | U89: 广告投放部 | V89: 媒介部
A90: 线上品宣 | B90: OTV广告 | C90: =VLOOKUP(B90,'收集数据表'!$A$2:$A$201,1,FALSE) | D90: 品牌媒介 | E90: 线上品宣媒介 | F90: 线上品宣媒介 | G90: 否 | L90: 否 | M90: 否 | N90: 否 | O90: 否 | P90: 营销费用 | Q90: 媒介宣传费 | R90: 线上媒介费 | S90: 品牌运营中心 | T90: 市场广告推广部 | U90: 广告投放部 | V90: 媒介部
A91: 线上品宣 | B91: 程序化投放 | C91: =VLOOKUP(B91,'收集数据表'!$A$2:$A$201,1,FALSE) | D91: 品牌媒介 | E91: 线上品宣媒介 | F91: 线上品宣媒介 | G91: 否 | L91: 否 | M91: 否 | N91: 否 | O91: 否 | P91: 营销费用 | Q91: 媒介宣传费 | R91: 线上媒介费 | S91: 品牌运营中心 | T91: 市场广告推广部 | U91: 广告投放部 | V91: 媒介部
A92: 线下品宣 | B92: 地标广告 | C92: =VLOOKUP(B92,'收集数据表'!$A$2:$A$201,1,FALSE) | D92: 品牌媒介 | E92: 线下品宣媒介 | F92: 线下品宣媒介 | G92: 否 | L92: 否 | M92: 否 | N92: 否 | O92: 否 | P92: 营销费用 | Q92: 媒介宣传费 | R92: 线下媒介费 | S92: 品牌运营中心 | T92: 市场广告推广部 | U92: 广告投放部 | V92: 媒介部
A93: 线下品宣 | B93: 电梯广告 | C93: =VLOOKUP(B93,'收集数据表'!$A$2:$A$201,1,FALSE) | D93: 品牌媒介 | E93: 线下品宣媒介 | F93: 线下品宣媒介 | G93: 否 | L93: 否 | M93: 否 | N93: 否 | O93: 否 | P93: 营销费用 | Q93: 媒介宣传费 | R93: 线下媒介费 | S93: 品牌运营中心 | T93: 市场广告推广部 | U93: 广告投放部 | V93: 媒介部
A94: 线下品宣 | B94: 电影院广告 | C94: =VLOOKUP(B94,'收集数据表'!$A$2:$A$201,1,FALSE) | D94: 品牌媒介 | E94: 线下品宣媒介 | F94: 线下品宣媒介 | G94: 否 | L94: 否 | M94: 否 | N94: 否 | O94: 否 | P94: 营销费用 | Q94: 媒介宣传费 | R94: 线下媒介费 | S94: 品牌运营中心 | T94: 市场广告推广部 | U94: 广告投放部 | V94: 媒介部
... A99: 线上品宣 | B99: 商业化资源包合作 | C99: =VLOOKUP(B99,'收集数据表'!$A$2:$A$201,1,FALSE) | D99: 品牌媒介 | E99: 线上品宣媒介 | F99: 线上品宣媒介 | G99: 否 | L99: 否 | M99: 否 | N99: 否 | O99: 否 | P99: 营销费用 | Q99: 媒介宣传费 | R99: 线上媒介费 | S99: 品牌运营中心 | T99: 市场广告推广部 | U99: 广告投放部 | V99: 媒介部
A100: 线上品宣 | B100: 投放策略调研 | C100: =VLOOKUP(B100,'收集数据表'!$A$2:$A$201,1,FALSE) | D100: 品牌媒介 | E100: 调研费（其他非标） | F100: 调研费（其他非标） | G100: 否 | L100: 否 | M100: 否 | N100: 否 | O100: 否 | P100: 营销费用 | Q100: 品牌宣传费 | R100: 市场调研费 | S100: 品牌运营中心 | T100: 市场广告推广部 | U100: 策略部
A101: IMC国妆 | B101: IMC国妆 | C101: =VLOOKUP(B101,'收集数据表'!$A$2:$A$201,1,FALSE) | D101: 品牌项目 | E101: IMC国妆 | F101: IMC国妆 | G101: 否 | L101: 否 | M101: 否 | N101: 是 | O101: 是 | P101: 营销费用 | Q101: 内容制作费 | R101: 视频制作费 | S101: 品牌产品中心 | T101: 品牌营销部
A102: IMC花养 | B102: IMC花养 | C102: =VLOOKUP(B102,'收集数据表'!$A$2:$A$201,1,FALSE) | D102: 品牌项目 | E102: IMC花养 | F102: IMC花养 | G102: 否 | L102: 否 | M102: 否 | N102: 是 | O102: 是 | P102: 营销费用 | Q102: 内容制作费 | R102: 视频制作费 | S102: 品牌产品中心 | T102: 品牌营销部
A103: IMC文化 | B103: IMC文化 | C103: =VLOOKUP(B103,'收集数据表'!$A$2:$A$201,1,FALSE) | D103: 品牌项目 | E103: IMC文化 | F103: IMC文化 | G103: 否 | L103: 否 | M103: 否 | N103: 是 | O103: 是 | P103: 营销费用 | Q103: 内容制作费 | R103: 视频制作费 | S103: 品牌产品中心 | T103: 品牌营销部
A104: 日常-创意与物料 | B104: 日常-创意与物料 | C104: =VLOOKUP(B104,'收集数据表'!$A$2:$A$201,1,FALSE) | D104: 品牌项目 | E104: 日常-创意与物料 | F104: 日常-创意与物料 | G104: 否 | L104: 否 | M104: 否 | N104: 否 | O104: 否 | P104: 营销费用 | Q104: 品牌宣传费 | R104: 明星合作费 | S104: 品牌产品中心 | T104: 品牌营销部
A105: 调研费 | B105: 数据采买和调研费 | C105: =VLOOKUP(B105,'收集数据表'!$A$2:$A$201,1,FALSE) | D105: 品牌项目 | E105: 日常-测试 | F105: 日常-测试 | G105: 否 | L105: 否 | M105: 否 | N105: 否 | O105: 否 | P105: 营销费用 | Q105: 品牌宣传费 | R105: 市场调研费 | S105: 品牌产品中心 | T105: 品牌营销部
A106: 新媒体费用 | B106: 私域代运营费用 | C106: =VLOOKUP(B106,'收集数据表'!$A$2:$A$201,1,FALSE) | D106: 品牌项目 | E106: 日常-私域 | F106: 日常-私域 | G106: 否 | L106: 否 | M106: 否 | N106: 否 | O106: 否 | P106: 营销费用 | Q106: 渠道推广费 | R106: 代运营服务费 | S106: 品牌产品中心 | T106: 品牌营销部
A107: 新媒体费用 | B107: 私域视频制作 | C107: =VLOOKUP(B107,'收集数据表'!$A$2:$A$201,1,FALSE) | D107: 品牌项目 | E107: 日常-私域 | F107: 日常-私域 | G107: 否 | L107: 否 | M107: 否 | N107: 否 | O107: 否 | P107: 营销费用 | Q107: 内容制作费 | R107: 视频制作费 | S107: 品牌产品中心 | T107: 品牌营销部
A108: 新媒体费用 | B108: 私域图文制作费 | C108: =VLOOKUP(B108,'收集数据表'!$A$2:$A$201,1,FALSE) | D108: 品牌项目 | E108: 日常-私域 | F108: 日常-私域 | G108: 否 | L108: 否 | M108: 否 | N108: 否 | O108: 否 | P108: 营销费用 | Q108: 内容制作费 | R108: 图文平面制作费 | S108: 品牌产品中心 | T108: 品牌营销部
A109: 新媒体费用 | B109: 私域账号运营费 | C109: =VLOOKUP(B109,'收集数据表'!$A$2:$A$201,1,FALSE) | D109: 品牌项目 | E109: 日常-私域 | F109: 日常-私域 | G109: 否 | L109: 否 | M109: 否 | N109: 否 | O109: 否 | P109: 营销费用 | Q109: 其他费用 | R109: 日常营运费用 | S109: 品牌产品中心 | T109: 品牌营销部
A110: 李佳琦全案 | B110: 佳琦全案-服务费 | C110: =VLOOKUP(B110,'收集数据表'!$A$2:$A$201,1,FALSE) | D110: 品牌营销直播专项 | E110: 佳琦全案 | F110: 佳琦全案 | G110: 否 | L110: 否 | M110: 否 | N110: 否 | O110: 否 | P110: 营销费用 | Q110: 内容制作费 | R110: 拍摄服务费 | S110: 品牌运营中心 | T110: 直播运营部 | U110: 达播BD部
A111: 李佳琦全案 | B111: 佳琦全案-设计费 | C111: =VLOOKUP(B111,'收集数据表'!$A$2:$A$201,1,FALSE) | D111: 品牌营销直播专项 | E111: 佳琦全案 | F111: 佳琦全案 | G111: 否 | L111: 否 | M111: 否 | N111: 否 | O111: 否 | P111: 营销费用 | Q111: 内容制作费 | R111: 视频制作费 | S111: 品牌运营中心 | T111: 直播运营部 | U111: 达播BD部
A112: 直播公关费 | B112: 李佳琦公关礼 | C112: =VLOOKUP(B112,'收集数据表'!$A$2:$A$201,1,FALSE) | D112: 品牌营销直播专项 | E112: BD公关费-李佳琦专项 | F112: BD公关费-李佳琦专项 | G112: 否 | L112: 否 | M112: 否 | N112: 是 | O112: 是 | P112: 营销费用 | Q112: 其他费用 | R112: 公关礼品费 | S112: 品牌运营中心 | T112: 直播运营部 | U112: 达播BD部
A113: 直播公关费 | B113: 直播公关礼-外采-达播二部 | C113: =VLOOKUP(B113,'收集数据表'!$A$2:$A$201,1,FALSE) | D113: 品牌营销直播专项 | E113: BD公关费-达播二部 | F113: BD公关费-达播二部 | G113: 否 | L113: 否 | M113: 否 | N113: 是 | O113: 是 | P113: 营销费用 | Q113: 其他费用 | R113: 公关礼品费 | S113: 品牌运营中心 | T113: 市场广告推广部 | U113: 达播2部
A114: 直播公关费 | B114: 直播公关礼-外采-淘宝其他 | C114: =VLOOKUP(B114,'收集数据表'!$A$2:$A$201,1,FALSE) | D114: 品牌营销直播专项 | E114: BD公关费-淘宝其他 | F114: BD公关费-淘宝其他 | G114: 否 | L114: 否 | M114: 否 | N114: 是 | O114: 是 | P114: 营销费用 | Q114: 其他费用 | R114: 公关礼品费 | S114: 品牌运营中心 | T114: 市场广告推广部 | U114: 达播2部
A115: 直播公关费 | B115: 直播公关礼-外采-田恬 | C115: =VLOOKUP(B115,'收集数据表'!$A$2:$A$201,1,FALSE) | D115: 品牌营销直播专项 | E115: BD公关费-田恬 | F115: BD公关费-田恬 | G115: 否 | L115: 否 | M115: 否 | N115: 是 | O115: 是 | P115: 营销费用 | Q115: 其他费用 | R115: 公关礼品费 | S115: 品牌运营中心 | T115: 直播运营部 | U115: 达播BD部
A116: 直播公关费 | B116: 直播公关礼-自有-达播二部 | C116: =VLOOKUP(B116,'收集数据表'!$A$2:$A$201,1,FALSE) | D116: 品牌营销直播专项 | E116: BD公关费-达播二部 | F116: BD公关费-达播二部 | G116: 否 | L116: 否 | M116: 否 | N116: 是 | O116: 是 | P116: 营销费用 | Q116: 其他费用 | R116: 公关礼品费 | S116: 品牌运营中心 | T116: 市场广告推广部 | U116: 达播2部
A117: 直播公关费 | B117: 直播公关礼-自有-淘宝其他 | C117: =VLOOKUP(B117,'收集数据表'!$A$2:$A$201,1,FALSE) | D117: 品牌营销直播专项 | E117: BD公关费-淘宝其他 | F117: BD公关费-淘宝其他 | G117: 否 | L117: 否 | M117: 否 | N117: 是 | O117: 是 | P117: 营销费用 | Q117: 其他费用 | R117: 公关礼品费 | S117: 品牌运营中心 | T117: 市场广告推广部 | U117: 达播2部
A118: 直播公关费 | B118: 直播公关礼-自有-田恬 | C118: =VLOOKUP(B118,'收集数据表'!$A$2:$A$201,1,FALSE) | D118: 品牌营销直播专项 | E118: BD公关费-田恬 | F118: BD公关费-田恬 | G118: 否 | L118: 否 | M118: 否 | N118: 是 | O118: 是 | P118: 营销费用 | Q118: 其他费用 | R118: 公关礼品费 | S118: 品牌运营中心 | T118: 直播运营部 | U118: 达播BD部
A119: 品牌营销-跨中心协同 | B119: 项目推广协同 | C119: =VLOOKUP(B119,'收集数据表'!$A$2:$A$201,1,FALSE) | D119: 品牌运营其他 | E119: 市场价值营销 | F119: 市场价值营销 | G119: 否 | L119: 否 | M119: 否 | N119: 否 | O119: 否 | P119: 营销费用 | Q119: 0 | R119: 0
A120: GWP外采 | B120: 虚拟权益赠送 | C120: =VLOOKUP(B120,'收集数据表'!$A$2:$A$201,1,FALSE) | D120: 品牌运营其他 | E120: 运营4P需求 - 外采 | F120: #N/A | G120: 否 | H120: #N/A | I120: #N/A | J120: #N/A | L120: #N/A | M120: #N/A | N120: #N/A | O120: #N/A | P120: #N/A | Q120: #N/A | R120: #N/A | S120: 品牌运营中心 | T120: 运营策略部 | U120: 销售策略部
A121: 天猫站外推广 | B121: AD信息流 | C121: =VLOOKUP(B121,'收集数据表'!$A$2:$A$201,1,FALSE) | D121: 平台电商推广 | E121: 竞价信息流-天猫 | F121: 竞价信息流-天猫 | G121: 是 | H121: 天猫花西子旗舰店 | I121: 天猫渠道 | J121: 天猫货架 | L121: 是 | M121: 否 | N121: 否 | O121: 否 | P121: 营销费用 | Q121: 渠道推广费 | R121: 站外推广费 | S121: 品牌运营中心 | T121: 运营策略部 | U121: 天猫运营部 | V121: 天猫推广组
A122: 天猫站外推广 | B122: UD信息流 | C122: =VLOOKUP(B122,'收集数据表'!$A$2:$A$201,1,FALSE) | D122: 平台电商推广 | E122: 竞价信息流-天猫 | F122: 竞价信息流-天猫 | G122: 是 | H122: 天猫花西子旗舰店 | I122: 天猫渠道 | J122: 天猫货架 | L122: 是 | M122: 否 | N122: 否 | O122: 否 | P122: 营销费用 | Q122: 渠道推广费 | R122: 站外推广费 | S122: 品牌运营中心 | T122: 运营策略部 | U122: 天猫运营部 | V122: 天猫推广组
...

Sheet 收集数据表
A1: 营销活动场景名称 | C1: 营销活动场景编码 | D1: 能否到店铺 | E1: 店铺 | F1: 渠道 | G1: 业务来源 | H1: 业务单元 | I1: 能否到品类（单品简称） | J1: 能否到SKU | K1: 是否允许个人报销 | L1: 是否允许无票报销 | M1: 预算科目 | N1: 预算二级科目 | O1: 费用类型 | P1: 费用大类 | Q1: 费用小类
A2: 抖音品牌信息流 | B2: =VLOOKUP(A2,'营销计划（活动-更新）'!$B$2:$D$213,1,FALSE) | C2: YXHD01 | D2: 否 | I2: 否 | K2: 否 | L2: =K2 | M2: 品牌媒介 | N2: 线上品宣媒介 | O2: 营销费用 | P2: 媒介宣传费 | Q2: 线上媒介费
A3: 快手品牌信息流 | B3: =VLOOKUP(A3,'营销计划（活动-更新）'!$B$2:$D$213,1,FALSE) | C3: YXHD02 | D3: 否 | I3: 否 | K3: 否 | L3: =K3 | M3: 品牌媒介 | N3: 线上品宣媒介 | O3: 营销费用 | P3: 媒介宣传费 | Q3: 线上媒介费
A4: 开屏类广告 | B4: =VLOOKUP(A4,'营销计划（活动-更新）'!$B$2:$D$213,1,FALSE) | C4: YXHD03 | D4: 否 | I4: 否 | K4: 否 | L4: =K4 | M4: 品牌媒介 | N4: 线上品宣媒介 | O4: 营销费用 | P4: 媒介宣传费 | Q4: 线上媒介费
A5: 程序化投放 | B5: =VLOOKUP(A5,'营销计划（活动-更新）'!$B$2:$D$213,1,FALSE) | C5: YXHD04 | D5: 否 | I5: 否 | K5: 否 | L5: =K5 | M5: 品牌媒介 | N5: 线上品宣媒介 | O5: 营销费用 | P5: 媒介宣传费 | Q5: 线上媒介费
A6: OTT广告 | B6: =VLOOKUP(A6,'营销计划（活动-更新）'!$B$2:$D$213,1,FALSE) | C6: YXHD05 | D6: 否 | I6: 否 | K6: 否 | L6: =K6 | M6: 品牌媒介 | N6: 线上品宣媒介 | O6: 营销费用 | P6: 媒介宣传费 | Q6: 线上媒介费
A7: OTV广告 | B7: =VLOOKUP(A7,'营销计划（活动-更新）'!$B$2:$D$213,1,FALSE) | C7: YXHD06 | D7: 否 | I7: 否 | K7: 否 | L7: =K7 | M7: 品牌媒介 | N7: 线上品宣媒介 | O7: 营销费用 | P7: 媒介宣传费 | Q7: 线上媒介费
A8: 商业化资源包合作 | B8: =VLOOKUP(A8,'营销计划（活动-更新）'!$B$2:$D$213,1,FALSE) | C8: YXHD07 | D8: 否 | I8: 否 | K8: 否 | L8: =K8 | M8: 品牌媒介 | N8: 线上品宣媒介 | O8: 营销费用 | P8: 媒介宣传费 | Q8: 线上媒介费
A9: 广告效果监测 | B9: =VLOOKUP(A9,'营销计划（活动-更新）'!$B$2:$D$213,1,FALSE) | C9: YXHD08 | D9: 否 | I9: 否 | K9: 否 | L9: =K9 | M9: 品牌媒介 | N9: 线上品宣媒介 | O9: 营销费用 | P9: 媒介宣传费 | Q9: 线上媒介费
A10: 电梯广告 | B10: =VLOOKUP(A10,'营销计划（活动-更新）'!$B$2:$D$213,1,FALSE) | C10: YXHD09 | D10: 否 | I10: 否 | K10: 否 | L10: =K10 | M10: 品牌媒介 | N10: 线下品宣媒介 | O10: 营销费用 | P10: 媒介宣传费 | Q10: 线下媒介费
A11: 电影院广告 | B11: =VLOOKUP(A11,'营销计划（活动-更新）'!$B$2:$D$213,1,FALSE) | C11: YXHD10 | D11: 否 | I11: 否 | K11: 否 | L11: =K11 | M11: 品牌媒介 | N11: 线下品宣媒介 | O11: 营销费用 | P11: 媒介宣传费 | Q11: 线下媒介费
A12: 地标广告 | B12: =VLOOKUP(A12,'营销计划（活动-更新）'!$B$2:$D$213,1,FALSE) | C12: YXHD11 | D12: 否 | I12: 否 | K12: 否 | L12: =K12 | M12: 品牌媒介 | N12: 线下品宣媒介 | O12: 营销费用 | P12: 媒介宣传费 | Q12: 线下媒介费
A13: 投放策略调研 | B13: =VLOOKUP(A13,'营销计划（活动-更新）'!$B$2:$D$213,1,FALSE) | C13: YXHD12 | D13: 否 | I13: 否 | K13: 否 | L13: =K13 | M13: 品牌媒介 | N13: 调研费（其他非标） | O13: 营销费用 | P13: 品牌宣传费 | Q13: 市场调研费
... A25: DOU+ | B25: =VLOOKUP(A25,'营销计划（活动-更新）'!$B$2:$D$213,1,FALSE) | C25: YXHD24 | D25: 否 | I25: 否 | K25: 否 | L25: =K25 | M25: 品类内容推广 | N25: 内容加热 | O25: 营销费用 | P25: 达人推广费 | Q25: 内容推广费
A26: 快手作品推荐 | B26: =VLOOKUP(A26,'营销计划（活动-更新）'!$B$2:$D$213,1,FALSE) | C26: YXHD25 | D26: 是 | E26: 天猫花西子旗舰店 | I26: 否 | K26: 否 | L26: =K26 | M26: 品类内容推广 | N26: 内容加热 | O26: 营销费用 | P26: 达人推广费 | Q26: 内容推广费
A27: 内容热推 | B27: =VLOOKUP(A27,'营销计划（活动-更新）'!$B$2:$D$213,1,FALSE) | C27: YXHD26 | D27: 否 | I27: 否 | K27: 否 | L27: =K27 | M27: 品类内容推广 | N27: 内容加热 | O27: 营销费用 | P27: 达人推广费 | Q27: 内容推广费
A28: 内容服务 | B28: =VLOOKUP(A28,'营销计划（活动-更新）'!$B$2:$D$213,1,FALSE) | C28: YXHD27 | D28: 否 | I28: 否 | K28: 否 | L28: =K28 | M28: 品类内容推广 | N28: 内容加热 | O28: 营销费用 | P28: 达人推广费 | Q28: 内容推广费
A29: 星聚力 | B29: =VLOOKUP(A29,'营销计划（活动-更新）'!$B$2:$D$213,1,FALSE) | C29: YXHD28 | D29: 否 | I29: 否 | K29: 否 | L29: =K29 | M29: 品类内容推广 | N29: 内容加热 | O29: 营销费用 | P29: 达人推广费 | Q29: 内容推广费
A30: 小红书加热 | B30: =VLOOKUP(A30,'营销计划（活动-更新）'!$B$2:$D$213,1,FALSE) | C30: YXHD29 | D30: 否 | I30: 否 | K30: 否 | L30: =K30 | M30: 品类内容推广 | N30: 其他新媒体加热 | O30: 营销费用 | P30: 达人推广费 | Q30: 内容推广费
A31: B站起飞加热 | B31: =VLOOKUP(A31,'营销计划（活动-更新）'!$B$2:$D$213,1,FALSE) | C31: YXHD30 | D31: 否 | I31: 否 | K31: 否 | L31: =K31 | M31: 品类内容推广 | N31: 其他新媒体加热 | O31: 营销费用 | P31: 达人推广费 | Q31: 内容推广费
A32: 微博粉条 | B32: =VLOOKUP(A32,'营销计划（活动-更新）'!$B$2:$D$213,1,FALSE) | C32: YXHD31 | D32: 否 | I32: 否 | K32: 否 | L32: =K32 | M32: 品类内容推广 | N32: 其他新媒体加热 | O32: 营销费用 | P32: 达人推广费 | Q32: 内容推广费
A33: 粉丝通 | B33: =VLOOKUP(A33,'营销计划（活动-更新）'!$B$2:$D$213,1,FALSE) | C33: YXHD32 | D33: 否 | I33: 否 | K33: 否 | L33: =K33 | M33: 品类内容推广 | N33: 其他新媒体加热 | O33: 营销费用 | P33: 达人推广费 | Q33: 内容推广费
A34: 微博搜索 | B34: =VLOOKUP(A34,'营销计划（活动-更新）'!$B$2:$D$213,1,FALSE) | C34: YXHD33 | D34: 否 | I34: 否 | K34: 否 | L34: =K34 | M34: 品类内容推广 | N34: 其他新媒体加热 | O34: 营销费用 | P34: 达人推广费 | Q34: 内容推广费
A35: 天猫-直通车 | B35: =VLOOKUP(A35,'营销计划（活动-更新）'!$B$2:$D$213,1,FALSE) | C35: YXHD34 | D35: 是 | E35: 天猫花西子旗舰店 | F35: 天猫渠道 | G35: 天猫货架 | I35: 是 | J35: 是 | K35: 否 | L35: =K35 | M35: 平台电商推广 | N35: 淘内-推广 | O35: 营销费用 | P35: 渠道推广费 | Q35: 站内推广费
A36: 天猫-引力魔方 | B36: =VLOOKUP(A36,'营销计划（活动-更新）'!$B$2:$D$213,1,FALSE) | C36: YXHD35 | D36: 是 | E36: 天猫花西子旗舰店 | F36: 天猫渠道 | G36: 天猫货架 | I36: 是 | J36: 是 | K36: 否 | L36: =K36 | M36: 平台电商推广 | N36: 淘内-推广 | O36: 营销费用 | P36: 渠道推广费 | Q36: 站内推广费
A37: 天猫-万相台-超级短视频 | B37: =VLOOKUP(A37,'营销计划（活动-更新）'!$B$2:$D$213,1,FALSE) | C37: YXHD36 | D37: 是 | E37: 天猫花西子旗舰店 | F37: 天猫渠道 | G37: 天猫货架 | I37: 否 | J37: 否 | K37: 否 | L37: =K37 | M37: 平台电商推广 | N37: 淘内-推广 | O37: 营销费用 | P37: 渠道推广费 | Q37: 站内推广费
A38: 天猫-明星店铺 | B38: =VLOOKUP(A38,'营销计划（活动-更新）'!$B$2:$D$213,1,FALSE) | C38: YXHD37 | D38: 是 | E38: 天猫花西子旗舰店 | F38: 天猫渠道 | G38: 天猫货架 | I38: 否 | J38: 否 | K38: 否 | L38: =K38 | M38: 平台电商推广 | N38: 淘内-推广 | O38: 营销费用 | P38: 渠道推广费 | Q38: 站内推广费
A39: 天猫-互动城 | B39: =VLOOKUP(A39,'营销计划（活动-更新）'!$B$2:$D$213,1,FALSE) | C39: YXHD38 | D39: 是 | E39: 天猫花西子旗舰店 | F39: 天猫渠道 | G39: 天猫货架 | I39: 否 | J39: 否 | K39: 否 | L39: =K39 | M39: 平台电商推广 | N39: 淘内-推广 | O39: 营销费用 | P39: 渠道推广费 | Q39: 站内推广费
A40: 天猫-万相台-超级直播 | B40: =VLOOKUP(A40,'营销计划（活动-更新）'!$B$2:$D$213,1,FALSE) | C40: YXHD39 | D40: 是 | E40: 天猫花西子旗舰店 | F40: 天猫渠道 | G40: 天猫自播 | I40: 否 | J40: 否 | K40: 否 | L40: =K40 | M40: 平台电商推广 | N40: 淘内-推广 | O40: 营销费用 | P40: 渠道推广费 | Q40: 站内推广费
A41: 天猫-超级互动城 | B41: =VLOOKUP(A41,'营销计划（活动-更新）'!$B$2:$D$213,1,FALSE) | C41: YXHD40 | D41: 是 | E41: 天猫花西子旗舰店 | F41: 天猫渠道 | G41: 天猫货架 | I41: 否 | J41: 否 | K41: 否 | L41: =K41 | M41: 平台电商推广 | N41: 淘内-推广 | O41: 营销费用 | P41: 渠道推广费 | Q41: 站内推广费
A42: 天猫-极速推 | B42: =VLOOKUP(A42,'营销计划（活动-更新）'!$B$2:$D$213,1,FALSE) | C42: YXHD41 | D42: 是 | E42: 天猫花西子旗舰店 | F42: 天猫渠道 | G42: 天猫货架 | I42: 否 | J42: 否 | K42: 否 | L42: =K42 | M42: 平台电商推广 | N42: 淘内-推广 | O42: 营销费用 | P42: 渠道推广费 | Q42: 站内推广费
A43: 天猫-妈妈Club | B43: =VLOOKUP(A43,'营销计划（活动-更新）'!$B$2:$D$213,1,FALSE) | C43: YXHD42 | D43: 是 | E43: 天猫花西子旗舰店 | F43: 天猫渠道 | G43: 天猫货架 | I43: 否 | J43: 否 | K43: 否 | L43: =K43 | M43: 平台电商推广 | N43: 淘内-推广 | O43: 营销费用 | P43: 渠道推广费 | Q43: 站内推广费
A44: 天猫-品牌专区 | B44: =VLOOKUP(A44,'营销计划（活动-更新）'!$B$2:$D$213,1,FALSE) | C44: YXHD43 | D44: 是 | E44: 天猫花西子旗舰店 | F44: 天猫渠道 | G44: 天猫货架 | I44: 否 | J44: 否 | K44: 否 | L44: =K44 | M44: 平台电商推广 | N44: 淘内-品专 | O44: 营销费用 | P44: 渠道推广费 | Q44: 站内推广费
A45: 淘宝客 | B45: =VLOOKUP(A45,'营销计划（活动-更新）'!$B$2:$D$213,1,FALSE) | C45: YXHD44 | D45: 是 | E45: 天猫花西子旗舰店 | F45: 天猫渠道 | G45: 天猫货架 | I45: 是 | J45: 是 | K45: 否 | L45: =K45 | M45: 平台电商推广 | N45: 淘内-淘宝客 | O45: 营销费用 | P45: 渠道推广费 | Q45: 站内推广费
A46: 京东自营-京准通常规投放 | B46: =VLOOKUP(A46,'营销计划（活动-更新）'!$B$2:$D$213,1,FALSE) | C46: YXHD45 | D46: 是 | E46: 花西子京东自营旗舰店 | F46: 京东渠道 | G46: 自营货架 | I46: 是 | J46: 是 | K46: 否 | L46: =K46 | M46: 平台电商推广 | N46: 京东渠道推广（自营） | O46: 营销费用 | P46: 渠道推广费 | Q46: 站内推广费
... A57: 京东POP-联合活动 | B57: =VLOOKUP(A57,'营销计划（活动-更新）'!$B$2:$D$213,1,FALSE) | C57: YXHD56 | D57: 是 | E57: 京东花西子旗舰店 | F57: 京东渠道 | G57: POP货架 | I57: 否 | J57: 否 | K57: 否 | L57: =K57 | M57: 平台电商推广 | N57: 京东渠道推广（POP） | O57: 营销费用 | P57: 渠道推广费 | Q57: 站内推广费
A58: 日常-创意与物料 | B58: =VLOOKUP(A58,'营销计划（活动-更新）'!$B$2:$D$213,1,FALSE) | C58: YXHD57 | D58: 否 | I58: 否 | J58: 否 | K58: 否 | L58: =K58 | M58: 品牌项目 | N58: 日常-创意与物料 | O58: 营销费用 | P58: 品牌宣传费 | Q58: 明星合作费
A59: 唯品会-唯品常规投放 | B59: =VLOOKUP(A59,'营销计划（活动-更新）'!$B$2:$D$213,1,FALSE) | C59: YXHD58 | D59: 是 | E59: 唯品会自营花西子旗舰店 | F59: 唯品会 | G59: 唯品货架 | I59: 是 | J59: 否 | K59: 否 | L59: =K59 | M59: 平台电商推广 | N59: 唯品渠道推广 | O59: 营销费用 | P59: 渠道推广费 | Q59: 站内推广费
A60: 唯品会-达人卖货 | B60: =VLOOKUP(A60,'营销计划（活动-更新）'!$B$2:$D$213,1,FALSE) | C60: YXHD59 | D60: 是 | E60: 唯品会自营花西子旗舰店 | F60: 唯品会 | G60: 唯品货架 | I60: 是 | J60: 是 | K60: 否 | L60: =K60 | M60: 平台电商推广 | N60: 唯品渠道推广 | O60: 营销费用 | P60: 渠道推广费 | Q60: 站内推广费
A61: 自营其他 | B61: =VLOOKUP(A61,'营销计划（活动-更新）'!$B$2:$D$213,1,FALSE) | C61: YXHD60 | D61: 是 | K61: 否 | L61: =K61 | M61: 平台电商推广 | N61: 自营其他渠道推广 | O61: 营销费用 | P61: 渠道推广费 | Q61: 站内推广费
A62: 拼多多 | B62: =VLOOKUP(A62,'营销计划（活动-更新）'!$B$2:$D$213,1,FALSE) | C62: YXHD61 | D62: 是 | K62: 否 | L62: =K62 | M62: 平台电商推广 | N62: 拼多多渠道推广 | O62: 营销费用 | P62: 渠道推广费 | Q62: 站内推广费
A63: AD信息流 | B63: =VLOOKUP(A63,'营销计划（活动-更新）'!$B$2:$D$213,1,FALSE) | C63: YXHD62 | D63: 是 | E63: 天猫花西子旗舰店 | F63: 天猫渠道 | G63: 天猫货架 | I63: 是 | J63: 否 | K63: 否 | L63: =K63 | M63: 平台电商推广 | N63: 竞价信息流-天猫 | O63: 营销费用 | P63: 渠道推广费 | Q63: 站外推广费
A64: UD信息流 | B64: =VLOOKUP(A64,'营销计划（活动-更新）'!$B$2:$D$213,1,FALSE) | C64: YXHD63 | D64: 是 | E64: 天猫花西子旗舰店 | F64: 天猫渠道 | G64: 天猫货架 | I64: 是 | J64: 否 | K64: 否 | L64: =K64 | M64: 平台电商推广 | N64: 竞价信息流-天猫 | O64: 营销费用 | P64: 渠道推广费 | Q64: 站外推广费
A65: 磁力引擎 | B65: =VLOOKUP(A65,'营销计划（活动-更新）'!$B$2:$D$213,1,FALSE) | C65: YXHD64 | D65: 是 | E65: 天猫花西子旗舰店 | F65: 天猫渠道 | G65: 天猫货架 | I65: 是 | J65: 否 | K65: 否 | L65: =K65 | M65: 平台电商推广 | N65: 竞价信息流-天猫 | O65: 营销费用 | P65: 渠道推广费 | Q65: 站外推广费
A66: 磁力金牛 | B66: =VLOOKUP(A66,'营销计划（活动-更新）'!$B$2:$D$213,1,FALSE) | C66: YXHD65 | D66: 是 | E66: 快手花西子旗舰店 | F66: 快手渠道 | G66: 快手自播 | I66: 是 | J66: 否 | K66: 否 | L66: =K66 | M66: 直播电商推广 | N66: 快手电商渠道推广 | O66: 营销费用 | P66: 渠道推广费 | Q66: 站内推广费
A67: 百度SEO竞价广告 | B67: =VLOOKUP(A67,'营销计划（活动-更新）'!$B$2:$D$213,1,FALSE) | C67: YXHD66 | D67: 是 | E67: 天猫花西子旗舰店 | F67: 天猫渠道 | G67: 天猫货架 | I67: 否 | J67: 否 | K67: 否 | L67: =K67 | M67: 平台电商推广 | N67: 竞价信息流-天猫 | O67: 营销费用 | P67: 渠道推广费 | Q67: 站外推广费
A68: 百度SEO搜索广告 | B68: =VLOOKUP(A68,'营销计划（活动-更新）'!$B$2:$D$213,1,FALSE) | C68: YXHD67 | D68: 是 | E68: 天猫花西子旗舰店 | F68: 天猫渠道 | G68: 天猫货架 | I68: 否 | J68: 否 | K68: 否 | L68: =K68 | M68: 平台电商推广 | N68: 竞价信息流-天猫 | O68: 营销费用 | P68: 渠道推广费 | Q68: 站外推广费
A69: 微信-店铺 | B69: =VLOOKUP(A69,'营销计划（活动-更新）'!$B$2:$D$213,1,FALSE) | C69: YXHD68 | D69: 是 | E69: 有赞花西子有赞旗舰店 | F69: 综合渠道 | G69: 有赞货架 | K69: 否 | L69: =K69 | M69: 社交电商推广 | N69: 微信-店铺 | O69: 营销费用 | P69: 渠道推广费 | Q69: 站内推广费
A70: AD竞价内容创意-场地租赁 | B70: =VLOOKUP(A70,'营销计划（活动-更新）'!$B$2:$D$213,1,FALSE) | C70: YXHD69 | D70: 否 | I70: 否 | J70: 否 | K70: 是 | L70: =K70 | M70: 品类内容推广 | N70: AD竞价内容创意 | O70: 营销费用 | P70: 其他费用 | Q70: 场地租赁费
A71: AD竞价内容创意-舞台场地 | B71: =VLOOKUP(A71,'营销计划（活动-更新）'!$B$2:$D$213,1,FALSE) | C71: YXHD70 | D71: 否 | I71: 否 | J71: 否 | K71: 是 | L71: =K71 | M71: 品类内容推广 | N71: AD竞价内容创意 | O71: 营销费用 | P71: 其他费用 | Q71: 舞台场地搭建费
A72: AD竞价内容创意-设备租赁 | B72: =VLOOKUP(A72,'营销计划（活动-更新）'!$B$2:$D$213,1,FALSE) | C72: YXHD71 | D72: 否 | I72: 否 | J72: 否 | K72: 是 | L72: =K72 | M72: 品类内容推广 | N72: AD竞价内容创意 | O72: 营销费用 | P72: 其他费用 | Q72: 设备租赁费
A73: IMC花养 | B73: =VLOOKUP(A73,'营销计划（活动-更新）'!$B$2:$D$213,1,FALSE) | C73: YXHD72 | D73: 否 | I73: 否 | J73: 否 | K73: 是 | L73: =K73 | M73: 品牌项目 | N73: IMC花养 | O73: 营销费用 | P73: 内容制作费 | Q73: 视频制作费
A74: IMC国妆 | B74: =VLOOKUP(A74,'营销计划（活动-更新）'!$B$2:$D$213,1,FALSE) | C74: YXHD73 | D74: 否 | I74: 否 | J74: 否 | K74: 是 | L74: =K74 | M74: 品牌项目 | N74: IMC国妆 | O74: 营销费用 | P74: 内容制作费 | Q74: 视频制作费
A75: IMC文化 | B75: =VLOOKUP(A75,'营销计划（活动-更新）'!$B$2:$D$213,1,FALSE) | C75: YXHD74 | D75: 否 | I75: 否 | J75: 否 | K75: 是 | L75: =K75 | M75: 品牌项目 | N75: IMC文化 | O75: 营销费用 | P75: 内容制作费 | Q75: 视频制作费
A76: 数据采买和调研费 | B76: =VLOOKUP(A76,'营销计划（活动-更新）'!$B$2:$D$213,1,FALSE) | C76: YXHD75 | D76: 否 | I76: 否 | J76: 否 | K76: 否 | L76: =K76 | M76: 品牌项目 | N76: 日常-测试 | O76: 营销费用 | P76: 品牌宣传费 | Q76: 市场调研费
A77: 私域图文制作费 | B77: =VLOOKUP(A77,'营销计划（活动-更新）'!$B$2:$D$213,1,FALSE) | C77: YXHD76 | D77: 否 | I77: 否 | J77: 否 | K77: 否 | L77: =K77 | M77: 品牌项目 | N77: 日常-私域 | O77: 营销费用 | P77: 内容制作费 | Q77: 图文平面制作费
A78: 私域视频制作 | B78: =VLOOKUP(A78,'营销计划（活动-更新）'!$B$2:$D$213,1,FALSE) | C78: YXHD77 | D78: 否 | I78: 否 | J78: 否 | K78: 否 | L78: =K78 | M78: 品牌项目 | N78: 日常-私域 | O78: 营销费用 | P78: 内容制作费 | Q78: 视频制作费
A79: 私域代运营费用 | B79: =VLOOKUP(A79,'营销计划（活动-更新）'!$B$2:$D$213,1,FALSE) | C79: YXHD78 | D79: 否 | I79: 否 | J79: 否 | K79: 否 | L79: =K79 | M79: 品牌项目 | N79: 日常-私域 | O79: 营销费用 | P79: 渠道推广费 | Q79: 代运营服务费
A80: 私域账号运营费 | B80: =VLOOKUP(A80,'营销计划（活动-更新）'!$B$2:$D$213,1,FALSE) | C80: YXHD79 | D80: 否 | I80: 否 | J80: 否 | K80: 否 | L80: =K80 | M80: 品牌项目 | N80: 日常-私域 | O80: 营销费用 | P80: 其他费用 | Q80: 日常营运费用
A81: 京东2B企业购 | B81: =VLOOKUP(A81,'营销计划（活动-更新）'!$B$2:$D$213,1,FALSE) | C81: YXHD80 | D81: 是 | E81: 花西子京东自营旗舰店 | F81: 京东渠道 | G81: 自营货架 | K81: 否 | L81: =K81 | M81: 平台电商推广 | N81: 京东2B企业购 | O81: 营销费用 | P81: 渠道推广费 | Q81: 站内推广费
A82: 京东达播佣金 | B82: =VLOOKUP(A82,'营销计划（活动-更新）'!$B$2:$D$213,1,FALSE) | C82: YXHD81 | D82: 是 | E82: 花西子京东自营旗舰店 | F82: 京东渠道 | G82: 京东达播 | K82: 否 | L82: =K82 | M82: 平台电商推广 | N82: 达播-京东 | O82: 营销费用 | P82: 渠道推广费 | Q82: 直播服务费
A83: 京东达播服务费 | B83: =VLOOKUP(A83,'营销计划（活动-更新）'!$B$2:$D$213,1,FALSE) | C83: YXHD82 | D83: 是 | E83: 花西子京东自营旗舰店 | F83: 京东渠道 | G83: 京东达播 | K83: 否 | L83: =K83 | M83: 平台电商推广 | N83: 达播-京东 | O83: 营销费用 | P83: 渠道推广费 | Q83: 直播坑位费
A84: 京东自播服务 | B84: =VLOOKUP(A84,'营销计划（活动-更新）'!$B$2:$D$213,1,FALSE) | C84: YXHD83 | D84: 是 | E84: 花西子京东自营旗舰店 | F84: 京东渠道 | G84: 自营自播 | K84: 否 | L84: =K84 | M84: 平台电商推广 | N84: 京东自播服务费 | O84: 营销费用 | P84: 渠道推广费 | Q84: 直播服务费
A85: 唯享客 | B85: =VLOOKUP(A85,'营销计划（活动-更新）'!$B$2:$D$213,1,FALSE) | C85: YXHD84 | D85: 是 | E85: 唯品会自营花西子旗舰店 | F85: 唯品渠道 | G85: 唯品货架 | K85: 否 | L85: =K85 | M85: 平台电商推广 | N85: 唯享客 | O85: 营销费用 | P85: 渠道推广费 | Q85: 站内推广费
A86: 快手人设号-内容制作 | B86: =VLOOKUP(A86,'营销计划（活动-更新）'!$B$2:$D$213,1,FALSE) | C86: YXHD85 | D86: 是 | E86: 快手花西子旗舰店 | F86: 快手渠道 | G86: 快手人设号 | I86: 否 | J86: 否 | K86: 否 | L86: =K86 | M86: 直播电商推广 | N86: 快手人设号 | O86: 营销费用 | P86: 内容制作费 | Q86: 内容制作费
A87: 快手人设号-图文平面制作 | B87: =VLOOKUP(A87,'营销计划（活动-更新）'!$B$2:$D$213,1,FALSE) | C87: YXHD86 | D87: 是 | E87: 快手花西子旗舰店 | F87: 快手渠道 | G87: 快手人设号 | I87: 否 | J87: 否 | K87: 否 | L87: =K87 | M87: 直播电商推广 | N87: 快手人设号 | O87: 营销费用 | P87: 内容制作费 | Q87: 图文平面制作费
A88: 快手人设号-视频制作 | B88: =VLOOKUP(A88,'营销计划（活动-更新）'!$B$2:$D$213,1,FALSE) | C88: YXHD87 | D88: 是 | E88: 快手花西子旗舰店 | F88: 快手渠道 | G88: 快手人设号 | I88: 否 | J88: 否 | K88: 否 | L88: =K88 | M88: 直播电商推广 | N88: 快手人设号 | O88: 营销费用 | P88: 内容制作费 | Q88: 视频制作费
A89: 微信-达播服务费 | B89: =VLOOKUP(A89,'营销计划（活动-更新）'!$B$2:$D$213,1,FALSE) | C89: YXHD88 | D89: 是 | E89: 有赞花西子有赞旗舰店 | F89: 综合渠道 | G89: 有赞达播 | I89: 否 | J89: 否 | K89: 否 | L89: =K89 | M89: 社交电商推广 | N89: 微信-达播 | O89: 营销费用 | P89: 渠道推广费 | Q89: 直播服务费
A90: 微信-达播佣金 | B90: =VLOOKUP(A90,'营销计划（活动-更新）'!$B$2:$D$213,1,FALSE) | C90: YXHD89 | D90: 是 | E90: 有赞花西子有赞旗舰店 | F90: 综合渠道 | G90: 有赞达播 | I90: 是 | J90: 是 | K90: 否 | L90: =K90 | M90: 社交电商推广 | N90: 微信-达播 | O90: 营销费用 | P90: 渠道推广费 | Q90: 直播服务费
A91: 特渠运营 | B91: =VLOOKUP(A91,'营销计划（活动-更新）'!$B$2:$D$213,1,FALSE) | C91: YXHD90 | D91: 否 | I91: 否 | J91: 否 | K91: 否 | L91: =K91 | M91: 特殊渠道推广 | N91: 特殊渠道推广 | O91: 营销费用 | P91: 渠道推广费 | Q91: 线下推广费
A92: 抖音视频创意-矩阵号-视频制作 | B92: =VLOOKUP(A92,'营销计划（活动-更新）'!$B$2:$D$213,1,FALSE) | C92: YXHD91 | D92: 是 | E92: 抖音花西子官方旗舰店 | F92: 抖音渠道 | G92: 抖音矩阵号 | I92: 否 | J92: 否 | K92: 是 | L92: =K92 | M92: 品类内容推广 | N92: 抖音视频创意-矩阵号 | O92: 营销费用 | P92: 内容制作费 | Q92: 视频制作费
A93: 抖音视频创意-店铺-视频制作 | B93: =VLOOKUP(A93,'营销计划（活动-更新）'!$B$2:$D$213,1,FALSE) | C93: YXHD92 | D93: 是 | E93: 抖音花西子官方旗舰店 | F93: 抖音渠道 | G93: 抖音自播 | I93: 否 | J93: 否 | K93: 是 | L93: =K93 | M93: 品类内容推广 | N93: 抖音视频创意-店铺 | O93: 营销费用 | P93: 内容制作费 | Q93: 视频制作费
A94: 抖音视频创意-矩阵号-动画制作 | B94: =VLOOKUP(A94,'营销计划（活动-更新）'!$B$2:$D$213,1,FALSE) | C94: YXHD93 | D94: 是 | E94: 抖音花西子官方旗舰店 | F94: 抖音渠道 | G94: 抖音矩阵号 | I94: 否 | J94: 否 | K94: 是 | L94: =K94 | M94: 品类内容推广 | N94: 抖音视频创意-矩阵号 | O94: 营销费用 | P94: 内容制作费 | Q94: 动画制作费
A95: 抖音视频创意-店铺-动画制作 | B95: =VLOOKUP(A95,'营销计划（活动-更新）'!$B$2:$D$213,1,FALSE) | C95: YXHD94 | D95: 是 | E95: 抖音花西子官方旗舰店 | F95: 抖音渠道 | G95: 抖音自播 | I95: 否 | J95: 否 | K95: 是 | L95: =K95 | M95: 品类内容推广 | N95: 抖音视频创意-店铺 | O95: 营销费用 | P95: 内容制作费 | Q95: 动画制作费
A96: 抖音视频创意-矩阵号-图文平面制作 | B96: =VLOOKUP(A96,'营销计划（活动-更新）'!$B$2:$D$213,1,FALSE) | C96: YXHD95 | D96: 是 | E96: 抖音花西子官方旗舰店 | F96: 抖音渠道 | G96: 抖音矩阵号 | I96: 否 | J96: 否 | K96: 是 | L96: =K96 | M96: 品类内容推广 | N96: 抖音视频创意-矩阵号 | O96: 营销费用 | P96: 内容制作费 | Q96: 图文平面制作费
A97: 抖音视频创意-店铺-图文平面制作 | B97: =VLOOKUP(A97,'营销计划（活动-更新）'!$B$2:$D$213,1,FALSE) | C97: YXHD96 | D97: 是 | E97: 抖音花西子官方旗舰店 | F97: 抖音渠道 | G97: 抖音自播 | I97: 否 | J97: 否 | K97: 是 | L97: =K97 | M97: 品类内容推广 | N97: 抖音视频创意-店铺 | O97: 营销费用 | P97: 内容制作费 | Q97: 图文平面制作费
A98: 抖音视频创意-矩阵号-建模服务 | B98: =VLOOKUP(A98,'营销计划（活动-更新）'!$B$2:$D$213,1,FALSE) | C98: YXHD97 | D98: 是 | E98: 抖音花西子官方旗舰店 | F98: 抖音渠道 | G98: 抖音矩阵号 | I98: 否 | J98: 否 | K98: 是 | L98: =K98 | M98: 品类内容推广 | N98: 抖音视频创意-矩阵号 | O98: 营销费用 | P98: 内容制作费 | Q98: 建模服务费
A99: 抖音视频创意-店铺-建模服务 | B99: =VLOOKUP(A99,'营销计划（活动-更新）'!$B$2:$D$213,1,FALSE) | C99: YXHD98 | D99: 是 | E99: 抖音花西子官方旗舰店 | F99: 抖音渠道 | G99: 抖音自播 | I99: 否 | J99: 否 | K99: 是 | L99: =K99 | M99: 品类内容推广 | N99: 抖音视频创意-店铺 | O99: 营销费用 | P99: 内容制作费 | Q99: 建模服务费
A100: 抖音视频创意-矩阵号-渲染服务 | B100: =VLOOKUP(A100,'营销计划（活动-更新）'!$B$2:$D$213,1,FALSE) | C100: YXHD99 | D100: 是 | E100: 抖音花西子官方旗舰店 | F100: 抖音渠道 | G100: 抖音矩阵号 | I100: 否 | J100: 否 | K100: 是 | L100: =K100 | M100: 品类内容推广 | N100: 抖音视频创意-矩阵号 | O100: 营销费用 | P100: 内容制作费 | Q100: 渲染服务费
A101: 抖音视频创意-店铺-渲染服务 | B101: =VLOOKUP(A101,'营销计划（活动-更新）'!$B$2:$D$213,1,FALSE) | C101: YXHD100 | D101: 是 | E101: 抖音花西子官方旗舰店 | F101: 抖音渠道 | G101: 抖音自播 | I101: 否 | J101: 否 | K101: 是 | L101: =K101 | M101: 品类内容推广 | N101: 抖音视频创意-店铺 | O101: 营销费用 | P101: 内容制作费 | Q101: 渲染服务费
A102: 抖音视频创意-矩阵号-模特服务 | B102: =VLOOKUP(A102,'营销计划（活动-更新）'!$B$2:$D$213,1,FALSE) | C102: YXHD101 | D102: 是 | E102: 抖音花西子官方旗舰店 | F102: 抖音渠道 | G102: 抖音矩阵号 | I102: 否 | J102: 否 | K102: 是 | L102: =K102 | M102: 品类内容推广 | N102: 抖音视频创意-矩阵号 | O102: 营销费用 | P102: 内容制作费 | Q102: 模特服务费
A103: 抖音视频创意-店铺-模特服务 | B103: =VLOOKUP(A103,'营销计划（活动-更新）'!$B$2:$D$213,1,FALSE) | C103: YXHD102 | D103: 是 | E103: 抖音花西子官方旗舰店 | F103: 抖音渠道 | G103: 抖音自播 | I103: 否 | J103: 否 | K103: 是 | L103: =K103 | M103: 品类内容推广 | N103: 抖音视频创意-店铺 | O103: 营销费用 | P103: 内容制作费 | Q103: 模特服务费
... A119: 矩阵号佣金 | B119: =VLOOKUP(A119,'营销计划（活动-更新）'!$B$2:$D$213,1,FALSE) | C119: YXHD118 | D119: 是 | E119: 抖音花西子官方旗舰店 | F119: 抖音渠道 | G119: 抖音矩阵号 | I119: 是 | J119: 是 | K119: 否 | L119: =K119 | M119: 直播电商推广 | N119: 抖音矩阵号直播佣金服务费 | O119: 营销费用 | P119: 渠道推广费 | Q119: 代运营佣金
A120: 共创直播间服务费-唯品会 | B120: =VLOOKUP(A120,'营销计划（活动-更新）'!$B$2:$D$213,1,FALSE) | C120: YXHD119 | D120: 是 | I120: 否 | J120: 否 | K120: 否 | L120: =K120 | M120: 平台电商推广 | N120: 唯品渠道推广（共创） | O120: 营销费用 | P120: 渠道推广费 | Q120: 代运营服务费
A121: 共创直播间服务费-京东 | B121: =VLOOKUP(A121,'营销计划（活动-更新）'!$B$2:$D$213,1,FALSE) | C121: YXHD120 | D121: 是 | I121: 否 | J121: 否 | K121: 否 | L121: =K121 | M121: 平台电商推广 | N121: 京东渠道推广（共创） | O121: 营销费用 | P121: 渠道推广费 | Q121: 代运营服务费
A122: 共创直播间佣金-唯品会 | B122: =VLOOKUP(A122,'营销计划（活动-更新）'!$B$2:$D$213,1,FALSE) | C122: YXHD121 | D122: 是 | I122: 是 | J122: 是 | K122: 否 | L122: =K122 | M122: 平台电商推广 | N122: 唯品渠道推广（共创） | O122: 营销费用 | P122: 渠道推广费 | Q122: 代运营佣金
A123: 共创直播间佣金-京东 | B123: =VLOOKUP(A123,'营销计划（活动-更新）'!$B$2:$D$213,1,FALSE) | C123: YXHD122 | D123: 是 | I123: 是 | J123: 是 | K123: 否 | L123: =K123 | M123: 平台电商推广 | N123: 京东渠道推广（共创） | O123: 营销费用 | P123: 渠道推广费 | Q123: 代运营佣金
A124: 店铺服务费 | B124: =VLOOKUP(A124,'营销计划（活动-更新）'!$B$2:$D$213,1,FALSE) | C124: YXHD123 | D124: 是 | I124: 否 | J124: 否 | K124: 否 | L124: =K124 | M124: 平台扣点 | N124: 平台服务费 | O124: 营销费用 | P124: 店铺运营费 | Q124: 店铺服务费
A125: 快递拦截费 | B125: =VLOOKUP(A125,'营销计划（活动-更新）'!$B$2:$D$213,1,FALSE) | C125: YXHD124 | D125: 是 | I125: 否 | J125: 否 | K125: 否 | L125: =K125 | M125: 平台扣点 | N125: 平台服务费 | O125: 营销费用 | P125: 店铺运营费 | Q125: 快递拦截费
A126: 店铺保险费 | B126: =VLOOKUP(A126,'营销计划（活动-更新）'!$B$2:$D$213,1,FALSE) | C126: YXHD125 | D126: 是 | I126: 否 | J126: 否 | K126: 否 | L126: =K126 | M126: 平台扣点 | N126: 平台服务费 | O126: 营销费用 | P126: 店铺运营费 | Q126: 代收保险费
A127: 支付服务费 | B127: =VLOOKUP(A127,'营销计划（活动-更新）'!$B$2:$D$213,1,FALSE) | C127: YXHD126 | D127: 是 | I127: 否 | J127: 否 | K127: 否 | L127: =K127 | M127: 平台扣点 | N127: 平台服务费 | O127: 营销费用 | P127: 店铺运营费 | Q127: 支付服务费
A128: 平台技术服务费 | B128: =VLOOKUP(A128,'营销计划（活动-更新）'!$B$2:$D$213,1,FALSE) | C128: YXHD127 | D128: 是 | I128: 否 | J128: 否 | K128: 否 | L128: =K128 | M128: 平台扣点 | N128: 平台服务费 | O128: 营销费用 | P128: 店铺运营费 | Q128: 平台技术服务费
A129: 支付手续费 | B129: =VLOOKUP(A129,'营销计划（活动-更新）'!$B$2:$D$213,1,FALSE) | C129: YXHD128 | D129: 是 | I129: 否 | J129: 否 | K129: 否 | L129: =K129 | M129: 平台扣点 | N129: 平台服务费 | O129: 营销费用 | P129: 店铺运营费 | Q129: 支付手续费
A130: 软件费用 | B130: =VLOOKUP(A130,'营销计划（活动-更新）'!$B$2:$D$213,1,FALSE) | C130: YXHD129 | D130: 是 | I130: 否 | J130: 否 | K130: 否 | L130: =K130 | M130: 平台扣点 | N130: 软件服务费 | O130: 营销费用 | P130: 店铺运营费 | Q130: 平台软件费
A131: 抖音视频创意-矩阵号-场地租赁 | B131: =VLOOKUP(A131,'营销计划（活动-更新）'!$B$2:$D$213,1,FALSE) | C131: YXHD130 | D131: 是 | E131: 抖音花西子官方旗舰店 | F131: 抖音渠道 | G131: 抖音矩阵号 | I131: 否 | J131: 否 | K131: 是 | L131: =K131 | M131: 品类内容推广 | N131: 抖音视频创意-矩阵号 | O131: 营销费用 | P131: 其他费用 | Q131: 场地租赁费
A132: 抖音视频创意-店铺-场地租赁 | B132: =VLOOKUP(A132,'营销计划（活动-更新）'!$B$2:$D$213,1,FALSE) | C132: YXHD131 | D132: 是 | E132: 抖音花西子官方旗舰店 | F132: 抖音渠道 | G132: 抖音自播 | I132: 否 | J132: 否 | K132: 是 | L132: =K132 | M132: 品类内容推广 | N132: 抖音视频创意-店铺 | O132: 营销费用 | P132: 其他费用 | Q132: 场地租赁费
A133: 抖音视频创意-矩阵号-舞台场地搭建 | B133: =VLOOKUP(A133,'营销计划（活动-更新）'!$B$2:$D$213,1,FALSE) | C133: YXHD132 | D133: 是 | E133: 抖音花西子官方旗舰店 | F133: 抖音渠道 | G133: 抖音矩阵号 | I133: 否 | J133: 否 | K133: 是 | L133: =K133 | M133: 品类内容推广 | N133: 抖音视频创意-矩阵号 | O133: 营销费用 | P133: 其他费用 | Q133: 舞台场地搭建费
A134: 抖音视频创意-店铺-舞台场地搭建 | B134: =VLOOKUP(A134,'营销计划（活动-更新）'!$B$2:$D$213,1,FALSE) | C134: YXHD133 | D134: 是 | E134: 抖音花西子官方旗舰店 | F134: 抖音渠道 | G134: 抖音自播 | I134: 否 | J134: 否 | K134: 是 | L134: =K134 | M134: 品类内容推广 | N134: 抖音视频创意-店铺 | O134: 营销费用 | P134: 其他费用 | Q134: 舞台场地搭建费
A135: 抖音视频创意-矩阵号-设备租赁 | B135: =VLOOKUP(A135,'营销计划（活动-更新）'!$B$2:$D$213,1,FALSE) | C135: YXHD134 | D135: 是 | E135: 抖音花西子官方旗舰店 | F135: 抖音渠道 | G135: 抖音矩阵号 | I135: 否 | J135: 否 | K135: 是 | L135: =K135 | M135: 品类内容推广 | N135: 抖音视频创意-矩阵号 | O135: 营销费用 | P135: 其他费用 | Q135: 设备租赁费
A136: 抖音视频创意-店铺-设备租赁 | B136: =VLOOKUP(A136,'营销计划（活动-更新）'!$B$2:$D$213,1,FALSE) | C136: YXHD135 | D136: 是 | E136: 抖音花西子官方旗舰店 | F136: 抖音渠道 | G136: 抖音自播 | I136: 否 | J136: 否 | K136: 是 | L136: =K136 | M136: 品类内容推广 | N136: 抖音视频创意-店铺 | O136: 营销费用 | P136: 其他费用 | Q136: 设备租赁费
...

Sheet 预算部门->营销活动计划分类
A1: 营销活动分类 | C1: 一级部门 | D1: 二级部门 | E1: 三级部门 | F1: 四级部门 | H1: YSZZ01030205 | I1: HDFL01 | J1: HDFL01
A2: IP明星内容合作 | B2: =VLOOKUP(A2,'营销活动计划分类'!$A$1:$B$43,2,FALSE) | C2: 品牌运营中心 | D2: 市场广告推广部 | E2: 市场推广部 | F2: 市场PR组 | H2: YSZZ0102 | I2: HDFL39 | J2: HDFL39
A3: IP明星内容合作 | B3: =VLOOKUP(A3,'营销活动计划分类'!$A$1:$B$43,2,FALSE) | C3: 品牌运营中心 | D3: 市场广告推广部 | E3: 市场推广部 | F3: 娱乐营销组 | H3: YSZZ010201 | I3: HDFL38 | J3: HDFL38
A4: IP明星内容合作 | B4: =VLOOKUP(A4,'营销活动计划分类'!$A$1:$B$43,2,FALSE) | C4: 品牌运营中心 | D4: 市场广告推广部 | E4: 市场推广部 | F4: 娱乐营销组 | H4: YSZZ010202 | I4: HDFL04 | J4: HDFL04；HDFL05；HDFL16；HDFL17
A5: IP明星内容合作 | B5: =VLOOKUP(A5,'营销活动计划分类'!$A$1:$B$43,2,FALSE) | C5: 品牌运营中心 | D5: 市场广告推广部 | E5: 市场推广部 | F5: 娱乐营销组 | H5: YSZZ010202 | I5: HDFL05
A6: IP明星内容合作 | B6: =VLOOKUP(A6,'营销活动计划分类'!$A$1:$B$43,2,FALSE) | C6: 品牌运营中心 | D6: 市场广告推广部 | E6: 市场推广部 | F6: 娱乐营销组 | H6: YSZZ010202 | I6: HDFL16
A7: IP明星内容合作 | B7: =VLOOKUP(A7,'营销活动计划分类'!$A$1:$B$43,2,FALSE) | C7: 品牌运营中心 | D7: 市场广告推广部 | E7: 市场推广部 | F7: 娱乐营销组 | H7: YSZZ010202 | I7: HDFL17
A8: IP明星内容合作 | B8: =VLOOKUP(A8,'营销活动计划分类'!$A$1:$B$43,2,FALSE) | C8: 品牌运营中心 | D8: 市场广告推广部 | E8: 市场推广部 | F8: 娱乐营销组 | H8: YSZZ010204 | I8: HDFL38 | J8: HDFL38；HDFL41
A9: IP明星内容合作 | B9: =VLOOKUP(A9,'营销活动计划分类'!$A$1:$B$43,2,FALSE) | C9: 品牌运营中心 | D9: 市场广告推广部 | E9: 市场推广部 | F9: 娱乐营销组 | H9: YSZZ010204 | I9: HDFL41
A10: IP明星内容合作 | B10: =VLOOKUP(A10,'营销活动计划分类'!$A$1:$B$43,2,FALSE) | C10: 品牌运营中心 | D10: 市场广告推广部 | E10: 市场推广部 | F10: 娱乐营销组 | H10: YSZZ01030101 | I10: HDFL06 | J10: HDFL06
A11: 其他达人直播 | B11: =VLOOKUP(A11,'营销活动计划分类'!$A$1:$B$43,2,FALSE) | C11: 品牌运营中心 | D11: 市场广告推广部 | E11: 达播2部 | H11: YSZZ01030102 | I11: HDFL08 | J11: HDFL08；HDFL09
A12: 田恬 | B12: =VLOOKUP(A12,'营销活动计划分类'!$A$1:$B$43,2,FALSE) | C12: 品牌运营中心 | D12: 直播运营部 | E12: SKA达播部 | H12: YSZZ01030102 | I12: HDFL09
A13: 其他达人直播 | B13: =VLOOKUP(A13,'营销活动计划分类'!$A$1:$B$43,2,FALSE) | C13: 品牌运营中心 | D13: 市场广告推广部 | E13: 达播2部 | H13: YSZZ010302 | I13: HDFL18 | J13: HDFL18；HDFL30；HDFL31
A14: 其他达人直播 | B14: =VLOOKUP(A14,'营销活动计划分类'!$A$1:$B$43,2,FALSE) | C14: 品牌运营中心 | D14: 市场广告推广部 | E14: 达播2部 | H14: YSZZ010302 | I14: HDFL30
A15: 田恬 | B15: =VLOOKUP(A15,'营销活动计划分类'!$A$1:$B$43,2,FALSE) | C15: 品牌运营中心 | D15: 直播运营部 | E15: SKA达播部 | H15: YSZZ010302 | I15: HDFL31
A16: 其他达人直播 | B16: =VLOOKUP(A16,'营销活动计划分类'!$A$1:$B$43,2,FALSE) | C16: 品牌运营中心 | D16: 市场广告推广部 | E16: 达播2部 | H16: YSZZ01030204 | I16: HDFL01 | J16: HDFL01
A17: 其他达人直播 | B17: =VLOOKUP(A17,'营销活动计划分类'!$A$1:$B$43,2,FALSE) | C17: 品牌运营中心 | D17: 市场广告推广部 | E17: 达播2部 | H17: YSZZ01030205 | I17: HDFL31 | J17: HDFL31
A18: 其他达人直播 | B18: =VLOOKUP(A18,'营销活动计划分类'!$A$1:$B$43,2,FALSE) | C18: 品牌运营中心 | D18: 市场广告推广部 | E18: 达播2部 | H18: YSZZ01030206 | I18: HDFL07 | J18: HDFL07
A19: 李佳琦 | B19: =VLOOKUP(A19,'营销活动计划分类'!$A$1:$B$43,2,FALSE) | C19: 品牌运营中心 | D19: 直播运营部 | E19: SKA达播部 | H19: YSZZ010303 | I19: HDFL08 | J19: HDFL08
A20: 其他达人直播 | B20: =VLOOKUP(A20,'营销活动计划分类'!$A$1:$B$43,2,FALSE) | C20: 品牌运营中心 | D20: 市场广告推广部 | E20: 达播2部 | H20: YSZZ010304 | I20: HDFL02 | J20: HDFL02；HDFL06；HDFL17；HDFL38
A21: 李佳琦 | B21: =VLOOKUP(A21,'营销活动计划分类'!$A$1:$B$43,2,FALSE) | C21: 品牌运营中心 | D21: 直播运营部 | E21: SKA达播部 | H21: YSZZ010304 | I21: HDFL06
A22: 其他达人直播 | B22: =VLOOKUP(A22,'营销活动计划分类'!$A$1:$B$43,2,FALSE) | C22: 品牌运营中心 | D22: 市场广告推广部 | E22: 达播2部 | H22: YSZZ010304 | I22: HDFL17
A23: 素材创意制作 | B23: =VLOOKUP(A23,'营销活动计划分类'!$A$1:$B$43,2,FALSE) | C23: 品牌运营中心 | D23: 市场广告推广部 | E23: 广告投放部 | F23: 内容策划组 | H23: YSZZ010304 | I23: HDFL38
A24: 素材创意制作 | B24: =VLOOKUP(A24,'营销活动计划分类'!$A$1:$B$43,2,FALSE) | C24: 品牌运营中心 | D24: 市场广告推广部 | E24: 广告投放部 | F24: 内容策划组 | H24: YSZZ010401 | I24: HDFL36 | J24: HDFL36
A25: 素材创意制作 | B25: =VLOOKUP(A25,'营销活动计划分类'!$A$1:$B$43,2,FALSE) | C25: 品牌运营中心 | D25: 市场广告推广部 | E25: 广告投放部 | F25: 内容策划组 | H25: YSZZ01040101 | I25: HDFL33 | J25: HDFL33
A26: 素材创意制作 | B26: =VLOOKUP(A26,'营销活动计划分类'!$A$1:$B$43,2,FALSE) | C26: 品牌运营中心 | D26: 市场广告推广部 | E26: 广告投放部 | F26: 内容策划组 | H26: YSZZ010402 | I26: HDFL29 | J26: HDFL29
A27: 素材创意制作 | B27: =VLOOKUP(A27,'营销活动计划分类'!$A$1:$B$43,2,FALSE) | C27: 品牌运营中心 | D27: 市场广告推广部 | E27: 广告投放部 | F27: 内容策划组 | H27: YSZZ01040301 | I27: HDFL06 | J27: HDFL06
A28: 素材创意制作 | B28: =VLOOKUP(A28,'营销活动计划分类'!$A$1:$B$43,2,FALSE) | C28: 品牌运营中心 | D28: 市场广告推广部 | E28: 广告投放部 | F28: 内容策划组 | H28: YSZZ01040302 | I28: HDFL06 | J28: HDFL06；HDFL07；HDFL34；HDFL35
A29: 素材创意制作 | B29: =VLOOKUP(A29,'营销活动计划分类'!$A$1:$B$43,2,FALSE) | C29: 品牌运营中心 | D29: 市场广告推广部 | E29: 广告投放部 | F29: 内容策划组 | H29: YSZZ01040302 | I29: HDFL07
A30: 素材创意制作 | B30: =VLOOKUP(A30,'营销活动计划分类'!$A$1:$B$43,2,FALSE) | C30: 品牌运营中心 | D30: 市场广告推广部 | E30: 广告投放部 | F30: 内容策划组 | H30: YSZZ01040302 | I30: HDFL34
A31: 素材创意制作 | B31: =VLOOKUP(A31,'营销活动计划分类'!$A$1:$B$43,2,FALSE) | C31: 品牌运营中心 | D31: 市场广告推广部 | E31: 广告投放部 | F31: 内容策划组 | H31: YSZZ01040302 | I31: HDFL35
A32: 素材创意制作 | B32: =VLOOKUP(A32,'营销活动计划分类'!$A$1:$B$43,2,FALSE) | C32: 品牌运营中心 | D32: 市场广告推广部 | E32: 广告投放部 | F32: 内容策划组 | H32: YSZZ01040306 | I32: HDFL07 | J32: HDFL07；HDFL37
A33: 素材创意制作 | B33: =VLOOKUP(A33,'营销活动计划分类'!$A$1:$B$43,2,FALSE) | C33: 品牌运营中心 | D33: 市场广告推广部 | E33: 广告投放部 | F33: 内容策划组 | H33: YSZZ01040306 | I33: HDFL37
A34: 素材创意制作 | B34: =VLOOKUP(A34,'营销活动计划分类'!$A$1:$B$43,2,FALSE) | C34: 品牌运营中心 | D34: 市场广告推广部 | E34: 广告投放部 | F34: 内容策划组 | H34: YSZZ010501 | I34: HDFL19 | J34: HDFL19；HDFL24
A35: 素材创意制作 | B35: =VLOOKUP(A35,'营销活动计划分类'!$A$1:$B$43,2,FALSE) | C35: 品牌运营中心 | D35: 市场广告推广部 | E35: 广告投放部 | F35: 内容策划组 | H35: YSZZ010501 | I35: HDFL24
A36: 素材创意制作 | B36: =VLOOKUP(A36,'营销活动计划分类'!$A$1:$B$43,2,FALSE) | C36: 品牌运营中心 | D36: 市场广告推广部 | E36: 广告投放部 | F36: 内容策划组 | H36: YSZZ0106 | I36: HDFL25 | J36: HDFL25
A37: 内容加热 | B37: =VLOOKUP(A37,'营销活动计划分类'!$A$1:$B$43,2,FALSE) | C37: 品牌运营中心 | D37: 市场广告推广部 | E37: 市场推广部 | F37: 内容投放组 | H37: YSZZ010801 | I37: HDFL40 | J37: HDFL40；HDFL42
A38: 内容加热 | B38: =VLOOKUP(A38,'营销活动计划分类'!$A$1:$B$43,2,FALSE) | C38: 品牌运营中心 | D38: 市场广告推广部 | E38: 市场推广部 | F38: 内容投放组 | H38: YSZZ010801 | I38: HDFL42
A39: 素材创意制作 | B39: =VLOOKUP(A39,'营销活动计划分类'!$A$1:$B$43,2,FALSE) | C39: 品牌运营中心 | D39: 内容电商部 | E39: 抖音部 | F39: 内容部 | H39: YSZZ010802 | I39: HDFL22 | J39: HDFL22
A40: 素材创意制作 | B40: =VLOOKUP(A40,'营销活动计划分类'!$A$1:$B$43,2,FALSE) | C40: 品牌运营中心 | D40: 内容电商部 | E40: 抖音部 | F40: 内容部 | H40: YSZZ010902 | I40: HDFL20 | J40: HDFL20；HDFL21；HDFL28
A41: 素材创意制作 | B41: =VLOOKUP(A41,'营销活动计划分类'!$A$1:$B$43,2,FALSE) | C41: 品牌运营中心 | D41: 内容电商部 | E41: 抖音部 | F41: 内容部 | H41: YSZZ010902 | I41: HDFL21
A42: 素材创意制作 | B42: =VLOOKUP(A42,'营销活动计划分类'!$A$1:$B$43,2,FALSE) | C42: 品牌运营中心 | D42: 内容电商部 | E42: 抖音部 | F42: 内容部 | H42: YSZZ010902 | I42: HDFL28
A43: 素材创意制作 | B43: =VLOOKUP(A43,'营销活动计划分类'!$A$1:$B$43,2,FALSE) | C43: 品牌运营中心 | D43: 内容电商部 | E43: 抖音部 | F43: 内容部 | H43: YSZZ0110 | I43: HDFL10 | J43: HDFL10；HDFL11；HDFL12；HDFL13；HDFL14；HDFL15
A44: 素材创意制作 | B44: =VLOOKUP(A44,'营销活动计划分类'!$A$1:$B$43,2,FALSE) | C44: 品牌运营中心 | D44: 内容电商部 | E44: 抖音部 | F44: 内容部 | H44: YSZZ0110 | I44: HDFL11
A45: 素材创意制作 | B45: =VLOOKUP(A45,'营销活动计划分类'!$A$1:$B$43,2,FALSE) | C45: 品牌运营中心 | D45: 内容电商部 | E45: 抖音部 | F45: 内容部 | H45: YSZZ0110 | I45: HDFL12
A46: 素材创意制作 | B46: =VLOOKUP(A46,'营销活动计划分类'!$A$1:$B$43,2,FALSE) | C46: 品牌运营中心 | D46: 内容电商部 | E46: 抖音部 | F46: 内容部 | H46: YSZZ0110 | I46: HDFL13
A47: 素材创意制作 | B47: =VLOOKUP(A47,'营销活动计划分类'!$A$1:$B$43,2,FALSE) | C47: 品牌运营中心 | D47: 内容电商部 | E47: 抖音部 | F47: 内容部 | H47: YSZZ0110 | I47: HDFL14
A48: 素材创意制作 | B48: =VLOOKUP(A48,'营销活动计划分类'!$A$1:$B$43,2,FALSE) | C48: 品牌运营中心 | D48: 内容电商部 | E48: 抖音部 | F48: 内容部 | H48: YSZZ0110 | I48: HDFL15
A49: 素材创意制作 | B49: =VLOOKUP(A49,'营销活动计划分类'!$A$1:$B$43,2,FALSE) | C49: 品牌运营中心 | D49: 内容电商部 | E49: 抖音部 | F49: 内容部
A50: 素材创意制作 | B50: =VLOOKUP(A50,'营销活动计划分类'!$A$1:$B$43,2,FALSE) | C50: 品牌运营中心 | D50: 内容电商部 | E50: 抖音部 | F50: 内容部
A51: 素材创意制作 | B51: =VLOOKUP(A51,'营销活动计划分类'!$A$1:$B$43,2,FALSE) | C51: 品牌运营中心 | D51: 内容电商部 | E51: 抖音部 | F51: 内容部
A52: 素材创意制作 | B52: =VLOOKUP(A52,'营销活动计划分类'!$A$1:$B$43,2,FALSE) | C52: 品牌运营中心 | D52: 内容电商部 | E52: 抖音部 | F52: 内容部
A53: 素材创意制作 | B53: =VLOOKUP(A53,'营销活动计划分类'!$A$1:$B$43,2,FALSE) | C53: 品牌运营中心 | D53: 内容电商部 | E53: 抖音部 | F53: 矩阵运营部
A54: 素材创意制作 | B54: =VLOOKUP(A54,'营销活动计划分类'!$A$1:$B$43,2,FALSE) | C54: 品牌运营中心 | D54: 内容电商部 | E54: 抖音部 | F54: 矩阵运营部
A55: 素材创意制作 | B55: =VLOOKUP(A55,'营销活动计划分类'!$A$1:$B$43,2,FALSE) | C55: 品牌运营中心 | D55: 内容电商部 | E55: 抖音部 | F55: 矩阵运营部
A56: 素材创意制作 | B56: =VLOOKUP(A56,'营销活动计划分类'!$A$1:$B$43,2,FALSE) | C56: 品牌运营中心 | D56: 内容电商部 | E56: 抖音部 | F56: 矩阵运营部
A57: 素材创意制作 | B57: =VLOOKUP(A57,'营销活动计划分类'!$A$1:$B$43,2,FALSE) | C57: 品牌运营中心 | D57: 内容电商部 | E57: 抖音部 | F57: 矩阵运营部
A58: 素材创意制作 | B58: =VLOOKUP(A58,'营销活动计划分类'!$A$1:$B$43,2,FALSE) | C58: 品牌运营中心 | D58: 内容电商部 | E58: 抖音部 | F58: 矩阵运营部
A59: 素材创意制作 | B59: =VLOOKUP(A59,'营销活动计划分类'!$A$1:$B$43,2,FALSE) | C59: 品牌运营中心 | D59: 内容电商部 | E59: 抖音部 | F59: 矩阵运营部
A60: 素材创意制作 | B60: =VLOOKUP(A60,'营销活动计划分类'!$A$1:$B$43,2,FALSE) | C60: 品牌运营中心 | D60: 内容电商部 | E60: 抖音部 | F60: 矩阵运营部
... A71: 内容加热 | B71: =VLOOKUP(A71,'营销活动计划分类'!$A$1:$B$43,2,FALSE) | C71: 品牌运营中心 | D71: 市场广告推广部 | E71: 市场推广部 | F71: 内容投放组
A72: 素材创意制作 | B72: =VLOOKUP(A72,'营销活动计划分类'!$A$1:$B$43,2,FALSE) | C72: 品牌运营中心 | D72: 市场广告推广部 | E72: 达播2部
A73: 内容加热 | B73: =VLOOKUP(A73,'营销活动计划分类'!$A$1:$B$43,2,FALSE) | C73: 品牌运营中心 | D73: 市场广告推广部 | E73: 市场推广部 | F73: 内容投放组
A74: 内容加热 | B74: =VLOOKUP(A74,'营销活动计划分类'!$A$1:$B$43,2,FALSE) | C74: 品牌运营中心 | D74: 市场广告推广部 | E74: 市场推广部 | F74: 内容投放组
A75: 内容加热 | B75: =VLOOKUP(A75,'营销活动计划分类'!$A$1:$B$43,2,FALSE) | C75: 品牌运营中心 | D75: 市场广告推广部 | E75: 市场推广部 | F75: 内容投放组
A76: 内容加热 | B76: =VLOOKUP(A76,'营销活动计划分类'!$A$1:$B$43,2,FALSE) | C76: 品牌运营中心 | D76: 市场广告推广部 | E76: 市场推广部 | F76: 内容投放组
A77: 素材创意制作 | B77: =VLOOKUP(A77,'营销活动计划分类'!$A$1:$B$43,2,FALSE) | C77: 品牌运营中心 | D77: 内容电商部 | E77: 抖音部 | F77: 内容部
A78: 素材创意制作 | B78: =VLOOKUP(A78,'营销活动计划分类'!$A$1:$B$43,2,FALSE) | C78: 品牌运营中心 | D78: 内容电商部 | E78: 抖音部 | F78: 内容部
A79: 线上品宣 | B79: =VLOOKUP(A79,'营销活动计划分类'!$A$1:$B$43,2,FALSE) | C79: 品牌运营中心 | D79: 市场广告推广部 | E79: 广告投放部 | F79: 媒介组
A80: 线上品宣 | B80: =VLOOKUP(A80,'营销活动计划分类'!$A$1:$B$43,2,FALSE) | C80: 品牌运营中心 | D80: 市场广告推广部 | E80: 广告投放部 | F80: 媒介组
A81: 线上品宣 | B81: =VLOOKUP(A81,'营销活动计划分类'!$A$1:$B$43,2,FALSE) | C81: 品牌运营中心 | D81: 市场广告推广部 | E81: 广告投放部 | F81: 媒介组
A82: 线下品宣 | B82: =VLOOKUP(A82,'营销活动计划分类'!$A$1:$B$43,2,FALSE) | C82: 品牌运营中心 | D82: 市场广告推广部 | E82: 广告投放部 | F82: 媒介组
A83: 线下品宣 | B83: =VLOOKUP(A83,'营销活动计划分类'!$A$1:$B$43,2,FALSE) | C83: 品牌运营中心 | D83: 市场广告推广部 | E83: 广告投放部 | F83: 媒介组
A84: 线下品宣 | B84: =VLOOKUP(A84,'营销活动计划分类'!$A$1:$B$43,2,FALSE) | C84: 品牌运营中心 | D84: 市场广告推广部 | E84: 广告投放部 | F84: 媒介组
... A89: 线上品宣 | B89: =VLOOKUP(A89,'营销活动计划分类'!$A$1:$B$43,2,FALSE) | C89: 品牌运营中心 | D89: 市场广告推广部 | E89: 广告投放部 | F89: 媒介组
A90: 线上品宣 | B90: =VLOOKUP(A90,'营销活动计划分类'!$A$1:$B$43,2,FALSE) | C90: 品牌运营中心 | D90: 市场广告推广部 | E90: 策略部
A91: IMC国妆 | B91: =VLOOKUP(A91,'营销活动计划分类'!$A$1:$B$43,2,FALSE) | C91: 品牌产品中心 | D91: 品牌营销部
A92: IMC花养 | B92: =VLOOKUP(A92,'营销活动计划分类'!$A$1:$B$43,2,FALSE) | C92: 品牌产品中心 | D92: 品牌营销部
A93: IMC文化 | B93: =VLOOKUP(A93,'营销活动计划分类'!$A$1:$B$43,2,FALSE) | C93: 品牌产品中心 | D93: 品牌营销部
A94: 日常-创意与物料 | B94: =VLOOKUP(A94,'营销活动计划分类'!$A$1:$B$43,2,FALSE) | C94: 品牌产品中心 | D94: 品牌营销部
A95: 调研费 | B95: =VLOOKUP(A95,'营销活动计划分类'!$A$1:$B$43,2,FALSE) | C95: 品牌产品中心 | D95: 品牌营销部
A96: 新媒体费用 | B96: =VLOOKUP(A96,'营销活动计划分类'!$A$1:$B$43,2,FALSE) | C96: 品牌产品中心 | D96: 品牌营销部
A97: 新媒体费用 | B97: =VLOOKUP(A97,'营销活动计划分类'!$A$1:$B$43,2,FALSE) | C97: 品牌产品中心 | D97: 品牌营销部
A98: 新媒体费用 | B98: =VLOOKUP(A98,'营销活动计划分类'!$A$1:$B$43,2,FALSE) | C98: 品牌产品中心 | D98: 品牌营销部
A99: 新媒体费用 | B99: =VLOOKUP(A99,'营销活动计划分类'!$A$1:$B$43,2,FALSE) | C99: 品牌产品中心 | D99: 品牌营销部
A100: 李佳琦全案 | B100: =VLOOKUP(A100,'营销活动计划分类'!$A$1:$B$43,2,FALSE) | C100: 品牌运营中心 | D100: 直播运营部 | E100: SKA达播部
A101: 李佳琦全案 | B101: =VLOOKUP(A101,'营销活动计划分类'!$A$1:$B$43,2,FALSE) | C101: 品牌运营中心 | D101: 直播运营部 | E101: SKA达播部
A102: 直播公关费 | B102: =VLOOKUP(A102,'营销活动计划分类'!$A$1:$B$43,2,FALSE) | C102: 品牌运营中心 | D102: 直播运营部 | E102: SKA达播部
A103: 直播公关费 | B103: =VLOOKUP(A103,'营销活动计划分类'!$A$1:$B$43,2,FALSE) | C103: 品牌运营中心 | D103: 市场广告推广部 | E103: 达播2部
A104: 直播公关费 | B104: =VLOOKUP(A104,'营销活动计划分类'!$A$1:$B$43,2,FALSE) | C104: 品牌运营中心 | D104: 市场广告推广部 | E104: 达播2部
A105: 直播公关费 | B105: =VLOOKUP(A105,'营销活动计划分类'!$A$1:$B$43,2,FALSE) | C105: 品牌运营中心 | D105: 直播运营部 | E105: SKA达播部
A106: 直播公关费 | B106: =VLOOKUP(A106,'营销活动计划分类'!$A$1:$B$43,2,FALSE) | C106: 品牌运营中心 | D106: 市场广告推广部 | E106: 达播2部
A107: 直播公关费 | B107: =VLOOKUP(A107,'营销活动计划分类'!$A$1:$B$43,2,FALSE) | C107: 品牌运营中心 | D107: 市场广告推广部 | E107: 达播2部
A108: 直播公关费 | B108: =VLOOKUP(A108,'营销活动计划分类'!$A$1:$B$43,2,FALSE) | C108: 品牌运营中心 | D108: 直播运营部 | E108: SKA达播部
A109: 品牌营销-跨中心协同 | B109: =VLOOKUP(A109,'营销活动计划分类'!$A$1:$B$43,2,FALSE) | C109: 品牌运营中心 | D109: 市场广告推广部 | E109: 市场推广部
A110: 天猫站外推广 | B110: =VLOOKUP(A110,'营销活动计划分类'!$A$1:$B$43,2,FALSE) | C110: 品牌运营中心 | D110: 天猫运营部 | E110: 推广中心组
A111: 天猫站外推广 | B111: =VLOOKUP(A111,'营销活动计划分类'!$A$1:$B$43,2,FALSE) | C111: 品牌运营中心 | D111: 天猫运营部 | E111: 推广中心组
... A129: 拼多多渠道推广 | B129: =VLOOKUP(A129,'营销活动计划分类'!$A$1:$B$43,2,FALSE) | C129: 品牌运营中心 | D129: 综合渠道运营部 | E129: 拼多多部
A130: 淘宝客 | B130: =VLOOKUP(A130,'营销活动计划分类'!$A$1:$B$43,2,FALSE) | C130: 品牌运营中心
A131: 淘宝客 | B131: =VLOOKUP(A131,'营销活动计划分类'!$A$1:$B$43,2,FALSE) | C131: 品牌运营中心
...

Sheet Sheet9
A1: 得物部 | B1: HDFL08 | C1: HDFL08；HDFL26；HDFL27；HDFL05；HDFL04；HDFL40；HDFL42
A2: 得物部 | B2: HDFL26
A3: 得物部 | B3: HDFL27
A4: 得物部 | B4: HDFL05
A5: 得物部 | B5: HDFL04
A6: 得物部 | B6: HDFL40
A7: 得物部 | B7: HDFL42
A8: 抖音部 | B8: HDFL06
A9: 抖音部 | B9: HDFL07
A10: 抖音部 | B10: HDFL08 | C10: HDFL08；HDFL24；HDFL25；HDFL34；HDFL35；HDFL37
A11: 抖音部 | B11: HDFL24
A12: 抖音部 | B12: HDFL25
A13: 抖音部 | B13: HDFL34
A14: 抖音部 | B14: HDFL35
A15: 抖音部 | B15: HDFL37
A16: 京东部 | B16: HDFL20 | C16: HDFL20；HDFL21；HDFL28
A17: 京东部 | B17: HDFL21
A18: 京东部 | B18: HDFL28
A19: 快手部 | B19: HDFL07 | C19: HDFL07；HDFL08；HDFL09；HDFL24；HDFL25；HDFL33；HDFL36；HDFL38
A20: 快手部 | B20: HDFL08
A21: 快手部 | B21: HDFL09
A22: 快手部 | B22: HDFL24
A23: 快手部 | B23: HDFL25
A24: 快手部 | B24: HDFL33
A25: 快手部 | B25: HDFL36
A26: 快手部 | B26: HDFL38
A27: 拼多多部 | B27: HDFL07 | C27: HDFL07；HDFL22
A28: 拼多多部 | B28: HDFL22
A29: 品牌产品中心 | B29: HDFL10 | C29: HDFL10；HDFL11；HDFL12；HDFL13；HDFL14；HDFL15；HDFL27；HDFL29；HDFL23；HDFL40
A30: 品牌产品中心 | B30: HDFL11
A31: 品牌产品中心 | B31: HDFL12
A32: 品牌产品中心 | B32: HDFL13
A33: 品牌产品中心 | B33: HDFL14
A34: 品牌产品中心 | B34: HDFL15
A35: 品牌运营中心 | B35: HDFL27
A36: 品牌运营中心 | B36: HDFL29
A37: 品牌运营中心 | B37: HDFL23
A38: 品牌运营中心 | B38: HDFL40
A39: 市场广告推广部 | B39: HDFL01 | C39: HDFL01；HDFL02；HDFL06；HDFL07；HDFL08；HDFL17；HDFL18；HDFL30；HDFL31
A40: 市场广告推广部 | B40: HDFL02
A41: 市场广告推广部 | B41: HDFL06
A42: 市场广告推广部 | B42: HDFL07
A43: 市场广告推广部 | B43: HDFL08
A44: 市场广告推广部 | B44: HDFL17
A45: 市场广告推广部 | B45: HDFL18
A46: 市场广告推广部 | B46: HDFL30
A47: 市场广告推广部 | B47: HDFL31
A48: 特渠部 | B48: HDFL32 | C48: HDFL32
A49: 天猫运营部 | B49: HDFL19 | C49: HDFL19
A50: 微信运营部 | B50: HDFL06 | C50: HDFL06；HDFL07；HDFL23；HDFL24；HDFL29
A51: 微信运营部 | B51: HDFL07
A52: 微信运营部 | B52: HDFL23
A53: 微信运营部 | B53: HDFL24
A54: 微信运营部 | B54: HDFL29
A55: 运营策略部 | B55: HDFL43 | C55: HDFL43
A56: 直播运营部 | B56: HDFL04 | C56: HDFL04；HDFL05；HDFL16；HDFL17；HDFL38；HDFL39；HDFL41
A57: 直播运营部 | B57: HDFL05
A58: 直播运营部 | B58: HDFL16
A59: 直播运营部 | B59: HDFL17
A60: 直播运营部 | B60: HDFL38
A61: 直播运营部 | B61: HDFL39
A62: 直播运营部 | B62: HDFL41
